Workbook

Sheet BC
A1: INFORMACIÓN GENERAL PARA CASO DE NEGOCIO (BC)
A2: Actualización: 08 enero 2026. 16:06
A3: FECHA MAXIMA PARA CALCULO DE CONSUMIBLES (NO MENOR A 48 HORAS)
A4: TIPO DE CLIENTE
A5: ENTIDAD CONTRATANTE
A6: CLIENTE
A7: Código del Proceso
A8: Objeto de contratación
A9: Provincia /Ciudad
A10: * Ambiente de Laboratorio :
A11: Número de días por semana que trabaja el laboratorio
A12: Turnos por dia
... A55: Observaciones
A57: *Inversiones adicionales | B57: Características | C57: Estado | D57: Cantidad | E57: Precio | F57: Total
A58: Control externo de tercera opinión | D58: 0 | F58: =E58*D58 -> 0
A59: Control interno interlaboratorial | D59: 0 | F59: =E59*D59 -> 0
A60: Póliza de Fiel Cumplimiento del Contrato | B60: 72126.03 | D60: 0 | F60: =E60*D60 -> 0
A61: Póliza de seguro de equipos | D61: 0 | F61: =E61*D61 -> 0
A62: Ups equipo | B62: Equipo | D62: 0 | F62: =E62*D62 -> 0
A63: Ups servidor | B63: Powest on line 1kva 1000VA | D63: 0 | E63: 200 | F63: =E63*D63 -> 0
A64: LIS | D64: 0 | F64: =E64*D64 -> 0
A65: Interfaz | D65: 0 | E65: 1500 | F65: =E65*D65 -> 0
A66: Lantronix | D66: 0 | F66: =E66*D66 -> 0
A67: IP publica | D67: 0 | F67: =E67*D67 -> 0
A68: Punto de consulta web | D68: 0 | F68: =E68*D68 -> 0
A69: Internet | D69: 0 | F69: =E69*D69 -> 0
A70: Router para Internet | D70: 0 | F70: =E70*D70 -> 0
A71: Servidor | D71: 0 | F71: =E71*D71 -> 0
A72: Computadores | B72: Monitor + Teclado y mouse | D72: 0 | E72: 900 | F72: =E72*D72 -> 0
A73: Mantenimiento Computador | F73: =E73*D73 -> 0
A74: Impresora | D74: 0 | E74: 300 | F74: =E74*D74 -> 0
A75: Mantenimiento Impresora | F75: =E75*D75 -> 0
A76: Tinta | D76: 0 | F76: =E76*D76 -> 0
A77: Toner para impresora de equipos (en caso de dejar las impresoras) | D77: 0 | E77: 200 | F77: =E77*D77 -> 0
A78: Impresora Zebra Termica ZD230 ETHERNET Y USB | D78: 0 | E78: 400 | F78: =E78*D78 -> 0
A79: Mantenimiento Impresora Zebra Termica ZD230 ETHERNET Y USB | F79: =E79*D79 -> 0
A80: Lector inalambrico de codigo de barra | D80: 0 | F80: =E80*D80 -> 0
A81: Sistema de destilación de agua pequeño | D81: 0 | F81: =E81*D81 -> 0
A82: Sistema de osmosis | D82: 0 | F82: =E82*D82 -> 0
A83: Mantenimiento sistema de osmosis | F83: =E83*D83 -> 0
A84: Sistema de prefiltracion | D84: 0 | F84: =E84*D84 -> 0
A85: Mantenimiento sistema pre filtración | F85: =E85*D85 -> 0
A86: Tanque para resina mixta (muerta) | D86: 0 | F86: =E86*D86 -> 0
A87: Estructura de proteccion para sistema de agua | D87: 0 | F87: =E87*D87 -> 0
A88: MEMBRANE EQ.OSMOSIS, AG2521TF 2.5 diam | D88: 0 | F88: =E88*D88 -> 0
A89: FILTER NOM. P/SEDIMENTS PX10-20XX PURTR (CARBON - AZUL) | D89: 0 | F89: =E89*D89 -> 0
A90: FILTER NOM.P/SEDIMENTS GX05-20XX HYTREX (FIBRA - PAPEL - PAPEL) | D90: 0 | F90: =E90*D90 -> 0
A91: RESINA IONICA REGENERADA 20 " | D91: 0 | F91: =E91*D91 -> 0
A92: RESINA MUERTA 16kilos | D92: 0 | F92: =E92*D92 -> 0
A93: Sal en grano x quintal | D93: 0 | F93: =E93*D93 -> 0
A94: Modificaciones de espacio fisico - estructura | D94: 0 | F94: =E94*D94 -> 0
A95: Modificaciones de espacio fisico - mobiliario | F95: =E95*D95 -> 0
A96: Climatizacion del area | D96: 0 | F96: =E96*D96 -> 0
A97: Mantenimiento Climatizacion | F97: =E97*D97 -> 0
A98: Rollo de cable UTP CAT5e x 100m | D98: 0 | E98: 31 | F98: =E98*D98 -> 0
A99: Conector RJ45 Delta CAT5E x 50 unds | D99: 0 | E99: 10 | F99: =E99*D99 -> 0
A100: Rack Cerrado POWEST 5UR | B100: Soporte para servidor | D100: 0 | E100: 150 | F100: =E100*D100 -> 0
A101: Switch HP Aruba Ion 5 puertos | D101: 0 | E101: 60 | F101: =E101*D101 -> 0
A102: Switch HP Aruba Ion 1430 24 puertos | D102: 0 | E102: 200 | F102: =E102*D102 -> 0
A103: Extensiones y cortapicos | D103: 0 | F103: =E103*D103 -> 0
A104: Extras (tairas, canaletas, espiral plastico) | D104: 0 | F104: =E104*D104 -> 0
A105: Etiquetas | B105: Rollo x2000 uds | D105: 0 | E105: 6.29 | F105: =E105*D105 -> 0
A106: A4 printer paper | B106: Paquete x 500 uds | D106: 0 | E106: 3.85 | F106: =E106*D106 -> 0
A107: Refrigerador panorámico | D107: 0 | F107: =E107*D107 -> 0
A108: Mantenimiento Refrigerador panorámico | F108: =E108*D108 -> 0
A109: Refrigerador médico | D109: 0 | F109: =E109*D109 -> 0
A110: Mantenimiento Refrigerador médico | F110: =E110*D110 -> 0
A111: Termometro para refrigerador | D111: 0 | F111: =E111*D111 -> 0
A112: Termohigrometros | D112: 0 | E112: 70 | F112: =E112*D112 -> 0
A113: Cronometros digitales | D113: 0 | E113: 60 | F113: =E113*D113 -> 0
A114: Centrifuga | B114: 24 Tubos | D114: 0 | E114: 3800 | F114: =E114*D114 -> 0
A115: Mantenimiento Centrifuga | F115: =E115*D115 -> 0
A116: Servicio Logisticos Proveedores | D116: 0 | F116: =E116*D116 -> 0
A117: Servicio Logisticos Clientes | D117: 0 | F117: =E117*D117 -> 0
A118: Ampolla de agua bidestilada | D118: 0 | F118: =E118*D118 -> 0
A119: Agua destilada por galón | D119: 0 | F119: =E119*D119 -> 0
A120: Hisopos x 100 uds | B120: Mantenimiento | D120: 0 | E120: 0.62 | F120: =E120*D120 -> 0
A121: Gasas x 100 uds | B121: Mantenimiento | D121: 0 | E121: 5.9 | F121: =E121*D121 -> 0
A122: Alcohol prepad 10 x 100 uds | B122: Mantenimiento | D122: 0 | E122: 5 | F122: =E122*D122 -> 0
A123: Tubos eppendorf X 500 UDS | F123: =E123*D123 -> 0
A124: Otros | B124: capacitacion, tiempo, lugar, dias, break, material, alojamiento, etc | F124: =E124*D124 -> 0
E125: Sub total | F125: =SUM(F58:F124) -> 0
E126: 0.15 | F126: =+F125*0.15 -> 0
E127: Total | F127: =F125+F126 -> 0
A129: ¿Porque es importante ganar este proceso ?

Sheet c111
A1: CLIENTE
A2: FECHA
A3: MODALIDAD
A4: PLAZO | C4: MESES
A5: PROYECCIÓN | C5: MESES
A6: EQUIPO | B6: c 111
A8: ID | B8: REACTIVO | C8: DET/KIT | D8: DIAS ESTABILIDAD | E8: CANTIDAD PROCESO/AÑO | F8: PRODUCTO CALCULADO | G8: MINIMOS POR ESTABILIDAD | H8: PRODUCTO A ENTREGAR
A9: 4657527190 | B9: Glucosa | C9: 400 | D9: 120 | F9: =E9/C9 -> 0 | G9: =365/D9 -> 3.0416667
A10: 4657616190 | B10: Urea | C10: 400 | D10: 120 | F10: =E10/C10 -> 0 | G10: =365/D10 -> 3.0416667
A11: 5401755190 | B11: Creatinina | C11: 400 | D11: 120 | F11: =E11/C11 -> 0 | G11: =365/D11 -> 3.0416667
A12: 4657608190 | B12: Acido Úrico | C12: 400 | D12: 120 | F12: =E12/C12 -> 0 | G12: =365/D12 -> 3.0416667
A13: 4718917190 | B13: Colesterol | C13: 400 | D13: 120 | F13: =E13/C13 -> 0 | G13: =365/D13 -> 3.0416667
A14: 4657594190 | B14: Triglicéridos | C14: 200 | D14: 120 | F14: =E14/C14 -> 0 | G14: =365/D14 -> 3.0416667
A15: 4718569190 | B15: ALT - TGP | C15: 400 | D15: 120 | F15: =E15/C15 -> 0 | G15: =365/D15 -> 3.0416667
A16: 4657543190 | B16: AST - TGO | C16: 400 | D16: 120 | F16: =E16/C16 -> 0 | G16: =365/D16 -> 3.0416667
A17: 4657373190 | B17: Fosfatasa alcalina | C17: 200 | D17: 120 | F17: =E17/C17 -> 0 | G17: =365/D17 -> 3.0416667
A18: 5795648190 | B18: Bilirrubina Total | C18: 400 | D18: 120 | F18: =E18/C18 -> 0 | G18: =365/D18 -> 3.0416667
A19: 5589134190 | B19: Bilirrubina Directa | C19: 100 | D19: 60 | F19: =E19/C19 -> 0 | G19: =365/D19 -> 6.0833333
A20: 7528604190 | B20: HDL Colesterol | C20: 200 | D20: 60 | F20: =E20/C20 -> 0 | G20: =365/D20 -> 6.0833333
... A37: 7442050190 | B37: CK-MB | C37: 100 | D37: 60 | F37: =E37/C37 -> 0 | G37: =365/D37 -> 6.0833333
C38: TOTAL DET | E38: =SUM(E9:E37) -> 0
A39: CALIBRADOR
A40: 10759350190 | B40: Calibrator f.a.s. 12x3 ml | C40: 12 | D40: 28 | G40: =(365/D40)/C40 -> 1.0863095
A41: 12172623122 | B41: Cfas Lipids 3x1ML | C41: 3 | D41: 28 | G41: =(365/D41)/C41 -> 4.3452381
A42: 11355279216 | B42: Cfas Proteins | C42: 5 | D42: 28 | G42: =(365/D42)/C42 -> 2.6071429
A43: 4528417190 | B43: Cfas HbA1c, 3x2ml | C43: 3 | D43: 84 | G43: =(365/D43)/C43 -> 1.4484127
A44: 20751995190 | B44: Ammonia/Ethanol/CO2 Calibrator | C44: 2 | D44: 56 | G44: =(365/D44)/C44 -> 3.2589286
A45: 5050901190 | B45: Cfas D- Dimer | C45: 1 | D45: 84 | G45: =(365/D45)/C45 -> 4.3452381
A46: 11447394216 | B46: Calibrator f.a.s. CK‑MB | C46: 3 | D46: 28 | G46: =(365/D46)/C46 -> 4.3452381
A47: CONTROL
A48: 5947626190 | B48: PreciControl ClinChem Multi 1 4x5ml | C48: 4 | D48: 14 | G48: =(365/D48)/C48 -> 6.5178571
A49: 5947774190 | B49: PreciControl ClinChem Multi 2 4x5ml | C49: 4 | D49: 14 | G49: =(365/D49)/C49 -> 6.5178571
A50: 5479207190 | B50: PreciControl HBA1c Norm | C50: 4 | D50: 28 | G50: =(365/D50)/C50 -> 3.2589286
A51: 5912504190 | B51: PRECICONTROL HBA1C PATH | C51: 4 | D51: 28 | G51: =(365/D51)/C51 -> 3.2589286
A52: 20752401190 | B52: Ammonia/Ethanol/CO2 Control Normal | C52: 5 | D52: 56 | G52: =(365/D52)/C52 -> 1.3035714
A53: 20753009190 | B53: Ammonia/Ethanol/CO2 Control Normal | C53: 5 | D53: 56 | G53: =(365/D53)/C53 -> 1.3035714
A54: 5050936190 | B54: PreciControl D- Dimer | C54: 2 | D54: 84 | G54: =(365/D54)/C54 -> 2.172619
A55: CONSUMIBLES
A56: 4774230190 | B56: NaCL 9% cobas c 111 | C56: 4 | D56: 28 | G56: =(365/D56)/C56 -> 3.2589286
A57: 5007232190 | B57: HAEMOLYSE REAGENT 800T COBAS C111 | C57: 8 | D57: 10 | G57: =(365/D57)/C57 -> 4.5625
A58: 4663632190 | B58: Activator for cobas c,Integra,c111 | C58: 9 | D58: 12 | G58: =(365/D58)/C58 -> 3.3796296
A59: 11298500316 | B59: ISE CLEANING SOLUTION 5x100ml | C59: 5 | D59: 73 | G59: =(365/D59)/C59 -> 1
A60: 20754765322 | B60: Cobas Integra Cleaner | C60: 1 | D60: 84 | G60: =(365/D60)/C60 -> 4.3452381
A61: 4357108001 | B61: Micro Cuvette Segment | C61: 1 | D61: 365 | G61: =(365/D61)/C61 -> 1
A62: 4444191001 | B62: Sample cup 250 St | C62: 1 | D62: 365 | G62: =(365/D62)/C62 -> 1
A63: 4352483001 | B63: URISYS Thermo-printer paper 5 | C63: 5 | D63: 365 | G63: =(365/D63)/C63 -> 0.2
A64: 5344620001 | B64: LAMP HALOGEN 12V/20W ASSY | C64: 1 | D64: 365 | G64: =(365/D64)/C64 -> 1

Sheet c111 DETERMIACION
B2: ID | C2: REACTIVO | D2: DET/KIT | E2: DIAS ESTABILIDAD | F2: CANTIDAD PROCESO/AÑO | G2: PRODUCTO CALCULADO | H2: MINIMOS POR ESTABILIDAD | I2: PRODUCTO A ENTREGAR | K2: REDONDEADO A ENTREGAR | L2: PVP | M2: TOTAL | N2: $ DETERMINACION | O2: $DETERMINACION CON CONSUMIBLES Y EXTRAS | P2: TOTAL CON CONSUMIBLES Y EXTRAS | Q2: $ PARA PROCESO | R2: TOTAL PARA PROCESO | S2: VALOR INICIAL DEL PROCESO | T2: VALOR FINAL DEL PROCESO
A3: cfas | B3: 4657527190 | C3: Glucosa | D3: 400 | E3: 120 | F3: ='c111'!E9 -> 0 | G3: =F3/D3 -> 0 | H3: =30*BC!$B$47/E3 -> 0 | I3: =IF(H3>G3,H3,G3) -> 0 | J3: =IF(G3=0,0,I3) -> 0 | K3: =ROUNDUP(J3,0) -> 0 | L3: 50 | M3: =L3*K3 -> 0 | N3: =L3/D3 -> 0.125 | O3: =N3+$N$62+((BC!$F$125)/'c111 DETERMIACION'!$F$32) -> #DIV/0! | P3: =O3*F3 -> #DIV/0! | Q3: =((O3*0.15)+O3) -> #DIV/0! | R3: =Q3*F3 -> #DIV/0! | S3: =SUM(R3:R31) -> #DIV/0! | T3: =SUM(P3:P31) -> #DIV/0!
A4: =SUM(F3+F4+F5+F6+F7+F8+F9+F10+F11+F12+F13+F15+F16+F17+F18+F20+F21+F22+F24+F25+F28+F30) -> 0 | B4: 4657616190 | C4: Urea | D4: 400 | E4: 120 | F4: ='c111'!E10 -> 0 | G4: =F4/D4 -> 0 | H4: =30*BC!$B$47/E4 -> 0 | I4: =IF(H4>G4,H4,G4) -> 0 | J4: =IF(G4=0,0,I4) -> 0 | K4: =ROUNDUP(J4,0) -> 0 | L4: 62 | M4: =L4*K4 -> 0 | N4: =L4/D4 -> 0.155 | O4: =N4+$N$62+((BC!$F$125)/'c111 DETERMIACION'!$F$32) -> #DIV/0! | P4: =O4*F4 -> #DIV/0! | Q4: =((O4*0.15)+O4) -> #DIV/0! | R4: =Q4*F4 -> #DIV/0!
B5: 5401755190 | C5: Creatinina | D5: 400 | E5: 120 | F5: ='c111'!E11 -> 0 | G5: =F5/D5 -> 0 | H5: =30*BC!$B$47/E5 -> 0 | I5: =IF(H5>G5,H5,G5) -> 0 | J5: =IF(G5=0,0,I5) -> 0 | K5: =ROUNDUP(J5,0) -> 0 | L5: 74 | M5: =L5*K5 -> 0 | N5: =L5/D5 -> 0.185 | O5: =N5+$N$62+((BC!$F$125)/'c111 DETERMIACION'!$F$32) -> #DIV/0! | P5: =O5*F5 -> #DIV/0! | Q5: =((O5*0.15)+O5) -> #DIV/0! | R5: =Q5*F5 -> #DIV/0!
A6: ClinChem | B6: 4657608190 | C6: Acido Úrico | D6: 400 | E6: 120 | F6: ='c111'!E12 -> 0 | G6: =F6/D6 -> 0 | H6: =30*BC!$B$47/E6 -> 0 | I6: =IF(H6>G6,H6,G6) -> 0 | J6: =IF(G6=0,0,I6) -> 0 | K6: =ROUNDUP(J6,0) -> 0 | L6: 89 | M6: =L6*K6 -> 0 | N6: =L6/D6 -> 0.2225 | O6: =N6+$N$62+((BC!$F$125)/'c111 DETERMIACION'!$F$32) -> #DIV/0! | P6: =O6*F6 -> #DIV/0! | Q6: =((O6*0.15)+O6) -> #DIV/0! | R6: =Q6*F6 -> #DIV/0!
A7: =F3+F4+F5+F6+F7+F8+F9+F10+F11+F12+F13+F14+F15+F16+F17+F18+F19+F20+F21+F22+F24+F25+F26+F28+F31+F30 -> 0 | B7: 4718917190 | C7: Colesterol | D7: 400 | E7: 120 | F7: ='c111'!E13 -> 0 | G7: =F7/D7 -> 0 | H7: =30*BC!$B$47/E7 -> 0 | I7: =IF(H7>G7,H7,G7) -> 0 | J7: =IF(G7=0,0,I7) -> 0 | K7: =ROUNDUP(J7,0) -> 0 | L7: 83 | M7: =L7*K7 -> 0 | N7: =L7/D7 -> 0.2075 | O7: =N7+$N$62+((BC!$F$125)/'c111 DETERMIACION'!$F$32) -> #DIV/0! | P7: =O7*F7 -> #DIV/0! | Q7: =((O7*0.15)+O7) -> #DIV/0! | R7: =Q7*F7 -> #DIV/0!
B8: 4657594190 | C8: Triglicéridos | D8: 200 | E8: 120 | F8: ='c111'!E14 -> 0 | G8: =F8/D8 -> 0 | H8: =30*BC!$B$47/E8 -> 0 | I8: =IF(H8>G8,H8,G8) -> 0 | J8: =IF(G8=0,0,I8) -> 0 | K8: =ROUNDUP(J8,0) -> 0 | L8: 63 | M8: =L8*K8 -> 0 | N8: =L8/D8 -> 0.315 | O8: =N8+$N$62+((BC!$F$125)/'c111 DETERMIACION'!$F$32) -> #DIV/0! | P8: =O8*F8 -> #DIV/0! | Q8: =((O8*0.15)+O8) -> #DIV/0! | R8: =Q8*F8 -> #DIV/0!
A9: cfas Lipids | B9: 4718569190 | C9: ALT - TGP | D9: 400 | E9: 120 | F9: ='c111'!E15 -> 0 | G9: =F9/D9 -> 0 | H9: =30*BC!$B$47/E9 -> 0 | I9: =IF(H9>G9,H9,G9) -> 0 | J9: =IF(G9=0,0,I9) -> 0 | K9: =ROUNDUP(J9,0) -> 0 | L9: 103 | M9: =L9*K9 -> 0 | N9: =L9/D9 -> 0.2575 | O9: =N9+$N$62+((BC!$F$125)/'c111 DETERMIACION'!$F$32) -> #DIV/0! | P9: =O9*F9 -> #DIV/0! | Q9: =((O9*0.15)+O9) -> #DIV/0! | R9: =Q9*F9 -> #DIV/0!
A10: =SUM(F14+F19) -> 0 | B10: 4657543190 | C10: AST - TGO | D10: 400 | E10: 120 | F10: ='c111'!E16 -> 0 | G10: =F10/D10 -> 0 | H10: =30*BC!$B$47/E10 -> 0 | I10: =IF(H10>G10,H10,G10) -> 0 | J10: =IF(G10=0,0,I10) -> 0 | K10: =ROUNDUP(J10,0) -> 0 | L10: 100 | M10: =L10*K10 -> 0 | N10: =L10/D10 -> 0.25 | O10: =N10+$N$62+((BC!$F$125)/'c111 DETERMIACION'!$F$32) -> #DIV/0! | P10: =O10*F10 -> #DIV/0! | Q10: =((O10*0.15)+O10) -> #DIV/0! | R10: =Q10*F10 -> #DIV/0!
B11: 4657373190 | C11: Fosfatasa alcalina | D11: 200 | E11: 120 | F11: ='c111'!E17 -> 0 | G11: =F11/D11 -> 0 | H11: =30*BC!$B$47/E11 -> 0 | I11: =IF(H11>G11,H11,G11) -> 0 | J11: =IF(G11=0,0,I11) -> 0 | K11: =ROUNDUP(J11,0) -> 0 | L11: 107 | M11: =L11*K11 -> 0 | N11: =L11/D11 -> 0.535 | O11: =N11+$N$62+((BC!$F$125)/'c111 DETERMIACION'!$F$32) -> #DIV/0! | P11: =O11*F11 -> #DIV/0! | Q11: =((O11*0.15)+O11) -> #DIV/0! | R11: =Q11*F11 -> #DIV/0!
B12: 5795648190 | C12: Bilirrubina Total | D12: 400 | E12: 120 | F12: ='c111'!E18 -> 0 | G12: =F12/D12 -> 0 | H12: =30*BC!$B$47/E12 -> 0 | I12: =IF(H12>G12,H12,G12) -> 0 | J12: =IF(G12=0,0,I12) -> 0 | K12: =ROUNDUP(J12,0) -> 0 | L12: 78 | M12: =L12*K12 -> 0 | N12: =L12/D12 -> 0.195 | O12: =N12+$N$62+((BC!$F$125)/'c111 DETERMIACION'!$F$32) -> #DIV/0! | P12: =O12*F12 -> #DIV/0! | Q12: =((O12*0.15)+O12) -> #DIV/0! | R12: =Q12*F12 -> #DIV/0!
B13: 5589134190 | C13: Bilirrubina Directa | D13: 100 | E13: 60 | F13: ='c111'!E19 -> 0 | G13: =F13/D13 -> 0 | H13: =30*BC!$B$47/E13 -> 0 | I13: =IF(H13>G13,H13,G13) -> 0 | J13: =IF(G13=0,0,I13) -> 0 | K13: =ROUNDUP(J13,0) -> 0 | L13: 58 | M13: =L13*K13 -> 0 | N13: =L13/D13 -> 0.58 | O13: =N13+$N$62+((BC!$F$125)/'c111 DETERMIACION'!$F$32) -> #DIV/0! | P13: =O13*F13 -> #DIV/0! | Q13: =((O13*0.15)+O13) -> #DIV/0! | R13: =Q13*F13 -> #DIV/0!
B14: 7528604190 | C14: HDL Colesterol | D14: 200 | E14: 60 | F14: ='c111'!E20 -> 0 | G14: =F14/D14 -> 0 | H14: =30*BC!$B$47/E14 -> 0 | I14: =IF(H14>G14,H14,G14) -> 0 | J14: =IF(G14=0,0,I14) -> 0 | K14: =ROUNDUP(J14,0) -> 0 | L14: 222 | M14: =L14*K14 -> 0 | N14: =L14/D14 -> 1.11 | O14: =N14+$N$62+((BC!$F$125)/'c111 DETERMIACION'!$F$32) -> #DIV/0! | P14: =O14*F14 -> #DIV/0! | Q14: =((O14*0.15)+O14) -> #DIV/0! | R14: =Q14*F14 -> #DIV/0!
B15: 5401496190 | C15: AMILASA | D15: 200 | E15: 60 | F15: ='c111'!E21 -> 0 | G15: =F15/D15 -> 0 | H15: =30*BC!$B$47/E15 -> 0 | I15: =IF(H15>G15,H15,G15) -> 0 | J15: =IF(G15=0,0,I15) -> 0 | K15: =ROUNDUP(J15,0) -> 0 | L15: 138 | M15: =L15*K15 -> 0 | N15: =L15/D15 -> 0.69 | O15: =N15+$N$62+((BC!$F$125)/'c111 DETERMIACION'!$F$32) -> #DIV/0! | P15: =O15*F15 -> #DIV/0! | Q15: =((O15*0.15)+O15) -> #DIV/0! | R15: =Q15*F15 -> #DIV/0!
B16: 5401704190 | C16: LIPASA | D16: 100 | E16: 60 | F16: ='c111'!E22 -> 0 | G16: =F16/D16 -> 0 | H16: =30*BC!$B$47/E16 -> 0 | I16: =IF(H16>G16,H16,G16) -> 0 | J16: =IF(G16=0,0,I16) -> 0 | K16: =ROUNDUP(J16,0) -> 0 | L16: 132 | M16: =L16*K16 -> 0 | N16: =L16/D16 -> 1.32 | O16: =N16+$N$62+((BC!$F$125)/'c111 DETERMIACION'!$F$32) -> #DIV/0! | P16: =O16*F16 -> #DIV/0! | Q16: =((O16*0.15)+O16) -> #DIV/0! | R16: =Q16*F16 -> #DIV/0!
B17: 5401461190 | C17: GGT | D17: 200 | E17: 60 | F17: ='c111'!E23 -> 0 | G17: =F17/D17 -> 0 | H17: =30*BC!$B$47/E17 -> 0 | I17: =IF(H17>G17,H17,G17) -> 0 | J17: =IF(G17=0,0,I17) -> 0 | K17: =ROUNDUP(J17,0) -> 0 | L17: 67 | M17: =L17*K17 -> 0 | N17: =L17/D17 -> 0.335 | O17: =N17+$N$62+((BC!$F$125)/'c111 DETERMIACION'!$F$32) -> #DIV/0! | P17: =O17*F17 -> #DIV/0! | Q17: =((O17*0.15)+O17) -> #DIV/0! | R17: =Q17*F17 -> #DIV/0!
B18: 4657357190 | C18: Albumina | D18: 400 | E18: 120 | F18: ='c111'!E24 -> 0 | G18: =F18/D18 -> 0 | H18: =30*BC!$B$47/E18 -> 0 | I18: =IF(H18>G18,H18,G18) -> 0 | J18: =IF(G18=0,0,I18) -> 0 | K18: =ROUNDUP(J18,0) -> 0 | L18: 85 | M18: =L18*K18 -> 0 | N18: =L18/D18 -> 0.2125 | O18: =N18+$N$62+((BC!$F$125)/'c111 DETERMIACION'!$F$32) -> #DIV/0! | P18: =O18*F18 -> #DIV/0! | Q18: =((O18*0.15)+O18) -> #DIV/0! | R18: =Q18*F18 -> #DIV/0!
B19: 7005806190 | C19: LDL Colesterol | D19: 100 | E19: 60 | F19: ='c111'!E25 -> 0 | G19: =F19/D19 -> 0 | H19: =30*BC!$B$47/E19 -> 0 | I19: =IF(H19>G19,H19,G19) -> 0 | J19: =IF(G19=0,0,I19) -> 0 | K19: =ROUNDUP(J19,0) -> 0 | L19: 109 | M19: =L19*K19 -> 0 | N19: =L19/D19 -> 1.09 | O19: =N19+$N$62+((BC!$F$125)/'c111 DETERMIACION'!$F$32) -> #DIV/0! | P19: =O19*F19 -> #DIV/0! | Q19: =((O19*0.15)+O19) -> #DIV/0! | R19: =Q19*F19 -> #DIV/0!
B20: 5061504190 | C20: Calcio | D20: 400 | E20: 120 | F20: ='c111'!E26 -> 0 | G20: =F20/D20 -> 0 | H20: =30*BC!$B$47/E20 -> 0 | I20: =IF(H20>G20,H20,G20) -> 0 | J20: =IF(G20=0,0,I20) -> 0 | K20: =ROUNDUP(J20,0) -> 0 | L20: 169 | M20: =L20*K20 -> 0 | N20: =L20/D20 -> 0.4225 | O20: =N20+$N$62+((BC!$F$125)/'c111 DETERMIACION'!$F$32) -> #DIV/0! | P20: =O20*F20 -> #DIV/0! | Q20: =((O20*0.15)+O20) -> #DIV/0! | R20: =Q20*F20 -> #DIV/0!
B21: 7442017190 | C21: CK | D21: 200 | E21: 60 | F21: ='c111'!E27 -> 0 | G21: =F21/D21 -> 0 | H21: =30*BC!$B$47/E21 -> 0 | I21: =IF(H21>G21,H21,G21) -> 0 | J21: =IF(G21=0,0,I21) -> 0 | K21: =ROUNDUP(J21,0) -> 0 | L21: 140 | M21: =L21*K21 -> 0 | N21: =L21/D21 -> 0.7 | O21: =N21+$N$62+((BC!$F$125)/'c111 DETERMIACION'!$F$32) -> #DIV/0! | P21: =O21*F21 -> #DIV/0! | Q21: =((O21*0.15)+O21) -> #DIV/0! | R21: =Q21*F21 -> #DIV/0!
B22: 5401674190 | C22: LDH | D22: 100 | E22: 60 | F22: ='c111'!E28 -> 0 | G22: =F22/D22 -> 0 | H22: =30*BC!$B$47/E22 -> 0 | I22: =IF(H22>G22,H22,G22) -> 0 | J22: =IF(G22=0,0,I22) -> 0 | K22: =ROUNDUP(J22,0) -> 0 | L22: 128 | M22: =L22*K22 -> 0 | N22: =L22/D22 -> 1.28 | O22: =N22+$N$62+((BC!$F$125)/'c111 DETERMIACION'!$F$32) -> #DIV/0! | P22: =O22*F22 -> #DIV/0! | Q22: =((O22*0.15)+O22) -> #DIV/0! | R22: =Q22*F22 -> #DIV/0!
... B31: 7442050190 | C31: CK-MB | D31: 100 | E31: 60 | F31: ='c111'!E37 -> 0 | G31: =F31/D31 -> 0 | H31: =30*BC!$B$47/E31 -> 0 | I31: =IF(H31>G31,H31,G31) -> 0 | J31: =IF(G31=0,0,I31) -> 0 | K31: =ROUNDUP(J31,0) -> 0 | L31: 164 | M31: =L31*K31 -> 0 | N31: =L31/D31 -> 1.64 | O31: =N31+$N$62+((BC!$F$125)/'c111 DETERMIACION'!$F$32) -> #DIV/0! | P31: =O31*F31 -> #DIV/0! | Q31: =((O31*0.15)+O31) -> #DIV/0! | R31: =Q31*F31 -> #DIV/0!
D32: TOTAL DET | F32: =SUM(F3:F31) -> 0
B33: CALIBRADOR | K33: MAXIMOS | L33: PVP POR UNIDADES | M33: VALOR POR CAJA | N33: VALOR TOTAL | O33: EN KITS | P33: EN KITS CERRADO
B34: 10759350190 | C34: Calibrator f.a.s. 12x3 ml | D34: 12 | E34: 28 | G34: =(A4/(0.005*400)/3000) -> 0 | H34: =30*BC!$B$47/E34 -> 0 | I34: =IF(G34>H34,G34,H34) -> 0 | J34: =ROUNDUP(I34,0) -> 0 | K34: =IF(A4>0,J34,0) -> 0 | L34: =M34/D34 -> 12 | M34: 144 | N34: =L34*K34 -> 0 | O34: =K34/D34 -> 0 | P34: =ROUNDUP(O34,0) -> 0
B35: 12172623122 | C35: Cfas Lipids 3x1ML | D35: 3 | E35: 28 | G35: =(A10*(0.008*(350/1000))) -> 0 | H35: =30*BC!$B$47/E35 -> 0 | I35: =IF(G35>H35,G35,H35) -> 0 | J35: =ROUNDUP(I35,0) -> 0 | K35: =IF(A10>0,J35,0) -> 0 | L35: =M35/D35 -> 31 | M35: 93 | N35: =L35*K35 -> 0 | O35: =K35/D35 -> 0 | P35: =ROUNDUP(O35,0) -> 0
B36: 11355279216 | C36: Cfas Proteins | D36: 5 | E36: 28 | G36: =(F26*(0.014*(500/2000))) -> 0 | H36: =30*BC!$B$47/E36 -> 0 | I36: =IF(G36>H36,G36,H36) -> 0 | J36: =ROUNDUP(I36,0) -> 0 | K36: =IF(F26>0,J36,0) -> 0 | L36: =M36/D36 -> 29.8 | M36: 149 | N36: =L36*K36 -> 0 | O36: =K36/D36 -> 0 | P36: =ROUNDUP(O36,0) -> 0
B37: 4528417190 | C37: Cfas HbA1c, 3x2ml | D37: 3 | E37: 84 | G37: =(F23*(0.014*(500/2000))) -> 0 | H37: =30*BC!$B$47/E37 -> 0 | I37: =IF(G37>H37,G37,H37) -> 0 | J37: =ROUNDUP(I37,0) -> 0 | K37: =IF(F23>0,J37,0) -> 0 | L37: =M37/D37 -> 150.33333 | M37: 451 | N37: =L37*K37 -> 0 | O37: =K37/D37 -> 0 | P37: =ROUNDUP(O37,0) -> 0
B38: 20751995190 | C38: Ammonia/Ethanol/CO2 Calibrator | D38: 2 | E38: 56 | G38: =(F29*(0.014*(500/2000))) -> 0 | H38: =30*BC!$B$47/E38 -> 0 | I38: =IF(G38>H38,G38,H38) -> 0 | J38: =ROUNDUP(I38,0) -> 0 | K38: =IF(F24>0,J38,0) -> 0 | L38: =M38/D38 -> 313.5 | M38: 627 | N38: =L38*K38 -> 0 | O38: =K38/D38 -> 0 | P38: =ROUNDUP(O38,0) -> 0
B39: 5050901190 | C39: Cfas D- Dimer | D39: 1 | E39: 84 | G39: =(F27*(0.014*(500/2000))) -> 0 | H39: =30*BC!$B$47/E39 -> 0 | I39: =IF(G39>H39,G39,H39) -> 0 | J39: =ROUNDUP(I39,0) -> 0 | K39: =IF(F27>0,J39,0) -> 0 | L39: =M39/D39 -> 282 | M39: 282 | N39: =L39*K39 -> 0 | O39: =K39/D39 -> 0 | P39: =ROUNDUP(O39,0) -> 0
B40: 11447394216 | C40: Calibrator f.a.s. CK‑MB | D40: 3 | E40: 28 | G40: =(F31*(0.014*(500/2000))) -> 0 | H40: =30*BC!$B$47/E40 -> 0 | I40: =IF(G40>H40,G40,H40) -> 0 | J40: =ROUNDUP(I40,0) -> 0 | K40: =IF(F28>0,J40,0) -> 0 | L40: =M40/D40 -> 25.333333 | M40: 76 | N40: =L40*K40 -> 0 | O40: =K40/D40 -> 0 | P40: =ROUNDUP(O40,0) -> 0
B41: CONTROL
B42: 5947626190 | C42: PreciControl ClinChem Multi 1 4x5ml | D42: 4 | E42: 14 | G42: =(A7/(0.003*350)/5000) -> 0 | H42: =30*BC!$B$47/E42 -> 0 | I42: =IF(G42>H42,G42,H42) -> 0 | J42: =ROUNDUP(I42,0) -> 0 | K42: =IF(F32>0,J42,0) -> 0 | L42: =M42/D42 -> 14.25 | M42: 57 | N42: =L42*K42 -> 0 | O42: =K42/D42 -> 0 | P42: =ROUNDUP(O42,0) -> 0
B43: 5947774190 | C43: PreciControl ClinChem Multi 2 4x5ml | D43: 4 | E43: 14 | G43: =(A7/(0.003*350)/5000) -> 0 | H43: =30*BC!$B$47/E43 -> 0 | I43: =IF(G43>H43,G43,H43) -> 0 | J43: =ROUNDUP(I43,0) -> 0 | K43: =IF(F32>0,J43,0) -> 0 | L43: =M43/D43 -> 22.75 | M43: 91 | N43: =L43*K43 -> 0 | O43: =K43/D43 -> 0 | P43: =ROUNDUP(O43,0) -> 0
B44: 5479207190 | C44: PreciControl HBA1c Norm | D44: 4 | E44: 28 | G44: =(F23/(0.0007*150)/1000) -> 0 | H44: =30*BC!$B$47/E44 -> 0 | I44: =IF(G44>H44,G44,H44) -> 0 | J44: =ROUNDUP(I44,0) -> 0 | K44: =IF(F23>0,J44,0) -> 0 | L44: =M44/D44 -> 77.25 | M44: 309 | N44: =L44*K44 -> 0 | O44: =K44/D44 -> 0 | P44: =ROUNDUP(O44,0) -> 0
B45: 5912504190 | C45: PRECICONTROL HBA1C PATH | D45: 4 | E45: 28 | G45: =(F23/(0.0007*150)/1000) -> 0 | H45: =30*BC!$B$47/E45 -> 0 | I45: =IF(G45>H45,G45,H45) -> 0 | J45: =ROUNDUP(I45,0) -> 0 | K45: =IF(F23>0,J45,0) -> 0 | L45: =M45/D45 -> 154.5 | M45: 618 | N45: =L45*K45 -> 0 | O45: =K45/D45 -> 0 | P45: =ROUNDUP(O45,0) -> 0
B46: 20752401190 | C46: Ammonia/Ethanol/CO2 Control Normal | D46: 5 | E46: 56 | G46: =(F29/(0.0007*150)/1000) -> 0 | H46: =30*BC!$B$47/E46 -> 0 | I46: =IF(G46>H46,G46,H46) -> 0 | J46: =ROUNDUP(I46,0) -> 0 | K46: =IF(F24>0,J46,0) -> 0 | L46: =M46/D46 -> 41.4 | M46: 207 | N46: =L46*K46 -> 0 | O46: =K46/D46 -> 0 | P46: =ROUNDUP(O46,0) -> 0
B47: 20753009190 | C47: Ammonia/Ethanol/CO2 Control Normal | D47: 5 | E47: 56 | G47: =F29/(0.0007*150)/1000 -> 0 | H47: =30*BC!$B$47/E47 -> 0 | I47: =IF(G47>H47,G47,H47) -> 0 | J47: =ROUNDUP(I47,0) -> 0 | K47: =IF(F25>0,J47,0) -> 0 | L47: =M47/D47 -> 45.4 | M47: 227 | N47: =L47*K47 -> 0 | O47: =K47/D47 -> 0 | P47: =ROUNDUP(O47,0) -> 0
B48: 5050936190 | C48: PreciControl D- Dimer | D48: 2 | E48: 84 | G48: =(F27/(0.0004*300)/3000) -> 0 | H48: =30*BC!$B$47/E48 -> 0 | I48: =IF(G48>H48,G48,H48) -> 0 | J48: =ROUNDUP(I48,0) -> 0 | K48: =IF(F27>0,J48,0) -> 0 | L48: =M48/D48 -> 244 | M48: 488 | N48: =L48*K48 -> 0 | O48: =K48/D48 -> 0 | P48: =ROUNDUP(O48,0) -> 0
B49: CONSUMIBLES
B50: 4774230190 | C50: NaCL 9% cobas c 111 | D50: 4 | E50: 28 | G50: =(F32/(0.002*800)/12000) -> 0 | H50: =30*BC!$B$47/E50 -> 0 | I50: =IF(G50>H50,G50,H50) -> 0 | J50: =ROUNDUP(I50,0) -> 0 | K50: =IF(F32>0,J50,0) -> 0 | L50: =M50/D50 -> 17.75 | M50: 71 | N50: =L50*K50 -> 0 | O50: =K50/D50 -> 0 | P50: =ROUNDUP(O50,0) -> 0
B51: 5007232190 | C51: HAEMOLYSE REAGENT 800T COBAS C111 | D51: 8 | E51: 10 | G51: =(F23/(0.00006*800)/6300) -> 0 | H51: =30*BC!$B$47/E51 -> 0 | I51: =IF(G51>H51,G51,H51) -> 0 | J51: =ROUNDUP(I51,0) -> 0 | K51: =IF(F23>0,J51,0) -> 0 | L51: =M51/D51 -> 54.875 | M51: 439 | N51: =L51*K51 -> 0 | O51: =K51/D51 -> 0 | P51: =ROUNDUP(O51,0) -> 0
B52: 4663632190 | C52: Activator for cobas c,Integra,c111 | D52: 9 | E52: 12 | G52: =30*BCB48/E52 -> 0 | H52: =30*BC!$B$47/E52 -> 0 | I52: =IF(G52>H52,G52,H52) -> 0 | J52: =ROUNDUP(I52,0) -> 0 | K52: =IF(F32>0,J52,0) -> 0 | L52: =M52/D52 -> 17.222222 | M52: 155 | N52: =L52*K52 -> 0 | O52: =K52/D52 -> 0 | P52: =ROUNDUP(O52,0) -> 0
B53: 11298500316 | C53: ISE CLEANING SOLUTION 5x100ml | D53: 5 | E53: 73 | G53: =30*BCB48/E53 -> 0 | H53: =30*BC!$B$47/E53 -> 0 | I53: =IF(G53>H53,G53,H53) -> 0 | J53: =ROUNDUP(I53,0) -> 0 | K53: =IF(F32>0,J53,0) -> 0 | L53: =M53/D53 -> 19.6 | M53: 98 | N53: =L53*K53 -> 0 | O53: =K53/D53 -> 0 | P53: =ROUNDUP(O53,0) -> 0
B54: 20754765322 | C54: Cobas Integra Cleaner | D54: 1 | E54: 84 | G54: =(F32/(0.005*48)/6300) -> 0 | H54: =30*BC!$B$47/E54 -> 0 | I54: =IF(G54>H54,G54,H54) -> 0 | J54: =ROUNDUP(I54,0) -> 0 | K54: =IF(F32>0,J54,0) -> 0 | L54: =M54/D54 -> 46 | M54: 46 | N54: =L54*K54 -> 0 | O54: =K54/D54 -> 0 | P54: =ROUNDUP(O54,0) -> 0
B55: 4357108001 | C55: Micro Cuvette Segment | D55: 1 | E55: 365 | G55: =((F32+(F32*0.01))/1680) -> 0 | H55: =((365/E55)) -> 1 | I55: =IF(G55>H55,G55,H55) -> 1 | J55: =ROUNDUP(I55,0) -> 1 | K55: =IF(F32>0,J55,0) -> 0 | L55: =M55/D55 -> 179 | M55: 179 | N55: =L55*K55 -> 0 | O55: =K55/D55 -> 0 | P55: =ROUNDUP(O55,0) -> 0
B56: 4444191001 | C56: Sample cup 250 St | D56: 1 | E56: 365 | G56: =((F32-(F32*0.9))/E56) -> 0 | H56: =365/E56 -> 1 | I56: =IF(G56>H56,G56,H56) -> 1 | J56: =ROUNDUP(I56,0) -> 1 | K56: =IF(F32>0,J56,0) -> 0 | L56: =M56/D56 -> 9 | M56: 9 | N56: =L56*K56 -> 0 | O56: =K56/D56 -> 0 | P56: =ROUNDUP(O56,0) -> 0
B57: 4352483001 | C57: URISYS Thermo-printer paper 5 | D57: 1 | E57: 365 | G57: =((F32-(F32*0.97))/E57) -> 0 | H57: =(365/E56) -> 1 | I57: =IF(G57>H57,G57,H57) -> 1 | J57: =ROUNDUP(I57,0) -> 1 | K57: =IF(F32>0,J57,0) -> 0 | L57: =M57/D57 -> 19 | M57: 19 | N57: =L57*K57 -> 0 | O57: =K57/D57 -> 0 | P57: =ROUNDUP(O57,0) -> 0
B58: 5344620001 | C58: LAMP HALOGEN 12V/20W ASSY | D58: 1 | E58: 365 | G58: =(F32/(0.05*30)/6300) -> 0 | H58: =365/E58 -> 1 | I58: =IF(G58>H58,G58,H58) -> 1 | J58: =ROUNDUP(I58,0) -> 1 | K58: =IF(F32>0,J58,0) -> 0 | L58: =M58/D58 -> 105 | M58: 105 | N58: =L58*K58 -> 0 | O58: =K58/D58 -> 0 | P58: =ROUNDUP(O58,0) -> 0
B59: INS218 | C59: Tubos eppendorf | D59: 1 | E59: 365 | G59: =((F32-(F32*0.98))/E59) -> 0 | H59: =365/E59 -> 1 | I59: =IF(G59>H59,G59,H59) -> 1 | J59: =ROUNDUP(I59,0) -> 1 | K59: =IF(F32>0,J59,0) -> 0 | L59: 6.5 | M59: =L59*K59 -> 0 | N59: =L59*K59 -> 0 | O59: =K59/D59 -> 0 | P59: =ROUNDUP(O59,0) -> 0
B60: ALQUILER | K60: =BCB48 -> 0 | L60: 390 | M60: =L60*K60 -> 0 | N60: =L60*K60 -> 0
N61: =SUM(N34:N60) -> 0
N62: =N61/F32 -> #DIV/0!

Sheet c111 PRUEBA EFECTIVA
B2: ID | C2: REACTIVO | D2: DET/KIT | E2: DIAS ESTABILIDAD | F2: CANTIDAD PROCESO/AÑO | G2: PARA PRUEBA EFECTIVA | H2: PRODUCTO CALCULADO | I2: MINIMOS POR ESTABILIDAD | J2: PRODUCTO A ENTREGAR | L2: REDONDEADO A ENTREGAR | M2: PVP | N2: TOTAL | O2: $ DETERMINACION | P2: $DETERMINACION CON CONSUMIBLES Y EXTRAS | Q2: TOTAL CON CONSUMIBLES Y EXTRAS | R2: $ PARA PROCESO | S2: TOTAL PARA PROCESO | T2: VALOR INICIAL DEL PROCESO | U2: VALOR FINAL DEL PROCESO
A3: =SUM(G3+G4+G5+G6+G7+G8+G9+G10+G11+G12+G13+G15+G16+G17+G18+G20+G21+G22+G24+G25+G28) -> 0 | B3: 4657527190 | C3: Glucosa | D3: 400 | E3: 120 | F3: ='c111'!E9 -> 0 | G3: =((F3*0.2)+(F3)) -> 0 | H3: =G3/D3 -> 0 | I3: =30*BC!$B$47/E3 -> 0 | J3: =IF(I3>H3,I3,H3) -> 0 | K3: =IF(H3=0,0,J3) -> 0 | L3: =ROUNDUP(K3,0) -> 0 | M3: 50 | N3: =M3*L3 -> 0 | O3: =M3/D3 -> 0.125 | P3: =O3+$O$62+((BC!$F$125)/'c111 DETERMIACION'!$F$32) -> #DIV/0! | Q3: =P3*F3 -> #DIV/0! | R3: =((P3*0.15)+P3) -> #DIV/0! | S3: =R3*F3 -> #DIV/0! | T3: =SUM(S3:S31) -> #DIV/0! | U3: =SUM(Q3:Q31) -> #DIV/0!
A4: =G3+G4+G5+G6+G7+G8+G9+G10+G11+G12+G13+G14+G15+G16+G17+G18+G19+G20+G21+G22+G24+G25+G26+G28 -> 0 | B4: 4657616190 | C4: Urea | D4: 400 | E4: 120 | F4: ='c111'!E10 -> 0 | G4: =((F4*0.2)+(F4)) -> 0 | H4: =G4/D4 -> 0 | I4: =30*BC!$B$47/E4 -> 0 | J4: =IF(I4>H4,I4,H4) -> 0 | K4: =IF(H4=0,0,J4) -> 0 | L4: =ROUNDUP(K4,0) -> 0 | M4: 62 | N4: =M4*L4 -> 0 | O4: =M4/D4 -> 0.155 | P4: =O4+$O$62+((BC!$F$125)/'c111 DETERMIACION'!$F$32) -> #DIV/0! | Q4: =P4*F4 -> #DIV/0! | R4: =((P4*0.15)+P4) -> #DIV/0! | S4: =R4*F4 -> #DIV/0!
B5: 5401755190 | C5: Creatinina | D5: 400 | E5: 120 | F5: ='c111'!E11 -> 0 | G5: =((F5*0.2)+(F5)) -> 0 | H5: =G5/D5 -> 0 | I5: =30*BC!$B$47/E5 -> 0 | J5: =IF(I5>H5,I5,H5) -> 0 | K5: =IF(H5=0,0,J5) -> 0 | L5: =ROUNDUP(K5,0) -> 0 | M5: 74 | N5: =M5*L5 -> 0 | O5: =M5/D5 -> 0.185 | P5: =O5+$O$62+((BC!$F$125)/'c111 DETERMIACION'!$F$32) -> #DIV/0! | Q5: =P5*F5 -> #DIV/0! | R5: =((P5*0.15)+P5) -> #DIV/0! | S5: =R5*F5 -> #DIV/0!
B6: 4657608190 | C6: Acido Úrico | D6: 400 | E6: 120 | F6: ='c111'!E12 -> 0 | G6: =((F6*0.2)+(F6)) -> 0 | H6: =G6/D6 -> 0 | I6: =30*BC!$B$47/E6 -> 0 | J6: =IF(I6>H6,I6,H6) -> 0 | K6: =IF(H6=0,0,J6) -> 0 | L6: =ROUNDUP(K6,0) -> 0 | M6: 89 | N6: =M6*L6 -> 0 | O6: =M6/D6 -> 0.2225 | P6: =O6+$O$62+((BC!$F$125)/'c111 DETERMIACION'!$F$32) -> #DIV/0! | Q6: =P6*F6 -> #DIV/0! | R6: =((P6*0.15)+P6) -> #DIV/0! | S6: =R6*F6 -> #DIV/0!
B7: 4718917190 | C7: Colesterol | D7: 400 | E7: 120 | F7: ='c111'!E13 -> 0 | G7: =((F7*0.2)+(F7)) -> 0 | H7: =G7/D7 -> 0 | I7: =30*BC!$B$47/E7 -> 0 | J7: =IF(I7>H7,I7,H7) -> 0 | K7: =IF(H7=0,0,J7) -> 0 | L7: =ROUNDUP(K7,0) -> 0 | M7: 83 | N7: =M7*L7 -> 0 | O7: =M7/D7 -> 0.2075 | P7: =O7+$O$62+((BC!$F$125)/'c111 DETERMIACION'!$F$32) -> #DIV/0! | Q7: =P7*F7 -> #DIV/0! | R7: =((P7*0.15)+P7) -> #DIV/0! | S7: =R7*F7 -> #DIV/0!
B8: 4657594190 | C8: Triglicéridos | D8: 200 | E8: 120 | F8: ='c111'!E14 -> 0 | G8: =((F8*0.2)+(F8)) -> 0 | H8: =G8/D8 -> 0 | I8: =30*BC!$B$47/E8 -> 0 | J8: =IF(I8>H8,I8,H8) -> 0 | K8: =IF(H8=0,0,J8) -> 0 | L8: =ROUNDUP(K8,0) -> 0 | M8: 63 | N8: =M8*L8 -> 0 | O8: =M8/D8 -> 0.315 | P8: =O8+$O$62+((BC!$F$125)/'c111 DETERMIACION'!$F$32) -> #DIV/0! | Q8: =P8*F8 -> #DIV/0! | R8: =((P8*0.15)+P8) -> #DIV/0! | S8: =R8*F8 -> #DIV/0!
B9: 4718569190 | C9: ALT - TGP | D9: 400 | E9: 120 | F9: ='c111'!E15 -> 0 | G9: =((F9*0.2)+(F9)) -> 0 | H9: =G9/D9 -> 0 | I9: =30*BC!$B$47/E9 -> 0 | J9: =IF(I9>H9,I9,H9) -> 0 | K9: =IF(H9=0,0,J9) -> 0 | L9: =ROUNDUP(K9,0) -> 0 | M9: 103 | N9: =M9*L9 -> 0 | O9: =M9/D9 -> 0.2575 | P9: =O9+$O$62+((BC!$F$125)/'c111 DETERMIACION'!$F$32) -> #DIV/0! | Q9: =P9*F9 -> #DIV/0! | R9: =((P9*0.15)+P9) -> #DIV/0! | S9: =R9*F9 -> #DIV/0!
B10: 4657543190 | C10: AST - TGO | D10: 400 | E10: 120 | F10: ='c111'!E16 -> 0 | G10: =((F10*0.2)+(F10)) -> 0 | H10: =G10/D10 -> 0 | I10: =30*BC!$B$47/E10 -> 0 | J10: =IF(I10>H10,I10,H10) -> 0 | K10: =IF(H10=0,0,J10) -> 0 | L10: =ROUNDUP(K10,0) -> 0 | M10: 100 | N10: =M10*L10 -> 0 | O10: =M10/D10 -> 0.25 | P10: =O10+$O$62+((BC!$F$125)/'c111 DETERMIACION'!$F$32) -> #DIV/0! | Q10: =P10*F10 -> #DIV/0! | R10: =((P10*0.15)+P10) -> #DIV/0! | S10: =R10*F10 -> #DIV/0!
B11: 4657373190 | C11: Fosfatasa alcalina | D11: 200 | E11: 120 | F11: ='c111'!E17 -> 0 | G11: =((F11*0.2)+(F11)) -> 0 | H11: =G11/D11 -> 0 | I11: =30*BC!$B$47/E11 -> 0 | J11: =IF(I11>H11,I11,H11) -> 0 | K11: =IF(H11=0,0,J11) -> 0 | L11: =ROUNDUP(K11,0) -> 0 | M11: 107 | N11: =M11*L11 -> 0 | O11: =M11/D11 -> 0.535 | P11: =O11+$O$62+((BC!$F$125)/'c111 DETERMIACION'!$F$32) -> #DIV/0! | Q11: =P11*F11 -> #DIV/0! | R11: =((P11*0.15)+P11) -> #DIV/0! | S11: =R11*F11 -> #DIV/0!
B12: 5795648190 | C12: Bilirrubina Total | D12: 400 | E12: 120 | F12: ='c111'!E18 -> 0 | G12: =((F12*0.2)+(F12)) -> 0 | H12: =G12/D12 -> 0 | I12: =30*BC!$B$47/E12 -> 0 | J12: =IF(I12>H12,I12,H12) -> 0 | K12: =IF(H12=0,0,J12) -> 0 | L12: =ROUNDUP(K12,0) -> 0 | M12: 78 | N12: =M12*L12 -> 0 | O12: =M12/D12 -> 0.195 | P12: =O12+$O$62+((BC!$F$125)/'c111 DETERMIACION'!$F$32) -> #DIV/0! | Q12: =P12*F12 -> #DIV/0! | R12: =((P12*0.15)+P12) -> #DIV/0! | S12: =R12*F12 -> #DIV/0!
B13: 5589134190 | C13: Bilirrubina Directa | D13: 100 | E13: 60 | F13: ='c111'!E19 -> 0 | G13: =((F13*0.2)+(F13)) -> 0 | H13: =G13/D13 -> 0 | I13: =30*BC!$B$47/E13 -> 0 | J13: =IF(I13>H13,I13,H13) -> 0 | K13: =IF(H13=0,0,J13) -> 0 | L13: =ROUNDUP(K13,0) -> 0 | M13: 58 | N13: =M13*L13 -> 0 | O13: =M13/D13 -> 0.58 | P13: =O13+$O$62+((BC!$F$125)/'c111 DETERMIACION'!$F$32) -> #DIV/0! | Q13: =P13*F13 -> #DIV/0! | R13: =((P13*0.15)+P13) -> #DIV/0! | S13: =R13*F13 -> #DIV/0!
A14: =SUM(G14+G19) -> 0 | B14: 7528604190 | C14: HDL Colesterol | D14: 200 | E14: 60 | F14: ='c111'!E20 -> 0 | G14: =((F14*0.2)+(F14)) -> 0 | H14: =G14/D14 -> 0 | I14: =30*BC!$B$47/E14 -> 0 | J14: =IF(I14>H14,I14,H14) -> 0 | K14: =IF(H14=0,0,J14) -> 0 | L14: =ROUNDUP(K14,0) -> 0 | M14: 222 | N14: =M14*L14 -> 0 | O14: =M14/D14 -> 1.11 | P14: =O14+$O$62+((BC!$F$125)/'c111 DETERMIACION'!$F$32) -> #DIV/0! | Q14: =P14*F14 -> #DIV/0! | R14: =((P14*0.15)+P14) -> #DIV/0! | S14: =R14*F14 -> #DIV/0!
B15: 5401496190 | C15: AMILASA | D15: 200 | E15: 60 | F15: ='c111'!E21 -> 0 | G15: =((F15*0.2)+(F15)) -> 0 | H15: =G15/D15 -> 0 | I15: =30*BC!$B$47/E15 -> 0 | J15: =IF(I15>H15,I15,H15) -> 0 | K15: =IF(H15=0,0,J15) -> 0 | L15: =ROUNDUP(K15,0) -> 0 | M15: 138 | N15: =M15*L15 -> 0 | O15: =M15/D15 -> 0.69 | P15: =O15+$O$62+((BC!$F$125)/'c111 DETERMIACION'!$F$32) -> #DIV/0! | Q15: =P15*F15 -> #DIV/0! | R15: =((P15*0.15)+P15) -> #DIV/0! | S15: =R15*F15 -> #DIV/0!
B16: 5401704190 | C16: LIPASA | D16: 100 | E16: 60 | F16: ='c111'!E22 -> 0 | G16: =((F16*0.2)+(F16)) -> 0 | H16: =G16/D16 -> 0 | I16: =30*BC!$B$47/E16 -> 0 | J16: =IF(I16>H16,I16,H16) -> 0 | K16: =IF(H16=0,0,J16) -> 0 | L16: =ROUNDUP(K16,0) -> 0 | M16: 132 | N16: =M16*L16 -> 0 | O16: =M16/D16 -> 1.32 | P16: =O16+$O$62+((BC!$F$125)/'c111 DETERMIACION'!$F$32) -> #DIV/0! | Q16: =P16*F16 -> #DIV/0! | R16: =((P16*0.15)+P16) -> #DIV/0! | S16: =R16*F16 -> #DIV/0!
B17: 5401461190 | C17: GGT | D17: 200 | E17: 60 | F17: ='c111'!E23 -> 0 | G17: =((F17*0.2)+(F17)) -> 0 | H17: =G17/D17 -> 0 | I17: =30*BC!$B$47/E17 -> 0 | J17: =IF(I17>H17,I17,H17) -> 0 | K17: =IF(H17=0,0,J17) -> 0 | L17: =ROUNDUP(K17,0) -> 0 | M17: 67 | N17: =M17*L17 -> 0 | O17: =M17/D17 -> 0.335 | P17: =O17+$O$62+((BC!$F$125)/'c111 DETERMIACION'!$F$32) -> #DIV/0! | Q17: =P17*F17 -> #DIV/0! | R17: =((P17*0.15)+P17) -> #DIV/0! | S17: =R17*F17 -> #DIV/0!
B18: 4657357190 | C18: Albumina | D18: 400 | E18: 120 | F18: ='c111'!E24 -> 0 | G18: =((F18*0.2)+(F18)) -> 0 | H18: =G18/D18 -> 0 | I18: =30*BC!$B$47/E18 -> 0 | J18: =IF(I18>H18,I18,H18) -> 0 | K18: =IF(H18=0,0,J18) -> 0 | L18: =ROUNDUP(K18,0) -> 0 | M18: 85 | N18: =M18*L18 -> 0 | O18: =M18/D18 -> 0.2125 | P18: =O18+$O$62+((BC!$F$125)/'c111 DETERMIACION'!$F$32) -> #DIV/0! | Q18: =P18*F18 -> #DIV/0! | R18: =((P18*0.15)+P18) -> #DIV/0! | S18: =R18*F18 -> #DIV/0!
B19: 7005806190 | C19: LDL Colesterol | D19: 100 | E19: 60 | F19: ='c111'!E25 -> 0 | G19: =((F19*0.2)+(F19)) -> 0 | H19: =G19/D19 -> 0 | I19: =30*BC!$B$47/E19 -> 0 | J19: =IF(I19>H19,I19,H19) -> 0 | K19: =IF(H19=0,0,J19) -> 0 | L19: =ROUNDUP(K19,0) -> 0 | M19: 109 | N19: =M19*L19 -> 0 | O19: =M19/D19 -> 1.09 | P19: =O19+$O$62+((BC!$F$125)/'c111 DETERMIACION'!$F$32) -> #DIV/0! | Q19: =P19*F19 -> #DIV/0! | R19: =((P19*0.15)+P19) -> #DIV/0! | S19: =R19*F19 -> #DIV/0!
B20: 5061504190 | C20: Calcio | D20: 400 | E20: 120 | F20: ='c111'!E26 -> 0 | G20: =((F20*0.2)+(F20)) -> 0 | H20: =G20/D20 -> 0 | I20: =30*BC!$B$47/E20 -> 0 | J20: =IF(I20>H20,I20,H20) -> 0 | K20: =IF(H20=0,0,J20) -> 0 | L20: =ROUNDUP(K20,0) -> 0 | M20: 169 | N20: =M20*L20 -> 0 | O20: =M20/D20 -> 0.4225 | P20: =O20+$O$62+((BC!$F$125)/'c111 DETERMIACION'!$F$32) -> #DIV/0! | Q20: =P20*F20 -> #DIV/0! | R20: =((P20*0.15)+P20) -> #DIV/0! | S20: =R20*F20 -> #DIV/0!
B21: 7442017190 | C21: CK | D21: 200 | E21: 60 | F21: ='c111'!E27 -> 0 | G21: =((F21*0.2)+(F21)) -> 0 | H21: =G21/D21 -> 0 | I21: =30*BC!$B$47/E21 -> 0 | J21: =IF(I21>H21,I21,H21) -> 0 | K21: =IF(H21=0,0,J21) -> 0 | L21: =ROUNDUP(K21,0) -> 0 | M21: 140 | N21: =M21*L21 -> 0 | O21: =M21/D21 -> 0.7 | P21: =O21+$O$62+((BC!$F$125)/'c111 DETERMIACION'!$F$32) -> #DIV/0! | Q21: =P21*F21 -> #DIV/0! | R21: =((P21*0.15)+P21) -> #DIV/0! | S21: =R21*F21 -> #DIV/0!
B22: 5401674190 | C22: LDH | D22: 100 | E22: 60 | F22: ='c111'!E28 -> 0 | G22: =((F22*0.2)+(F22)) -> 0 | H22: =G22/D22 -> 0 | I22: =30*BC!$B$47/E22 -> 0 | J22: =IF(I22>H22,I22,H22) -> 0 | K22: =IF(H22=0,0,J22) -> 0 | L22: =ROUNDUP(K22,0) -> 0 | M22: 128 | N22: =M22*L22 -> 0 | O22: =M22/D22 -> 1.28 | P22: =O22+$O$62+((BC!$F$125)/'c111 DETERMIACION'!$F$32) -> #DIV/0! | Q22: =P22*F22 -> #DIV/0! | R22: =((P22*0.15)+P22) -> #DIV/0! | S22: =R22*F22 -> #DIV/0!
B23: 5336180190 | C23: HbA1c | D23: 200 | E23: 60 | F23: ='c111'!E29 -> 0 | G23: =((F23*0.2)+(F23)) -> 0 | H23: =G23/D23 -> 0 | I23: =30*BC!$B$47/E23 -> 0 | J23: =IF(I23>H23,I23,H23) -> 0 | K23: =IF(H23=0,0,J23) -> 0 | L23: =ROUNDUP(K23,0) -> 0 | M23: 310 | N23: =M23*L23 -> 0 | O23: =M23/D23 -> 1.55 | P23: =O23+$O$62+((BC!$F$125)/'c111 DETERMIACION'!$F$32) -> #DIV/0! | Q23: =P23*F23 -> #DIV/0! | R23: =((P23*0.15)+P23) -> #DIV/0! | S23: =R23*F23 -> #DIV/0!
B24: 5401658190 | C24: Hierro | D24: 100 | E24: 60 | F24: ='c111'!E30 -> 0 | G24: =((F24*0.2)+(F24)) -> 0 | H24: =G24/D24 -> 0 | I24: =30*BC!$B$47/E24 -> 0 | J24: =IF(I24>H24,I24,H24) -> 0 | K24: =IF(H24=0,0,J24) -> 0 | L24: =ROUNDUP(K24,0) -> 0 | M24: 87 | N24: =M24*L24 -> 0 | O24: =M24/D24 -> 0.87 | P24: =O24+$O$62+((BC!$F$125)/'c111 DETERMIACION'!$F$32) -> #DIV/0! | Q24: =P24*F24 -> #DIV/0! | R24: =((P24*0.15)+P24) -> #DIV/0! | S24: =R24*F24 -> #DIV/0!
B25: 4657586190 | C25: Proteinas totales | D25: 400 | E25: 120 | F25: ='c111'!E31 -> 0 | G25: =((F25*0.2)+(F25)) -> 0 | H25: =G25/D25 -> 0 | I25: =30*BC!$B$47/E25 -> 0 | J25: =IF(I25>H25,I25,H25) -> 0 | K25: =IF(H25=0,0,J25) -> 0 | L25: =ROUNDUP(K25,0) -> 0 | M25: 80 | N25: =M25*L25 -> 0 | O25: =M25/D25 -> 0.2 | P25: =O25+$O$62+((BC!$F$125)/'c111 DETERMIACION'!$F$32) -> #DIV/0! | Q25: =P25*F25 -> #DIV/0! | R25: =((P25*0.15)+P25) -> #DIV/0! | S25: =R25*F25 -> #DIV/0!
B26: 7876432190 | C26: PCR latex | D26: 200 | E26: 60 | F26: ='c111'!E32 -> 0 | G26: =((F26*0.2)+(F26)) -> 0 | H26: =G26/D26 -> 0 | I26: =30*BC!$B$47/E26 -> 0 | J26: =IF(I26>H26,I26,H26) -> 0 | K26: =IF(H26=0,0,J26) -> 0 | L26: =ROUNDUP(K26,0) -> 0 | M26: 180 | N26: =M26*L26 -> 0 | O26: =M26/D26 -> 0.9 | P26: =O26+$O$62+((BC!$F$125)/'c111 DETERMIACION'!$F$32) -> #DIV/0! | Q26: =P26*F26 -> #DIV/0! | R26: =((P26*0.15)+P26) -> #DIV/0! | S26: =R26*F26 -> #DIV/0!
... B28: 5401780190 | C28: Phosforo | D28: 100 | E28: 60 | F28: ='c111'!E34 -> 0 | G28: =((F28*0.2)+(F28)) -> 0 | H28: =G28/D28 -> 0 | I28: =30*BC!$B$47/E28 -> 0 | J28: =IF(I28>H28,I28,H28) -> 0 | K28: =IF(H28=0,0,J28) -> 0 | L28: =ROUNDUP(K28,0) -> 0 | M28: 136 | N28: =M28*L28 -> 0 | O28: =M28/D28 -> 1.36 | P28: =O28+$O$62+((BC!$F$125)/'c111 DETERMIACION'!$F$32) -> #DIV/0! | Q28: =P28*F28 -> #DIV/0! | R28: =((P28*0.15)+P28) -> #DIV/0! | S28: =R28*F28 -> #DIV/0!
B29: 5401739190 | C29: NH3L Ammonia | D29: 100 | E29: 56 | F29: ='c111'!E35 -> 0 | G29: =((F29*0.2)+(F29)) -> 0 | H29: =F29/D29 -> 0 | I29: =30*BC!$B$47/E29 -> 0 | J29: =IF(I29>H29,I29,H29) -> 0 | K29: =IF(H29=0,0,J29) -> 0 | L29: =ROUNDUP(K29,0) -> 0 | M29: 221 | N29: =M29*L29 -> 0 | O29: =M29/D29 -> 2.21 | P29: =O29+$O$62+((BC!$F$125)/'c111 DETERMIACION'!$F$32) -> #DIV/0! | Q29: =P29*F29 -> #DIV/0! | R29: =((P29*0.15)+P29) -> #DIV/0! | S29: =R29*F29 -> #DIV/0!
B30: 8900019190 | C30: MG2, 100T, COBAS C 111 | D30: 100 | E30: 56 | F30: ='c111'!E36 -> 0 | G30: =((F30*0.2)+(F30)) -> 0 | H30: =F30/D30 -> 0 | I30: =30*BC!$B$47/E30 -> 0 | J30: =IF(I30>H30,I30,H30) -> 0 | K30: =IF(H30=0,0,J30) -> 0 | L30: =ROUNDUP(K30,0) -> 0 | M30: 90 | N30: =M30*L30 -> 0 | O30: =M30/D30 -> 0.9 | P30: =O30+$O$62+((BC!$F$125)/'c111 DETERMIACION'!$F$32) -> #DIV/0! | Q30: =P30*F30 -> #DIV/0! | R30: =((P30*0.15)+P30) -> #DIV/0! | S30: =R30*F30 -> #DIV/0!
B31: 7442050190 | C31: CK-MB | D31: 100 | E31: 60 | F31: ='c111'!E37 -> 0 | G31: =((F31*0.2)+(F31)) -> 0 | H31: =G31/D31 -> 0 | I31: =30*BC!$B$47/E31 -> 0 | J31: =IF(I31>H31,I31,H31) -> 0 | K31: =IF(H31=0,0,J31) -> 0 | L31: =ROUNDUP(K31,0) -> 0 | M31: 164 | N31: =M31*L31 -> 0 | O31: =M31/D31 -> 1.64 | P31: =O31+$O$62+((BC!$F$125)/'c111 DETERMIACION'!$F$32) -> #DIV/0! | Q31: =P31*F31 -> #DIV/0! | R31: =((P31*0.15)+P31) -> #DIV/0! | S31: =R31*F31 -> #DIV/0!
D32: TOTAL DET | F32: =SUM(F3:F31) -> 0 | G32: =SUM(G3:G31) -> 0
B33: CALIBRADOR | D33: PRESENTACION | E33: DIAS ESTABILIDAD | H33: PRODUCTO CALCULADO | I33: MINIMOS POR ESTABILIDAD | J33: PRODUCTO A ENTREGAR | L33: MAXIMOS | M33: PVP POR UNIDADES | N33: VALOR POR CAJA | O33: VALOR TOTAL | P33: EN KITS | Q33: EN KITS CERRADO
B34: 10759350190 | C34: Calibrator f.a.s. 12x3 ml | D34: 12 | E34: 28 | H34: =(A3/(0.005*400)/3000) -> 0 | I34: =30*BC!$B$47/E34 -> 0 | J34: =IF(H34>I34,H34,I34) -> 0 | K34: =ROUNDUP(J34,0) -> 0 | L34: =IF(A3>0,K34,0) -> 0 | M34: =N34/D34 -> 12 | N34: 144 | O34: =M34*L34 -> 0 | P34: =L34/D34 -> 0 | Q34: =ROUNDUP(P34,0) -> 0
B35: 12172623122 | C35: Cfas Lipids 3x1ML | D35: 3 | E35: 28 | H35: =(A14*(0.008*(350/1000))) -> 0 | I35: =30*BC!$B$47/E35 -> 0 | J35: =IF(H35>I35,H35,I35) -> 0 | K35: =ROUNDUP(J35,0) -> 0 | L35: =IF(A14>0,K35,0) -> 0 | M35: =N35/D35 -> 31 | N35: 93 | O35: =M35*L35 -> 0 | P35: =L35/D35 -> 0 | Q35: =ROUNDUP(P35,0) -> 0
B36: 11355279216 | C36: Cfas Proteins | D36: 5 | E36: 28 | H36: =(G26*(0.014*(500/2000))) -> 0 | I36: =30*BC!$B$47/E36 -> 0 | J36: =IF(H36>I36,H36,I36) -> 0 | K36: =ROUNDUP(J36,0) -> 0 | L36: =IF(F26>0,K36,0) -> 0 | M36: =N36/D36 -> 29.8 | N36: 149 | O36: =M36*L36 -> 0 | P36: =L36/D36 -> 0 | Q36: =ROUNDUP(P36,0) -> 0
B37: 4528417190 | C37: Cfas HbA1c, 3x2ml | D37: 3 | E37: 84 | H37: =(G23*(0.014*(500/2000))) -> 0 | I37: =30*BC!$B$47/E37 -> 0 | J37: =IF(H37>I37,H37,I37) -> 0 | K37: =ROUNDUP(J37,0) -> 0 | L37: =IF(F23>0,K37,0) -> 0 | M37: =N37/D37 -> 150.33333 | N37: 451 | O37: =M37*L37 -> 0 | P37: =L37/D37 -> 0 | Q37: =ROUNDUP(P37,0) -> 0
B38: 20751995190 | C38: Ammonia/Ethanol/CO2 Calibrator | D38: 2 | E38: 56 | H38: =(F29*(0.014*(500/2000))) -> 0 | I38: =30*BC!$B$47/E38 -> 0 | J38: =IF(H38>I38,H38,I38) -> 0 | K38: =ROUNDUP(J38,0) -> 0 | L38: =IF(F24>0,K38,0) -> 0 | M38: =N38/D38 -> 313.5 | N38: 627 | O38: =M38*L38 -> 0 | P38: =L38/D38 -> 0 | Q38: =ROUNDUP(P38,0) -> 0
B39: 5050901190 | C39: Cfas D- Dimer | D39: 1 | E39: 84 | H39: =(G27*(0.014*(500/2000))) -> 0 | I39: =30*BC!$B$47/E39 -> 0 | J39: =IF(H39>I39,H39,I39) -> 0 | K39: =ROUNDUP(J39,0) -> 0 | L39: =IF(F27>0,K39,0) -> 0 | M39: =N39/D39 -> 282 | N39: 282 | O39: =M39*L39 -> 0 | P39: =L39/D39 -> 0 | Q39: =ROUNDUP(P39,0) -> 0
B40: 11447394216 | C40: Calibrator f.a.s. CK‑MB | D40: 3 | E40: 28 | H40: =(G31*(0.014*(500/2000))) -> 0 | I40: =30*BC!$B$47/E40 -> 0 | J40: =IF(H40>I40,H40,I40) -> 0 | K40: =ROUNDUP(J40,0) -> 0 | L40: =IF(F28>0,K40,0) -> 0 | M40: =N40/D40 -> 25.333333 | N40: 76 | O40: =M40*L40 -> 0 | P40: =L40/D40 -> 0 | Q40: =ROUNDUP(P40,0) -> 0
B41: CONTROL
B42: 5947626190 | C42: PreciControl ClinChem Multi 1 4x5ml | D42: 4 | E42: 14 | H42: =(A4/(0.003*350)/5000) -> 0 | I42: =30*BC!$B$47/E42 -> 0 | J42: =IF(H42>I42,H42,I42) -> 0 | K42: =ROUNDUP(J42,0) -> 0 | L42: =IF(F32>0,K42,0) -> 0 | M42: =N42/D42 -> 14.25 | N42: 57 | O42: =M42*L42 -> 0 | P42: =L42/D42 -> 0 | Q42: =ROUNDUP(P42,0) -> 0
B43: 5947774190 | C43: PreciControl ClinChem Multi 2 4x5ml | D43: 4 | E43: 14 | H43: =(A4/(0.003*350)/5000) -> 0 | I43: =30*BC!$B$47/E43 -> 0 | J43: =IF(H43>I43,H43,I43) -> 0 | K43: =ROUNDUP(J43,0) -> 0 | L43: =IF(F32>0,K43,0) -> 0 | M43: =N43/D43 -> 22.75 | N43: 91 | O43: =M43*L43 -> 0 | P43: =L43/D43 -> 0 | Q43: =ROUNDUP(P43,0) -> 0
B44: 5479207190 | C44: PreciControl HBA1c Norm | D44: 4 | E44: 28 | H44: =(G23/(0.0007*150)/1000) -> 0 | I44: =30*BC!$B$47/E44 -> 0 | J44: =IF(H44>I44,H44,I44) -> 0 | K44: =ROUNDUP(J44,0) -> 0 | L44: =IF(F23>0,K44,0) -> 0 | M44: =N44/D44 -> 77.25 | N44: 309 | O44: =M44*L44 -> 0 | P44: =L44/D44 -> 0 | Q44: =ROUNDUP(P44,0) -> 0
B45: 5912504190 | C45: PRECICONTROL HBA1C PATH | D45: 4 | E45: 28 | H45: =(G23/(0.0007*150)/1000) -> 0 | I45: =30*BC!$B$47/E45 -> 0 | J45: =IF(H45>I45,H45,I45) -> 0 | K45: =ROUNDUP(J45,0) -> 0 | L45: =IF(F23>0,K45,0) -> 0 | M45: =N45/D45 -> 154.5 | N45: 618 | O45: =M45*L45 -> 0 | P45: =L45/D45 -> 0 | Q45: =ROUNDUP(P45,0) -> 0
B46: 20752401190 | C46: Ammonia/Ethanol/CO2 Control Normal | D46: 5 | E46: 56 | H46: =(F29/(0.0007*150)/1000) -> 0 | I46: =30*BC!$B$47/E46 -> 0 | J46: =IF(H46>I46,H46,I46) -> 0 | K46: =ROUNDUP(J46,0) -> 0 | L46: =IF(F24>0,K46,0) -> 0 | M46: =N46/D46 -> 41.4 | N46: 207 | O46: =M46*L46 -> 0 | P46: =L46/D46 -> 0 | Q46: =ROUNDUP(P46,0) -> 0
B47: 20753009190 | C47: Ammonia/Ethanol/CO2 Control Normal | D47: 5 | E47: 56 | H47: =F29/(0.0007*150)/1000 -> 0 | I47: =30*BC!$B$47/E47 -> 0 | J47: =IF(H47>I47,H47,I47) -> 0 | K47: =ROUNDUP(J47,0) -> 0 | L47: =IF(F25>0,K47,0) -> 0 | M47: =N47/D47 -> 45.4 | N47: 227 | O47: =M47*L47 -> 0 | P47: =L47/D47 -> 0 | Q47: =ROUNDUP(P47,0) -> 0
B48: 5050936190 | C48: PreciControl D- Dimer | D48: 2 | E48: 84 | H48: =(G27/(0.0004*300)/3000) -> 0 | I48: =30*BC!$B$47/E48 -> 0 | J48: =IF(H48>I48,H48,I48) -> 0 | K48: =ROUNDUP(J48,0) -> 0 | L48: =IF(F27>0,K48,0) -> 0 | M48: =N48/D48 -> 244 | N48: 488 | O48: =M48*L48 -> 0 | P48: =L48/D48 -> 0 | Q48: =ROUNDUP(P48,0) -> 0
B49: CONSUMIBLES
B50: 4774230190 | C50: NaCL 9% cobas c 111 | D50: 4 | E50: 28 | H50: =(G32/(0.002*800)/12000) -> 0 | I50: =30*BC!$B$47/E50 -> 0 | J50: =IF(H50>I50,H50,I50) -> 0 | K50: =ROUNDUP(J50,0) -> 0 | L50: =IF(F32>0,K50,0) -> 0 | M50: =N50/D50 -> 17.75 | N50: 71 | O50: =M50*L50 -> 0 | P50: =L50/D50 -> 0 | Q50: =ROUNDUP(P50,0) -> 0
B51: 5007232190 | C51: HAEMOLYSE REAGENT 800T COBAS C111 | D51: 8 | E51: 10 | H51: =(G23/(0.00006*800)/6300) -> 0 | I51: =30*BC!$B$47/E51 -> 0 | J51: =IF(H51>I51,H51,I51) -> 0 | K51: =ROUNDUP(J51,0) -> 0 | L51: =IF(F23>0,K51,0) -> 0 | M51: =N51/D51 -> 54.875 | N51: 439 | O51: =M51*L51 -> 0 | P51: =L51/D51 -> 0 | Q51: =ROUNDUP(P51,0) -> 0
B52: 4663632190 | C52: Activator for cobas c,Integra,c111 | D52: 9 | E52: 12 | H52: =30*BCB48/E52 -> 0 | I52: =30*BC!$B$47/E52 -> 0 | J52: =IF(H52>I52,H52,I52) -> 0 | K52: =ROUNDUP(J52,0) -> 0 | L52: =IF(F32>0,K52,0) -> 0 | M52: =N52/D52 -> 17.222222 | N52: 155 | O52: =M52*L52 -> 0 | P52: =L52/D52 -> 0 | Q52: =ROUNDUP(P52,0) -> 0
B53: 11298500316 | C53: ISE CLEANING SOLUTION 5x100ml | D53: 5 | E53: 73 | H53: =30*BCB48/E53 -> 0 | I53: =30*BC!$B$47/E53 -> 0 | J53: =IF(H53>I53,H53,I53) -> 0 | K53: =ROUNDUP(J53,0) -> 0 | L53: =IF(F32>0,K53,0) -> 0 | M53: =N53/D53 -> 19.6 | N53: 98 | O53: =M53*L53 -> 0 | P53: =L53/D53 -> 0 | Q53: =ROUNDUP(P53,0) -> 0
B54: 20754765322 | C54: Cobas Integra Cleaner | D54: 1 | E54: 84 | H54: =(G32/(0.005*48)/6300) -> 0 | I54: =30*BC!$B$47/E54 -> 0 | J54: =IF(H54>I54,H54,I54) -> 0 | K54: =ROUNDUP(J54,0) -> 0 | L54: =IF(F32>0,K54,0) -> 0 | M54: =N54/D54 -> 46 | N54: 46 | O54: =M54*L54 -> 0 | P54: =L54/D54 -> 0 | Q54: =ROUNDUP(P54,0) -> 0
B55: 4357108001 | C55: Micro Cuvette Segment | D55: 1 | E55: 365 | H55: =((G32+(G32*0.01))/1680) -> 0 | I55: =((365/E55)) -> 1 | J55: =IF(H55>I55,H55,I55) -> 1 | K55: =ROUNDUP(J55,0) -> 1 | L55: =IF(F32>0,K55,0) -> 0 | M55: =N55/D55 -> 179 | N55: 179 | O55: =M55*L55 -> 0 | P55: =L55/D55 -> 0 | Q55: =ROUNDUP(P55,0) -> 0
B56: 4444191001 | C56: Sample cup 250 St | D56: 1 | E56: 365 | H56: =((G32-(G32*0.9))/E56) -> 0 | I56: =365/E56 -> 1 | J56: =IF(H56>I56,H56,I56) -> 1 | K56: =ROUNDUP(J56,0) -> 1 | L56: =IF(F32>0,K56,0) -> 0 | M56: =N56/D56 -> 9 | N56: 9 | O56: =M56*L56 -> 0 | P56: =L56/D56 -> 0 | Q56: =ROUNDUP(P56,0) -> 0
B57: 4352483001 | C57: URISYS Thermo-printer paper 5 | D57: 1 | E57: 365 | H57: =((G32-(G32*0.97))/E57) -> 0 | I57: =(365/E56) -> 1 | J57: =IF(H57>I57,H57,I57) -> 1 | K57: =ROUNDUP(J57,0) -> 1 | L57: =IF(F32>0,K57,0) -> 0 | M57: =N57/D57 -> 19 | N57: 19 | O57: =M57*L57 -> 0 | P57: =L57/D57 -> 0 | Q57: =ROUNDUP(P57,0) -> 0
B58: 5344620001 | C58: LAMP HALOGEN 12V/20W ASSY | D58: 1 | E58: 365 | H58: =(G32/(0.05*30)/6300) -> 0 | I58: =365/E58 -> 1 | J58: =IF(H58>I58,H58,I58) -> 1 | K58: =ROUNDUP(J58,0) -> 1 | L58: =IF(F32>0,K58,0) -> 0 | M58: =N58/D58 -> 105 | N58: 105 | O58: =M58*L58 -> 0 | P58: =L58/D58 -> 0 | Q58: =ROUNDUP(P58,0) -> 0
B59: INS218 | C59: Tubos eppendorf | D59: 1 | E59: 365 | H59: =((G32-(G32*0.98))/E59) -> 0 | I59: =365/E59 -> 1 | J59: =IF(H59>I59,H59,I59) -> 1 | K59: =ROUNDUP(J59,0) -> 1 | L59: =IF(F32>0,K59,0) -> 0 | M59: 6.5 | N59: =M59*L59 -> 0 | O59: =M59*L59 -> 0 | P59: =L59/D59 -> 0 | Q59: =ROUNDUP(P59,0) -> 0
B60: ALQUILER | L60: =BCB48 -> 0 | M60: 390 | N60: =M60*L60 -> 0 | O60: =M60*L60 -> 0
O61: =SUM(O34:O60) -> 0
O62: =O61/F32 -> #DIV/0!

Sheet c111 TODO COMPRADO
B2: ID | C2: REACTIVO | D2: DET/KIT | E2: DIAS ESTABILIDAD | F2: CANTIDAD PROCESO/AÑO | G2: PRODUCTO CALCULADO | H2: MINIMOS POR ESTABILIDAD | I2: PRODUCTO A ENTREGAR | K2: REDONDEADO A ENTREGAR | L2: PVP | M2: TOTAL | N2: PVP TODO COMPRADO | O2: TOTAL PVP TODO COMPRADO | P2: $ DETERMINACION | Q2: $DETERMINACION CON CONSUMIBLES Y EXTRAS | R2: TOTAL CON CONSUMIBLES Y EXTRAS | S2: $ PARA PROCESO | T2: TOTAL PARA PROCESO | U2: VALOR INICIAL DEL PROCESO | V2: VALOR FINAL DEL PROCESO
A3: =SUM(F3+F4+F5+F6+F7+F8+F9+F10+F11+F12+F13+F15+F16+F17+F18+F20+F21+F22+F24+F25+F28) -> 0 | B3: 4657527190 | C3: Glucosa | D3: 400 | E3: 120 | F3: ='c111'!E9 -> 0 | G3: =F3/D3 -> 0 | H3: =30*BC!B47/E3 -> 0 | I3: =IF(H3>G3,H3,G3) -> 0 | J3: =IF(G3=0,0,I3) -> 0 | K3: =ROUNDUP(J3,0) -> 0 | L3: 50 | M3: =L3*K3 -> 0 | N3: =((L3*$L$65)+L3) -> 50 | O3: =N3*K3 -> 0 | P3: =L3/D3 -> 0.125 | Q3: =P3+$M$62+((BC!$F$125)/'c111 DETERMIACION'!$F$32) -> #DIV/0! | R3: =Q3*F3 -> #DIV/0! | S3: =((Q3*0.15)+Q3) -> #DIV/0! | T3: =S3*F3 -> #DIV/0! | U3: =SUM(T3:T31) -> #DIV/0! | V3: =SUM(R3:R31) -> #DIV/0!
A4: =F3+F4+F5+F6+F7+F8+F9+F10+F11+F12+F13+F14+F15+F16+F17+F18+F19+F20+F21+F22+F24+F25+F26+F28 -> 0 | B4: 4657616190 | C4: Urea | D4: 400 | E4: 120 | F4: ='c111'!E10 -> 0 | G4: =F4/D4 -> 0 | H4: =30*BC!B48/E4 -> 0 | I4: =IF(H4>G4,H4,G4) -> 0 | J4: =IF(G4=0,0,I4) -> 0 | K4: =ROUNDUP(J4,0) -> 0 | L4: 62 | M4: =L4*K4 -> 0 | N4: =((L4*$L$65)+L4) -> 62 | O4: =N4*K4 -> 0 | P4: =L4/D4 -> 0.155 | Q4: =P4+$M$62+((BC!$F$125)/'c111 DETERMIACION'!$F$32) -> #DIV/0! | R4: =Q4*F4 -> #DIV/0! | S4: =((Q4*0.15)+Q4) -> #DIV/0! | T4: =S4*F4 -> #DIV/0!
B5: 5401755190 | C5: Creatinina | D5: 400 | E5: 120 | F5: ='c111'!E11 -> 0 | G5: =F5/D5 -> 0 | H5: =30*BC!B49/E5 -> 0 | I5: =IF(H5>G5,H5,G5) -> 0 | J5: =IF(G5=0,0,I5) -> 0 | K5: =ROUNDUP(J5,0) -> 0 | L5: 74 | M5: =L5*K5 -> 0 | N5: =((L5*$L$65)+L5) -> 74 | O5: =N5*K5 -> 0 | P5: =L5/D5 -> 0.185 | Q5: =P5+$M$62+((BC!$F$125)/'c111 DETERMIACION'!$F$32) -> #DIV/0! | R5: =Q5*F5 -> #DIV/0! | S5: =((Q5*0.15)+Q5) -> #DIV/0! | T5: =S5*F5 -> #DIV/0!
B6: 4657608190 | C6: Acido Úrico | D6: 400 | E6: 120 | F6: ='c111'!E12 -> 0 | G6: =F6/D6 -> 0 | H6: =30*BC!B50/E6 -> 0 | I6: =IF(H6>G6,H6,G6) -> 0 | J6: =IF(G6=0,0,I6) -> 0 | K6: =ROUNDUP(J6,0) -> 0 | L6: 89 | M6: =L6*K6 -> 0 | N6: =((L6*$L$65)+L6) -> 89 | O6: =N6*K6 -> 0 | P6: =L6/D6 -> 0.2225 | Q6: =P6+$M$62+((BC!$F$125)/'c111 DETERMIACION'!$F$32) -> #DIV/0! | R6: =Q6*F6 -> #DIV/0! | S6: =((Q6*0.15)+Q6) -> #DIV/0! | T6: =S6*F6 -> #DIV/0!
B7: 4718917190 | C7: Colesterol | D7: 400 | E7: 120 | F7: ='c111'!E13 -> 0 | G7: =F7/D7 -> 0 | H7: =30*BC!B51/E7 -> 0 | I7: =IF(H7>G7,H7,G7) -> 0 | J7: =IF(G7=0,0,I7) -> 0 | K7: =ROUNDUP(J7,0) -> 0 | L7: 83 | M7: =L7*K7 -> 0 | N7: =((L7*$L$65)+L7) -> 83 | O7: =N7*K7 -> 0 | P7: =L7/D7 -> 0.2075 | Q7: =P7+$M$62+((BC!$F$125)/'c111 DETERMIACION'!$F$32) -> #DIV/0! | R7: =Q7*F7 -> #DIV/0! | S7: =((Q7*0.15)+Q7) -> #DIV/0! | T7: =S7*F7 -> #DIV/0!
B8: 4657594190 | C8: Triglicéridos | D8: 200 | E8: 120 | F8: ='c111'!E14 -> 0 | G8: =F8/D8 -> 0 | H8: =30*BC!B52/E8 -> 0 | I8: =IF(H8>G8,H8,G8) -> 0 | J8: =IF(G8=0,0,I8) -> 0 | K8: =ROUNDUP(J8,0) -> 0 | L8: 63 | M8: =L8*K8 -> 0 | N8: =((L8*$L$65)+L8) -> 63 | O8: =N8*K8 -> 0 | P8: =L8/D8 -> 0.315 | Q8: =P8+$M$62+((BC!$F$125)/'c111 DETERMIACION'!$F$32) -> #DIV/0! | R8: =Q8*F8 -> #DIV/0! | S8: =((Q8*0.15)+Q8) -> #DIV/0! | T8: =S8*F8 -> #DIV/0!
B9: 4718569190 | C9: ALT - TGP | D9: 400 | E9: 120 | F9: ='c111'!E15 -> 0 | G9: =F9/D9 -> 0 | H9: =30*BC!B53/E9 -> 0 | I9: =IF(H9>G9,H9,G9) -> 0 | J9: =IF(G9=0,0,I9) -> 0 | K9: =ROUNDUP(J9,0) -> 0 | L9: 103 | M9: =L9*K9 -> 0 | N9: =((L9*$L$65)+L9) -> 103 | O9: =N9*K9 -> 0 | P9: =L9/D9 -> 0.2575 | Q9: =P9+$M$62+((BC!$F$125)/'c111 DETERMIACION'!$F$32) -> #DIV/0! | R9: =Q9*F9 -> #DIV/0! | S9: =((Q9*0.15)+Q9) -> #DIV/0! | T9: =S9*F9 -> #DIV/0!
B10: 4657543190 | C10: AST - TGO | D10: 400 | E10: 120 | F10: ='c111'!E16 -> 0 | G10: =F10/D10 -> 0 | H10: =30*BC!B54/E10 -> 0 | I10: =IF(H10>G10,H10,G10) -> 0 | J10: =IF(G10=0,0,I10) -> 0 | K10: =ROUNDUP(J10,0) -> 0 | L10: 100 | M10: =L10*K10 -> 0 | N10: =((L10*$L$65)+L10) -> 100 | O10: =N10*K10 -> 0 | P10: =L10/D10 -> 0.25 | Q10: =P10+$M$62+((BC!$F$125)/'c111 DETERMIACION'!$F$32) -> #DIV/0! | R10: =Q10*F10 -> #DIV/0! | S10: =((Q10*0.15)+Q10) -> #DIV/0! | T10: =S10*F10 -> #DIV/0!
B11: 4657373190 | C11: Fosfatasa alcalina | D11: 200 | E11: 120 | F11: ='c111'!E17 -> 0 | G11: =F11/D11 -> 0 | H11: =30*BC!B55/E11 -> 0 | I11: =IF(H11>G11,H11,G11) -> 0 | J11: =IF(G11=0,0,I11) -> 0 | K11: =ROUNDUP(J11,0) -> 0 | L11: 107 | M11: =L11*K11 -> 0 | N11: =((L11*$L$65)+L11) -> 107 | O11: =N11*K11 -> 0 | P11: =L11/D11 -> 0.535 | Q11: =P11+$M$62+((BC!$F$125)/'c111 DETERMIACION'!$F$32) -> #DIV/0! | R11: =Q11*F11 -> #DIV/0! | S11: =((Q11*0.15)+Q11) -> #DIV/0! | T11: =S11*F11 -> #DIV/0!
B12: 5795648190 | C12: Bilirrubina Total | D12: 400 | E12: 120 | F12: ='c111'!E18 -> 0 | G12: =F12/D12 -> 0 | H12: =30*BC!B56/E12 -> 0 | I12: =IF(H12>G12,H12,G12) -> 0 | J12: =IF(G12=0,0,I12) -> 0 | K12: =ROUNDUP(J12,0) -> 0 | L12: 78 | M12: =L12*K12 -> 0 | N12: =((L12*$L$65)+L12) -> 78 | O12: =N12*K12 -> 0 | P12: =L12/D12 -> 0.195 | Q12: =P12+$M$62+((BC!$F$125)/'c111 DETERMIACION'!$F$32) -> #DIV/0! | R12: =Q12*F12 -> #DIV/0! | S12: =((Q12*0.15)+Q12) -> #DIV/0! | T12: =S12*F12 -> #DIV/0!
B13: 5589134190 | C13: Bilirrubina Directa | D13: 100 | E13: 60 | F13: ='c111'!E19 -> 0 | G13: =F13/D13 -> 0 | H13: =30*BC!B57/E13 -> #VALUE! | I13: =IF(H13>G13,H13,G13) -> #VALUE! | J13: =IF(G13=0,0,I13) -> 0 | K13: =ROUNDUP(J13,0) -> 0 | L13: 58 | M13: =L13*K13 -> 0 | N13: =((L13*$L$65)+L13) -> 58 | O13: =N13*K13 -> 0 | P13: =L13/D13 -> 0.58 | Q13: =P13+$M$62+((BC!$F$125)/'c111 DETERMIACION'!$F$32) -> #DIV/0! | R13: =Q13*F13 -> #DIV/0! | S13: =((Q13*0.15)+Q13) -> #DIV/0! | T13: =S13*F13 -> #DIV/0!
A14: =SUM(F14+F19) -> 0 | B14: 7528604190 | C14: HDL Colesterol | D14: 200 | E14: 60 | F14: ='c111'!E20 -> 0 | G14: =F14/D14 -> 0 | H14: =30*BC!B58/E14 -> 0 | I14: =IF(H14>G14,H14,G14) -> 0 | J14: =IF(G14=0,0,I14) -> 0 | K14: =ROUNDUP(J14,0) -> 0 | L14: 222 | M14: =L14*K14 -> 0 | N14: =((L14*$L$65)+L14) -> 222 | O14: =N14*K14 -> 0 | P14: =L14/D14 -> 1.11 | Q14: =P14+$M$62+((BC!$F$125)/'c111 DETERMIACION'!$F$32) -> #DIV/0! | R14: =Q14*F14 -> #DIV/0! | S14: =((Q14*0.15)+Q14) -> #DIV/0! | T14: =S14*F14 -> #DIV/0!
B15: 5401496190 | C15: AMILASA | D15: 200 | E15: 60 | F15: ='c111'!E21 -> 0 | G15: =F15/D15 -> 0 | H15: =30*BC!B59/E15 -> 0 | I15: =IF(H15>G15,H15,G15) -> 0 | J15: =IF(G15=0,0,I15) -> 0 | K15: =ROUNDUP(J15,0) -> 0 | L15: 138 | M15: =L15*K15 -> 0 | N15: =((L15*$L$65)+L15) -> 138 | O15: =N15*K15 -> 0 | P15: =L15/D15 -> 0.69 | Q15: =P15+$M$62+((BC!$F$125)/'c111 DETERMIACION'!$F$32) -> #DIV/0! | R15: =Q15*F15 -> #DIV/0! | S15: =((Q15*0.15)+Q15) -> #DIV/0! | T15: =S15*F15 -> #DIV/0!
B16: 5401704190 | C16: LIPASA | D16: 100 | E16: 60 | F16: ='c111'!E22 -> 0 | G16: =F16/D16 -> 0 | H16: =30*BC!B60/E16 -> 36063.015 | I16: =IF(H16>G16,H16,G16) -> 36063.015 | J16: =IF(G16=0,0,I16) -> 0 | K16: =ROUNDUP(J16,0) -> 0 | L16: 132 | M16: =L16*K16 -> 0 | N16: =((L16*$L$65)+L16) -> 132 | O16: =N16*K16 -> 0 | P16: =L16/D16 -> 1.32 | Q16: =P16+$M$62+((BC!$F$125)/'c111 DETERMIACION'!$F$32) -> #DIV/0! | R16: =Q16*F16 -> #DIV/0! | S16: =((Q16*0.15)+Q16) -> #DIV/0! | T16: =S16*F16 -> #DIV/0!
B17: 5401461190 | C17: GGT | D17: 200 | E17: 60 | F17: ='c111'!E23 -> 0 | G17: =F17/D17 -> 0 | H17: =30*BC!B61/E17 -> 0 | I17: =IF(H17>G17,H17,G17) -> 0 | J17: =IF(G17=0,0,I17) -> 0 | K17: =ROUNDUP(J17,0) -> 0 | L17: 67 | M17: =L17*K17 -> 0 | N17: =((L17*$L$65)+L17) -> 67 | O17: =N17*K17 -> 0 | P17: =L17/D17 -> 0.335 | Q17: =P17+$M$62+((BC!$F$125)/'c111 DETERMIACION'!$F$32) -> #DIV/0! | R17: =Q17*F17 -> #DIV/0! | S17: =((Q17*0.15)+Q17) -> #DIV/0! | T17: =S17*F17 -> #DIV/0!
B18: 4657357190 | C18: Albumina | D18: 400 | E18: 120 | F18: ='c111'!E24 -> 0 | G18: =F18/D18 -> 0 | H18: =30*BC!B62/E18 -> #VALUE! | I18: =IF(H18>G18,H18,G18) -> #VALUE! | J18: =IF(G18=0,0,I18) -> 0 | K18: =ROUNDUP(J18,0) -> 0 | L18: 85 | M18: =L18*K18 -> 0 | N18: =((L18*$L$65)+L18) -> 85 | O18: =N18*K18 -> 0 | P18: =L18/D18 -> 0.2125 | Q18: =P18+$M$62+((BC!$F$125)/'c111 DETERMIACION'!$F$32) -> #DIV/0! | R18: =Q18*F18 -> #DIV/0! | S18: =((Q18*0.15)+Q18) -> #DIV/0! | T18: =S18*F18 -> #DIV/0!
B19: 7005806190 | C19: LDL Colesterol | D19: 100 | E19: 60 | F19: ='c111'!E25 -> 0 | G19: =F19/D19 -> 0 | H19: =30*BC!B63/E19 -> #VALUE! | I19: =IF(H19>G19,H19,G19) -> #VALUE! | J19: =IF(G19=0,0,I19) -> 0 | K19: =ROUNDUP(J19,0) -> 0 | L19: 109 | M19: =L19*K19 -> 0 | N19: =((L19*$L$65)+L19) -> 109 | O19: =N19*K19 -> 0 | P19: =L19/D19 -> 1.09 | Q19: =P19+$M$62+((BC!$F$125)/'c111 DETERMIACION'!$F$32) -> #DIV/0! | R19: =Q19*F19 -> #DIV/0! | S19: =((Q19*0.15)+Q19) -> #DIV/0! | T19: =S19*F19 -> #DIV/0!
B20: 5061504190 | C20: Calcio | D20: 400 | E20: 120 | F20: ='c111'!E26 -> 0 | G20: =F20/D20 -> 0 | H20: =30*BC!B64/E20 -> 0 | I20: =IF(H20>G20,H20,G20) -> 0 | J20: =IF(G20=0,0,I20) -> 0 | K20: =ROUNDUP(J20,0) -> 0 | L20: 169 | M20: =L20*K20 -> 0 | N20: =((L20*$L$65)+L20) -> 169 | O20: =N20*K20 -> 0 | P20: =L20/D20 -> 0.4225 | Q20: =P20+$M$62+((BC!$F$125)/'c111 DETERMIACION'!$F$32) -> #DIV/0! | R20: =Q20*F20 -> #DIV/0! | S20: =((Q20*0.15)+Q20) -> #DIV/0! | T20: =S20*F20 -> #DIV/0!
B21: 7442017190 | C21: CK | D21: 200 | E21: 60 | F21: ='c111'!E27 -> 0 | G21: =F21/D21 -> 0 | H21: =30*BC!B65/E21 -> 0 | I21: =IF(H21>G21,H21,G21) -> 0 | J21: =IF(G21=0,0,I21) -> 0 | K21: =ROUNDUP(J21,0) -> 0 | L21: 140 | M21: =L21*K21 -> 0 | N21: =((L21*$L$65)+L21) -> 140 | O21: =N21*K21 -> 0 | P21: =L21/D21 -> 0.7 | Q21: =P21+$M$62+((BC!$F$125)/'c111 DETERMIACION'!$F$32) -> #DIV/0! | R21: =Q21*F21 -> #DIV/0! | S21: =((Q21*0.15)+Q21) -> #DIV/0! | T21: =S21*F21 -> #DIV/0!
B22: 5401674190 | C22: LDH | D22: 100 | E22: 60 | F22: ='c111'!E28 -> 0 | G22: =F22/D22 -> 0 | H22: =30*BC!B66/E22 -> 0 | I22: =IF(H22>G22,H22,G22) -> 0 | J22: =IF(G22=0,0,I22) -> 0 | K22: =ROUNDUP(J22,0) -> 0 | L22: 128 | M22: =L22*K22 -> 0 | N22: =((L22*$L$65)+L22) -> 128 | O22: =N22*K22 -> 0 | P22: =L22/D22 -> 1.28 | Q22: =P22+$M$62+((BC!$F$125)/'c111 DETERMIACION'!$F$32) -> #DIV/0! | R22: =Q22*F22 -> #DIV/0! | S22: =((Q22*0.15)+Q22) -> #DIV/0! | T22: =S22*F22 -> #DIV/0!
B23: 5336180190 | C23: HbA1c | D23: 200 | E23: 60 | F23: ='c111'!E29 -> 0 | G23: =F23/D23 -> 0 | H23: =30*BC!B67/E23 -> 0 | I23: =IF(H23>G23,H23,G23) -> 0 | J23: =IF(G23=0,0,I23) -> 0 | K23: =ROUNDUP(J23,0) -> 0 | L23: 310 | M23: =L23*K23 -> 0 | N23: =((L23*$L$65)+L23) -> 310 | O23: =N23*K23 -> 0 | P23: =L23/D23 -> 1.55 | Q23: =P23+$M$62+((BC!$F$125)/'c111 DETERMIACION'!$F$32) -> #DIV/0! | R23: =Q23*F23 -> #DIV/0! | S23: =((Q23*0.15)+Q23) -> #DIV/0! | T23: =S23*F23 -> #DIV/0!
B24: 5401658190 | C24: Hierro | D24: 100 | E24: 60 | F24: ='c111'!E30 -> 0 | G24: =F24/D24 -> 0 | H24: =30*BC!B68/E24 -> 0 | I24: =IF(H24>G24,H24,G24) -> 0 | J24: =IF(G24=0,0,I24) -> 0 | K24: =ROUNDUP(J24,0) -> 0 | L24: 87 | M24: =L24*K24 -> 0 | N24: =((L24*$L$65)+L24) -> 87 | O24: =N24*K24 -> 0 | P24: =L24/D24 -> 0.87 | Q24: =P24+$M$62+((BC!$F$125)/'c111 DETERMIACION'!$F$32) -> #DIV/0! | R24: =Q24*F24 -> #DIV/0! | S24: =((Q24*0.15)+Q24) -> #DIV/0! | T24: =S24*F24 -> #DIV/0!
B25: 4657586190 | C25: Proteinas totales | D25: 400 | E25: 120 | F25: ='c111'!E31 -> 0 | G25: =F25/D25 -> 0 | H25: =30*BC!B69/E25 -> 0 | I25: =IF(H25>G25,H25,G25) -> 0 | J25: =IF(G25=0,0,I25) -> 0 | K25: =ROUNDUP(J25,0) -> 0 | L25: 80 | M25: =L25*K25 -> 0 | N25: =((L25*$L$65)+L25) -> 80 | O25: =N25*K25 -> 0 | P25: =L25/D25 -> 0.2 | Q25: =P25+$M$62+((BC!$F$125)/'c111 DETERMIACION'!$F$32) -> #DIV/0! | R25: =Q25*F25 -> #DIV/0! | S25: =((Q25*0.15)+Q25) -> #DIV/0! | T25: =S25*F25 -> #DIV/0!
B26: 7876432190 | C26: PCR latex | D26: 200 | E26: 60 | F26: ='c111'!E32 -> 0 | G26: =F26/D26 -> 0 | H26: =30*BC!B70/E26 -> 0 | I26: =IF(H26>G26,H26,G26) -> 0 | J26: =IF(G26=0,0,I26) -> 0 | K26: =ROUNDUP(J26,0) -> 0 | L26: 180 | M26: =L26*K26 -> 0 | N26: =((L26*$L$65)+L26) -> 180 | O26: =N26*K26 -> 0 | P26: =L26/D26 -> 0.9 | Q26: =P26+$M$62+((BC!$F$125)/'c111 DETERMIACION'!$F$32) -> #DIV/0! | R26: =Q26*F26 -> #DIV/0! | S26: =((Q26*0.15)+Q26) -> #DIV/0! | T26: =S26*F26 -> #DIV/0!
... B30: 8900019190 | C30: MG2, 100T, COBAS C 111 | D30: 100 | E30: 56 | F30: ='c111'!E36 -> 0 | G30: =F30/D30 -> 0 | H30: =30*BC!B74/E30 -> 0 | I30: =IF(H30>G30,H30,G30) -> 0 | J30: =IF(G30=0,0,I30) -> 0 | K30: =ROUNDUP(J30,0) -> 0 | L30: 90 | M30: =L30*K30 -> 0 | N30: =((L30*$L$65)+L30) -> 90 | O30: =N30*K30 -> 0 | P30: =L30/D30 -> 0.9 | Q30: =P30+$M$62+((BC!$F$125)/'c111 DETERMIACION'!$F$32) -> #DIV/0! | R30: =Q30*F30 -> #DIV/0! | S30: =((Q30*0.15)+Q30) -> #DIV/0! | T30: =S30*F30 -> #DIV/0!
B31: 7442050190 | C31: CK-MB | D31: 100 | E31: 60 | F31: ='c111'!E37 -> 0 | G31: =F31/D31 -> 0 | H31: =30*BC!B74/E31 -> 0 | I31: =IF(H31>G31,H31,G31) -> 0 | J31: =IF(G31=0,0,I31) -> 0 | K31: =ROUNDUP(J31,0) -> 0 | L31: 164 | M31: =L31*K31 -> 0 | N31: =((L31*$L$65)+L31) -> 164 | O31: =N31*K31 -> 0 | P31: =L31/D31 -> 1.64 | Q31: =P31+$M$62+((BC!$F$125)/'c111 DETERMIACION'!$F$32) -> #DIV/0! | R31: =Q31*F31 -> #DIV/0! | S31: =((Q31*0.15)+Q31) -> #DIV/0! | T31: =S31*F31 -> #DIV/0!
D32: TOTAL DET | F32: =SUM(F3:F31) -> 0 | M32: =SUM(M3:M31)+M61 -> 4940 | O32: =SUM(O3:O31)+P60 -> 520.37222
B33: CALIBRADOR | D33: PRESENTACION | E33: DIAS ESTABILIDAD | G33: PRODUCTO CALCULADO | H33: MINIMOS POR ESTABILIDAD | I33: PRODUCTO A ENTREGAR | K33: MAXIMOS | L33: PVP POR UDS | M33: VALOR TOTAL | N33: PVP TODO COMPRADO CAJA | O33: PVP TODO COMPRADO POR UDS | P33: TOTAL PVP TODO COMPRADO POR UDS
B34: 10759350190 | C34: Calibrator f.a.s. 12x3 ml | D34: 12 | E34: 28 | G34: =(A4/(0.005*400)/3000) -> 0 | H34: =30*BC!$B$47/E34 -> 0 | I34: =IF(G34>H34,G34,H34) -> 0 | J34: =ROUNDUP(I34,0) -> 0 | K34: 1 | L34: =M34/D34 -> 12 | M34: 144 | N34: =O34*D34 -> 144 | O34: =((L34*$L$65)+L34) -> 12 | P34: =O34*K34 -> 12
B35: 12172623122 | C35: Cfas Lipids 3x1ML | D35: 3 | E35: 28 | G35: =(A10*(0.008*(350/1000))) -> 0 | H35: =30*BC!$B$47/E35 -> 0 | I35: =IF(G35>H35,G35,H35) -> 0 | J35: =ROUNDUP(I35,0) -> 0 | K35: 1 | L35: =M35/D35 -> 31 | M35: 93 | N35: =O35*D35 -> 93 | O35: =((L35*$L$65)+L35) -> 31 | P35: =O35*K35 -> 31
B36: 11355279216 | C36: Cfas Proteins | D36: 5 | E36: 28 | G36: =(F26*(0.014*(500/2000))) -> 0 | H36: =30*BC!$B$47/E36 -> 0 | I36: =IF(G36>H36,G36,H36) -> 0 | J36: =ROUNDUP(I36,0) -> 0 | K36: 1 | L36: =M36/D36 -> 29.8 | M36: 149 | N36: =O36*D36 -> 149 | O36: =((L36*$L$65)+L36) -> 29.8 | P36: =O36*K36 -> 29.8
B37: 4528417190 | C37: Cfas HbA1c, 3x2ml | D37: 3 | E37: 84 | G37: =(F23*(0.014*(500/2000))) -> 0 | H37: =30*BC!$B$47/E37 -> 0 | I37: =IF(G37>H37,G37,H37) -> 0 | J37: =ROUNDUP(I37,0) -> 0 | L37: =M37/D37 -> 150.33333 | M37: 451 | N37: =O37*D37 -> 451 | O37: =((L37*$L$65)+L37) -> 150.33333 | P37: =O37*K37 -> 0
B38: 20751995190 | C38: Ammonia/Ethanol/CO2 Calibrator | D38: 2 | E38: 56 | G38: =(F29*(0.014*(500/2000))) -> 0 | H38: =30*BC!$B$47/E38 -> 0 | I38: =IF(G38>H38,G38,H38) -> 0 | J38: =ROUNDUP(I38,0) -> 0 | K38: =IF(F24>0,J38,0) -> 0 | L38: =M38/D38 -> 313.5 | M38: 627 | N38: =O38*D38 -> 627 | O38: =((L38*$L$65)+L38) -> 313.5 | P38: =O38*K38 -> 0
B39: 5050901190 | C39: Cfas D- Dimer | D39: 1 | E39: 84 | G39: =(F27*(0.014*(500/2000))) -> 0 | H39: =30*BC!$B$47/E39 -> 0 | I39: =IF(G39>H39,G39,H39) -> 0 | J39: =ROUNDUP(I39,0) -> 0 | L39: =M39/D39 -> 282 | M39: 282 | N39: =O39*D39 -> 282 | O39: =((L39*$L$65)+L39) -> 282 | P39: =O39*K39 -> 0
B40: 11447394216 | C40: Calibrator f.a.s. CK‑MB | D40: 3 | E40: 28 | G40: =(F31*(0.014*(500/2000))) -> 0 | H40: =30*BC!$B$47/E40 -> 0 | I40: =IF(G40>H40,G40,H40) -> 0 | J40: =ROUNDUP(I40,0) -> 0 | K40: =IF(F28>0,J40,0) -> 0 | L40: =M40/D40 -> 25.333333 | M40: 76 | N40: =O40*D40 -> 76 | O40: =((L40*$L$65)+L40) -> 25.333333 | P40: =ROUNDUP(O40,0) -> 26
B41: CONTROL | N41: =O41*D41 -> 0 | O41: =((L41*$L$65)+L41) -> 0
B42: 5947626190 | C42: PreciControl ClinChem Multi 1 4x5ml | D42: 4 | E42: 14 | G42: =(A7/(0.003*350)/5000) -> 0 | H42: =30*BC!$B$47/E42 -> 0 | I42: =IF(G42>H42,G42,H42) -> 0 | J42: =ROUNDUP(I42,0) -> 0 | K42: 1 | L42: =M42/D42 -> 14.25 | M42: 57 | N42: =O42*D42 -> 57 | O42: =((L42*$L$65)+L42) -> 14.25 | P42: =O42*K42 -> 14.25
B43: 5947774190 | C43: PreciControl ClinChem Multi 2 4x5ml | D43: 4 | E43: 14 | G43: =(A7/(0.003*350)/5000) -> 0 | H43: =30*BC!$B$47/E43 -> 0 | I43: =IF(G43>H43,G43,H43) -> 0 | J43: =ROUNDUP(I43,0) -> 0 | K43: 1 | L43: =M43/D43 -> 22.75 | M43: 91 | N43: =O43*D43 -> 91 | O43: =((L43*$L$65)+L43) -> 22.75 | P43: =O43*K43 -> 22.75
B44: 5479207190 | C44: PreciControl HBA1c Norm | D44: 4 | E44: 28 | G44: =(F23/(0.0007*150)/1000) -> 0 | H44: =30*BC!$B$47/E44 -> 0 | I44: =IF(G44>H44,G44,H44) -> 0 | J44: =ROUNDUP(I44,0) -> 0 | L44: =M44/D44 -> 77.25 | M44: 309 | N44: =O44*D44 -> 309 | O44: =((L44*$L$65)+L44) -> 77.25 | P44: =O44*K44 -> 0
B45: 5912504190 | C45: PRECICONTROL HBA1C PATH | D45: 4 | E45: 28 | G45: =(F23/(0.0007*150)/1000) -> 0 | H45: =30*BC!$B$47/E45 -> 0 | I45: =IF(G45>H45,G45,H45) -> 0 | J45: =ROUNDUP(I45,0) -> 0 | L45: =M45/D45 -> 154.5 | M45: 618 | N45: =O45*D45 -> 618 | O45: =((L45*$L$65)+L45) -> 154.5 | P45: =O45*K45 -> 0
B46: 20752401190 | C46: Ammonia/Ethanol/CO2 Control Normal | D46: 5 | E46: 56 | G46: =(F29/(0.0007*150)/1000) -> 0 | H46: =30*BC!$B$47/E46 -> 0 | I46: =IF(G46>H46,G46,H46) -> 0 | J46: =ROUNDUP(I46,0) -> 0 | K46: =IF(F24>0,J46,0) -> 0 | L46: =M46/D46 -> 41.4 | M46: 207 | N46: =O46*D46 -> 207 | O46: =((L46*$L$65)+L46) -> 41.4 | P46: =O46*K46 -> 0
B47: 20753009190 | C47: Ammonia/Ethanol/CO2 Control Normal | D47: 5 | E47: 56 | G47: =F29/(0.0007*150)/1000 -> 0 | H47: =30*BC!$B$47/E47 -> 0 | I47: =IF(G47>H47,G47,H47) -> 0 | J47: =ROUNDUP(I47,0) -> 0 | K47: =IF(F25>0,J47,0) -> 0 | L47: =M47/D47 -> 45.4 | M47: 227 | N47: =O47*D47 -> 227 | O47: =((L47*$L$65)+L47) -> 45.4 | P47: =O47*K47 -> 0
B48: 5050936190 | C48: PreciControl D- Dimer | D48: 2 | E48: 84 | G48: =(F27/(0.0004*300)/3000) -> 0 | H48: =30*BC!$B$47/E48 -> 0 | I48: =IF(G48>H48,G48,H48) -> 0 | J48: =ROUNDUP(I48,0) -> 0 | L48: =M48/D48 -> 244 | M48: 488 | N48: =O48*D48 -> 488 | O48: =((L48*$L$65)+L48) -> 244 | P48: =O48*K48 -> 0
B49: CONSUMIBLES | N49: =O49*D49 -> 0 | O49: =((L49*$L$65)+L49) -> 0
B50: 4774230190 | C50: NaCL 9% cobas c 111 | D50: 4 | E50: 28 | G50: =(F32/(0.002*800)/12000) -> 0 | H50: =30*BC!$B$47/E50 -> 0 | I50: =IF(G50>H50,G50,H50) -> 0 | J50: =ROUNDUP(I50,0) -> 0 | K50: 1 | L50: =M50/D50 -> 17.75 | M50: 71 | N50: =O50*D50 -> 71 | O50: =((L50*$L$65)+L50) -> 17.75 | P50: =O50*K50 -> 17.75
B51: 5007232190 | C51: HAEMOLYSE REAGENT 800T COBAS C111 | D51: 8 | E51: 10 | G51: =(F23/(0.00006*800)/6300) -> 0 | H51: =30*BC!$B$47/E51 -> 0 | I51: =IF(G51>H51,G51,H51) -> 0 | J51: =ROUNDUP(I51,0) -> 0 | L51: =M51/D51 -> 54.875 | M51: 439 | N51: =O51*D51 -> 439 | O51: =((L51*$L$65)+L51) -> 54.875 | P51: =O51*K51 -> 0
B52: 4663632190 | C52: Activator for cobas c,Integra,c111 | D52: 9 | E52: 12 | G52: =30*BCB48/E52 -> 0 | H52: =30*BC!$B$47/E52 -> 0 | I52: =IF(G52>H52,G52,H52) -> 0 | J52: =ROUNDUP(I52,0) -> 0 | K52: 1 | L52: =M52/D52 -> 17.222222 | M52: 155 | N52: =O52*D52 -> 155 | O52: =((L52*$L$65)+L52) -> 17.222222 | P52: =O52*K52 -> 17.222222
B53: 11298500316 | C53: ISE CLEANING SOLUTION 5x100ml | D53: 5 | E53: 73 | G53: =30*BCB48/E53 -> 0 | H53: =30*BC!$B$47/E53 -> 0 | I53: =IF(G53>H53,G53,H53) -> 0 | J53: =ROUNDUP(I53,0) -> 0 | K53: 1 | L53: =M53/D53 -> 19.6 | M53: 98 | N53: =O53*D53 -> 98 | O53: =((L53*$L$65)+L53) -> 19.6 | P53: =O53*K53 -> 19.6
B54: 20754765322 | C54: Cobas Integra Cleaner | D54: 1 | E54: 84 | G54: =(F32/(0.005*48)/6300) -> 0 | H54: =30*BC!$B$47/E54 -> 0 | I54: =IF(G54>H54,G54,H54) -> 0 | J54: =ROUNDUP(I54,0) -> 0 | K54: 1 | L54: =M54/D54 -> 46 | M54: 46 | N54: =O54*D54 -> 46 | O54: =((L54*$L$65)+L54) -> 46 | P54: =O54*K54 -> 46
B55: 4357108001 | C55: Micro Cuvette Segment | D55: 11 | E55: 365 | G55: =((F32+(F32*0.01))/1680) -> 0 | H55: =((365/E55)) -> 1 | I55: =IF(G55>H55,G55,H55) -> 1 | J55: =ROUNDUP(I55,0) -> 1 | K55: 1 | L55: 179 | M55: 179 | N55: =O55*1 -> 179 | O55: =((L55*$L$65)+L55) -> 179 | P55: =O55*K55 -> 179
B56: 4444191001 | C56: Sample cup 250 St | D56: 1 | E56: 365 | G56: =((F32-(F32*0.9))/E56) -> 0 | H56: =365/E56 -> 1 | I56: =IF(G56>H56,G56,H56) -> 1 | J56: =ROUNDUP(I56,0) -> 1 | L56: =M56/D56 -> 9 | M56: 9 | N56: =O56*1 -> 9 | O56: =((L56*$L$65)+L56) -> 9 | P56: =O56*K56 -> 0
B57: 4352483001 | C57: URISYS Thermo-printer paper 5 | D57: 1 | E57: 365 | G57: =((F32-(F32*0.97))/E57) -> 0 | H57: =(365/E56) -> 1 | I57: =IF(G57>H57,G57,H57) -> 1 | J57: =ROUNDUP(I57,0) -> 1 | L57: =M57/D57 -> 19 | M57: 19 | N57: =O57*D57 -> 19 | O57: =((L57*$L$65)+L57) -> 19 | P57: =O57*K57 -> 0
B58: 5344620001 | C58: LAMP HALOGEN 12V/20W ASSY | D58: 1 | E58: 365 | G58: =(F32/(0.05*30)/6300) -> 0 | H58: =365/E58 -> 1 | I58: =IF(G58>H58,G58,H58) -> 1 | J58: =ROUNDUP(I58,0) -> 1 | K58: 1 | L58: =M58/D58 -> 105 | M58: 105 | N58: =O58*D58 -> 105 | O58: =((L58*$L$65)+L58) -> 105 | P58: =O58*K58 -> 105
B59: INS218 | C59: Tubos eppendorf | D59: 500 | E59: 365 | G59: =((F32-(F32*0.98))/E59) -> 0 | H59: =365/E59 -> 1 | I59: =IF(G59>H59,G59,H59) -> 1 | J59: =ROUNDUP(I59,0) -> 1 | L59: 6.5 | M59: =L59*K59 -> 0 | N59: =O59*1 -> 6.5 | O59: =((L59*$L$65)+L59) -> 6.5 | P59: =O59*K59 -> 0
B60: ALQUILER | K60: =BCB48 -> 0 | L60: 390 | M60: =L60*K60 -> 0 | P60: =SUM(P34:P59) -> 520.37222
M61: =SUM(M34:M59) -> 4940
M62: =M61/F32 -> #DIV/0!
L65: =(L60/M32)*K60 -> 0 | M65: =O32-M32 -> -4419.6278

Sheet c311
A1: CLIENTE
A2: FECHA
A3: MODALIDAD
A4: PLAZO | C4: MESES
A5: PROYECCIÓN | C5: MESES
A6: EQUIPO | B6: C311
A8: I.D | B8: DESCRIPCION | C8: DET/KIT | D8: DIAS ESTABILIDAD | E8: DET/AÑO/PROCESO | F8: PRODUCTO CALCULADO | G8: MINIMOS POR ESTABILIDAD | H8: PRODUCTO A ENTREGAR
A9: 6750052190 | B9: A-1MG TQ GEN.2, 100TEST, COBAS C/INT | C9: 200 | D9: 84 | F9: =E9/C9 -> 0 | G9: =365/D9 -> 4.3452381
A10: 3005771322 | B10: AAT GEN.2, 100TESTS, COBAS C, INTEGRA | C10: 100 | D10: 84 | F10: =E10/C10 -> 0 | G10: =365/D10 -> 4.3452381
A11: 4375351190 | B11: ACP HIT 917 LARGE | C11: 400 | D11: 84 | F11: =E11/C11 -> 0 | G11: =365/D11 -> 4.3452381
A12: 3183688122 | B12: ALB2, 300T, COBAS C, INTEGRA | C12: 300 | D12: 84 | F12: =E12/C12 -> 0 | G12: =365/D12 -> 4.3452381
A13: 4469658190 | B13: ALB-T TQ GEN.2, 100TESTS, COBAS C, INT | C13: 100 | D13: 84 | F13: =E13/C13 -> 0 | G13: =365/D13 -> 4.3452381
A14: 3333752190 | B14: ALP2, 200T, COBAS C, INTEGRA | C14: 200 | D14: 56 | F14: =E14/C14 -> 0 | G14: =365/D14 -> 6.5178571
A15: 20764957322 | B15: ALTL, 500TESTS, COBAS C, INTEGRA | C15: 500 | D15: 84 | F15: =E15/C15 -> 0 | G15: =365/D15 -> 4.3452381
A16: 3183742122 | B16: AMYL GEN.2, 300TESTS, COBAS C, INTEGRA | C16: 300 | D16: 84 | F16: =E16/C16 -> 0 | G16: =365/D16 -> 4.3452381
A17: 3032566122 | B17: APOAT, 100TESTS, COBAS C, INTEGRA | C17: 100 | D17: 84 | F17: =E17/C17 -> 0 | G17: =365/D17 -> 4.3452381
A18: 3032574122 | B18: APOBT, 100TESTS, COBAS C, INTEGRA | C18: 100 | D18: 84 | F18: =E18/C18 -> 0 | G18: =365/D18 -> 4.3452381
A19: 4489403190 | B19: ASLO TQ, 150TESTS, COBAS C | C19: 150 | D19: 84 | F19: =E19/C19 -> 0 | G19: =365/D19 -> 4.3452381
A20: 20764949322 | B20: ASTL, 500TESTS, COBAS C, INTEGRA | C20: 500 | D20: 84 | F20: =E20/C20 -> 0 | G20: =365/D20 -> 4.3452381
... A73: 4460715190 | B73: UREAL, 500T, COBAS C, INTEGRA | C73: 500 | D73: 56 | F73: =E73/C73 -> 0 | G73: =365/D73 -> 6.5178571
D74: TOTAL DET | E74: =SUM(E9:E73) -> 0
B75: CALIBRADORES | D75: DIAS ESTABILIDAD | F75: PRODUCTO CALCULADO | G75: MINIMOS POR ESTABILIDAD | H75: PRODUCTO A ENTREGAR
A76: 20751995190 | B76: Ammonia/Ethanol/CO2 Calibrator | C76: 2 | D76: 56 | G76: =(365/D76)/C76 -> 3.2589286
A77: 4975901190 | B77: C.f.a.s. Cystatin C | C77: 1 | G77: =(365/D77)/C77 -> #DIV/0!
A78: 3555941190 | B78: C.f.a.s. PAC | C78: 3 | D78: 14 | G78: =(365/D78)/C78 -> 8.6904762
A79: 10759350190 | B79: Calibrator f.a.s. | C79: 12 | D79: 28 | G79: =(365/D79)/C79 -> 1.0863095
A80: 11447394216 | B80: Calibrator f.a.s. CK-MB | C80: 3 | D80: 28 | G80: =(365/D80)/C80 -> 4.3452381
A81: 6533850190 | B81: Calibrator f.a.s. IgA/IgM CSF | C81: 3 | D81: 14 | G81: =(365/D81)/C81 -> 8.6904762
A82: 12172623122 | B82: Calibrator f.a.s. Lipids | C82: 3 | D82: 28 | G82: =(365/D82)/C82 -> 4.3452381
A83: 11355279216 | B83: Calibrator f.a.s.proteins | C83: 5 | D83: 28 | G83: =(365/D83)/C83 -> 2.6071429
A84: 8753776190 | B84: CALIBRATOR STFR GEN.2 | C84: 3 | D84: 28 | G84: =(365/D84)/C84 -> 4.3452381
A85: 8047545190 | B85: Calibrator β2‑Microglobulin | C85: 2 | D85: 84 | G85: =(365/D85)/C85 -> 2.172619
A86: 4528417190 | B86: Cfas HbA1c | C86: 3 | D86: 84 | G86: =(365/D86)/C86 -> 1.4484127
A87: 3121305122 | B87: Cfas Proteins U | C87: 5 | D87: 28 | G87: =(365/D87)/C87 -> 2.6071429
A88: 5050901190 | B88: D-Dimer Gen.2 Calibrator Set | C88: 1 | D88: 84 | G88: =(365/D88)/C88 -> 4.3452381
A89: 12146401216 | B89: Fe Standard | C89: 1 | D89: 360 | G89: =(365/D89)/C89 -> 1.0138889
... A94: 12172828322 | B94: Preciset RF | C94: 1 | D94: 30 | G94: =(365/D94)/C94 -> 12.166667
B95: CONTROLES | C95: PRESENTACION | D95: DIAS ESTABILIDAD | F95: PRODUCTO CALCULADO | G95: MINIMOS POR ESTABILIDAD | H95: PRODUCTO A ENTREGAR
A96: 20752401190 | B96: Ammonia/Ethanol/CO2 Control Normal | C96: 5 | D96: 56 | G96: =(365/D96)/C96 -> 1.3035714
A97: 20753009190 | B97: Ammonia/Ethanol/CO2 Control Abnormal | C97: 5 | D97: 56 | G97: =(365/D97)/C97 -> 1.3035714
A98: 8362785190 | B98: Control Set β2‑Microglobulin (Nivel 1-2) | C98: 2 | D98: 84 | G98: =(365/D98)/C98 -> 2.172619
A99: 8278202190 | B99: CONTROL-SET STFR | C99: 3 | D99: 28 | G99: =(365/D99)/C99 -> 4.3452381
A100: 6729371190 | B100: Cystatin C Control Set Gen.2 (1,2,3) | C100: 3 | D100: 30 | G100: =(365/D100)/C100 -> 4.0555556
A101: 5050936190 | B101: D-Dimer Gen.2 Control I/II | C101: 2 | D101: 84 | G101: =(365/D101)/C101 -> 2.172619
A102: 5142423190 | B102: HCYS Control Kit Control 1 y 2 | C102: 2 | D102: 28 | G102: =(365/D102)/C102 -> 6.5178571
A103: 5947626190 | B103: PreciControl ClinChem Multi 1, 4x5 ml | C103: 4 | D103: 14 | G103: =(365/D103)/C103 -> 6.5178571
A104: 5947774190 | B104: PreciControl ClinChem Multi 2, 4x5 ml | C104: 4 | D104: 14 | G104: =(365/D104)/C104 -> 6.5178571
A105: 5479207190 | B105: PreciControl HbA1c norm | C105: 4 | D105: 28 | G105: =(365/D105)/C105 -> 3.2589286
A106: 5912504190 | B106: PreciControl HbA1c path | C106: 4 | D106: 28 | G106: =(365/D106)/C106 -> 3.2589286
A107: 5852650190 | B107: PreciControl Lp(a) Gen.2 | C107: 2 | D107: 14 | G107: =(365/D107)/C107 -> 13.035714
... A112: 3005496122 | B112: RF Control Set | C112: 4 | D112: 30 | G112: =(365/D112)/C112 -> 3.0416667
B113: CONSUMIBLES | C113: PRESENTACION | D113: DIAS ESTABILIDAD | F113: PRODUCTO CALCULADO | G113: MINIMOS POR ESTABILIDAD | H113: PRODUCTO A ENTREGAR
A114: 4880285190 | B114: Cell Wash Solution I / NaOH-D | C114: 2 | D114: 70 | G114: 2.61
A115: 4880307190 | B115: Cell Wash Solution II / Acid Wash | C115: 2 | D115: 84 | G115: 2.17
A116: 4444191001 | B116: cobas sample cups | C116: 1 | D116: 365 | G116: 1.00
A117: 4555040001 | B117: Cuvettes – reaction cell sets | C117: 3 | D117: 84 | G117: 1.45
A118: 5422485190 | B118: Ecotergent | C118: 1 | D118: 28 | G118: 13.04
A119: 4554124001 | B119: FILTRO DE RESINA IONICA REGENERADA 20" | C119: 1 | D119: 30 | G119: 12.17
A120: 4516273001 | B120: FILTRO NOM. P/SEDIMENTS GX05-20XX (BLANCO) | C120: 1 | D120: 30 | G120: 12.17
A121: 4516265001 | B121: FILTRO NOM. P/SEDIMENTS PX5-20 PURTR (AZUL) | C121: 1 | D121: 30 | G121: 12.17
A122: 4528182190 | B122: HBA1C TQ HAEMOLYZING RGT, COBAS C | C122: 1 | D122: 28 | G122: 13.04
A123: 4813707001 | B123: Lamp, Halogen | C123: 1 | D123: 45 | G123: 8.11
A124: 4516303001 | B124: MEMBRANE EQ.OSMOSIS, AG2521TF 2.5 diam | C124: 1 | D124: 360 | G124: 1.01
A125: 4708725190 | B125: Multiclean, Sample Cleaner 1 | C125: 12 | D125: 28 | G125: 1.09
... A129: 4516303001 | B129: MEMBRANE EQ.OSMOSIS, AG2521TF 2.5 DIAM | C129: 1 | D129: 365 | G129: 1.00
A130: FAM154 | B130: RESINA MIXTA GRANEL X KG | C130: 1 | D130: 365 | G130: 1.00
A131: 4516265001 | B131: FILTRO NOM. P/SEDIMENTS PX5-20 PURTR (AZUL) | C131: 1 | D131: 365 | G131: 1.00
A132: 4516273001 | B132: FILTRO NOM. P/SEDIMENTS GX05-20XX (BLANCO) | C132: 1 | D132: 365 | G132: 1.00
A133: 4554124001 | B133: FILTRO DE RESINA IONICA REGENERADA 20" | C133: 1 | D133: 365 | G133: 1.00
A134: FAM00001143 | B134: SAL EN GRANO X QUINTAL | C134: 1 | D134: 365 | G134: 1.00
A136: SISTEMA PARA ELECTROLITOS | C136: DET/AÑO/PROCESO | D136: PRESENTACION | E136: DIAS ESTABILIDAD | F136: PRODUCTO CALCULADO | G136: MINIMOS POR ESTABILIDAD | H136: PRODUCTO A ENTREGAR
A137: 11183974216 | B137: ISE Standard low 10x3ML | D137: 10 | E137: 1 | G137: 36.5
A138: 11183982216 | B138: ISE Standard high 10x3ML | D138: 10 | E138: 1 | G138: 36.5
A139: 11298500316 | B139: ISE cleaning solution Sys Clean | D139: 5 | E139: 74 | G139: 73
A140: 4663632190 | B140: Activator | D140: 9 | E140: 28 | G140: 40.56
A141: 4522630190 | B141: ISE Diluent Gen.2 (5 × 300 mL) | D141: 5 | E141: 14 | G141: 73
A142: 4522320190 | B142: ISE Internal Standard Gen.2 (5 × 600 mL) | D142: 5 | E142: 14 | G142: 73
A143: 11360981216 | B143: ISE Reference Electrolyte (5 × 300 mL) | D143: 5 | E143: 28 | G143: 73
A144: 3149501001 | B144: REFERENCE ELECTRODE | D144: 1 | E144: 168 | G144: 365
A145: 10825468001 | B145: Electrodo sodio | D145: 1 | E145: 56 | G145: 365
A146: 10825441001 | B146: Electrodo potasio | D146: 1 | E146: 56 | G146: 365
A147: 3246353001 | B147: Electrodo cloro | D147: 1 | E147: 56 | G147: 365

Sheet c311 DETERMINACION
B1: CLIENTE
B2: FECHA
B3: MODALIDAD
B4: PLAZO | D4: MESES
B5: PROYECCIÓN | D5: MESES
B6: EQUIPO | C6: C311
B8: I.D | C8: DESCRIPCION | D8: DET/KIT | E8: DIAS ESTABILIDAD | F8: DET/AÑO/PROCESO | G8: PRODUCTO CALCULADO | H8: MINIMOS POR ESTABILIDAD | I8: PRODUCTO A ENTREGAR | K8: REDONDEADO A ENTREGAR | L8: PVP | M8: TOTAL | N8: $ DETERMINACION | O8: $DETERMINACION CON CONSUMIBLES Y EXTRAS | P8: TOTAL CON CONSUMIBLES Y EXTRAS | Q8: $ PARA PROCESO | R8: TOTAL PARA PROCESO | S8: VALOR INICIAL DEL PROCESO | T8: VALOR FINAL DEL PROCESO
A9: CFAS | B9: 6750052190 | C9: A-1MG TQ GEN.2, 100TEST, COBAS C/INT | D9: 200 | E9: 84 | F9: ='c311'!E9 -> 0 | G9: =F9/D9 -> 0 | H9: =30*BC!B47/E9 -> 0 | I9: =IF(H9>G9,H9,G9) -> 0 | J9: =IF(G9=0,0,I9) -> 0 | K9: =ROUNDUP(J9,0) -> 0 | L9: 762 | M9: =L9*K9 -> 0 | N9: =L9/D9 -> 3.81 | O9: =N9+$N$137+((BC!$F$125)/$F$74) -> #DIV/0! | P9: =O9*F9 -> #DIV/0! | Q9: =((O9*0.15)+O9) -> #DIV/0! | R9: =Q9*F9 -> #DIV/0! | S9: =SUM(R9:R73) -> #DIV/0! | T9: =SUM(P9:P73) -> #DIV/0!
A10: =F11+F12+F14+F15+F16+F20+F22+F23+F26+F28+F29+F30+F34+F41+F42+F45+F52+F54+F56+F58+F60+F62+F67+F69+F71+F73 -> 0 | B10: 3005771322 | C10: AAT GEN.2, 100TESTS, COBAS C, INTEGRA | D10: 100 | E10: 84 | F10: ='c311'!E10 -> 0 | G10: =F10/D10 -> 0 | H10: =30*BC!B48/E10 -> 0 | I10: =IF(H10>G10,H10,G10) -> 0 | J10: =IF(G10=0,0,I10) -> 0 | K10: =ROUNDUP(J10,0) -> 0 | L10: 436 | M10: =L10*K10 -> 0 | N10: =L10/D10 -> 4.36 | O10: =N10+$N$137+((BC!$F$125)/$F$74) -> #DIV/0! | P10: =O10*F10 -> #DIV/0! | Q10: =((O10*0.15)+O10) -> #DIV/0! | R10: =Q10*F10 -> #DIV/0!
B11: 4375351190 | C11: ACP HIT 917 LARGE | D11: 400 | E11: 84 | F11: ='c311'!E11 -> 0 | G11: =F11/D11 -> 0 | H11: =30*BC!B49/E11 -> 0 | I11: =IF(H11>G11,H11,G11) -> 0 | J11: =IF(G11=0,0,I11) -> 0 | K11: =ROUNDUP(J11,0) -> 0 | L11: 456 | M11: =L11*K11 -> 0 | N11: =L11/D11 -> 1.14 | O11: =N11+$N$137+((BC!$F$125)/$F$74) -> #DIV/0! | P11: =O11*F11 -> #DIV/0! | Q11: =((O11*0.15)+O11) -> #DIV/0! | R11: =Q11*F11 -> #DIV/0!
A12: CCLINCHEM | B12: 3183688122 | C12: ALB2, 300T, COBAS C, INTEGRA | D12: 300 | E12: 84 | F12: ='c311'!E12 -> 0 | G12: =F12/D12 -> 0 | H12: =30*BC!B50/E12 -> 0 | I12: =IF(H12>G12,H12,G12) -> 0 | J12: =IF(G12=0,0,I12) -> 0 | K12: =ROUNDUP(J12,0) -> 0 | L12: 72 | M12: =L12*K12 -> 0 | N12: =L12/D12 -> 0.24 | O12: =N12+$N$137+((BC!$F$125)/$F$74) -> #DIV/0! | P12: =O12*F12 -> #DIV/0! | Q12: =((O12*0.15)+O12) -> #DIV/0! | R12: =Q12*F12 -> #DIV/0!
A13: =F10+F11+F12+F14+F15+F16+F17+F18+F19+F20+F22+F23+F26+F28+F29+F30+F31+F34+F35+F36+F41+F42+F43+F45+F47+F48+F49+F50+F51+F52+F53+F54+F55+F57+F58+F60+F62+F63+F67+F69+F70+F71++F72+F73 -> 0 | B13: 4469658190 | C13: ALB-T TQ GEN.2, 100TESTS, COBAS C, INT | D13: 100 | E13: 84 | F13: ='c311'!E13 -> 0 | G13: =F13/D13 -> 0 | H13: =30*BC!B51/E13 -> 0 | I13: =IF(H13>G13,H13,G13) -> 0 | J13: =IF(G13=0,0,I13) -> 0 | K13: =ROUNDUP(J13,0) -> 0 | L13: 287 | M13: =L13*K13 -> 0 | N13: =L13/D13 -> 2.87 | O13: =N13+$N$137+((BC!$F$125)/$F$74) -> #DIV/0! | P13: =O13*F13 -> #DIV/0! | Q13: =((O13*0.15)+O13) -> #DIV/0! | R13: =Q13*F13 -> #DIV/0!
B14: 3333752190 | C14: ALP2, 200T, COBAS C, INTEGRA | D14: 200 | E14: 56 | F14: ='c311'!E14 -> 0 | G14: =F14/D14 -> 0 | H14: =30*BC!B52/E14 -> 0 | I14: =IF(H14>G14,H14,G14) -> 0 | J14: =IF(G14=0,0,I14) -> 0 | K14: =ROUNDUP(J14,0) -> 0 | L14: 62 | M14: =L14*K14 -> 0 | N14: =L14/D14 -> 0.31 | O14: =N14+$N$137+((BC!$F$125)/$F$74) -> #DIV/0! | P14: =O14*F14 -> #DIV/0! | Q14: =((O14*0.15)+O14) -> #DIV/0! | R14: =Q14*F14 -> #DIV/0!
A15: PUC | B15: 20764957322 | C15: ALTL, 500TESTS, COBAS C, INTEGRA | D15: 500 | E15: 84 | F15: ='c311'!E15 -> 0 | G15: =F15/D15 -> 0 | H15: =30*BC!B53/E15 -> 0 | I15: =IF(H15>G15,H15,G15) -> 0 | J15: =IF(G15=0,0,I15) -> 0 | K15: =ROUNDUP(J15,0) -> 0 | L15: 145 | M15: =L15*K15 -> 0 | N15: =L15/D15 -> 0.29 | O15: =N15+$N$137+((BC!$F$125)/$F$74) -> #DIV/0! | P15: =O15*F15 -> #DIV/0! | Q15: =((O15*0.15)+O15) -> #DIV/0! | R15: =Q15*F15 -> #DIV/0!
A16: =F9+F68 -> 0 | B16: 3183742122 | C16: AMYL GEN.2, 300TESTS, COBAS C, INTEGRA | D16: 300 | E16: 84 | F16: ='c311'!E16 -> 0 | G16: =F16/D16 -> 0 | H16: =30*BC!B54/E16 -> 0 | I16: =IF(H16>G16,H16,G16) -> 0 | J16: =IF(G16=0,0,I16) -> 0 | K16: =ROUNDUP(J16,0) -> 0 | L16: 198 | M16: =L16*K16 -> 0 | N16: =L16/D16 -> 0.66 | O16: =N16+$N$137+((BC!$F$125)/$F$74) -> #DIV/0! | P16: =O16*F16 -> #DIV/0! | Q16: =((O16*0.15)+O16) -> #DIV/0! | R16: =Q16*F16 -> #DIV/0!
B17: 3032566122 | C17: APOAT, 100TESTS, COBAS C, INTEGRA | D17: 100 | E17: 84 | F17: ='c311'!E17 -> 0 | G17: =F17/D17 -> 0 | H17: =30*BC!B55/E17 -> 0 | I17: =IF(H17>G17,H17,G17) -> 0 | J17: =IF(G17=0,0,I17) -> 0 | K17: =ROUNDUP(J17,0) -> 0 | L17: 225 | M17: =L17*K17 -> 0 | N17: =L17/D17 -> 2.25 | O17: =N17+$N$137+((BC!$F$125)/$F$74) -> #DIV/0! | P17: =O17*F17 -> #DIV/0! | Q17: =((O17*0.15)+O17) -> #DIV/0! | R17: =Q17*F17 -> #DIV/0!
A18: AMMONIA | B18: 3032574122 | C18: APOBT, 100TESTS, COBAS C, INTEGRA | D18: 100 | E18: 84 | F18: ='c311'!E18 -> 0 | G18: =F18/D18 -> 0 | H18: =30*BC!B56/E18 -> 0 | I18: =IF(H18>G18,H18,G18) -> 0 | J18: =IF(G18=0,0,I18) -> 0 | K18: =ROUNDUP(J18,0) -> 0 | L18: 225 | M18: =L18*K18 -> 0 | N18: =L18/D18 -> 2.25 | O18: =N18+$N$137+((BC!$F$125)/$F$74) -> #DIV/0! | P18: =O18*F18 -> #DIV/0! | Q18: =((O18*0.15)+O18) -> #DIV/0! | R18: =Q18*F18 -> #DIV/0!
A19: =F32+F39+F61 -> 0 | B19: 4489403190 | C19: ASLO TQ, 150TESTS, COBAS C | D19: 150 | E19: 84 | F19: ='c311'!E19 -> 0 | G19: =F19/D19 -> 0 | H19: =30*BC!B57/E19 -> #VALUE! | I19: =IF(H19>G19,H19,G19) -> #VALUE! | J19: =IF(G19=0,0,I19) -> 0 | K19: =ROUNDUP(J19,0) -> 0 | L19: 494 | M19: =L19*K19 -> 0 | N19: =L19/D19 -> 3.2933333 | O19: =N19+$N$137+((BC!$F$125)/$F$74) -> #DIV/0! | P19: =O19*F19 -> #DIV/0! | Q19: =((O19*0.15)+O19) -> #DIV/0! | R19: =Q19*F19 -> #DIV/0!
B20: 20764949322 | C20: ASTL, 500TESTS, COBAS C, INTEGRA | D20: 500 | E20: 84 | F20: ='c311'!E20 -> 0 | G20: =F20/D20 -> 0 | H20: =30*BC!B58/E20 -> 0 | I20: =IF(H20>G20,H20,G20) -> 0 | J20: =IF(G20=0,0,I20) -> 0 | K20: =ROUNDUP(J20,0) -> 0 | L20: 145 | M20: =L20*K20 -> 0 | N20: =L20/D20 -> 0.29 | O20: =N20+$N$137+((BC!$F$125)/$F$74) -> #DIV/0! | P20: =O20*F20 -> #DIV/0! | Q20: =((O20*0.15)+O20) -> #DIV/0! | R20: =Q20*F20 -> #DIV/0!
A21: CFAS PROTEIN | B21: 8047430190 | C21: B2MG, 140T, COBAS C 311, COBAS C 501/502 | D21: 140 | E21: 84 | F21: ='c311'!E21 -> 0 | G21: =F21/D21 -> 0 | H21: =30*BC!B59/E21 -> 0 | I21: =IF(H21>G21,H21,G21) -> 0 | J21: =IF(G21=0,0,I21) -> 0 | K21: =ROUNDUP(J21,0) -> 0 | L21: 1169 | M21: =L21*K21 -> 0 | N21: =L21/D21 -> 8.35 | O21: =N21+$N$137+((BC!$F$125)/$F$74) -> #DIV/0! | P21: =O21*F21 -> #DIV/0! | Q21: =((O21*0.15)+O21) -> #DIV/0! | R21: =Q21*F21 -> #DIV/0!
A22: =F10+F24+F25+F35+F36+F43+F48+F50+F51+F53+F55+F70 -> 0 | B22: 5589061190 | C22: BIL-D GEN.2, 350TESTS COBAS C, INTEGRA | D22: 350 | E22: 42 | F22: ='c311'!E22 -> 0 | G22: =F22/D22 -> 0 | H22: =30*BC!B60/E22 -> 51518.593 | I22: =IF(H22>G22,H22,G22) -> 51518.593 | J22: =IF(G22=0,0,I22) -> 0 | K22: =ROUNDUP(J22,0) -> 0 | L22: 144 | M22: =L22*K22 -> 0 | N22: =L22/D22 -> 0.41142857 | O22: =N22+$N$137+((BC!$F$125)/$F$74) -> #DIV/0! | P22: =O22*F22 -> #DIV/0! | Q22: =((O22*0.15)+O22) -> #DIV/0! | R22: =Q22*F22 -> #DIV/0!
B23: 5795397190 | C23: BIL-T GEN.3, 250TESTS COBAS C,INTEGRA | D23: 250 | E23: 42 | F23: ='c311'!E23 -> 0 | G23: =F23/D23 -> 0 | H23: =30*BC!B61/E23 -> 0 | I23: =IF(H23>G23,H23,G23) -> 0 | J23: =IF(G23=0,0,I23) -> 0 | K23: =ROUNDUP(J23,0) -> 0 | L23: 85 | M23: =L23*K23 -> 0 | N23: =L23/D23 -> 0.34 | O23: =N23+$N$137+((BC!$F$125)/$F$74) -> #DIV/0! | P23: =O23*F23 -> #DIV/0! | Q23: =((O23*0.15)+O23) -> #DIV/0! | R23: =Q23*F23 -> #DIV/0!
A24: C.f.a.s. PAC | B24: 3001938322 | C24: C3C, 100TESTS, COBAS C, INTEGRA | D24: 100 | E24: 42 | F24: ='c311'!E24 -> 0 | G24: =F24/D24 -> 0 | H24: =30*BC!B62/E24 -> #VALUE! | I24: =IF(H24>G24,H24,G24) -> #VALUE! | J24: =IF(G24=0,0,I24) -> 0 | K24: =ROUNDUP(J24,0) -> 0 | L24: 307 | M24: =L24*K24 -> 0 | N24: =L24/D24 -> 3.07 | O24: =N24+$N$137+((BC!$F$125)/$F$74) -> #DIV/0! | P24: =O24*F24 -> #DIV/0! | Q24: =((O24*0.15)+O24) -> #DIV/0! | R24: =Q24*F24 -> #DIV/0!
A25: =F19+F27+F63 -> 0 | B25: 3001962322 | C25: C4, 100TESTS, COBAS C, INTEGRA | D25: 100 | E25: 56 | F25: ='c311'!E25 -> 0 | G25: =F25/D25 -> 0 | H25: =30*BC!B63/E25 -> #VALUE! | I25: =IF(H25>G25,H25,G25) -> #VALUE! | J25: =IF(G25=0,0,I25) -> 0 | K25: =ROUNDUP(J25,0) -> 0 | L25: 309 | M25: =L25*K25 -> 0 | N25: =L25/D25 -> 3.09 | O25: =N25+$N$137+((BC!$F$125)/$F$74) -> #DIV/0! | P25: =O25*F25 -> #DIV/0! | Q25: =((O25*0.15)+O25) -> #DIV/0! | R25: =Q25*F25 -> #DIV/0!
B26: 5061482190 | C26: CA, GEN.2, 300TESTS, COBAS C,INTEGRA | D26: 300 | E26: 56 | F26: ='c311'!E26 -> 0 | G26: =F26/D26 -> 0 | H26: =30*BC!B64/E26 -> 0 | I26: =IF(H26>G26,H26,G26) -> 0 | J26: =IF(G26=0,0,I26) -> 0 | K26: =ROUNDUP(J26,0) -> 0 | L26: 108 | M26: =L26*K26 -> 0 | N26: =L26/D26 -> 0.36 | O26: =N26+$N$137+((BC!$F$125)/$F$74) -> #DIV/0! | P26: =O26*F26 -> #DIV/0! | Q26: =((O26*0.15)+O26) -> #DIV/0! | R26: =Q26*F26 -> #DIV/0!
A27: Calibrator f.a.s. Lipids | B27: 20764663322 | C27: CERU, 100TESTS, COBAS C, INTEGRA | D27: 100 | E27: 56 | F27: ='c311'!E27 -> 0 | G27: =F27/D27 -> 0 | H27: =30*BC!B65/E27 -> 0 | I27: =IF(H27>G27,H27,G27) -> 0 | J27: =IF(G27=0,0,I27) -> 0 | K27: =ROUNDUP(J27,0) -> 0 | L27: 259 | M27: =L27*K27 -> 0 | N27: =L27/D27 -> 2.59 | O27: =N27+$N$137+((BC!$F$125)/$F$74) -> #DIV/0! | P27: =O27*F27 -> #DIV/0! | Q27: =((O27*0.15)+O27) -> #DIV/0! | R27: =Q27*F27 -> #DIV/0!
A28: =F17+F18+F47+F57 -> 0 | B28: 4498577190 | C28: CHE GEN.2, 200TESTS, COBAS C, INTEGRA | D28: 200 | E28: 28 | F28: ='c311'!E28 -> 0 | G28: =F28/D28 -> 0 | H28: =30*BC!B66/E28 -> 0 | I28: =IF(H28>G28,H28,G28) -> 0 | J28: =IF(G28=0,0,I28) -> 0 | K28: =ROUNDUP(J28,0) -> 0 | L28: 166 | M28: =L28*K28 -> 0 | N28: =L28/D28 -> 0.83 | O28: =N28+$N$137+((BC!$F$125)/$F$74) -> #DIV/0! | P28: =O28*F28 -> #DIV/0! | Q28: =((O28*0.15)+O28) -> #DIV/0! | R28: =Q28*F28 -> #DIV/0!
B29: 3039773190 | C29: CHOL HICO GEN.2, 400TESTS, COBAS C, INT. | D29: 400 | E29: 28 | F29: ='c311'!E29 -> 0 | G29: =F29/D29 -> 0 | H29: =30*BC!B67/E29 -> 0 | I29: =IF(H29>G29,H29,G29) -> 0 | J29: =IF(G29=0,0,I29) -> 0 | K29: =ROUNDUP(J29,0) -> 0 | L29: 88 | M29: =L29*K29 -> 0 | N29: =L29/D29 -> 0.22 | O29: =N29+$N$137+((BC!$F$125)/$F$74) -> #DIV/0! | P29: =O29*F29 -> #DIV/0! | Q29: =((O29*0.15)+O29) -> #DIV/0! | R29: =Q29*F29 -> #DIV/0!
A30: PRECISET DAT PLUS I | B30: 7190794190 | C30: CK 200 TESTS, COBAS C/INTEGRA | D30: 200 | E30: 56 | F30: ='c311'!E30 -> 0 | G30: =F30/D30 -> 0 | H30: =30*BC!B68/E30 -> 0 | I30: =IF(H30>G30,H30,G30) -> 0 | J30: =IF(G30=0,0,I30) -> 0 | K30: =ROUNDUP(J30,0) -> 0 | L30: 112 | M30: =L30*K30 -> 0 | N30: =L30/D30 -> 0.56 | O30: =N30+$N$137+((BC!$F$125)/$F$74) -> #DIV/0! | P30: =O30*F30 -> #DIV/0! | Q30: =((O30*0.15)+O30) -> #DIV/0! | R30: =Q30*F30 -> #DIV/0!
A31: =F33+F66 -> 0 | B31: 7190808190 | C31: CK-MB 100TESTS, COBAS C/INTEGRA | D31: 100 | E31: 56 | F31: ='c311'!E31 -> 0 | G31: =F31/D31 -> 0 | H31: =30*BC!B69/E31 -> 0 | I31: =IF(H31>G31,H31,G31) -> 0 | J31: =IF(G31=0,0,I31) -> 0 | K31: =ROUNDUP(J31,0) -> 0 | L31: 276 | M31: =L31*K31 -> 0 | N31: =L31/D31 -> 2.76 | O31: =N31+$N$137+((BC!$F$125)/$F$74) -> #DIV/0! | P31: =O31*F31 -> #DIV/0! | Q31: =((O31*0.15)+O31) -> #DIV/0! | R31: =Q31*F31 -> #DIV/0!
B32: 3289923190 | C32: COBAS INTEGRA CO2-L GEN.2 250 TEST | D32: 250 | E32: 42 | F32: ='c311'!E32 -> 0 | G32: =F32/D32 -> 0 | H32: =30*BC!B70/E32 -> 0 | I32: =IF(H32>G32,H32,G32) -> 0 | J32: =IF(G32=0,0,I32) -> 0 | K32: =ROUNDUP(J32,0) -> 0 | L32: 174 | M32: =L32*K32 -> 0 | N32: =L32/D32 -> 0.696 | O32: =N32+$N$137+((BC!$F$125)/$F$74) -> #DIV/0! | P32: =O32*F32 -> #DIV/0! | Q32: =((O32*0.15)+O32) -> #DIV/0! | R32: =Q32*F32 -> #DIV/0!
B33: 4490827190 | C33: COC2, 200T, COBAS C | D33: 200 | E33: 56 | F33: ='c311'!E33 -> 0 | G33: =F33/D33 -> 0 | H33: =30*BC!B71/E33 -> 0 | I33: =IF(H33>G33,H33,G33) -> 0 | J33: =IF(G33=0,0,I33) -> 0 | K33: =ROUNDUP(J33,0) -> 0 | L33: 120 | M33: =L33*K33 -> 0 | N33: =L33/D33 -> 0.6 | O33: =N33+$N$137+((BC!$F$125)/$F$74) -> #DIV/0! | P33: =O33*F33 -> #DIV/0! | Q33: =((O33*0.15)+O33) -> #DIV/0! | R33: =Q33*F33 -> #DIV/0!
B34: 4810716190 | C34: CREAJ2, 700T, COBAS C, INTEGRA | D34: 700 | E34: 56 | F34: ='c311'!E34 -> 0 | G34: =F34/D34 -> 0 | H34: =30*BC!B72/E34 -> #VALUE! | I34: =IF(H34>G34,H34,G34) -> #VALUE! | J34: =IF(G34=0,0,I34) -> 0 | K34: =ROUNDUP(J34,0) -> 0 | L34: 136 | M34: =L34*K34 -> 0 | N34: =L34/D34 -> 0.19428571 | O34: =N34+$N$137+((BC!$F$125)/$F$74) -> #DIV/0! | P34: =O34*F34 -> #DIV/0! | Q34: =((O34*0.15)+O34) -> #DIV/0! | R34: =Q34*F34 -> #DIV/0!
B35: 4628918190 | C35: CRP LX HS, 300TESTS, COBAS C, INTEGRA | D35: 100 | E35: 84 | F35: ='c311'!E35 -> 0 | G35: =F35/D35 -> 0 | H35: =30*BC!B73/E35 -> 0 | I35: =IF(H35>G35,H35,G35) -> 0 | J35: =IF(G35=0,0,I35) -> 0 | K35: =ROUNDUP(J35,0) -> 0 | L35: 750 | M35: =L35*K35 -> 0 | N35: =L35/D35 -> 7.5 | O35: =N35+$N$137+((BC!$F$125)/$F$74) -> #DIV/0! | P35: =O35*F35 -> #DIV/0! | Q35: =((O35*0.15)+O35) -> #DIV/0! | R35: =Q35*F35 -> #DIV/0!
B36: 7876033190 | C36: CRP4, 250T, COBAS C 311/501/502,INTEGRA | D36: 250 | E36: 84 | F36: ='c311'!E36 -> 0 | G36: =F36/D36 -> 0 | H36: =30*BC!B74/E36 -> 0 | I36: =IF(H36>G36,H36,G36) -> 0 | J36: =IF(G36=0,0,I36) -> 0 | K36: =ROUNDUP(J36,0) -> 0 | L36: 643 | M36: =L36*K36 -> 0 | N36: =L36/D36 -> 2.572 | O36: =N36+$N$137+((BC!$F$125)/$F$74) -> #DIV/0! | P36: =O36*F36 -> #DIV/0! | Q36: =((O36*0.15)+O36) -> #DIV/0! | R36: =Q36*F36 -> #DIV/0!
B37: 6600239190 | C37: CYSC2, 225T, COBAS INTEGRA | D37: 225 | E37: 56 | F37: ='c311'!E37 -> 0 | G37: =F37/D37 -> 0 | H37: =30*BC!B75/E37 -> 0 | I37: =IF(H37>G37,H37,G37) -> 0 | J37: =IF(G37=0,0,I37) -> 0 | K37: =ROUNDUP(J37,0) -> 0 | L37: 1282 | M37: =L37*K37 -> 0 | N37: =L37/D37 -> 5.6977778 | O37: =N37+$N$137+((BC!$F$125)/$F$74) -> #DIV/0! | P37: =O37*F37 -> #DIV/0! | Q37: =((O37*0.15)+O37) -> #DIV/0! | R37: =Q37*F37 -> #DIV/0!
B38: 4912551190 | C38: D-DIMER GEN.2, 100TEST, COBAS C, INTEGRA | D38: 100 | E38: 84 | F38: ='c311'!E38 -> 0 | G38: =F38/D38 -> 0 | H38: =30*BC!B76/E38 -> 0 | I38: =IF(H38>G38,H38,G38) -> 0 | J38: =IF(G38=0,0,I38) -> 0 | K38: =ROUNDUP(J38,0) -> 0 | L38: 1066 | M38: =L38*K38 -> 0 | N38: =L38/D38 -> 10.66 | O38: =N38+$N$137+((BC!$F$125)/$F$74) -> #DIV/0! | P38: =O38*F38 -> #DIV/0! | Q38: =((O38*0.15)+O38) -> #DIV/0! | R38: =Q38*F38 -> #DIV/0!
B39: 3183777190 | C39: ETOH2 , 100T, COBAS INTEGRA | D39: 100 | E39: 84 | F39: ='c311'!E39 -> 0 | G39: =F39/D39 -> 0 | H39: =30*BC!B77/E39 -> 0 | I39: =IF(H39>G39,H39,G39) -> 0 | J39: =IF(G39=0,0,I39) -> 0 | K39: =ROUNDUP(J39,0) -> 0 | L39: 341 | M39: =L39*K39 -> 0 | N39: =L39/D39 -> 3.41 | O39: =N39+$N$137+((BC!$F$125)/$F$74) -> #DIV/0! | P39: =O39*F39 -> #DIV/0! | Q39: =((O39*0.15)+O39) -> #DIV/0! | R39: =Q39*F39 -> #DIV/0!
B40: 4537939190 | C40: FRUC, 150TESTS, COBAS C, INTEGRA | D40: 150 | E40: 56 | F40: ='c311'!E40 -> 0 | G40: =F40/D40 -> 0 | H40: =30*BC!B78/E40 -> 0 | I40: =IF(H40>G40,H40,G40) -> 0 | J40: =IF(G40=0,0,I40) -> 0 | K40: =ROUNDUP(J40,0) -> 0 | L40: 126 | M40: =L40*K40 -> 0 | N40: =L40/D40 -> 0.84 | O40: =N40+$N$137+((BC!$F$125)/$F$74) -> #DIV/0! | P40: =O40*F40 -> #DIV/0! | Q40: =((O40*0.15)+O40) -> #DIV/0! | R40: =Q40*F40 -> #DIV/0!
B41: 3002721122 | C41: GGT-2, 400T, COBAS C, INTEGRA | D41: 400 | E41: 84 | F41: ='c311'!E41 -> 0 | G41: =F41/D41 -> 0 | H41: =30*BC!B79/E41 -> 0 | I41: =IF(H41>G41,H41,G41) -> 0 | J41: =IF(G41=0,0,I41) -> 0 | K41: =ROUNDUP(J41,0) -> 0 | L41: 192 | M41: =L41*K41 -> 0 | N41: =L41/D41 -> 0.48 | O41: =N41+$N$137+((BC!$F$125)/$F$74) -> #DIV/0! | P41: =O41*F41 -> #DIV/0! | Q41: =((O41*0.15)+O41) -> #DIV/0! | R41: =Q41*F41 -> #DIV/0!
B42: 4404483190 | C42: GLUC HK GEN.3, 800TESTS, COBAS C, INT. | D42: 800 | E42: 56 | F42: ='c311'!E42 -> 0 | G42: =F42/D42 -> 0 | H42: =30*BC!B80/E42 -> 0 | I42: =IF(H42>G42,H42,G42) -> 0 | J42: =IF(G42=0,0,I42) -> 0 | K42: =ROUNDUP(J42,0) -> 0 | L42: 176 | M42: =L42*K42 -> 0 | N42: =L42/D42 -> 0.22 | O42: =N42+$N$137+((BC!$F$125)/$F$74) -> #DIV/0! | P42: =O42*F42 -> #DIV/0! | Q42: =((O42*0.15)+O42) -> #DIV/0! | R42: =Q42*F42 -> #DIV/0!
B43: 3005593322 | C43: HAPT GEN.2, 100TESTS, COBAS C, INTEGRA | D43: 100 | E43: 84 | F43: ='c311'!E43 -> 0 | G43: =F43/D43 -> 0 | H43: =30*BC!B81/E43 -> 0 | I43: =IF(H43>G43,H43,G43) -> 0 | J43: =IF(G43=0,0,I43) -> 0 | K43: =ROUNDUP(J43,0) -> 0 | L43: 301 | M43: =L43*K43 -> 0 | N43: =L43/D43 -> 3.01 | O43: =N43+$N$137+((BC!$F$125)/$F$74) -> #DIV/0! | P43: =O43*F43 -> #DIV/0! | Q43: =((O43*0.15)+O43) -> #DIV/0! | R43: =Q43*F43 -> #DIV/0!
... B73: 4460715190 | C73: UREAL, 500T, COBAS C, INTEGRA | D73: 500 | E73: 56 | F73: ='c311'!E73 -> 0 | G73: =F73/D73 -> 0 | H73: =30*BC!B111/E73 -> 0 | I73: =IF(H73>G73,H73,G73) -> 0 | J73: =IF(G73=0,0,I73) -> 0 | K73: =ROUNDUP(J73,0) -> 0 | L73: 120 | M73: =L73*K73 -> 0 | N73: =L73/D73 -> 0.24 | O73: =N73+$N$137+((BC!$F$125)/$F$74) -> #DIV/0! | P73: =O73*F73 -> #DIV/0! | Q73: =((O73*0.15)+O73) -> #DIV/0! | R73: =Q73*F73 -> #DIV/0!
E74: TOTAL DET | F74: =SUM(F9:F73) -> 0
C75: CALIBRADORES | D75: PRESENTACION | E75: DIAS ESTABILIDAD | G75: PRODUCTO CALCULADO | H75: MINIMOS POR ESTABILIDAD | I75: PRODUCTO A ENTREGAR | K75: MAXIMOS | L75: PVP POR UNIDADES | M75: VALOR POR CAJA | N75: VALOR TOTAL | O75: EN KITS | P75: EN KITS CERRADO
B76: 20751995190 | C76: Ammonia/Ethanol/CO2 Calibrator | D76: 2 | E76: 56 | G76: =(A19*(0.014*(500/2000))) -> 0 | H76: =30*BC!$B$47/E76 -> 0 | I76: =IF(G76>H76,G76,H76) -> 0 | J76: =ROUNDUP(I76,0) -> 0 | K76: =IF(A19>0,J76,0) -> 0 | L76: =M76/D76 -> 313.5 | M76: 627 | N76: =L76*K76 -> 0 | O76: =K76/D76 -> 0 | P76: =ROUNDUP(O76,0) -> 0
B77: 4975901190 | C77: C.f.a.s. Cystatin C | D77: 1 | H77: =30*BC!$B$47/E77 -> #DIV/0! | I77: =IF(G77>H77,G77,H77) -> #DIV/0! | J77: =ROUNDUP(I77,0) -> #DIV/0! | K77: =IF(F37>0,J77,0) -> 0 | N77: =L77*K77 -> 0 | O77: =K77/D77 -> 0 | P77: =ROUNDUP(O77,0) -> 0
B78: 3555941190 | C78: C.f.a.s. PAC | D78: 3 | E78: 14 | G78: =(A25*(0.014*(500/2000))) -> 0 | H78: =30*BC!$B$47/E78 -> 0 | I78: =IF(G78>H78,G78,H78) -> 0 | J78: =ROUNDUP(I78,0) -> 0 | K78: =IF(A25>0,J78,0) -> 0 | L78: =M78/D78 -> 70.666667 | M78: 212 | N78: =L78*K78 -> 0 | O78: =K78/D78 -> 0 | P78: =ROUNDUP(O78,0) -> 0
B79: 10759350190 | C79: Calibrator f.a.s. | D79: 12 | E79: 28 | G79: =(A13/(0.005*400)/3000) -> 0 | H79: =30*BC!$B$47/E79 -> 0 | I79: =IF(G79>H79,G79,H79) -> 0 | J79: =ROUNDUP(I79,0) -> 0 | K79: =IF(A10>0,J79,0) -> 0 | L79: =M79/D79 -> 12 | M79: 144 | N79: =L79*K79 -> 0 | O79: =K79/D79 -> 0 | P79: =ROUNDUP(O79,0) -> 0
B80: 11447394216 | C80: Calibrator f.a.s. CK-MB | D80: 3 | E80: 28 | G80: =(F31*(0.014*(500/2000))) -> 0 | H80: =30*BC!$B$47/E80 -> 0 | I80: =IF(G80>H80,G80,H80) -> 0 | J80: =ROUNDUP(I80,0) -> 0 | K80: =IF(F31>0,J80,0) -> 0 | L80: =M80/D80 -> 25.333333 | M80: 76 | N80: =L80*K80 -> 0 | O80: =K80/D80 -> 0 | P80: =ROUNDUP(O80,0) -> 0
B81: 6533850190 | C81: Calibrator f.a.s. IgA/IgM CSF | D81: 3 | E81: 14 | G81: =(F49*(0.014*(500/2000))) -> 0 | H81: =30*BC!$B$47/E81 -> 0 | I81: =IF(G81>H81,G81,H81) -> 0 | J81: =ROUNDUP(I81,0) -> 0 | K81: =IF(F49>0,J81,0) -> 0 | L81: =M81/D81 -> 323 | M81: 969 | N81: =L81*K81 -> 0 | O81: =K81/D81 -> 0 | P81: =ROUNDUP(O81,0) -> 0
B82: 12172623122 | C82: Calibrator f.a.s. Lipids | D82: 3 | E82: 28 | G82: =(A28*(0.008*(350/1000))) -> 0 | H82: =30*BC!$B$47/E82 -> 0 | I82: =IF(G82>H82,G82,H82) -> 0 | J82: =ROUNDUP(I82,0) -> 0 | K82: =IF(A28>0,J82,0) -> 0 | L82: =M82/D82 -> 31 | M82: 93 | N82: =L82*K82 -> 0 | O82: =K82/D82 -> 0 | P82: =ROUNDUP(O82,0) -> 0
B83: 11355279216 | C83: Calibrator f.a.s.proteins | D83: 5 | E83: 28 | G83: =(A22*(0.008*(350/1000))) -> 0 | H83: =30*BC!$B$47/E83 -> 0 | I83: =IF(G83>H83,G83,H83) -> 0 | J83: =ROUNDUP(I83,0) -> 0 | K83: =IF(A22>0,J83,0) -> 0 | L83: =M83/D83 -> 29.8 | M83: 149 | N83: =L83*K83 -> 0 | O83: =K83/D83 -> 0 | P83: =ROUNDUP(O83,0) -> 0
B84: 8753776190 | C84: CALIBRATOR STFR GEN.2 | D84: 3 | E84: 28 | G84: =(F65*(0.014*(500/2000))) -> 0 | H84: =30*BC!$B$47/E84 -> 0 | I84: =IF(G84>H84,G84,H84) -> 0 | J84: =ROUNDUP(I84,0) -> 0 | K84: =IF(F65>0,J84,0) -> 0 | L84: =M84/D84 -> 127 | M84: 381 | N84: =L84*K84 -> 0 | O84: =K84/D84 -> 0 | P84: =ROUNDUP(O84,0) -> 0
B85: 8047545190 | C85: Calibrator β2‑Microglobulin | D85: 2 | E85: 84 | G85: =(F21*(0.014*(500/2000))) -> 0 | H85: =30*BC!$B$47/E85 -> 0 | I85: =IF(G85>H85,G85,H85) -> 0 | J85: =ROUNDUP(I85,0) -> 0 | K85: =IF(F21>0,J85,0) -> 0 | L85: =M85/D85 -> 25.5 | M85: 51 | N85: =L85*K85 -> 0 | O85: =K85/D85 -> 0 | P85: =ROUNDUP(O85,0) -> 0
B86: 4528417190 | C86: Cfas HbA1c | D86: 3 | E86: 84 | G86: =(F44*(0.014*(500/2000))) -> 0 | H86: =30*BC!$B$47/E86 -> 0 | I86: =IF(G86>H86,G86,H86) -> 0 | J86: =ROUNDUP(I86,0) -> 0 | K86: =IF(F44>0,J86,0) -> 0 | L86: =M86/D86 -> 150.33333 | M86: 451 | N86: =L86*K86 -> 0 | O86: =K86/D86 -> 0 | P86: =ROUNDUP(O86,0) -> 0
B87: 3121305122 | C87: Cfas Proteins U | D87: 5 | E87: 28 | G87: =(A16*(0.008*(350/1000))) -> 0 | H87: =30*BC!$B$47/E87 -> 0 | I87: =IF(G87>H87,G87,H87) -> 0 | J87: =ROUNDUP(I87,0) -> 0 | K87: =IF(A16>0,J87,0) -> 0 | L87: =M87/D87 -> 75.2 | M87: 376 | N87: =L87*K87 -> 0 | O87: =K87/D87 -> 0 | P87: =ROUNDUP(O87,0) -> 0
B88: 5050901190 | C88: D-Dimer Gen.2 Calibrator Set | D88: 1 | E88: 84 | G88: =(F38*(0.04*(350/1000))) -> 0 | H88: =30*BC!$B$47/E88 -> 0 | I88: =IF(G88>H88,G88,H88) -> 0 | J88: =ROUNDUP(I88,0) -> 0 | K88: =IF(F38>0,J88,0) -> 0 | L88: =M88/D88 -> 282 | M88: 282 | N88: =L88*K88 -> 0 | O88: =K88/D88 -> 0 | P88: =ROUNDUP(O88,0) -> 0
B89: 12146401216 | C89: Fe Standard | D89: 1 | E89: 360 | G89: =(F72*(0.02*(200/1000))) -> 0 | H89: =30*BC!$B$47/E89 -> 0 | I89: =IF(G89>H89,G89,H89) -> 0 | J89: =ROUNDUP(I89,0) -> 0 | K89: =IF(F72>0,J89,0) -> 0 | L89: =M89/D89 -> 183 | M89: 183 | N89: =L89*K89 -> 0 | O89: =K89/D89 -> 0 | P89: =ROUNDUP(O89,0) -> 0
B90: 5385504190 | C90: HCYS Calibrator Kit | D90: 2 | E90: 28 | G90: =(F46*(0.02*(200/1000))) -> 0 | H90: =30*BC!$B$47/E90 -> 0 | I90: =IF(G90>H90,G90,H90) -> 0 | J90: =ROUNDUP(I90,0) -> 0 | K90: =IF(F46>0,J90,0) -> 0 | L90: =M90/D90 -> 40 | M90: 80 | N90: =L90*K90 -> 0 | O90: =K90/D90 -> 0 | P90: =ROUNDUP(O90,0) -> 0
B91: 11098993122 | C91: Precimat Fructosamina | D91: 3 | E91: 28 | G91: =(F40*(0.02*(200/1000))) -> 0 | H91: =30*BC!$B$47/E91 -> 0 | I91: =IF(G91>H91,G91,H91) -> 0 | J91: =ROUNDUP(I91,0) -> 0 | K91: =IF(F40>0,J91,0) -> 0 | L91: =M91/D91 -> 26.666667 | M91: 80 | N91: =L91*K91 -> 0 | O91: =K91/D91 -> 0 | P91: =ROUNDUP(O91,0) -> 0
B92: 3304671190 | C92: PRECISET DAT PLUS I | D92: 1 | E92: 60 | G92: =(A31*(0.02*(200/1000))) -> 0 | H92: =30*BC!$B$47/E92 -> 0 | I92: =IF(G92>H92,G92,H92) -> 0 | J92: =ROUNDUP(I92,0) -> 0 | K92: =IF(A31>0,J92,0) -> 0 | L92: =M92/D92 -> 231 | M92: 231 | N92: =L92*K92 -> 0 | O92: =K92/D92 -> 0 | P92: =ROUNDUP(O92,0) -> 0
B93: 5852641190 | C93: Preciset Lp(a) Gen.2 | D93: 1 | E93: 14 | G93: =(F59*(0.02*(200/1000))) -> 0 | H93: =30*BC!$B$47/E93 -> 0 | I93: =IF(G93>H93,G93,H93) -> 0 | J93: =ROUNDUP(I93,0) -> 0 | K93: =IF(F59>0,J93,0) -> 0 | L93: =M93/D93 -> 384 | M93: 384 | N93: =L93*K93 -> 0 | O93: =K93/D93 -> 0 | P93: =ROUNDUP(O93,0) -> 0
B94: 12172828322 | C94: Preciset RF | D94: 1 | E94: 30 | G94: =(F64*(0.04*(350/1000))) -> 0 | H94: =30*BC!$B$47/E94 -> 0 | I94: =IF(G94>H94,G94,H94) -> 0 | J94: =ROUNDUP(I94,0) -> 0 | K94: =IF(F64>0,J94,0) -> 0 | L94: =M94/D94 -> 197 | M94: 197 | N94: =L94*K94 -> 0 | O94: =K94/D94 -> 0 | P94: =ROUNDUP(O94,0) -> 0
C95: CONTROLES | D95: PRESENTACION | E95: DIAS ESTABILIDAD | G95: PRODUCTO CALCULADO | H95: MINIMOS POR ESTABILIDAD | I95: PRODUCTO A ENTREGAR | K95: MAXIMOS | L95: PVP POR UNIDADES | M95: VALOR TOTAL | N95: VALOR TOTAL | O95: EN KITS | P95: EN KITS CERRADO
B96: 20752401190 | C96: Ammonia/Ethanol/CO2 Control Normal | D96: 5 | E96: 56 | G96: =(A19*(0.025*(500/2000))) -> 0 | H96: =30*BC!$B$47/E96 -> 0 | I96: =IF(G96>H96,G96,H96) -> 0 | J96: =ROUNDUP(I96,0) -> 0 | K96: =IF(A19>0,J96,0) -> 0 | L96: =M96/D96 -> 41.4 | M96: 207 | N96: =L96*K96 -> 0 | O96: =K96/D96 -> 0 | P96: =ROUNDUP(O96,0) -> 0
B97: 20753009190 | C97: Ammonia/Ethanol/CO2 Control Abnormal | D97: 5 | E97: 56 | G97: =(A19*(0.025*(500/2000))) -> 0 | H97: =30*BC!$B$47/E97 -> 0 | I97: =IF(G97>H97,G97,H97) -> 0 | J97: =ROUNDUP(I97,0) -> 0 | K97: =IF(A19>0,J97,0) -> 0 | L97: =M97/D97 -> 45.4 | M97: 227 | N97: =L97*K97 -> 0 | O97: =K97/D97 -> 0 | P97: =ROUNDUP(O97,0) -> 0
B98: 8362785190 | C98: Control Set β2‑Microglobulin (Nivel 1-2) | D98: 2 | E98: 84 | G98: =(F21*(0.025*(500/2000))) -> 0 | H98: =30*BC!$B$47/E98 -> 0 | I98: =IF(G98>H98,G98,H98) -> 0 | J98: =ROUNDUP(I98,0) -> 0 | K98: =IF(F21>0,J98,0) -> 0 | L98: =M98/D98 -> 122 | M98: 244 | N98: =L98*K98 -> 0 | O98: =K98/D98 -> 0 | P98: =ROUNDUP(O98,0) -> 0
B99: 8278202190 | C99: CONTROL-SET STFR | D99: 3 | E99: 28 | G99: =(F65*(0.025*(500/2000))) -> 0 | H99: =30*BC!$B$47/E99 -> 0 | I99: =IF(G99>H99,G99,H99) -> 0 | J99: =ROUNDUP(I99,0) -> 0 | K99: =IF(F65>0,J99,0) -> 0 | L99: =M99/D99 -> 103 | M99: 309 | N99: =L99*K99 -> 0 | O99: =K99/D99 -> 0 | P99: =ROUNDUP(O99,0) -> 0
B100: 6729371190 | C100: Cystatin C Control Set Gen.2 (1,2,3) | D100: 3 | E100: 30 | H100: =30*BC!$B$47/E100 -> 0 | I100: =IF(G100>H100,G100,H100) -> 0 | J100: =ROUNDUP(I100,0) -> 0 | K100: =IF(F37>0,J100,0) -> 0 | L100: =M100/D100 -> 527 | M100: 1581 | N100: =L100*K100 -> 0 | O100: =K100/D100 -> 0 | P100: =ROUNDUP(O100,0) -> 0
B101: 5050936190 | C101: D-Dimer Gen.2 Control I/II | D101: 2 | E101: 84 | G101: =(F38*(0.5*(350/1000))) -> 0 | H101: =30*BC!$B$47/E101 -> 0 | I101: =IF(G101>H101,G101,H101) -> 0 | J101: =ROUNDUP(I101,0) -> 0 | K101: =IF(F38>0,J101,0) -> 0 | L101: =M101/D101 -> 244 | M101: 488 | N101: =L101*K101 -> 0 | O101: =K101/D101 -> 0 | P101: =ROUNDUP(O101,0) -> 0
B102: 5142423190 | C102: HCYS Control Kit Control 1 y 2 | D102: 2 | E102: 28 | G102: =(F46*(0.04*(200/1000))) -> 0 | H102: =30*BC!$B$47/E102 -> 0 | I102: =IF(G102>H102,G102,H102) -> 0 | J102: =ROUNDUP(I102,0) -> 0 | K102: =IF(F46>0,J102,0) -> 0 | L102: =M102/D102 -> 37 | M102: 74 | N102: =L102*K102 -> 0 | O102: =K102/D102 -> 0 | P102: =ROUNDUP(O102,0) -> 0
B103: 5947626190 | C103: PreciControl ClinChem Multi 1, 4x5 ml | D103: 4 | E103: 14 | G103: =(A13/(0.003*400)/3000) -> 0 | H103: =30*BC!$B$47/E103 -> 0 | I103: =IF(G103>H103,G103,H103) -> 0 | J103: =ROUNDUP(I103,0) -> 0 | K103: =IF(A13>0,J103,0) -> 0 | L103: =M103/D103 -> 14.25 | M103: 57 | N103: =L103*K103 -> 0 | O103: =K103/D103 -> 0 | P103: =ROUNDUP(O103,0) -> 0
B104: 5947774190 | C104: PreciControl ClinChem Multi 2, 4x5 ml | D104: 4 | E104: 14 | G104: =(A13/(0.003*400)/3000) -> 0 | H104: =30*BC!$B$47/E104 -> 0 | I104: =IF(G104>H104,G104,H104) -> 0 | J104: =ROUNDUP(I104,0) -> 0 | K104: =IF(A13>0,J104,0) -> 0 | L104: =M104/D104 -> 22.75 | M104: 91 | N104: =L104*K104 -> 0 | O104: =K104/D104 -> 0 | P104: =ROUNDUP(O104,0) -> 0
B105: 5479207190 | C105: PreciControl HbA1c norm | D105: 4 | E105: 28 | G105: =(F44*(0.025*(500/2000))) -> 0 | H105: =30*BC!$B$47/E105 -> 0 | I105: =IF(G105>H105,G105,H105) -> 0 | J105: =ROUNDUP(I105,0) -> 0 | K105: =IF(F44>0,J105,0) -> 0 | L105: =M105/D105 -> 77.25 | M105: 309 | N105: =L105*K105 -> 0 | O105: =K105/D105 -> 0 | P105: =ROUNDUP(O105,0) -> 0
B106: 5912504190 | C106: PreciControl HbA1c path | D106: 4 | E106: 28 | G106: =(F44*(0.025*(500/2000))) -> 0 | H106: =30*BC!$B$47/E106 -> 0 | I106: =IF(G106>H106,G106,H106) -> 0 | J106: =ROUNDUP(I106,0) -> 0 | K106: =IF(F44>0,J106,0) -> 0 | L106: =M106/D106 -> 154.5 | M106: 618 | N106: =L106*K106 -> 0 | O106: =K106/D106 -> 0 | P106: =ROUNDUP(O106,0) -> 0
B107: 5852650190 | C107: PreciControl Lp(a) Gen.2 | D107: 2 | E107: 14 | G107: =(F59*(0.04*(200/1000))) -> 0 | H107: =30*BC!$B$47/E107 -> 0 | I107: =IF(G107>H107,G107,H107) -> 0 | J107: =ROUNDUP(I107,0) -> 0 | K107: =IF(F59>0,J107,0) -> 0 | L107: =M107/D107 -> 286 | M107: 572 | N107: =L107*K107 -> 0 | O107: =K107/D107 -> 0 | P107: =ROUNDUP(O107,0) -> 0
B108: 11098985122 | C108: PRECINORM FRUC | D108: 3 | E108: 28 | G108: =(F40*(0.04*(200/1000))) -> 0 | H108: =30*BC!$B$47/E108 -> 0 | I108: =IF(G108>H108,G108,H108) -> 0 | J108: =ROUNDUP(I108,0) -> 0 | K108: =IF(F40>0,J108,0) -> 0 | L108: =M108/D108 -> 21 | M108: 63 | N108: =L108*K108 -> 0 | O108: =K108/D108 -> 0 | P108: =ROUNDUP(O108,0) -> 0
B109: 3121313122 | C109: PRECINORM PUC | D109: 4 | E109: 28 | G109: =(A16*(0.0025*(250/100))) -> 0 | H109: =30*BC!$B$47/E109 -> 0 | I109: =IF(G109>H109,G109,H109) -> 0 | J109: =ROUNDUP(I109,0) -> 0 | K109: =IF(A16>0,J109,0) -> 0 | L109: =M109/D109 -> 115 | M109: 460 | N109: =L109*K109 -> 0 | O109: =K109/D109 -> 0 | P109: =ROUNDUP(O109,0) -> 0
B110: 11174118122 | C110: PRECIPATH FRUC | D110: 3 | E110: 28 | G110: =(F40*(0.04*(200/1000))) -> 0 | H110: =30*BC!$B$47/E110 -> 0 | I110: =IF(G110>H110,G110,H110) -> 0 | J110: =ROUNDUP(I110,0) -> 0 | K110: =IF(F40>0,J110,0) -> 0 | L110: =M110/D110 -> 23.666667 | M110: 71 | N110: =L110*K110 -> 0 | O110: =K110/D110 -> 0 | P110: =ROUNDUP(O110,0) -> 0
B111: 3121291122 | C111: PRECIPATH PUC | D111: 4 | E111: 28 | G111: =(A16*(0.0025*(250/100))) -> 0 | H111: =30*BC!$B$47/E111 -> 0 | I111: =IF(G111>H111,G111,H111) -> 0 | J111: =ROUNDUP(I111,0) -> 0 | K111: =IF(A16>0,J111,0) -> 0 | L111: =M111/D111 -> 98 | M111: 392 | N111: =L111*K111 -> 0 | O111: =K111/D111 -> 0 | P111: =ROUNDUP(O111,0) -> 0
B112: 3005496122 | C112: RF Control Set | D112: 4 | E112: 30 | G112: =(F64*(0.08*(350/1000))) -> 0 | H112: =30*BC!$B$47/E112 -> 0 | I112: =IF(G112>H112,G112,H112) -> 0 | J112: =ROUNDUP(I112,0) -> 0 | K112: =IF(F64>0,J112,0) -> 0 | L112: =M112/D112 -> 52.75 | M112: 211 | N112: =L112*K112 -> 0 | O112: =K112/D112 -> 0 | P112: =ROUNDUP(O112,0) -> 0
C113: CONSUMIBLES | D113: PRESENTACION | E113: DIAS ESTABILIDAD | G113: PRODUCTO CALCULADO | H113: MINIMOS POR ESTABILIDAD | I113: PRODUCTO A ENTREGAR | K113: MAXIMOS | L113: PVP POR UNIDADES | M113: VALOR TOTAL | N113: VALOR TOTAL | O113: EN KITS | P113: EN KITS CERRADO
B114: 4880285190 | C114: Cell Wash Solution I / NaOH-D | D114: 2 | E114: 70 | G114: =(F74/(0.00025*800)/12000) -> 0 | H114: =30*BC!$B$47/E114 -> 0 | I114: =IF(G114>H114,G114,H114) -> 0 | J114: =ROUNDUP(I114,0) -> 0 | K114: =IF(F74>0,J114,0) -> 0 | L114: =M114/D114 -> 32.5 | M114: 65 | N114: =L114*K114 -> 0 | O114: =K114/D114 -> 0 | P114: =ROUNDUP(O114,0) -> 0
B115: 4880307190 | C115: Cell Wash Solution II / Acid Wash | D115: 2 | E115: 84 | G115: =(F74/(0.025*800)/12000) -> 0 | H115: =30*BC!$B$47/E115 -> 0 | I115: =IF(G115>H115,G115,H115) -> 0 | J115: =ROUNDUP(I115,0) -> 0 | K115: =IF(F74>0,J115,0) -> 0 | L115: =M115/D115 -> 35.5 | M115: 71 | N115: =L115*K115 -> 0 | O115: =K115/D115 -> 0 | P115: =ROUNDUP(O115,0) -> 0
B116: 4444191001 | C116: cobas sample cups | D116: 1 | E116: 365 | G116: =((F74-(F74*0.9))/E116) -> 0 | H116: =30*BC!$B$47/E116 -> 0 | I116: =IF(G116>H116,G116,H116) -> 0 | J116: =ROUNDUP(I116,0) -> 0 | K116: =IF(F74>0,J116,0) -> 0 | L116: =M116/D116 -> 9 | M116: 9 | N116: =L116*K116 -> 0 | O116: =K116/D116 -> 0 | P116: =ROUNDUP(O116,0) -> 0
B117: 4555040001 | C117: Cuvettes – reaction cell sets | D117: 3 | E117: 84 | G117: =(F74/(0.07*30)/6300) -> 0 | H117: =30*BC!$B$47/E117 -> 0 | I117: =IF(G117>H117,G117,H117) -> 0 | J117: =ROUNDUP(I117,0) -> 0 | K117: =IF(F74>0,J117,0) -> 0 | L117: =M117/D117 -> 312 | M117: 936 | N117: =L117*K117 -> 0 | O117: =K117/D117 -> 0 | P117: =ROUNDUP(O117,0) -> 0
B118: 5422485190 | C118: Ecotergent | D118: 1 | E118: 28 | G118: =(F74/(1.2*11)/120) -> 0 | H118: =30*BC!$B$47/E118 -> 0 | I118: =IF(G118>H118,G118,H118) -> 0 | J118: =ROUNDUP(I118,0) -> 0 | K118: =IF(F74>0,J118,0) -> 0 | L118: =M118/D118 -> 32 | M118: 32 | N118: =L118*K118 -> 0 | O118: =K118/D118 -> 0 | P118: =ROUNDUP(O118,0) -> 0
B119: 4554124001 | C119: FILTRO DE RESINA IONICA REGENERADA 20" | D119: 1 | E119: 30 | G119: =(F74/(0.05*30)/6300) -> 0 | H119: =30*BC!$B$47/E119 -> 0 | I119: =IF(G119>H119,G119,H119) -> 0 | J119: =ROUNDUP(I119,0) -> 0 | K119: =IF(F74>0,J119,0) -> 0 | L119: =M119/D119 -> 178 | M119: 178 | N119: =L119*K119 -> 0 | O119: =K119/D119 -> 0 | P119: =ROUNDUP(O119,0) -> 0
B120: 4516273001 | C120: FILTRO NOM. P/SEDIMENTS GX05-20XX (BLANCO) | D120: 1 | E120: 30 | G120: =(F74/(0.05*30)/6300) -> 0 | H120: =30*BC!$B$47/E120 -> 0 | I120: =IF(G120>H120,G120,H120) -> 0 | J120: =ROUNDUP(I120,0) -> 0 | K120: =IF(F74>0,J120,0) -> 0 | L120: =M120/D120 -> 26 | M120: 26 | N120: =L120*K120 -> 0 | O120: =K120/D120 -> 0 | P120: =ROUNDUP(O120,0) -> 0
B121: 4516265001 | C121: FILTRO NOM. P/SEDIMENTS PX5-20 PURTR (AZUL) | D121: 1 | E121: 30 | G121: =(F74/(0.05*30)/6300) -> 0 | H121: =30*BC!$B$47/E121 -> 0 | I121: =IF(G121>H121,G121,H121) -> 0 | J121: =ROUNDUP(I121,0) -> 0 | K121: =IF(F74>0,J121,0) -> 0 | L121: =M121/D121 -> 61 | M121: 61 | N121: =L121*K121 -> 0 | O121: =K121/D121 -> 0 | P121: =ROUNDUP(O121,0) -> 0
B122: 4528182190 | C122: HBA1C TQ HAEMOLYZING RGT, COBAS C | D122: 1 | E122: 28 | G122: =(F44/(0.025*500)/100) -> 0 | H122: =30*BC!$B$47/E122 -> 0 | I122: =IF(G122>H122,G122,H122) -> 0 | J122: =ROUNDUP(I122,0) -> 0 | K122: =IF(F44>0,J122,0) -> 0 | L122: =M122/D122 -> 26 | M122: 26 | N122: =L122*K122 -> 0 | O122: =K122/D122 -> 0 | P122: =ROUNDUP(O122,0) -> 0
B123: 4813707001 | C123: Lamp, Halogen | D123: 1 | E123: 45 | G123: =(F74/(0.07*30)/6300) -> 0 | H123: =30*BC!$B$47/E123 -> 0 | I123: =IF(G123>H123,G123,H123) -> 0 | J123: =ROUNDUP(I123,0) -> 0 | K123: =IF(F74>0,J123,0) -> 0 | L123: =M123/D123 -> 402 | M123: 402 | N123: =L123*K123 -> 0 | O123: =K123/D123 -> 0 | P123: =ROUNDUP(O123,0) -> 0
B124: 4516303001 | C124: MEMBRANE EQ.OSMOSIS, AG2521TF 2.5 diam | D124: 1 | E124: 360 | G124: =(F74/(0.025*500)/12000) -> 0 | H124: =30*BC!$B$47/E124 -> 0 | I124: =IF(G124>H124,G124,H124) -> 0 | J124: =ROUNDUP(I124,0) -> 0 | K124: =IF(F74>0,J124,0) -> 0 | L124: =M124/D124 -> 859 | M124: 859 | N124: =L124*K124 -> 0 | O124: =K124/D124 -> 0 | P124: =ROUNDUP(O124,0) -> 0
B125: 4708725190 | C125: Multiclean, Sample Cleaner 1 | D125: 12 | E125: 28 | G125: =(F74/(0.00025*250)/56000) -> 0 | H125: =30*BC!$B$47/E125 -> 0 | I125: =IF(G125>H125,G125,H125) -> 0 | J125: =ROUNDUP(I125,0) -> 0 | K125: =IF(F74>0,J125,0) -> 0 | L125: =M125/D125 -> 4.0833333 | M125: 49 | N125: =L125*K125 -> 0 | O125: =K125/D125 -> 0 | P125: =ROUNDUP(O125,0) -> 0
B126: 4489357190 | C126: NaCl 9% Diluent | D126: 1 | E126: 84 | G126: =(F74/(0.03*200)/12000) -> 0 | H126: =30*BC!$B$47/E126 -> 0 | I126: =IF(G126>H126,G126,H126) -> 0 | J126: =ROUNDUP(I126,0) -> 0 | K126: =IF(F74>0,J126,0) -> 0 | L126: =M126/D126 -> 14 | M126: 14 | N126: =L126*K126 -> 0 | O126: =K126/D126 -> 0 | P126: =ROUNDUP(O126,0) -> 0
B127: 4489241190 | C127: NaOH-D c pack | D127: 1 | E127: 84 | G127: =(F74/(0.0003*800)/12000) -> 0 | H127: =30*BC!$B$47/E127 -> 0 | I127: =IF(G127>H127,G127,H127) -> 0 | J127: =ROUNDUP(I127,0) -> 0 | K127: =IF(F74>0,J127,0) -> 0 | L127: =M127/D127 -> 5 | M127: 5 | N127: =L127*K127 -> 0 | O127: =K127/D127 -> 0 | P127: =ROUNDUP(O127,0) -> 0
B128: 4489225190 | C128: SMS | D128: 1 | E128: 84 | G128: =(F74/(0.04*300)/12000) -> 0 | H128: =30*BC!$B$47/E128 -> 0 | I128: =IF(G128>H128,G128,H128) -> 0 | J128: =ROUNDUP(I128,0) -> 0 | K128: =IF(F74>0,J128,0) -> 0 | L128: =M128/D128 -> 7 | M128: 7 | N128: =L128*K128 -> 0 | O128: =K128/D128 -> 0 | P128: =ROUNDUP(O128,0) -> 0
B129: 4516303001 | C129: MEMBRANE EQ.OSMOSIS, AG2521TF 2.5 DIAM | D129: 1 | E129: 365 | G129: =(F75/(0.04*300)/12000) -> 0 | H129: =30*BC!$B$47/E129 -> 0 | I129: =IF(G129>H129,G129,H129) -> 0 | J129: =ROUNDUP(I129,0) -> 0 | K129: =IF(F75>0,J129,0) -> 0 | L129: =M129/D129 -> 859 | M129: 859 | N129: =L129*K129 -> 0 | O129: =K129/D129 -> 0 | P129: =ROUNDUP(O129,0) -> 0
B130: FAM154 | C130: RESINA MIXTA GRANEL X KG | D130: 1 | E130: 365 | G130: =(F76/(0.04*300)/12000) -> 0 | H130: =30*BC!$B$47/E130 -> 0 | I130: =IF(G130>H130,G130,H130) -> 0 | J130: =ROUNDUP(I130,0) -> 0 | K130: =IF(F76>0,J130,0) -> 0 | L130: =M130/D130 -> 50 | M130: 50 | N130: =L130*K130 -> 0 | O130: =K130/D130 -> 0 | P130: =ROUNDUP(O130,0) -> 0
...

Sheet c311 PRUEBA EFECTIVA
B1: CLIENTE
B2: FECHA
B3: MODALIDAD
B4: PLAZO | D4: MESES
B5: PROYECCIÓN | D5: MESES
B6: EQUIPO | C6: C311
A8: CFAS | B8: I.D | C8: DESCRIPCION | D8: DET/KIT | E8: DIAS ESTABILIDAD | F8: DET/AÑO/PROCESO | G8: PRUEBA EFECTIVA | H8: PRODUCTO CALCULADO | I8: MINIMOS POR ESTABILIDAD | J8: PRODUCTO A ENTREGAR | L8: REDONDEADO A ENTREGAR | M8: PVP | N8: TOTAL | O8: $ DETERMINACION | P8: $DETERMINACION CON CONSUMIBLES Y EXTRAS | Q8: TOTAL CON CONSUMIBLES Y EXTRAS | R8: $ PARA PROCESO | S8: TOTAL PARA PROCESO | T8: VALOR INICIAL DEL PROCESO | U8: VALOR FINAL DEL PROCESO
A9: =G11+G12+G14+G15+G16+G20+G22+G23+G26+G28+G29+G30+G34+G41+G42+G45+G52+G54+G56+G58+G60+G62+G67+G69+G71+G73 -> 0 | B9: 6750052190 | C9: A-1MG TQ GEN.2, 100TEST, COBAS C/INT | D9: 200 | E9: 84 | F9: ='c311'!E9 -> 0 | G9: =(F9*0.2)+(F9) -> 0 | H9: =G9/D9 -> 0 | I9: =30*BC!$B$47/E9 -> 0 | J9: =IF(I9>H9,I9,H9) -> 0 | K9: =IF(H9=0,0,J9) -> 0 | L9: =ROUNDUP(K9,0) -> 0 | M9: 762 | N9: =M9*L9 -> 0 | O9: =M9/D9 -> 3.81 | P9: =O9+$O$137+((BC!$F$125)/$F$74) -> #DIV/0! | Q9: =P9*F9 -> #DIV/0! | R9: =((P9*0.15)+P9) -> #DIV/0! | S9: =R9*F9 -> #DIV/0! | T9: =SUM(S9:S73) -> #DIV/0! | U9: =SUM(Q9:Q73) -> #DIV/0!
B10: 3005771322 | C10: AAT GEN.2, 100TESTS, COBAS C, INTEGRA | D10: 100 | E10: 84 | F10: ='c311'!E10 -> 0 | G10: =(F10*0.2)+(F10) -> 0 | H10: =G10/D10 -> 0 | I10: =30*BC!$B$47/E10 -> 0 | J10: =IF(I10>H10,I10,H10) -> 0 | K10: =IF(H10=0,0,J10) -> 0 | L10: =ROUNDUP(K10,0) -> 0 | M10: 436 | N10: =M10*L10 -> 0 | O10: =M10/D10 -> 4.36 | P10: =O10+$O$137+((BC!$F$125)/$F$74) -> #DIV/0! | Q10: =P10*F10 -> #DIV/0! | R10: =((P10*0.15)+P10) -> #DIV/0! | S10: =R10*F10 -> #DIV/0!
A11: CCLINCHEM | B11: 4375351190 | C11: ACP HIT 917 LARGE | D11: 400 | E11: 84 | F11: ='c311'!E11 -> 0 | G11: =(F11*0.2)+(F11) -> 0 | H11: =G11/D11 -> 0 | I11: =30*BC!$B$47/E11 -> 0 | J11: =IF(I11>H11,I11,H11) -> 0 | K11: =IF(H11=0,0,J11) -> 0 | L11: =ROUNDUP(K11,0) -> 0 | M11: 456 | N11: =M11*L11 -> 0 | O11: =M11/D11 -> 1.14 | P11: =O11+$O$137+((BC!$F$125)/$F$74) -> #DIV/0! | Q11: =P11*F11 -> #DIV/0! | R11: =((P11*0.15)+P11) -> #DIV/0! | S11: =R11*F11 -> #DIV/0!
A12: =G10+G11+G12+G14+G15+G16+G17+G18+G19+G20+G22+G23+G26+G28+G29+G30+G31+G34+G35+G36+G41+G42+G43+G45+G47+G48+G49+G50+G51+G52+G53+G54+G55+G57+G58+G60+G62+G63+G67+G69+G70+G71+G72+G73 -> 0 | B12: 3183688122 | C12: ALB2, 300T, COBAS C, INTEGRA | D12: 300 | E12: 84 | F12: ='c311'!E12 -> 0 | G12: =(F12*0.2)+(F12) -> 0 | H12: =G12/D12 -> 0 | I12: =30*BC!$B$47/E12 -> 0 | J12: =IF(I12>H12,I12,H12) -> 0 | K12: =IF(H12=0,0,J12) -> 0 | L12: =ROUNDUP(K12,0) -> 0 | M12: 72 | N12: =M12*L12 -> 0 | O12: =M12/D12 -> 0.24 | P12: =O12+$O$137+((BC!$F$125)/$F$74) -> #DIV/0! | Q12: =P12*F12 -> #DIV/0! | R12: =((P12*0.15)+P12) -> #DIV/0! | S12: =R12*F12 -> #DIV/0!
B13: 4469658190 | C13: ALB-T TQ GEN.2, 100TESTS, COBAS C, INT | D13: 100 | E13: 84 | F13: ='c311'!E13 -> 0 | G13: =(F13*0.2)+(F13) -> 0 | H13: =G13/D13 -> 0 | I13: =30*BC!$B$47/E13 -> 0 | J13: =IF(I13>H13,I13,H13) -> 0 | K13: =IF(H13=0,0,J13) -> 0 | L13: =ROUNDUP(K13,0) -> 0 | M13: 287 | N13: =M13*L13 -> 0 | O13: =M13/D13 -> 2.87 | P13: =O13+$O$137+((BC!$F$125)/$F$74) -> #DIV/0! | Q13: =P13*F13 -> #DIV/0! | R13: =((P13*0.15)+P13) -> #DIV/0! | S13: =R13*F13 -> #DIV/0!
A14: PUC | B14: 3333752190 | C14: ALP2, 200T, COBAS C, INTEGRA | D14: 200 | E14: 56 | F14: ='c311'!E14 -> 0 | G14: =(F14*0.2)+(F14) -> 0 | H14: =G14/D14 -> 0 | I14: =30*BC!$B$47/E14 -> 0 | J14: =IF(I14>H14,I14,H14) -> 0 | K14: =IF(H14=0,0,J14) -> 0 | L14: =ROUNDUP(K14,0) -> 0 | M14: 62 | N14: =M14*L14 -> 0 | O14: =M14/D14 -> 0.31 | P14: =O14+$O$137+((BC!$F$125)/$F$74) -> #DIV/0! | Q14: =P14*F14 -> #DIV/0! | R14: =((P14*0.15)+P14) -> #DIV/0! | S14: =R14*F14 -> #DIV/0!
A15: =G9+G68 -> 0 | B15: 20764957322 | C15: ALTL, 500TESTS, COBAS C, INTEGRA | D15: 500 | E15: 84 | F15: ='c311'!E15 -> 0 | G15: =(F15*0.2)+(F15) -> 0 | H15: =G15/D15 -> 0 | I15: =30*BC!$B$47/E15 -> 0 | J15: =IF(I15>H15,I15,H15) -> 0 | K15: =IF(H15=0,0,J15) -> 0 | L15: =ROUNDUP(K15,0) -> 0 | M15: 145 | N15: =M15*L15 -> 0 | O15: =M15/D15 -> 0.29 | P15: =O15+$O$137+((BC!$F$125)/$F$74) -> #DIV/0! | Q15: =P15*F15 -> #DIV/0! | R15: =((P15*0.15)+P15) -> #DIV/0! | S15: =R15*F15 -> #DIV/0!
B16: 3183742122 | C16: AMYL GEN.2, 300TESTS, COBAS C, INTEGRA | D16: 300 | E16: 84 | F16: ='c311'!E16 -> 0 | G16: =(F16*0.2)+(F16) -> 0 | H16: =G16/D16 -> 0 | I16: =30*BC!$B$47/E16 -> 0 | J16: =IF(I16>H16,I16,H16) -> 0 | K16: =IF(H16=0,0,J16) -> 0 | L16: =ROUNDUP(K16,0) -> 0 | M16: 198 | N16: =M16*L16 -> 0 | O16: =M16/D16 -> 0.66 | P16: =O16+$O$137+((BC!$F$125)/$F$74) -> #DIV/0! | Q16: =P16*F16 -> #DIV/0! | R16: =((P16*0.15)+P16) -> #DIV/0! | S16: =R16*F16 -> #DIV/0!
A17: AMMONIA | B17: 3032566122 | C17: APOAT, 100TESTS, COBAS C, INTEGRA | D17: 100 | E17: 84 | F17: ='c311'!E17 -> 0 | G17: =(F17*0.2)+(F17) -> 0 | H17: =G17/D17 -> 0 | I17: =30*BC!$B$47/E17 -> 0 | J17: =IF(I17>H17,I17,H17) -> 0 | K17: =IF(H17=0,0,J17) -> 0 | L17: =ROUNDUP(K17,0) -> 0 | M17: 225 | N17: =M17*L17 -> 0 | O17: =M17/D17 -> 2.25 | P17: =O17+$O$137+((BC!$F$125)/$F$74) -> #DIV/0! | Q17: =P17*F17 -> #DIV/0! | R17: =((P17*0.15)+P17) -> #DIV/0! | S17: =R17*F17 -> #DIV/0!
A18: =G32+G39+G61 -> 0 | B18: 3032574122 | C18: APOBT, 100TESTS, COBAS C, INTEGRA | D18: 100 | E18: 84 | F18: ='c311'!E18 -> 0 | G18: =(F18*0.2)+(F18) -> 0 | H18: =G18/D18 -> 0 | I18: =30*BC!$B$47/E18 -> 0 | J18: =IF(I18>H18,I18,H18) -> 0 | K18: =IF(H18=0,0,J18) -> 0 | L18: =ROUNDUP(K18,0) -> 0 | M18: 225 | N18: =M18*L18 -> 0 | O18: =M18/D18 -> 2.25 | P18: =O18+$O$137+((BC!$F$125)/$F$74) -> #DIV/0! | Q18: =P18*F18 -> #DIV/0! | R18: =((P18*0.15)+P18) -> #DIV/0! | S18: =R18*F18 -> #DIV/0!
B19: 4489403190 | C19: ASLO TQ, 150TESTS, COBAS C | D19: 150 | E19: 84 | F19: ='c311'!E19 -> 0 | G19: =(F19*0.2)+(F19) -> 0 | H19: =G19/D19 -> 0 | I19: =30*BC!$B$47/E19 -> 0 | J19: =IF(I19>H19,I19,H19) -> 0 | K19: =IF(H19=0,0,J19) -> 0 | L19: =ROUNDUP(K19,0) -> 0 | M19: 494 | N19: =M19*L19 -> 0 | O19: =M19/D19 -> 3.2933333 | P19: =O19+$O$137+((BC!$F$125)/$F$74) -> #DIV/0! | Q19: =P19*F19 -> #DIV/0! | R19: =((P19*0.15)+P19) -> #DIV/0! | S19: =R19*F19 -> #DIV/0!
A20: CFAS PROTEIN | B20: 20764949322 | C20: ASTL, 500TESTS, COBAS C, INTEGRA | D20: 500 | E20: 84 | F20: ='c311'!E20 -> 0 | G20: =(F20*0.2)+(F20) -> 0 | H20: =G20/D20 -> 0 | I20: =30*BC!$B$47/E20 -> 0 | J20: =IF(I20>H20,I20,H20) -> 0 | K20: =IF(H20=0,0,J20) -> 0 | L20: =ROUNDUP(K20,0) -> 0 | M20: 145 | N20: =M20*L20 -> 0 | O20: =M20/D20 -> 0.29 | P20: =O20+$O$137+((BC!$F$125)/$F$74) -> #DIV/0! | Q20: =P20*F20 -> #DIV/0! | R20: =((P20*0.15)+P20) -> #DIV/0! | S20: =R20*F20 -> #DIV/0!
A21: =G10+G24+G25+G35+G36+G43+G48+G50+G51+G53+G55+G70 -> 0 | B21: 8047430190 | C21: B2MG, 140T, COBAS C 311, COBAS C 501/502 | D21: 140 | E21: 84 | F21: ='c311'!E21 -> 0 | G21: =(F21*0.2)+(F21) -> 0 | H21: =G21/D21 -> 0 | I21: =30*BC!$B$47/E21 -> 0 | J21: =IF(I21>H21,I21,H21) -> 0 | K21: =IF(H21=0,0,J21) -> 0 | L21: =ROUNDUP(K21,0) -> 0 | M21: 1169 | N21: =M21*L21 -> 0 | O21: =M21/D21 -> 8.35 | P21: =O21+$O$137+((BC!$F$125)/$F$74) -> #DIV/0! | Q21: =P21*F21 -> #DIV/0! | R21: =((P21*0.15)+P21) -> #DIV/0! | S21: =R21*F21 -> #DIV/0!
B22: 5589061190 | C22: BIL-D GEN.2, 350TESTS COBAS C, INTEGRA | D22: 350 | E22: 42 | F22: ='c311'!E22 -> 0 | G22: =(F22*0.2)+(F22) -> 0 | H22: =G22/D22 -> 0 | I22: =30*BC!$B$47/E22 -> 0 | J22: =IF(I22>H22,I22,H22) -> 0 | K22: =IF(H22=0,0,J22) -> 0 | L22: =ROUNDUP(K22,0) -> 0 | M22: 144 | N22: =M22*L22 -> 0 | O22: =M22/D22 -> 0.41142857 | P22: =O22+$O$137+((BC!$F$125)/$F$74) -> #DIV/0! | Q22: =P22*F22 -> #DIV/0! | R22: =((P22*0.15)+P22) -> #DIV/0! | S22: =R22*F22 -> #DIV/0!
A23: C.f.a.s. PAC | B23: 5795397190 | C23: BIL-T GEN.3, 250TESTS COBAS C,INTEGRA | D23: 250 | E23: 42 | F23: ='c311'!E23 -> 0 | G23: =(F23*0.2)+(F23) -> 0 | H23: =G23/D23 -> 0 | I23: =30*BC!$B$47/E23 -> 0 | J23: =IF(I23>H23,I23,H23) -> 0 | K23: =IF(H23=0,0,J23) -> 0 | L23: =ROUNDUP(K23,0) -> 0 | M23: 85 | N23: =M23*L23 -> 0 | O23: =M23/D23 -> 0.34 | P23: =O23+$O$137+((BC!$F$125)/$F$74) -> #DIV/0! | Q23: =P23*F23 -> #DIV/0! | R23: =((P23*0.15)+P23) -> #DIV/0! | S23: =R23*F23 -> #DIV/0!
A24: =G19+G27+G63 -> 0 | B24: 3001938322 | C24: C3C, 100TESTS, COBAS C, INTEGRA | D24: 100 | E24: 42 | F24: ='c311'!E24 -> 0 | G24: =(F24*0.2)+(F24) -> 0 | H24: =G24/D24 -> 0 | I24: =30*BC!$B$47/E24 -> 0 | J24: =IF(I24>H24,I24,H24) -> 0 | K24: =IF(H24=0,0,J24) -> 0 | L24: =ROUNDUP(K24,0) -> 0 | M24: 307 | N24: =M24*L24 -> 0 | O24: =M24/D24 -> 3.07 | P24: =O24+$O$137+((BC!$F$125)/$F$74) -> #DIV/0! | Q24: =P24*F24 -> #DIV/0! | R24: =((P24*0.15)+P24) -> #DIV/0! | S24: =R24*F24 -> #DIV/0!
B25: 3001962322 | C25: C4, 100TESTS, COBAS C, INTEGRA | D25: 100 | E25: 56 | F25: ='c311'!E25 -> 0 | G25: =(F25*0.2)+(F25) -> 0 | H25: =G25/D25 -> 0 | I25: =30*BC!$B$47/E25 -> 0 | J25: =IF(I25>H25,I25,H25) -> 0 | K25: =IF(H25=0,0,J25) -> 0 | L25: =ROUNDUP(K25,0) -> 0 | M25: 309 | N25: =M25*L25 -> 0 | O25: =M25/D25 -> 3.09 | P25: =O25+$O$137+((BC!$F$125)/$F$74) -> #DIV/0! | Q25: =P25*F25 -> #DIV/0! | R25: =((P25*0.15)+P25) -> #DIV/0! | S25: =R25*F25 -> #DIV/0!
A26: Calibrator f.a.s. Lipids | B26: 5061482190 | C26: CA, GEN.2, 300TESTS, COBAS C,INTEGRA | D26: 300 | E26: 56 | F26: ='c311'!E26 -> 0 | G26: =(F26*0.2)+(F26) -> 0 | H26: =G26/D26 -> 0 | I26: =30*BC!$B$47/E26 -> 0 | J26: =IF(I26>H26,I26,H26) -> 0 | K26: =IF(H26=0,0,J26) -> 0 | L26: =ROUNDUP(K26,0) -> 0 | M26: 108 | N26: =M26*L26 -> 0 | O26: =M26/D26 -> 0.36 | P26: =O26+$O$137+((BC!$F$125)/$F$74) -> #DIV/0! | Q26: =P26*F26 -> #DIV/0! | R26: =((P26*0.15)+P26) -> #DIV/0! | S26: =R26*F26 -> #DIV/0!
A27: =G17+G18+G47+G57 -> 0 | B27: 20764663322 | C27: CERU, 100TESTS, COBAS C, INTEGRA | D27: 100 | E27: 56 | F27: ='c311'!E27 -> 0 | G27: =(F27*0.2)+(F27) -> 0 | H27: =G27/D27 -> 0 | I27: =30*BC!$B$47/E27 -> 0 | J27: =IF(I27>H27,I27,H27) -> 0 | K27: =IF(H27=0,0,J27) -> 0 | L27: =ROUNDUP(K27,0) -> 0 | M27: 259 | N27: =M27*L27 -> 0 | O27: =M27/D27 -> 2.59 | P27: =O27+$O$137+((BC!$F$125)/$F$74) -> #DIV/0! | Q27: =P27*F27 -> #DIV/0! | R27: =((P27*0.15)+P27) -> #DIV/0! | S27: =R27*F27 -> #DIV/0!
B28: 4498577190 | C28: CHE GEN.2, 200TESTS, COBAS C, INTEGRA | D28: 200 | E28: 28 | F28: ='c311'!E28 -> 0 | G28: =(F28*0.2)+(F28) -> 0 | H28: =G28/D28 -> 0 | I28: =30*BC!$B$47/E28 -> 0 | J28: =IF(I28>H28,I28,H28) -> 0 | K28: =IF(H28=0,0,J28) -> 0 | L28: =ROUNDUP(K28,0) -> 0 | M28: 166 | N28: =M28*L28 -> 0 | O28: =M28/D28 -> 0.83 | P28: =O28+$O$137+((BC!$F$125)/$F$74) -> #DIV/0! | Q28: =P28*F28 -> #DIV/0! | R28: =((P28*0.15)+P28) -> #DIV/0! | S28: =R28*F28 -> #DIV/0!
A29: PRECISET DAT PLUS I | B29: 3039773190 | C29: CHOL HICO GEN.2, 400TESTS, COBAS C, INT. | D29: 400 | E29: 28 | F29: ='c311'!E29 -> 0 | G29: =(F29*0.2)+(F29) -> 0 | H29: =G29/D29 -> 0 | I29: =30*BC!$B$47/E29 -> 0 | J29: =IF(I29>H29,I29,H29) -> 0 | K29: =IF(H29=0,0,J29) -> 0 | L29: =ROUNDUP(K29,0) -> 0 | M29: 88 | N29: =M29*L29 -> 0 | O29: =M29/D29 -> 0.22 | P29: =O29+$O$137+((BC!$F$125)/$F$74) -> #DIV/0! | Q29: =P29*F29 -> #DIV/0! | R29: =((P29*0.15)+P29) -> #DIV/0! | S29: =R29*F29 -> #DIV/0!
A30: =G33+G66 -> 0 | B30: 7190794190 | C30: CK 200 TESTS, COBAS C/INTEGRA | D30: 200 | E30: 56 | F30: ='c311'!E30 -> 0 | G30: =(F30*0.2)+(F30) -> 0 | H30: =G30/D30 -> 0 | I30: =30*BC!$B$47/E30 -> 0 | J30: =IF(I30>H30,I30,H30) -> 0 | K30: =IF(H30=0,0,J30) -> 0 | L30: =ROUNDUP(K30,0) -> 0 | M30: 112 | N30: =M30*L30 -> 0 | O30: =M30/D30 -> 0.56 | P30: =O30+$O$137+((BC!$F$125)/$F$74) -> #DIV/0! | Q30: =P30*F30 -> #DIV/0! | R30: =((P30*0.15)+P30) -> #DIV/0! | S30: =R30*F30 -> #DIV/0!
B31: 7190808190 | C31: CK-MB 100TESTS, COBAS C/INTEGRA | D31: 100 | E31: 56 | F31: ='c311'!E31 -> 0 | G31: =(F31*0.2)+(F31) -> 0 | H31: =G31/D31 -> 0 | I31: =30*BC!$B$47/E31 -> 0 | J31: =IF(I31>H31,I31,H31) -> 0 | K31: =IF(H31=0,0,J31) -> 0 | L31: =ROUNDUP(K31,0) -> 0 | M31: 276 | N31: =M31*L31 -> 0 | O31: =M31/D31 -> 2.76 | P31: =O31+$O$137+((BC!$F$125)/$F$74) -> #DIV/0! | Q31: =P31*F31 -> #DIV/0! | R31: =((P31*0.15)+P31) -> #DIV/0! | S31: =R31*F31 -> #DIV/0!
B32: 3289923190 | C32: COBAS INTEGRA CO2-L GEN.2 250 TEST | D32: 250 | E32: 42 | F32: ='c311'!E32 -> 0 | G32: =(F32*0.2)+(F32) -> 0 | H32: =G32/D32 -> 0 | I32: =30*BC!$B$47/E32 -> 0 | J32: =IF(I32>H32,I32,H32) -> 0 | K32: =IF(H32=0,0,J32) -> 0 | L32: =ROUNDUP(K32,0) -> 0 | M32: 174 | N32: =M32*L32 -> 0 | O32: =M32/D32 -> 0.696 | P32: =O32+$O$137+((BC!$F$125)/$F$74) -> #DIV/0! | Q32: =P32*F32 -> #DIV/0! | R32: =((P32*0.15)+P32) -> #DIV/0! | S32: =R32*F32 -> #DIV/0!
B33: 4490827190 | C33: COC2, 200T, COBAS C | D33: 200 | E33: 56 | F33: ='c311'!E33 -> 0 | G33: =(F33*0.2)+(F33) -> 0 | H33: =G33/D33 -> 0 | I33: =30*BC!$B$47/E33 -> 0 | J33: =IF(I33>H33,I33,H33) -> 0 | K33: =IF(H33=0,0,J33) -> 0 | L33: =ROUNDUP(K33,0) -> 0 | M33: 120 | N33: =M33*L33 -> 0 | O33: =M33/D33 -> 0.6 | P33: =O33+$O$137+((BC!$F$125)/$F$74) -> #DIV/0! | Q33: =P33*F33 -> #DIV/0! | R33: =((P33*0.15)+P33) -> #DIV/0! | S33: =R33*F33 -> #DIV/0!
B34: 4810716190 | C34: CREAJ2, 700T, COBAS C, INTEGRA | D34: 700 | E34: 56 | F34: ='c311'!E34 -> 0 | G34: =(F34*0.2)+(F34) -> 0 | H34: =G34/D34 -> 0 | I34: =30*BC!$B$47/E34 -> 0 | J34: =IF(I34>H34,I34,H34) -> 0 | K34: =IF(H34=0,0,J34) -> 0 | L34: =ROUNDUP(K34,0) -> 0 | M34: 136 | N34: =M34*L34 -> 0 | O34: =M34/D34 -> 0.19428571 | P34: =O34+$O$137+((BC!$F$125)/$F$74) -> #DIV/0! | Q34: =P34*F34 -> #DIV/0! | R34: =((P34*0.15)+P34) -> #DIV/0! | S34: =R34*F34 -> #DIV/0!
B35: 4628918190 | C35: CRP LX HS, 300TESTS, COBAS C, INTEGRA | D35: 100 | E35: 84 | F35: ='c311'!E35 -> 0 | G35: =(F35*0.2)+(F35) -> 0 | H35: =G35/D35 -> 0 | I35: =30*BC!$B$47/E35 -> 0 | J35: =IF(I35>H35,I35,H35) -> 0 | K35: =IF(H35=0,0,J35) -> 0 | L35: =ROUNDUP(K35,0) -> 0 | M35: 750 | N35: =M35*L35 -> 0 | O35: =M35/D35 -> 7.5 | P35: =O35+$O$137+((BC!$F$125)/$F$74) -> #DIV/0! | Q35: =P35*F35 -> #DIV/0! | R35: =((P35*0.15)+P35) -> #DIV/0! | S35: =R35*F35 -> #DIV/0!
B36: 7876033190 | C36: CRP4, 250T, COBAS C 311/501/502,INTEGRA | D36: 250 | E36: 84 | F36: ='c311'!E36 -> 0 | G36: =(F36*0.2)+(F36) -> 0 | H36: =G36/D36 -> 0 | I36: =30*BC!$B$47/E36 -> 0 | J36: =IF(I36>H36,I36,H36) -> 0 | K36: =IF(H36=0,0,J36) -> 0 | L36: =ROUNDUP(K36,0) -> 0 | M36: 643 | N36: =M36*L36 -> 0 | O36: =M36/D36 -> 2.572 | P36: =O36+$O$137+((BC!$F$125)/$F$74) -> #DIV/0! | Q36: =P36*F36 -> #DIV/0! | R36: =((P36*0.15)+P36) -> #DIV/0! | S36: =R36*F36 -> #DIV/0!
B37: 6600239190 | C37: CYSC2, 225T, COBAS INTEGRA | D37: 225 | E37: 56 | F37: ='c311'!E37 -> 0 | G37: =(F37*0.2)+(F37) -> 0 | H37: =G37/D37 -> 0 | I37: =30*BC!$B$47/E37 -> 0 | J37: =IF(I37>H37,I37,H37) -> 0 | K37: =IF(H37=0,0,J37) -> 0 | L37: =ROUNDUP(K37,0) -> 0 | M37: 1282 | N37: =M37*L37 -> 0 | O37: =M37/D37 -> 5.6977778 | P37: =O37+$O$137+((BC!$F$125)/$F$74) -> #DIV/0! | Q37: =P37*F37 -> #DIV/0! | R37: =((P37*0.15)+P37) -> #DIV/0! | S37: =R37*F37 -> #DIV/0!
B38: 4912551190 | C38: D-DIMER GEN.2, 100TEST, COBAS C, INTEGRA | D38: 100 | E38: 84 | F38: ='c311'!E38 -> 0 | G38: =(F38*0.2)+(F38) -> 0 | H38: =G38/D38 -> 0 | I38: =30*BC!$B$47/E38 -> 0 | J38: =IF(I38>H38,I38,H38) -> 0 | K38: =IF(H38=0,0,J38) -> 0 | L38: =ROUNDUP(K38,0) -> 0 | M38: 1066 | N38: =M38*L38 -> 0 | O38: =M38/D38 -> 10.66 | P38: =O38+$O$137+((BC!$F$125)/$F$74) -> #DIV/0! | Q38: =P38*F38 -> #DIV/0! | R38: =((P38*0.15)+P38) -> #DIV/0! | S38: =R38*F38 -> #DIV/0!
B39: 3183777190 | C39: ETOH2 , 100T, COBAS INTEGRA | D39: 100 | E39: 84 | F39: ='c311'!E39 -> 0 | G39: =(F39*0.2)+(F39) -> 0 | H39: =G39/D39 -> 0 | I39: =30*BC!$B$47/E39 -> 0 | J39: =IF(I39>H39,I39,H39) -> 0 | K39: =IF(H39=0,0,J39) -> 0 | L39: =ROUNDUP(K39,0) -> 0 | M39: 341 | N39: =M39*L39 -> 0 | O39: =M39/D39 -> 3.41 | P39: =O39+$O$137+((BC!$F$125)/$F$74) -> #DIV/0! | Q39: =P39*F39 -> #DIV/0! | R39: =((P39*0.15)+P39) -> #DIV/0! | S39: =R39*F39 -> #DIV/0!
B40: 4537939190 | C40: FRUC, 150TESTS, COBAS C, INTEGRA | D40: 150 | E40: 56 | F40: ='c311'!E40 -> 0 | G40: =(F40*0.2)+(F40) -> 0 | H40: =G40/D40 -> 0 | I40: =30*BC!$B$47/E40 -> 0 | J40: =IF(I40>H40,I40,H40) -> 0 | K40: =IF(H40=0,0,J40) -> 0 | L40: =ROUNDUP(K40,0) -> 0 | M40: 126 | N40: =M40*L40 -> 0 | O40: =M40/D40 -> 0.84 | P40: =O40+$O$137+((BC!$F$125)/$F$74) -> #DIV/0! | Q40: =P40*F40 -> #DIV/0! | R40: =((P40*0.15)+P40) -> #DIV/0! | S40: =R40*F40 -> #DIV/0!
B41: 3002721122 | C41: GGT-2, 400T, COBAS C, INTEGRA | D41: 400 | E41: 84 | F41: ='c311'!E41 -> 0 | G41: =(F41*0.2)+(F41) -> 0 | H41: =G41/D41 -> 0 | I41: =30*BC!$B$47/E41 -> 0 | J41: =IF(I41>H41,I41,H41) -> 0 | K41: =IF(H41=0,0,J41) -> 0 | L41: =ROUNDUP(K41,0) -> 0 | M41: 192 | N41: =M41*L41 -> 0 | O41: =M41/D41 -> 0.48 | P41: =O41+$O$137+((BC!$F$125)/$F$74) -> #DIV/0! | Q41: =P41*F41 -> #DIV/0! | R41: =((P41*0.15)+P41) -> #DIV/0! | S41: =R41*F41 -> #DIV/0!
B42: 4404483190 | C42: GLUC HK GEN.3, 800TESTS, COBAS C, INT. | D42: 800 | E42: 56 | F42: ='c311'!E42 -> 0 | G42: =(F42*0.2)+(F42) -> 0 | H42: =G42/D42 -> 0 | I42: =30*BC!$B$47/E42 -> 0 | J42: =IF(I42>H42,I42,H42) -> 0 | K42: =IF(H42=0,0,J42) -> 0 | L42: =ROUNDUP(K42,0) -> 0 | M42: 176 | N42: =M42*L42 -> 0 | O42: =M42/D42 -> 0.22 | P42: =O42+$O$137+((BC!$F$125)/$F$74) -> #DIV/0! | Q42: =P42*F42 -> #DIV/0! | R42: =((P42*0.15)+P42) -> #DIV/0! | S42: =R42*F42 -> #DIV/0!
... B73: 4460715190 | C73: UREAL, 500T, COBAS C, INTEGRA | D73: 500 | E73: 56 | F73: ='c311'!E73 -> 0 | G73: =(F73*0.2)+(F73) -> 0 | H73: =G73/D73 -> 0 | I73: =30*BC!$B$47/E73 -> 0 | J73: =IF(I73>H73,I73,H73) -> 0 | K73: =IF(H73=0,0,J73) -> 0 | L73: =ROUNDUP(K73,0) -> 0 | M73: 120 | N73: =M73*L73 -> 0 | O73: =M73/D73 -> 0.24 | P73: =O73+$O$137+((BC!$F$125)/$F$74) -> #DIV/0! | Q73: =P73*F73 -> #DIV/0! | R73: =((P73*0.15)+P73) -> #DIV/0! | S73: =R73*F73 -> #DIV/0!
E74: TOTAL DET | F74: =SUM(F9:F73) -> 0 | G74: =SUM(G9:G73) -> 0
C75: CALIBRADORES | L75: MAXIMOS | M75: PVP POR UNIDADES | N75: VALOR POR CAJA | O75: VALOR TOTAL | P75: EN KITS | Q75: EN KITS CERRADO
B76: 20751995190 | C76: Ammonia/Ethanol/CO2 Calibrator | D76: 2 | E76: 56 | H76: =(B19*(0.014*(500/2000))) -> 15712911 | I76: =30*BC!$B$47/E76 -> 0 | J76: =IF(H76>I76,H76,I76) -> 15712911 | K76: =ROUNDUP(J76,0) -> 15712912 | L76: =IF(A18>0,K76,0) -> 0 | M76: =N76/D76 -> 313.5 | N76: 627 | O76: =M76*L76 -> 0 | P76: =L76/D76 -> 0 | Q76: =ROUNDUP(P76,0) -> 0
B77: 4975901190 | C77: C.f.a.s. Cystatin C | D77: 1 | I77: =30*BC!$B$47/E77 -> #DIV/0! | J77: =IF(H77>I77,H77,I77) -> #DIV/0! | K77: =ROUNDUP(J77,0) -> #DIV/0! | L77: =IF(F37>0,K77,0) -> 0 | M77: =N77/D77 -> 0 | O77: =M77*L77 -> 0 | P77: =L77/D77 -> 0 | Q77: =ROUNDUP(P77,0) -> 0
B78: 3555941190 | C78: C.f.a.s. PAC | D78: 3 | E78: 14 | H78: =(B25*(0.014*(500/2000))) -> 10506868 | I78: =30*BC!$B$47/E78 -> 0 | J78: =IF(H78>I78,H78,I78) -> 10506868 | K78: =ROUNDUP(J78,0) -> 10506869 | L78: =IF(A24>0,K78,0) -> 0 | M78: =N78/D78 -> 70.666667 | N78: 212 | O78: =M78*L78 -> 0 | P78: =L78/D78 -> 0 | Q78: =ROUNDUP(P78,0) -> 0
B79: 10759350190 | C79: Calibrator f.a.s. | D79: 12 | E79: 28 | H79: =(B13/(0.005*400)/3000) -> 744943.03 | I79: =30*BC!$B$47/E79 -> 0 | J79: =IF(H79>I79,H79,I79) -> 744943.03 | K79: =ROUNDUP(J79,0) -> 744944 | L79: =IF(A9>0,K79,0) -> 0 | M79: =N79/D79 -> 12 | N79: 144 | O79: =M79*L79 -> 0 | P79: =L79/D79 -> 0 | Q79: =ROUNDUP(P79,0) -> 0
B80: 11447394216 | C80: Calibrator f.a.s. CK-MB | D80: 3 | E80: 28 | H80: =(G31*(0.014*(500/2000))) -> 0 | I80: =30*BC!$B$47/E80 -> 0 | J80: =IF(H80>I80,H80,I80) -> 0 | K80: =ROUNDUP(J80,0) -> 0 | L80: =IF(F31>0,K80,0) -> 0 | M80: =N80/D80 -> 25.333333 | N80: 76 | O80: =M80*L80 -> 0 | P80: =L80/D80 -> 0 | Q80: =ROUNDUP(P80,0) -> 0
B81: 6533850190 | C81: Calibrator f.a.s. IgA/IgM CSF | D81: 3 | E81: 14 | H81: =(G49*(0.014*(500/2000))) -> 0 | I81: =30*BC!$B$47/E81 -> 0 | J81: =IF(H81>I81,H81,I81) -> 0 | K81: =ROUNDUP(J81,0) -> 0 | L81: =IF(F49>0,K81,0) -> 0 | M81: =N81/D81 -> 323 | N81: 969 | O81: =M81*L81 -> 0 | P81: =L81/D81 -> 0 | Q81: =ROUNDUP(P81,0) -> 0
B82: 12172623122 | C82: Calibrator f.a.s. Lipids | D82: 3 | E82: 28 | H82: =(B28*(0.008*(350/1000))) -> 12596016 | I82: =30*BC!$B$47/E82 -> 0 | J82: =IF(H82>I82,H82,I82) -> 12596016 | K82: =ROUNDUP(J82,0) -> 12596017 | L82: =IF(A27>0,K82,0) -> 0 | M82: =N82/D82 -> 31 | N82: 93 | O82: =M82*L82 -> 0 | P82: =L82/D82 -> 0 | Q82: =ROUNDUP(P82,0) -> 0
B83: 11355279216 | C83: Calibrator f.a.s.proteins | D83: 5 | E83: 28 | H83: =(B22*(0.008*(350/1000))) -> 15649371 | I83: =30*BC!$B$47/E83 -> 0 | J83: =IF(H83>I83,H83,I83) -> 15649371 | K83: =ROUNDUP(J83,0) -> 15649372 | L83: =IF(A21>0,K83,0) -> 0 | M83: =N83/D83 -> 29.8 | N83: 149 | O83: =M83*L83 -> 0 | P83: =L83/D83 -> 0 | Q83: =ROUNDUP(P83,0) -> 0
B84: 8753776190 | C84: CALIBRATOR STFR GEN.2 | D84: 3 | E84: 28 | H84: =(G65*(0.014*(500/2000))) -> 0 | I84: =30*BC!$B$47/E84 -> 0 | J84: =IF(H84>I84,H84,I84) -> 0 | K84: =ROUNDUP(J84,0) -> 0 | L84: =IF(F65>0,K84,0) -> 0 | M84: =N84/D84 -> 127 | N84: 381 | O84: =M84*L84 -> 0 | P84: =L84/D84 -> 0 | Q84: =ROUNDUP(P84,0) -> 0
B85: 8047545190 | C85: Calibrator β2‑Microglobulin | D85: 2 | E85: 84 | H85: =(G21*(0.014*(500/2000))) -> 0 | I85: =30*BC!$B$47/E85 -> 0 | J85: =IF(H85>I85,H85,I85) -> 0 | K85: =ROUNDUP(J85,0) -> 0 | L85: =IF(F21>0,K85,0) -> 0 | M85: =N85/D85 -> 25.5 | N85: 51 | O85: =M85*L85 -> 0 | P85: =L85/D85 -> 0 | Q85: =ROUNDUP(P85,0) -> 0
B86: 4528417190 | C86: Cfas HbA1c | D86: 3 | E86: 84 | H86: =(G44*(0.014*(500/2000))) -> 0 | I86: =30*BC!$B$47/E86 -> 0 | J86: =IF(H86>I86,H86,I86) -> 0 | K86: =ROUNDUP(J86,0) -> 0 | L86: =IF(F44>0,K86,0) -> 0 | M86: =N86/D86 -> 150.33333 | N86: 451 | O86: =M86*L86 -> 0 | P86: =L86/D86 -> 0 | Q86: =ROUNDUP(P86,0) -> 0
B87: 3121305122 | C87: Cfas Proteins U | D87: 5 | E87: 28 | H87: =(B16*(0.008*(350/1000))) -> 8914477.9 | I87: =30*BC!$B$47/E87 -> 0 | J87: =IF(H87>I87,H87,I87) -> 8914477.9 | K87: =ROUNDUP(J87,0) -> 8914478 | L87: =IF(A15>0,K87,0) -> 0 | M87: =N87/D87 -> 75.2 | N87: 376 | O87: =M87*L87 -> 0 | P87: =L87/D87 -> 0 | Q87: =ROUNDUP(P87,0) -> 0
B88: 5050901190 | C88: D-Dimer Gen.2 Calibrator Set | D88: 1 | E88: 84 | H88: =(G38*(0.04*(350/1000))) -> 0 | I88: =30*BC!$B$47/E88 -> 0 | J88: =IF(H88>I88,H88,I88) -> 0 | K88: =ROUNDUP(J88,0) -> 0 | L88: =IF(F38>0,K88,0) -> 0 | M88: =N88/D88 -> 282 | N88: 282 | O88: =M88*L88 -> 0 | P88: =L88/D88 -> 0 | Q88: =ROUNDUP(P88,0) -> 0
B89: 12146401216 | C89: Fe Standard | D89: 1 | E89: 360 | H89: =(G72*(0.02*(200/1000))) -> 0 | I89: =30*BC!$B$47/E89 -> 0 | J89: =IF(H89>I89,H89,I89) -> 0 | K89: =ROUNDUP(J89,0) -> 0 | L89: =IF(F72>0,K89,0) -> 0 | M89: =N89/D89 -> 183 | N89: 183 | O89: =M89*L89 -> 0 | P89: =L89/D89 -> 0 | Q89: =ROUNDUP(P89,0) -> 0
B90: 5385504190 | C90: HCYS Calibrator Kit | D90: 2 | E90: 28 | H90: =(G46*(0.02*(200/1000))) -> 0 | I90: =30*BC!$B$47/E90 -> 0 | J90: =IF(H90>I90,H90,I90) -> 0 | K90: =ROUNDUP(J90,0) -> 0 | L90: =IF(F46>0,K90,0) -> 0 | M90: =N90/D90 -> 40 | N90: 80 | O90: =M90*L90 -> 0 | P90: =L90/D90 -> 0 | Q90: =ROUNDUP(P90,0) -> 0
B91: 11098993122 | C91: Precimat Fructosamina | D91: 3 | E91: 28 | H91: =(G40*(0.02*(200/1000))) -> 0 | I91: =30*BC!$B$47/E91 -> 0 | J91: =IF(H91>I91,H91,I91) -> 0 | K91: =ROUNDUP(J91,0) -> 0 | L91: =IF(F40>0,K91,0) -> 0 | M91: =N91/D91 -> 26.666667 | N91: 80 | O91: =M91*L91 -> 0 | P91: =L91/D91 -> 0 | Q91: =ROUNDUP(P91,0) -> 0
B92: 3304671190 | C92: PRECISET DAT PLUS I | D92: 1 | E92: 60 | H92: =(B31*(0.02*(200/1000))) -> 28763233 | I92: =30*BC!$B$47/E92 -> 0 | J92: =IF(H92>I92,H92,I92) -> 28763233 | K92: =ROUNDUP(J92,0) -> 28763233 | L92: =IF(A30>0,K92,0) -> 0 | M92: =N92/D92 -> 231 | N92: 231 | O92: =M92*L92 -> 0 | P92: =L92/D92 -> 0 | Q92: =ROUNDUP(P92,0) -> 0
B93: 5852641190 | C93: Preciset Lp(a) Gen.2 | D93: 1 | E93: 14 | H93: =(G59*(0.02*(200/1000))) -> 0 | I93: =30*BC!$B$47/E93 -> 0 | J93: =IF(H93>I93,H93,I93) -> 0 | K93: =ROUNDUP(J93,0) -> 0 | L93: =IF(F59>0,K93,0) -> 0 | M93: =N93/D93 -> 384 | N93: 384 | O93: =M93*L93 -> 0 | P93: =L93/D93 -> 0 | Q93: =ROUNDUP(P93,0) -> 0
B94: 12172828322 | C94: Preciset RF | D94: 1 | E94: 30 | H94: =(G64*(0.04*(350/1000))) -> 0 | I94: =30*BC!$B$47/E94 -> 0 | J94: =IF(H94>I94,H94,I94) -> 0 | K94: =ROUNDUP(J94,0) -> 0 | L94: =IF(F64>0,K94,0) -> 0 | M94: =N94/D94 -> 197 | N94: 197 | O94: =M94*L94 -> 0 | P94: =L94/D94 -> 0 | Q94: =ROUNDUP(P94,0) -> 0
C95: CONTROLES | H95: PRODUCTO CALCULADO | I95: MINIMOS POR ESTABILIDAD | N95: VALOR TOTAL
B96: 20752401190 | C96: Ammonia/Ethanol/CO2 Control Normal | D96: 5 | E96: 56 | H96: =(B19*(0.025*(500/2000))) -> 28058770 | I96: =30*BC!$B$47/E96 -> 0 | J96: =IF(H96>I96,H96,I96) -> 28058770 | K96: =ROUNDUP(J96,0) -> 28058770 | L96: =IF(A18>0,K96,0) -> 0 | M96: =N96/D96 -> 41.4 | N96: 207 | O96: =M96*L96 -> 0 | P96: =L96/D96 -> 0 | Q96: =ROUNDUP(P96,0) -> 0
B97: 20753009190 | C97: Ammonia/Ethanol/CO2 Control Abnormal | D97: 5 | E97: 56 | H97: =(B19*(0.025*(500/2000))) -> 28058770 | I97: =30*BC!$B$47/E97 -> 0 | J97: =IF(H97>I97,H97,I97) -> 28058770 | K97: =ROUNDUP(J97,0) -> 28058770 | L97: =IF(A18>0,K97,0) -> 0 | M97: =N97/D97 -> 45.4 | N97: 227 | O97: =M97*L97 -> 0 | P97: =L97/D97 -> 0 | Q97: =ROUNDUP(P97,0) -> 0
B98: 8362785190 | C98: Control Set β2‑Microglobulin (Nivel 1-2) | D98: 2 | E98: 84 | H98: =(G21*(0.025*(500/2000))) -> 0 | I98: =30*BC!$B$47/E98 -> 0 | J98: =IF(H98>I98,H98,I98) -> 0 | K98: =ROUNDUP(J98,0) -> 0 | L98: =IF(F21>0,K98,0) -> 0 | M98: =N98/D98 -> 122 | N98: 244 | O98: =M98*L98 -> 0 | P98: =L98/D98 -> 0 | Q98: =ROUNDUP(P98,0) -> 0
B99: 8278202190 | C99: CONTROL-SET STFR | D99: 3 | E99: 28 | H99: =(G65*(0.025*(500/2000))) -> 0 | I99: =30*BC!$B$47/E99 -> 0 | J99: =IF(H99>I99,H99,I99) -> 0 | K99: =ROUNDUP(J99,0) -> 0 | L99: =IF(F65>0,K99,0) -> 0 | M99: =N99/D99 -> 103 | N99: 309 | O99: =M99*L99 -> 0 | P99: =L99/D99 -> 0 | Q99: =ROUNDUP(P99,0) -> 0
B100: 6729371190 | C100: Cystatin C Control Set Gen.2 (1,2,3) | D100: 3 | E100: 30 | I100: =30*BC!$B$47/E100 -> 0 | J100: =IF(H100>I100,H100,I100) -> 0 | K100: =ROUNDUP(J100,0) -> 0 | L100: =IF(F37>0,K100,0) -> 0 | M100: =N100/D100 -> 527 | N100: 1581 | O100: =M100*L100 -> 0 | P100: =L100/D100 -> 0 | Q100: =ROUNDUP(P100,0) -> 0
B101: 5050936190 | C101: D-Dimer Gen.2 Control I/II | D101: 2 | E101: 84 | H101: =(G38*(0.08*(350/1000))) -> 0 | I101: =30*BC!$B$47/E101 -> 0 | J101: =IF(H101>I101,H101,I101) -> 0 | K101: =ROUNDUP(J101,0) -> 0 | L101: =IF(F38>0,K101,0) -> 0 | M101: =N101/D101 -> 244 | N101: 488 | O101: =M101*L101 -> 0 | P101: =L101/D101 -> 0 | Q101: =ROUNDUP(P101,0) -> 0
B102: 5142423190 | C102: HCYS Control Kit Control 1 y 2 | D102: 2 | E102: 28 | H102: =(G46*(0.04*(200/1000))) -> 0 | I102: =30*BC!$B$47/E102 -> 0 | J102: =IF(H102>I102,H102,I102) -> 0 | K102: =ROUNDUP(J102,0) -> 0 | L102: =IF(F46>0,K102,0) -> 0 | M102: =N102/D102 -> 37 | N102: 74 | O102: =M102*L102 -> 0 | P102: =L102/D102 -> 0 | Q102: =ROUNDUP(P102,0) -> 0
B103: 5947626190 | C103: PreciControl ClinChem Multi 1, 4x5 ml | D103: 4 | E103: 14 | H103: =(B13/(0.003*400)/3000) -> 1241571.7 | I103: =30*BC!$B$47/E103 -> 0 | J103: =IF(H103>I103,H103,I103) -> 1241571.7 | K103: =ROUNDUP(J103,0) -> 1241572 | L103: =IF(A12>0,K103,0) -> 0 | M103: =N103/D103 -> 14.25 | N103: 57 | O103: =M103*L103 -> 0 | P103: =L103/D103 -> 0 | Q103: =ROUNDUP(P103,0) -> 0
B104: 5947774190 | C104: PreciControl ClinChem Multi 2, 4x5 ml | D104: 4 | E104: 14 | H104: =(B13/(0.003*400)/3000) -> 1241571.7 | I104: =30*BC!$B$47/E104 -> 0 | J104: =IF(H104>I104,H104,I104) -> 1241571.7 | K104: =ROUNDUP(J104,0) -> 1241572 | L104: =IF(A12>0,K104,0) -> 0 | M104: =N104/D104 -> 22.75 | N104: 91 | O104: =M104*L104 -> 0 | P104: =L104/D104 -> 0 | Q104: =ROUNDUP(P104,0) -> 0
B105: 5479207190 | C105: PreciControl HbA1c norm | D105: 4 | E105: 28 | H105: =(G44*(0.025*(500/2000))) -> 0 | I105: =30*BC!$B$47/E105 -> 0 | J105: =IF(H105>I105,H105,I105) -> 0 | K105: =ROUNDUP(J105,0) -> 0 | L105: =IF(F44>0,K105,0) -> 0 | M105: =N105/D105 -> 77.25 | N105: 309 | O105: =M105*L105 -> 0 | P105: =L105/D105 -> 0 | Q105: =ROUNDUP(P105,0) -> 0
B106: 5912504190 | C106: PreciControl HbA1c path | D106: 4 | E106: 28 | H106: =(G44*(0.025*(500/2000))) -> 0 | I106: =30*BC!$B$47/E106 -> 0 | J106: =IF(H106>I106,H106,I106) -> 0 | K106: =ROUNDUP(J106,0) -> 0 | L106: =IF(F44>0,K106,0) -> 0 | M106: =N106/D106 -> 154.5 | N106: 618 | O106: =M106*L106 -> 0 | P106: =L106/D106 -> 0 | Q106: =ROUNDUP(P106,0) -> 0
B107: 5852650190 | C107: PreciControl Lp(a) Gen.2 | D107: 2 | E107: 14 | H107: =(G59*(0.04*(200/1000))) -> 0 | I107: =30*BC!$B$47/E107 -> 0 | J107: =IF(H107>I107,H107,I107) -> 0 | K107: =ROUNDUP(J107,0) -> 0 | L107: =IF(F59>0,K107,0) -> 0 | M107: =N107/D107 -> 286 | N107: 572 | O107: =M107*L107 -> 0 | P107: =L107/D107 -> 0 | Q107: =ROUNDUP(P107,0) -> 0
B108: 11098985122 | C108: PRECINORM FRUC | D108: 3 | E108: 28 | H108: =(G40*(0.04*(200/1000))) -> 0 | I108: =30*BC!$B$47/E108 -> 0 | J108: =IF(H108>I108,H108,I108) -> 0 | K108: =ROUNDUP(J108,0) -> 0 | L108: =IF(F40>0,K108,0) -> 0 | M108: =N108/D108 -> 21 | N108: 63 | O108: =M108*L108 -> 0 | P108: =L108/D108 -> 0 | Q108: =ROUNDUP(P108,0) -> 0
B109: 3121313122 | C109: PRECINORM PUC | D109: 4 | E109: 28 | H109: =(B16*(0.0025*(250/100))) -> 19898388 | I109: =30*BC!$B$47/E109 -> 0 | J109: =IF(H109>I109,H109,I109) -> 19898388 | K109: =ROUNDUP(J109,0) -> 19898389 | L109: =IF(A15>0,K109,0) -> 0 | M109: =N109/D109 -> 115 | N109: 460 | O109: =M109*L109 -> 0 | P109: =L109/D109 -> 0 | Q109: =ROUNDUP(P109,0) -> 0
B110: 11174118122 | C110: PRECIPATH FRUC | D110: 3 | E110: 28 | H110: =(G40*(0.04*(200/1000))) -> 0 | I110: =30*BC!$B$47/E110 -> 0 | J110: =IF(H110>I110,H110,I110) -> 0 | K110: =ROUNDUP(J110,0) -> 0 | L110: =IF(F40>0,K110,0) -> 0 | M110: =N110/D110 -> 23.666667 | N110: 71 | O110: =M110*L110 -> 0 | P110: =L110/D110 -> 0 | Q110: =ROUNDUP(P110,0) -> 0
B111: 3121291122 | C111: PRECIPATH PUC | D111: 4 | E111: 28 | H111: =(B16*(0.0025*(250/100))) -> 19898388 | I111: =30*BC!$B$47/E111 -> 0 | J111: =IF(H111>I111,H111,I111) -> 19898388 | K111: =ROUNDUP(J111,0) -> 19898389 | L111: =IF(A15>0,K111,0) -> 0 | M111: =N111/D111 -> 98 | N111: 392 | O111: =M111*L111 -> 0 | P111: =L111/D111 -> 0 | Q111: =ROUNDUP(P111,0) -> 0
B112: 3005496122 | C112: RF Control Set | D112: 4 | E112: 30 | H112: =(G64*(0.08*(350/1000))) -> 0 | I112: =30*BC!$B$47/E112 -> 0 | J112: =IF(H112>I112,H112,I112) -> 0 | K112: =ROUNDUP(J112,0) -> 0 | L112: =IF(F64>0,K112,0) -> 0 | M112: =N112/D112 -> 52.75 | N112: 211 | O112: =M112*L112 -> 0 | P112: =L112/D112 -> 0 | Q112: =ROUNDUP(P112,0) -> 0
C113: CONSUMIBLES | H113: PRODUCTO CALCULADO | I113: MINIMOS POR ESTABILIDAD | N113: VALOR TOTAL
B114: 4880285190 | C114: Cell Wash Solution I / NaOH-D | D114: 2 | E114: 70 | H114: =(G74/(0.00025*800)/12000) -> 0 | I114: =30*BC!$B$47/E114 -> 0 | J114: =IF(H114>I114,H114,I114) -> 0 | K114: =ROUNDUP(J114,0) -> 0 | L114: =IF(F74>0,K114,0) -> 0 | M114: =N114/D114 -> 32.5 | N114: 65 | O114: =M114*L114 -> 0 | P114: =L114/D114 -> 0 | Q114: =ROUNDUP(P114,0) -> 0
B115: 4880307190 | C115: Cell Wash Solution II / Acid Wash | D115: 2 | E115: 84 | H115: =(G74/(0.025*800)/12000) -> 0 | I115: =30*BC!$B$47/E115 -> 0 | J115: =IF(H115>I115,H115,I115) -> 0 | K115: =ROUNDUP(J115,0) -> 0 | L115: =IF(F74>0,K115,0) -> 0 | M115: =N115/D115 -> 35.5 | N115: 71 | O115: =M115*L115 -> 0 | P115: =L115/D115 -> 0 | Q115: =ROUNDUP(P115,0) -> 0
B116: 4444191001 | C116: cobas sample cups | D116: 1 | E116: 365 | H116: =((G74-(G74*0.9))/E116) -> 0 | I116: =30*BC!$B$47/E116 -> 0 | J116: =IF(H116>I116,H116,I116) -> 0 | K116: =ROUNDUP(J116,0) -> 0 | L116: =IF(F74>0,K116,0) -> 0 | M116: =N116/D116 -> 9 | N116: 9 | O116: =M116*L116 -> 0 | P116: =L116/D116 -> 0 | Q116: =ROUNDUP(P116,0) -> 0
B117: 4555040001 | C117: Cuvettes – reaction cell sets | D117: 3 | E117: 84 | H117: =(G74/(0.07*30)/6300) -> 0 | I117: =30*BC!$B$47/E117 -> 0 | J117: =IF(H117>I117,H117,I117) -> 0 | K117: =ROUNDUP(J117,0) -> 0 | L117: =IF(F74>0,K117,0) -> 0 | M117: =N117/D117 -> 312 | N117: 936 | O117: =M117*L117 -> 0 | P117: =L117/D117 -> 0 | Q117: =ROUNDUP(P117,0) -> 0
B118: 5422485190 | C118: Ecotergent | D118: 1 | E118: 28 | H118: =(G74/(0.7*11)/120) -> 0 | I118: =30*BC!$B$47/E118 -> 0 | J118: =IF(H118>I118,H118,I118) -> 0 | K118: =ROUNDUP(J118,0) -> 0 | L118: =IF(F74>0,K118,0) -> 0 | M118: =N118/D118 -> 32 | N118: 32 | O118: =M118*L118 -> 0 | P118: =L118/D118 -> 0 | Q118: =ROUNDUP(P118,0) -> 0
B119: 4554124001 | C119: FILTRO DE RESINA IONICA REGENERADA 20" | D119: 1 | E119: 30 | H119: =(G74/(0.05*30)/6300) -> 0 | I119: =30*BC!$B$47/E119 -> 0 | J119: =IF(H119>I119,H119,I119) -> 0 | K119: =ROUNDUP(J119,0) -> 0 | L119: =IF(F74>0,K119,0) -> 0 | M119: =N119/D119 -> 178 | N119: 178 | O119: =M119*L119 -> 0 | P119: =L119/D119 -> 0 | Q119: =ROUNDUP(P119,0) -> 0
B120: 4516273001 | C120: FILTRO NOM. P/SEDIMENTS GX05-20XX (BLANCO) | D120: 1 | E120: 30 | H120: =(G74/(0.05*30)/6300) -> 0 | I120: =30*BC!$B$47/E120 -> 0 | J120: =IF(H120>I120,H120,I120) -> 0 | K120: =ROUNDUP(J120,0) -> 0 | L120: =IF(F74>0,K120,0) -> 0 | M120: =N120/D120 -> 26 | N120: 26 | O120: =M120*L120 -> 0 | P120: =L120/D120 -> 0 | Q120: =ROUNDUP(P120,0) -> 0
B121: 4516265001 | C121: FILTRO NOM. P/SEDIMENTS PX5-20 PURTR (AZUL) | D121: 1 | E121: 30 | H121: =(G74/(0.05*30)/6300) -> 0 | I121: =30*BC!$B$47/E121 -> 0 | J121: =IF(H121>I121,H121,I121) -> 0 | K121: =ROUNDUP(J121,0) -> 0 | L121: =IF(F74>0,K121,0) -> 0 | M121: =N121/D121 -> 61 | N121: 61 | O121: =M121*L121 -> 0 | P121: =L121/D121 -> 0 | Q121: =ROUNDUP(P121,0) -> 0
B122: 4528182190 | C122: HBA1C TQ HAEMOLYZING RGT, COBAS C | D122: 1 | E122: 28 | H122: =(G44/(0.025*500)/100) -> 0 | I122: =30*BC!$B$47/E122 -> 0 | J122: =IF(H122>I122,H122,I122) -> 0 | K122: =ROUNDUP(J122,0) -> 0 | L122: =IF(F44>0,K122,0) -> 0 | M122: =N122/D122 -> 26 | N122: 26 | O122: =M122*L122 -> 0 | P122: =L122/D122 -> 0 | Q122: =ROUNDUP(P122,0) -> 0
B123: 4813707001 | C123: Lamp, Halogen | D123: 1 | E123: 45 | H123: =(G74/(0.07*30)/6300) -> 0 | I123: =30*BC!$B$47/E123 -> 0 | J123: =IF(H123>I123,H123,I123) -> 0 | K123: =ROUNDUP(J123,0) -> 0 | L123: =IF(F74>0,K123,0) -> 0 | M123: =N123/D123 -> 402 | N123: 402 | O123: =M123*L123 -> 0 | P123: =L123/D123 -> 0 | Q123: =ROUNDUP(P123,0) -> 0
B124: 4516303001 | C124: MEMBRANE EQ.OSMOSIS, AG2521TF 2.5 diam | D124: 1 | E124: 360 | H124: =(G74/(0.025*500)/12000) -> 0 | I124: =30*BC!$B$47/E124 -> 0 | J124: =IF(H124>I124,H124,I124) -> 0 | K124: =ROUNDUP(J124,0) -> 0 | L124: =IF(F74>0,K124,0) -> 0 | M124: =N124/D124 -> 859 | N124: 859 | O124: =M124*L124 -> 0 | P124: =L124/D124 -> 0 | Q124: =ROUNDUP(P124,0) -> 0
B125: 4708725190 | C125: Multiclean, Sample Cleaner 1 | D125: 12 | E125: 28 | H125: =(G74/(0.00025*250)/56000) -> 0 | I125: =30*BC!$B$47/E125 -> 0 | J125: =IF(H125>I125,H125,I125) -> 0 | K125: =ROUNDUP(J125,0) -> 0 | L125: =IF(F74>0,K125,0) -> 0 | M125: =N125/D125 -> 4.0833333 | N125: 49 | O125: =M125*L125 -> 0 | P125: =L125/D125 -> 0 | Q125: =ROUNDUP(P125,0) -> 0
B126: 4489357190 | C126: NaCl 9% Diluent | D126: 1 | E126: 84 | H126: =(G74/(0.03*200)/12000) -> 0 | I126: =30*BC!$B$47/E126 -> 0 | J126: =IF(H126>I126,H126,I126) -> 0 | K126: =ROUNDUP(J126,0) -> 0 | L126: =IF(F74>0,K126,0) -> 0 | M126: =N126/D126 -> 14 | N126: 14 | O126: =M126*L126 -> 0 | P126: =L126/D126 -> 0 | Q126: =ROUNDUP(P126,0) -> 0
B127: 4489241190 | C127: NaOH-D c pack | D127: 1 | E127: 84 | H127: =(G74/(0.0003*800)/12000) -> 0 | I127: =30*BC!$B$47/E127 -> 0 | J127: =IF(H127>I127,H127,I127) -> 0 | K127: =ROUNDUP(J127,0) -> 0 | L127: =IF(F74>0,K127,0) -> 0 | M127: =N127/D127 -> 5 | N127: 5 | O127: =M127*L127 -> 0 | P127: =L127/D127 -> 0 | Q127: =ROUNDUP(P127,0) -> 0
B128: 4489225190 | C128: SMS | D128: 1 | E128: 84 | H128: =(G74/(0.04*300)/12000) -> 0 | I128: =30*BC!$B$47/E128 -> 0 | J128: =IF(H128>I128,H128,I128) -> 0 | K128: =ROUNDUP(J128,0) -> 0 | L128: =IF(F74>0,K128,0) -> 0 | M128: =N128/D128 -> 7 | N128: 7 | O128: =M128*L128 -> 0 | P128: =L128/D128 -> 0 | Q128: =ROUNDUP(P128,0) -> 0
B129: 4516303001 | C129: MEMBRANE EQ.OSMOSIS, AG2521TF 2.5 DIAM | D129: 1 | E129: 365 | H129: =(G75/(0.04*300)/12000) -> 0 | I129: =30*BC!$B$47/E129 -> 0 | J129: =IF(H129>I129,H129,I129) -> 0 | K129: =ROUNDUP(J129,0) -> 0 | L129: =IF(F75>0,K129,0) -> 0 | M129: =N129/D129 -> 859 | N129: 859 | O129: =M129*L129 -> 0 | P129: =L129/D129 -> 0 | Q129: =ROUNDUP(P129,0) -> 0
B130: FAM154 | C130: RESINA MIXTA GRANEL X KG | D130: 1 | E130: 365 | H130: =(G76/(0.04*300)/12000) -> 0 | I130: =30*BC!$B$47/E130 -> 0 | J130: =IF(H130>I130,H130,I130) -> 0 | K130: =ROUNDUP(J130,0) -> 0 | L130: =IF(F76>0,K130,0) -> 0 | M130: =N130/D130 -> 50 | N130: 50 | O130: =M130*L130 -> 0 | P130: =L130/D130 -> 0 | Q130: =ROUNDUP(P130,0) -> 0
B131: 4516265001 | C131: FILTRO NOM. P/SEDIMENTS PX5-20 PURTR (AZUL) | D131: 1 | E131: 365 | H131: =(G77/(0.04*300)/12000) -> 0 | I131: =30*BC!$B$47/E131 -> 0 | J131: =IF(H131>I131,H131,I131) -> 0 | K131: =ROUNDUP(J131,0) -> 0 | L131: =IF(F77>0,K131,0) -> 0 | M131: =N131/D131 -> 61 | N131: 61 | O131: =M131*L131 -> 0 | P131: =L131/D131 -> 0 | Q131: =ROUNDUP(P131,0) -> 0
...

Sheet c311 TODO COMPRADO
B1: CLIENTE
B2: FECHA
B3: MODALIDAD
B4: PLAZO | D4: MESES
B5: PROYECCIÓN | D5: MESES
B6: EQUIPO | C6: C311
A8: CFAS | B8: I.D | C8: DESCRIPCION | D8: DET/KIT | E8: DIAS ESTABILIDAD | F8: DET/AÑO/PROCESO | G8: PRODUCTO CALCULADO | H8: MINIMOS POR ESTABILIDAD | I8: PRODUCTO A ENTREGAR | K8: REDONDEADO A ENTREGAR | L8: PVP | M8: TOTAL | N8: PVP TODO COMPRADO | O8: TOTAL PVP TODO COMPRADO | P8: $ DETERMINACION | Q8: $DETERMINACION CON CONSUMIBLES Y EXTRAS | R8: TOTAL CON CONSUMIBLES Y EXTRAS | S8: $ PARA PROCESO | T8: TOTAL PARA PROCESO | U8: VALOR INICIAL DEL PROCESO | V8: VALOR FINAL DEL PROCESO
A9: =F11+F12+F14+F15+F16+F20+F22+F23+F26+F28+F29+F30+F34+F41+F42+F45+F52+F54+F56+F58+F60+F62+F67+F69+F71+F73 -> 0 | B9: 6750052190 | C9: A-1MG TQ GEN.2, 100TEST, COBAS C/INT | D9: 200 | E9: 84 | F9: ='c311'!E9 -> 0 | G9: =F9/D9 -> 0 | H9: =30*BC!$B$47/E9 -> 0 | I9: =IF(H9>G9,H9,G9) -> 0 | J9: =IF(G9=0,0,I9) -> 0 | K9: =ROUNDUP(J9,0) -> 0 | L9: 762 | M9: =L9*K9 -> 0 | N9: =((L9*$L$139)+L9) -> #DIV/0! | O9: =N9*K9 -> #DIV/0! | P9: =L9/D9 -> 3.81 | Q9: =P9+$M$137+((BC!$F$125)/$F$74) -> #DIV/0! | R9: =Q9*F9 -> #DIV/0! | S9: =((Q9*0.15)+Q9) -> #DIV/0! | T9: =S9*F9 -> #DIV/0! | U9: =SUM(T9:T73) -> #DIV/0! | V9: =SUM(R9:R73) -> #DIV/0!
B10: 3005771322 | C10: AAT GEN.2, 100TESTS, COBAS C, INTEGRA | D10: 100 | E10: 84 | F10: ='c311'!E10 -> 0 | G10: =F10/D10 -> 0 | H10: =30*BC!$B$47/E10 -> 0 | I10: =IF(H10>G10,H10,G10) -> 0 | J10: =IF(G10=0,0,I10) -> 0 | K10: =ROUNDUP(J10,0) -> 0 | L10: 436 | M10: =L10*K10 -> 0 | N10: =((L10*$L$139)+L10) -> #DIV/0! | O10: =N10*K10 -> #DIV/0! | P10: =L10/D10 -> 4.36 | Q10: =P10+$M$137+((BC!$F$125)/$F$74) -> #DIV/0! | R10: =Q10*F10 -> #DIV/0! | S10: =((Q10*0.15)+Q10) -> #DIV/0! | T10: =S10*F10 -> #DIV/0!
A11: CCLINCHEM | B11: 4375351190 | C11: ACP HIT 917 LARGE | D11: 400 | E11: 84 | F11: ='c311'!E11 -> 0 | G11: =F11/D11 -> 0 | H11: =30*BC!$B$47/E11 -> 0 | I11: =IF(H11>G11,H11,G11) -> 0 | J11: =IF(G11=0,0,I11) -> 0 | K11: =ROUNDUP(J11,0) -> 0 | L11: 456 | M11: =L11*K11 -> 0 | N11: =((L11*$L$139)+L11) -> #DIV/0! | O11: =N11*K11 -> #DIV/0! | P11: =L11/D11 -> 1.14 | Q11: =P11+$M$137+((BC!$F$125)/$F$74) -> #DIV/0! | R11: =Q11*F11 -> #DIV/0! | S11: =((Q11*0.15)+Q11) -> #DIV/0! | T11: =S11*F11 -> #DIV/0!
A12: =F10+F11+F12+F14+F15+F16+F17+F18+F19+F20+F22+F23+F26+F28+F29+F30+F31+F34+F35+F36+F41+F42+F43+F45+F47+F48+F49+F50+F51+F52+F53+F54+F55+F57+F58+F60+F62+F63+F67+F69+F70+F71++F72+F73 -> 0 | B12: 3183688122 | C12: ALB2, 300T, COBAS C, INTEGRA | D12: 300 | E12: 84 | F12: ='c311'!E12 -> 0 | G12: =F12/D12 -> 0 | H12: =30*BC!$B$47/E12 -> 0 | I12: =IF(H12>G12,H12,G12) -> 0 | J12: =IF(G12=0,0,I12) -> 0 | K12: =ROUNDUP(J12,0) -> 0 | L12: 72 | M12: =L12*K12 -> 0 | N12: =((L12*$L$139)+L12) -> #DIV/0! | O12: =N12*K12 -> #DIV/0! | P12: =L12/D12 -> 0.24 | Q12: =P12+$M$137+((BC!$F$125)/$F$74) -> #DIV/0! | R12: =Q12*F12 -> #DIV/0! | S12: =((Q12*0.15)+Q12) -> #DIV/0! | T12: =S12*F12 -> #DIV/0!
B13: 4469658190 | C13: ALB-T TQ GEN.2, 100TESTS, COBAS C, INT | D13: 100 | E13: 84 | F13: ='c311'!E13 -> 0 | G13: =F13/D13 -> 0 | H13: =30*BC!$B$47/E13 -> 0 | I13: =IF(H13>G13,H13,G13) -> 0 | J13: =IF(G13=0,0,I13) -> 0 | K13: =ROUNDUP(J13,0) -> 0 | L13: 287 | M13: =L13*K13 -> 0 | N13: =((L13*$L$139)+L13) -> #DIV/0! | O13: =N13*K13 -> #DIV/0! | P13: =L13/D13 -> 2.87 | Q13: =P13+$M$137+((BC!$F$125)/$F$74) -> #DIV/0! | R13: =Q13*F13 -> #DIV/0! | S13: =((Q13*0.15)+Q13) -> #DIV/0! | T13: =S13*F13 -> #DIV/0!
A14: PUC | B14: 3333752190 | C14: ALP2, 200T, COBAS C, INTEGRA | D14: 200 | E14: 56 | F14: ='c311'!E14 -> 0 | G14: =F14/D14 -> 0 | H14: =30*BC!$B$47/E14 -> 0 | I14: =IF(H14>G14,H14,G14) -> 0 | J14: =IF(G14=0,0,I14) -> 0 | K14: =ROUNDUP(J14,0) -> 0 | L14: 62 | M14: =L14*K14 -> 0 | N14: =((L14*$L$139)+L14) -> #DIV/0! | O14: =N14*K14 -> #DIV/0! | P14: =L14/D14 -> 0.31 | Q14: =P14+$M$137+((BC!$F$125)/$F$74) -> #DIV/0! | R14: =Q14*F14 -> #DIV/0! | S14: =((Q14*0.15)+Q14) -> #DIV/0! | T14: =S14*F14 -> #DIV/0!
A15: =F9+F68 -> 0 | B15: 20764957322 | C15: ALTL, 500TESTS, COBAS C, INTEGRA | D15: 500 | E15: 84 | F15: ='c311'!E15 -> 0 | G15: =F15/D15 -> 0 | H15: =30*BC!$B$47/E15 -> 0 | I15: =IF(H15>G15,H15,G15) -> 0 | J15: =IF(G15=0,0,I15) -> 0 | K15: =ROUNDUP(J15,0) -> 0 | L15: 145 | M15: =L15*K15 -> 0 | N15: =((L15*$L$139)+L15) -> #DIV/0! | O15: =N15*K15 -> #DIV/0! | P15: =L15/D15 -> 0.29 | Q15: =P15+$M$137+((BC!$F$125)/$F$74) -> #DIV/0! | R15: =Q15*F15 -> #DIV/0! | S15: =((Q15*0.15)+Q15) -> #DIV/0! | T15: =S15*F15 -> #DIV/0!
B16: 3183742122 | C16: AMYL GEN.2, 300TESTS, COBAS C, INTEGRA | D16: 300 | E16: 84 | F16: ='c311'!E16 -> 0 | G16: =F16/D16 -> 0 | H16: =30*BC!$B$47/E16 -> 0 | I16: =IF(H16>G16,H16,G16) -> 0 | J16: =IF(G16=0,0,I16) -> 0 | K16: =ROUNDUP(J16,0) -> 0 | L16: 198 | M16: =L16*K16 -> 0 | N16: =((L16*$L$139)+L16) -> #DIV/0! | O16: =N16*K16 -> #DIV/0! | P16: =L16/D16 -> 0.66 | Q16: =P16+$M$137+((BC!$F$125)/$F$74) -> #DIV/0! | R16: =Q16*F16 -> #DIV/0! | S16: =((Q16*0.15)+Q16) -> #DIV/0! | T16: =S16*F16 -> #DIV/0!
A17: AMMONIA | B17: 3032566122 | C17: APOAT, 100TESTS, COBAS C, INTEGRA | D17: 100 | E17: 84 | F17: ='c311'!E17 -> 0 | G17: =F17/D17 -> 0 | H17: =30*BC!$B$47/E17 -> 0 | I17: =IF(H17>G17,H17,G17) -> 0 | J17: =IF(G17=0,0,I17) -> 0 | K17: =ROUNDUP(J17,0) -> 0 | L17: 225 | M17: =L17*K17 -> 0 | N17: =((L17*$L$139)+L17) -> #DIV/0! | O17: =N17*K17 -> #DIV/0! | P17: =L17/D17 -> 2.25 | Q17: =P17+$M$137+((BC!$F$125)/$F$74) -> #DIV/0! | R17: =Q17*F17 -> #DIV/0! | S17: =((Q17*0.15)+Q17) -> #DIV/0! | T17: =S17*F17 -> #DIV/0!
A18: =F32+F39+F61 -> 0 | B18: 3032574122 | C18: APOBT, 100TESTS, COBAS C, INTEGRA | D18: 100 | E18: 84 | F18: ='c311'!E18 -> 0 | G18: =F18/D18 -> 0 | H18: =30*BC!$B$47/E18 -> 0 | I18: =IF(H18>G18,H18,G18) -> 0 | J18: =IF(G18=0,0,I18) -> 0 | K18: =ROUNDUP(J18,0) -> 0 | L18: 225 | M18: =L18*K18 -> 0 | N18: =((L18*$L$139)+L18) -> #DIV/0! | O18: =N18*K18 -> #DIV/0! | P18: =L18/D18 -> 2.25 | Q18: =P18+$M$137+((BC!$F$125)/$F$74) -> #DIV/0! | R18: =Q18*F18 -> #DIV/0! | S18: =((Q18*0.15)+Q18) -> #DIV/0! | T18: =S18*F18 -> #DIV/0!
B19: 4489403190 | C19: ASLO TQ, 150TESTS, COBAS C | D19: 150 | E19: 84 | F19: ='c311'!E19 -> 0 | G19: =F19/D19 -> 0 | H19: =30*BC!$B$47/E19 -> 0 | I19: =IF(H19>G19,H19,G19) -> 0 | J19: =IF(G19=0,0,I19) -> 0 | K19: =ROUNDUP(J19,0) -> 0 | L19: 494 | M19: =L19*K19 -> 0 | N19: =((L19*$L$139)+L19) -> #DIV/0! | O19: =N19*K19 -> #DIV/0! | P19: =L19/D19 -> 3.2933333 | Q19: =P19+$M$137+((BC!$F$125)/$F$74) -> #DIV/0! | R19: =Q19*F19 -> #DIV/0! | S19: =((Q19*0.15)+Q19) -> #DIV/0! | T19: =S19*F19 -> #DIV/0!
A20: CFAS PROTEIN | B20: 20764949322 | C20: ASTL, 500TESTS, COBAS C, INTEGRA | D20: 500 | E20: 84 | F20: ='c311'!E20 -> 0 | G20: =F20/D20 -> 0 | H20: =30*BC!$B$47/E20 -> 0 | I20: =IF(H20>G20,H20,G20) -> 0 | J20: =IF(G20=0,0,I20) -> 0 | K20: =ROUNDUP(J20,0) -> 0 | L20: 145 | M20: =L20*K20 -> 0 | N20: =((L20*$L$139)+L20) -> #DIV/0! | O20: =N20*K20 -> #DIV/0! | P20: =L20/D20 -> 0.29 | Q20: =P20+$M$137+((BC!$F$125)/$F$74) -> #DIV/0! | R20: =Q20*F20 -> #DIV/0! | S20: =((Q20*0.15)+Q20) -> #DIV/0! | T20: =S20*F20 -> #DIV/0!
A21: =F10+F24+F25+F35+F36+F43+F48+F50+F51+F53+F55+F70 -> 0 | B21: 8047430190 | C21: B2MG, 140T, COBAS C 311, COBAS C 501/502 | D21: 140 | E21: 84 | F21: ='c311'!E21 -> 0 | G21: =F21/D21 -> 0 | H21: =30*BC!$B$47/E21 -> 0 | I21: =IF(H21>G21,H21,G21) -> 0 | J21: =IF(G21=0,0,I21) -> 0 | K21: =ROUNDUP(J21,0) -> 0 | L21: 1169 | M21: =L21*K21 -> 0 | N21: =((L21*$L$139)+L21) -> #DIV/0! | O21: =N21*K21 -> #DIV/0! | P21: =L21/D21 -> 8.35 | Q21: =P21+$M$137+((BC!$F$125)/$F$74) -> #DIV/0! | R21: =Q21*F21 -> #DIV/0! | S21: =((Q21*0.15)+Q21) -> #DIV/0! | T21: =S21*F21 -> #DIV/0!
B22: 5589061190 | C22: BIL-D GEN.2, 350TESTS COBAS C, INTEGRA | D22: 350 | E22: 42 | F22: ='c311'!E22 -> 0 | G22: =F22/D22 -> 0 | H22: =30*BC!$B$47/E22 -> 0 | I22: =IF(H22>G22,H22,G22) -> 0 | J22: =IF(G22=0,0,I22) -> 0 | K22: =ROUNDUP(J22,0) -> 0 | L22: 144 | M22: =L22*K22 -> 0 | N22: =((L22*$L$139)+L22) -> #DIV/0! | O22: =N22*K22 -> #DIV/0! | P22: =L22/D22 -> 0.41142857 | Q22: =P22+$M$137+((BC!$F$125)/$F$74) -> #DIV/0! | R22: =Q22*F22 -> #DIV/0! | S22: =((Q22*0.15)+Q22) -> #DIV/0! | T22: =S22*F22 -> #DIV/0!
A23: C.f.a.s. PAC | B23: 5795397190 | C23: BIL-T GEN.3, 250TESTS COBAS C,INTEGRA | D23: 250 | E23: 42 | F23: ='c311'!E23 -> 0 | G23: =F23/D23 -> 0 | H23: =30*BC!$B$47/E23 -> 0 | I23: =IF(H23>G23,H23,G23) -> 0 | J23: =IF(G23=0,0,I23) -> 0 | K23: =ROUNDUP(J23,0) -> 0 | L23: 85 | M23: =L23*K23 -> 0 | N23: =((L23*$L$139)+L23) -> #DIV/0! | O23: =N23*K23 -> #DIV/0! | P23: =L23/D23 -> 0.34 | Q23: =P23+$M$137+((BC!$F$125)/$F$74) -> #DIV/0! | R23: =Q23*F23 -> #DIV/0! | S23: =((Q23*0.15)+Q23) -> #DIV/0! | T23: =S23*F23 -> #DIV/0!
A24: =F19+F27+F63 -> 0 | B24: 3001938322 | C24: C3C, 100TESTS, COBAS C, INTEGRA | D24: 100 | E24: 42 | F24: ='c311'!E24 -> 0 | G24: =F24/D24 -> 0 | H24: =30*BC!$B$47/E24 -> 0 | I24: =IF(H24>G24,H24,G24) -> 0 | J24: =IF(G24=0,0,I24) -> 0 | K24: =ROUNDUP(J24,0) -> 0 | L24: 307 | M24: =L24*K24 -> 0 | N24: =((L24*$L$139)+L24) -> #DIV/0! | O24: =N24*K24 -> #DIV/0! | P24: =L24/D24 -> 3.07 | Q24: =P24+$M$137+((BC!$F$125)/$F$74) -> #DIV/0! | R24: =Q24*F24 -> #DIV/0! | S24: =((Q24*0.15)+Q24) -> #DIV/0! | T24: =S24*F24 -> #DIV/0!
B25: 3001962322 | C25: C4, 100TESTS, COBAS C, INTEGRA | D25: 100 | E25: 56 | F25: ='c311'!E25 -> 0 | G25: =F25/D25 -> 0 | H25: =30*BC!$B$47/E25 -> 0 | I25: =IF(H25>G25,H25,G25) -> 0 | J25: =IF(G25=0,0,I25) -> 0 | K25: =ROUNDUP(J25,0) -> 0 | L25: 309 | M25: =L25*K25 -> 0 | N25: =((L25*$L$139)+L25) -> #DIV/0! | O25: =N25*K25 -> #DIV/0! | P25: =L25/D25 -> 3.09 | Q25: =P25+$M$137+((BC!$F$125)/$F$74) -> #DIV/0! | R25: =Q25*F25 -> #DIV/0! | S25: =((Q25*0.15)+Q25) -> #DIV/0! | T25: =S25*F25 -> #DIV/0!
A26: Calibrator f.a.s. Lipids | B26: 5061482190 | C26: CA, GEN.2, 300TESTS, COBAS C,INTEGRA | D26: 300 | E26: 56 | F26: ='c311'!E26 -> 0 | G26: =F26/D26 -> 0 | H26: =30*BC!$B$47/E26 -> 0 | I26: =IF(H26>G26,H26,G26) -> 0 | J26: =IF(G26=0,0,I26) -> 0 | K26: =ROUNDUP(J26,0) -> 0 | L26: 108 | M26: =L26*K26 -> 0 | N26: =((L26*$L$139)+L26) -> #DIV/0! | O26: =N26*K26 -> #DIV/0! | P26: =L26/D26 -> 0.36 | Q26: =P26+$M$137+((BC!$F$125)/$F$74) -> #DIV/0! | R26: =Q26*F26 -> #DIV/0! | S26: =((Q26*0.15)+Q26) -> #DIV/0! | T26: =S26*F26 -> #DIV/0!
A27: =F17+F18+F47+F57 -> 0 | B27: 20764663322 | C27: CERU, 100TESTS, COBAS C, INTEGRA | D27: 100 | E27: 56 | F27: ='c311'!E27 -> 0 | G27: =F27/D27 -> 0 | H27: =30*BC!$B$47/E27 -> 0 | I27: =IF(H27>G27,H27,G27) -> 0 | J27: =IF(G27=0,0,I27) -> 0 | K27: =ROUNDUP(J27,0) -> 0 | L27: 259 | M27: =L27*K27 -> 0 | N27: =((L27*$L$139)+L27) -> #DIV/0! | O27: =N27*K27 -> #DIV/0! | P27: =L27/D27 -> 2.59 | Q27: =P27+$M$137+((BC!$F$125)/$F$74) -> #DIV/0! | R27: =Q27*F27 -> #DIV/0! | S27: =((Q27*0.15)+Q27) -> #DIV/0! | T27: =S27*F27 -> #DIV/0!
B28: 4498577190 | C28: CHE GEN.2, 200TESTS, COBAS C, INTEGRA | D28: 200 | E28: 28 | F28: ='c311'!E28 -> 0 | G28: =F28/D28 -> 0 | H28: =30*BC!$B$47/E28 -> 0 | I28: =IF(H28>G28,H28,G28) -> 0 | J28: =IF(G28=0,0,I28) -> 0 | K28: =ROUNDUP(J28,0) -> 0 | L28: 166 | M28: =L28*K28 -> 0 | N28: =((L28*$L$139)+L28) -> #DIV/0! | O28: =N28*K28 -> #DIV/0! | P28: =L28/D28 -> 0.83 | Q28: =P28+$M$137+((BC!$F$125)/$F$74) -> #DIV/0! | R28: =Q28*F28 -> #DIV/0! | S28: =((Q28*0.15)+Q28) -> #DIV/0! | T28: =S28*F28 -> #DIV/0!
A29: PRECISET DAT PLUS I | B29: 3039773190 | C29: CHOL HICO GEN.2, 400TESTS, COBAS C, INT. | D29: 400 | E29: 28 | F29: ='c311'!E29 -> 0 | G29: =F29/D29 -> 0 | H29: =30*BC!$B$47/E29 -> 0 | I29: =IF(H29>G29,H29,G29) -> 0 | J29: =IF(G29=0,0,I29) -> 0 | K29: =ROUNDUP(J29,0) -> 0 | L29: 88 | M29: =L29*K29 -> 0 | N29: =((L29*$L$139)+L29) -> #DIV/0! | O29: =N29*K29 -> #DIV/0! | P29: =L29/D29 -> 0.22 | Q29: =P29+$M$137+((BC!$F$125)/$F$74) -> #DIV/0! | R29: =Q29*F29 -> #DIV/0! | S29: =((Q29*0.15)+Q29) -> #DIV/0! | T29: =S29*F29 -> #DIV/0!
A30: =F33+F66 -> 0 | B30: 7190794190 | C30: CK 200 TESTS, COBAS C/INTEGRA | D30: 200 | E30: 56 | F30: ='c311'!E30 -> 0 | G30: =F30/D30 -> 0 | H30: =30*BC!$B$47/E30 -> 0 | I30: =IF(H30>G30,H30,G30) -> 0 | J30: =IF(G30=0,0,I30) -> 0 | K30: =ROUNDUP(J30,0) -> 0 | L30: 112 | M30: =L30*K30 -> 0 | N30: =((L30*$L$139)+L30) -> #DIV/0! | O30: =N30*K30 -> #DIV/0! | P30: =L30/D30 -> 0.56 | Q30: =P30+$M$137+((BC!$F$125)/$F$74) -> #DIV/0! | R30: =Q30*F30 -> #DIV/0! | S30: =((Q30*0.15)+Q30) -> #DIV/0! | T30: =S30*F30 -> #DIV/0!
B31: 7190808190 | C31: CK-MB 100TESTS, COBAS C/INTEGRA | D31: 100 | E31: 56 | F31: ='c311'!E31 -> 0 | G31: =F31/D31 -> 0 | H31: =30*BC!$B$47/E31 -> 0 | I31: =IF(H31>G31,H31,G31) -> 0 | J31: =IF(G31=0,0,I31) -> 0 | K31: =ROUNDUP(J31,0) -> 0 | L31: 276 | M31: =L31*K31 -> 0 | N31: =((L31*$L$139)+L31) -> #DIV/0! | O31: =N31*K31 -> #DIV/0! | P31: =L31/D31 -> 2.76 | Q31: =P31+$M$137+((BC!$F$125)/$F$74) -> #DIV/0! | R31: =Q31*F31 -> #DIV/0! | S31: =((Q31*0.15)+Q31) -> #DIV/0! | T31: =S31*F31 -> #DIV/0!
B32: 3289923190 | C32: COBAS INTEGRA CO2-L GEN.2 250 TEST | D32: 250 | E32: 42 | F32: ='c311'!E32 -> 0 | G32: =F32/D32 -> 0 | H32: =30*BC!$B$47/E32 -> 0 | I32: =IF(H32>G32,H32,G32) -> 0 | J32: =IF(G32=0,0,I32) -> 0 | K32: =ROUNDUP(J32,0) -> 0 | L32: 174 | M32: =L32*K32 -> 0 | N32: =((L32*$L$139)+L32) -> #DIV/0! | O32: =N32*K32 -> #DIV/0! | P32: =L32/D32 -> 0.696 | Q32: =P32+$M$137+((BC!$F$125)/$F$74) -> #DIV/0! | R32: =Q32*F32 -> #DIV/0! | S32: =((Q32*0.15)+Q32) -> #DIV/0! | T32: =S32*F32 -> #DIV/0!
B33: 4490827190 | C33: COC2, 200T, COBAS C | D33: 200 | E33: 56 | F33: ='c311'!E33 -> 0 | G33: =F33/D33 -> 0 | H33: =30*BC!$B$47/E33 -> 0 | I33: =IF(H33>G33,H33,G33) -> 0 | J33: =IF(G33=0,0,I33) -> 0 | K33: =ROUNDUP(J33,0) -> 0 | L33: 120 | M33: =L33*K33 -> 0 | N33: =((L33*$L$139)+L33) -> #DIV/0! | O33: =N33*K33 -> #DIV/0! | P33: =L33/D33 -> 0.6 | Q33: =P33+$M$137+((BC!$F$125)/$F$74) -> #DIV/0! | R33: =Q33*F33 -> #DIV/0! | S33: =((Q33*0.15)+Q33) -> #DIV/0! | T33: =S33*F33 -> #DIV/0!
B34: 4810716190 | C34: CREAJ2, 700T, COBAS C, INTEGRA | D34: 700 | E34: 56 | F34: ='c311'!E34 -> 0 | G34: =F34/D34 -> 0 | H34: =30*BC!$B$47/E34 -> 0 | I34: =IF(H34>G34,H34,G34) -> 0 | J34: =IF(G34=0,0,I34) -> 0 | K34: =ROUNDUP(J34,0) -> 0 | L34: 136 | M34: =L34*K34 -> 0 | N34: =((L34*$L$139)+L34) -> #DIV/0! | O34: =N34*K34 -> #DIV/0! | P34: =L34/D34 -> 0.19428571 | Q34: =P34+$M$137+((BC!$F$125)/$F$74) -> #DIV/0! | R34: =Q34*F34 -> #DIV/0! | S34: =((Q34*0.15)+Q34) -> #DIV/0! | T34: =S34*F34 -> #DIV/0!
B35: 4628918190 | C35: CRP LX HS, 300TESTS, COBAS C, INTEGRA | D35: 100 | E35: 84 | F35: ='c311'!E35 -> 0 | G35: =F35/D35 -> 0 | H35: =30*BC!$B$47/E35 -> 0 | I35: =IF(H35>G35,H35,G35) -> 0 | J35: =IF(G35=0,0,I35) -> 0 | K35: =ROUNDUP(J35,0) -> 0 | L35: 750 | M35: =L35*K35 -> 0 | N35: =((L35*$L$139)+L35) -> #DIV/0! | O35: =N35*K35 -> #DIV/0! | P35: =L35/D35 -> 7.5 | Q35: =P35+$M$137+((BC!$F$125)/$F$74) -> #DIV/0! | R35: =Q35*F35 -> #DIV/0! | S35: =((Q35*0.15)+Q35) -> #DIV/0! | T35: =S35*F35 -> #DIV/0!
B36: 7876033190 | C36: CRP4, 250T, COBAS C 311/501/502,INTEGRA | D36: 250 | E36: 84 | F36: ='c311'!E36 -> 0 | G36: =F36/D36 -> 0 | H36: =30*BC!$B$47/E36 -> 0 | I36: =IF(H36>G36,H36,G36) -> 0 | J36: =IF(G36=0,0,I36) -> 0 | K36: =ROUNDUP(J36,0) -> 0 | L36: 643 | M36: =L36*K36 -> 0 | N36: =((L36*$L$139)+L36) -> #DIV/0! | O36: =N36*K36 -> #DIV/0! | P36: =L36/D36 -> 2.572 | Q36: =P36+$M$137+((BC!$F$125)/$F$74) -> #DIV/0! | R36: =Q36*F36 -> #DIV/0! | S36: =((Q36*0.15)+Q36) -> #DIV/0! | T36: =S36*F36 -> #DIV/0!
B37: 6600239190 | C37: CYSC2, 225T, COBAS INTEGRA | D37: 225 | E37: 56 | F37: ='c311'!E37 -> 0 | G37: =F37/D37 -> 0 | H37: =30*BC!$B$47/E37 -> 0 | I37: =IF(H37>G37,H37,G37) -> 0 | J37: =IF(G37=0,0,I37) -> 0 | K37: =ROUNDUP(J37,0) -> 0 | L37: 1282 | M37: =L37*K37 -> 0 | N37: =((L37*$L$139)+L37) -> #DIV/0! | O37: =N37*K37 -> #DIV/0! | P37: =L37/D37 -> 5.6977778 | Q37: =P37+$M$137+((BC!$F$125)/$F$74) -> #DIV/0! | R37: =Q37*F37 -> #DIV/0! | S37: =((Q37*0.15)+Q37) -> #DIV/0! | T37: =S37*F37 -> #DIV/0!
B38: 4912551190 | C38: D-DIMER GEN.2, 100TEST, COBAS C, INTEGRA | D38: 100 | E38: 84 | F38: ='c311'!E38 -> 0 | G38: =F38/D38 -> 0 | H38: =30*BC!$B$47/E38 -> 0 | I38: =IF(H38>G38,H38,G38) -> 0 | J38: =IF(G38=0,0,I38) -> 0 | K38: =ROUNDUP(J38,0) -> 0 | L38: 1066 | M38: =L38*K38 -> 0 | N38: =((L38*$L$139)+L38) -> #DIV/0! | O38: =N38*K38 -> #DIV/0! | P38: =L38/D38 -> 10.66 | Q38: =P38+$M$137+((BC!$F$125)/$F$74) -> #DIV/0! | R38: =Q38*F38 -> #DIV/0! | S38: =((Q38*0.15)+Q38) -> #DIV/0! | T38: =S38*F38 -> #DIV/0!
B39: 3183777190 | C39: ETOH2 , 100T, COBAS INTEGRA | D39: 100 | E39: 84 | F39: ='c311'!E39 -> 0 | G39: =F39/D39 -> 0 | H39: =30*BC!$B$47/E39 -> 0 | I39: =IF(H39>G39,H39,G39) -> 0 | J39: =IF(G39=0,0,I39) -> 0 | K39: =ROUNDUP(J39,0) -> 0 | L39: 341 | M39: =L39*K39 -> 0 | N39: =((L39*$L$139)+L39) -> #DIV/0! | O39: =N39*K39 -> #DIV/0! | P39: =L39/D39 -> 3.41 | Q39: =P39+$M$137+((BC!$F$125)/$F$74) -> #DIV/0! | R39: =Q39*F39 -> #DIV/0! | S39: =((Q39*0.15)+Q39) -> #DIV/0! | T39: =S39*F39 -> #DIV/0!
B40: 4537939190 | C40: FRUC, 150TESTS, COBAS C, INTEGRA | D40: 150 | E40: 56 | F40: ='c311'!E40 -> 0 | G40: =F40/D40 -> 0 | H40: =30*BC!$B$47/E40 -> 0 | I40: =IF(H40>G40,H40,G40) -> 0 | J40: =IF(G40=0,0,I40) -> 0 | K40: =ROUNDUP(J40,0) -> 0 | L40: 126 | M40: =L40*K40 -> 0 | N40: =((L40*$L$139)+L40) -> #DIV/0! | O40: =N40*K40 -> #DIV/0! | P40: =L40/D40 -> 0.84 | Q40: =P40+$M$137+((BC!$F$125)/$F$74) -> #DIV/0! | R40: =Q40*F40 -> #DIV/0! | S40: =((Q40*0.15)+Q40) -> #DIV/0! | T40: =S40*F40 -> #DIV/0!
B41: 3002721122 | C41: GGT-2, 400T, COBAS C, INTEGRA | D41: 400 | E41: 84 | F41: ='c311'!E41 -> 0 | G41: =F41/D41 -> 0 | H41: =30*BC!$B$47/E41 -> 0 | I41: =IF(H41>G41,H41,G41) -> 0 | J41: =IF(G41=0,0,I41) -> 0 | K41: =ROUNDUP(J41,0) -> 0 | L41: 192 | M41: =L41*K41 -> 0 | N41: =((L41*$L$139)+L41) -> #DIV/0! | O41: =N41*K41 -> #DIV/0! | P41: =L41/D41 -> 0.48 | Q41: =P41+$M$137+((BC!$F$125)/$F$74) -> #DIV/0! | R41: =Q41*F41 -> #DIV/0! | S41: =((Q41*0.15)+Q41) -> #DIV/0! | T41: =S41*F41 -> #DIV/0!
B42: 4404483190 | C42: GLUC HK GEN.3, 800TESTS, COBAS C, INT. | D42: 800 | E42: 56 | F42: ='c311'!E42 -> 0 | G42: =F42/D42 -> 0 | H42: =30*BC!$B$47/E42 -> 0 | I42: =IF(H42>G42,H42,G42) -> 0 | J42: =IF(G42=0,0,I42) -> 0 | K42: =ROUNDUP(J42,0) -> 0 | L42: 176 | M42: =L42*K42 -> 0 | N42: =((L42*$L$139)+L42) -> #DIV/0! | O42: =N42*K42 -> #DIV/0! | P42: =L42/D42 -> 0.22 | Q42: =P42+$M$137+((BC!$F$125)/$F$74) -> #DIV/0! | R42: =Q42*F42 -> #DIV/0! | S42: =((Q42*0.15)+Q42) -> #DIV/0! | T42: =S42*F42 -> #DIV/0!
... B73: 4460715190 | C73: UREAL, 500T, COBAS C, INTEGRA | D73: 500 | E73: 56 | F73: ='c311'!E73 -> 0 | G73: =F73/D73 -> 0 | H73: =30*BC!$B$47/E73 -> 0 | I73: =IF(H73>G73,H73,G73) -> 0 | J73: =IF(G73=0,0,I73) -> 0 | K73: =ROUNDUP(J73,0) -> 0 | L73: 120 | M73: =L73*K73 -> 0 | N73: =((L73*$L$139)+L73) -> #DIV/0! | O73: =N73*K73 -> #DIV/0! | P73: =L73/D73 -> 0.24 | Q73: =P73+$M$137+((BC!$F$125)/$F$74) -> #DIV/0! | R73: =Q73*F73 -> #DIV/0! | S73: =((Q73*0.15)+Q73) -> #DIV/0! | T73: =S73*F73 -> #DIV/0!
E74: TOTAL DET | F74: =SUM(F9:F73) -> 0 | M74: =SUM(M9:M73) -> 0 | O74: =SUM(O9:O73) -> #DIV/0!
C75: CALIBRADORES | K75: MAXIMOS | L75: PVP POR UNIDADES | M75: VALOR TOTAL | P75: EN KITS | Q75: EN KITS CERRADO
B76: 20751995190 | C76: Ammonia/Ethanol/CO2 Calibrator | D76: 2 | E76: 56 | G76: =(A19*(0.014*(500/2000))) -> 0 | H76: =30*BC!$B$47/E76 -> 0 | I76: =IF(G76>H76,G76,H76) -> 0 | J76: =ROUNDUP(I76,0) -> 0 | K76: 1 | L76: 313.5 | M76: =L76*K76 -> 313.5 | N76: =((L76*$L$139)+L76) -> #DIV/0! | P76: =K76/D76 -> 0.5 | Q76: =ROUNDUP(P76,0) -> 1
B77: 4975901190 | C77: C.f.a.s. Cystatin C | D77: 1 | H77: =30*BC!$B$47/E77 -> #DIV/0! | I77: =IF(G77>H77,G77,H77) -> #DIV/0! | J77: =ROUNDUP(I77,0) -> #DIV/0! | K77: =IF(F37>0,J77,0) -> 0 | M77: =L77*K77 -> 0 | N77: =((L77*$L$139)+L77) -> #DIV/0! | P77: =K77/D77 -> 0 | Q77: =ROUNDUP(P77,0) -> 0
B78: 3555941190 | C78: C.f.a.s. PAC | D78: 3 | E78: 14 | G78: =(A25*(0.014*(500/2000))) -> 0 | H78: =30*BC!$B$47/E78 -> 0 | I78: =IF(G78>H78,G78,H78) -> 0 | J78: =ROUNDUP(I78,0) -> 0 | K78: 1 | L78: 70.67 | M78: =L78*K78 -> 70.67 | N78: =((L78*$L$139)+L78) -> #DIV/0! | P78: =K78/D78 -> 0.33333333 | Q78: =ROUNDUP(P78,0) -> 1
B79: 10759350190 | C79: Calibrator f.a.s. | D79: 12 | E79: 28 | G79: =(A13/(0.005*400)/3000) -> 0 | H79: =30*BC!$B$47/E79 -> 0 | I79: =IF(G79>H79,G79,H79) -> 0 | J79: =ROUNDUP(I79,0) -> 0 | K79: 1 | L79: 12 | M79: =L79*K79 -> 12 | N79: =((L79*$L$139)+L79) -> #DIV/0! | P79: =K79/D79 -> 0.083333333 | Q79: =ROUNDUP(P79,0) -> 1
B80: 11447394216 | C80: Calibrator f.a.s. CK-MB | D80: 3 | E80: 28 | G80: =(F31*(0.014*(500/2000))) -> 0 | H80: =30*BC!$B$47/E80 -> 0 | I80: =IF(G80>H80,G80,H80) -> 0 | J80: =ROUNDUP(I80,0) -> 0 | K80: 1 | L80: 25.34 | M80: =L80*K80 -> 25.34 | N80: =((L80*$L$139)+L80) -> #DIV/0! | P80: =K80/D80 -> 0.33333333 | Q80: =ROUNDUP(P80,0) -> 1
B81: 6533850190 | C81: Calibrator f.a.s. IgA/IgM CSF | D81: 3 | E81: 14 | G81: =(F49*(0.014*(500/2000))) -> 0 | H81: =30*BC!$B$47/E81 -> 0 | I81: =IF(G81>H81,G81,H81) -> 0 | J81: =ROUNDUP(I81,0) -> 0 | K81: 1 | L81: 323 | M81: =L81*K81 -> 323 | N81: =((L81*$L$139)+L81) -> #DIV/0! | P81: =K81/D81 -> 0.33333333 | Q81: =ROUNDUP(P81,0) -> 1
B82: 12172623122 | C82: Calibrator f.a.s. Lipids | D82: 3 | E82: 28 | G82: =(A28*(0.008*(350/1000))) -> 0 | H82: =30*BC!$B$47/E82 -> 0 | I82: =IF(G82>H82,G82,H82) -> 0 | J82: =ROUNDUP(I82,0) -> 0 | K82: 1 | L82: 31 | M82: =L82*K82 -> 31 | N82: =((L82*$L$139)+L82) -> #DIV/0! | P82: =K82/D82 -> 0.33333333 | Q82: =ROUNDUP(P82,0) -> 1
B83: 11355279216 | C83: Calibrator f.a.s.proteins | D83: 5 | E83: 28 | G83: =(A22*(0.008*(350/1000))) -> 0 | H83: =30*BC!$B$47/E83 -> 0 | I83: =IF(G83>H83,G83,H83) -> 0 | J83: =ROUNDUP(I83,0) -> 0 | K83: 1 | L83: 29.8 | M83: =L83*K83 -> 29.8 | N83: =((L83*$L$139)+L83) -> #DIV/0! | P83: =K83/D83 -> 0.2 | Q83: =ROUNDUP(P83,0) -> 1
B84: 8753776190 | C84: CALIBRATOR STFR GEN.2 | D84: 3 | E84: 28 | G84: =(F65*(0.014*(500/2000))) -> 0 | H84: =30*BC!$B$47/E84 -> 0 | I84: =IF(G84>H84,G84,H84) -> 0 | J84: =ROUNDUP(I84,0) -> 0 | K84: 1 | L84: 127 | M84: =L84*K84 -> 127 | N84: =((L84*$L$139)+L84) -> #DIV/0! | P84: =K84/D84 -> 0.33333333 | Q84: =ROUNDUP(P84,0) -> 1
B85: 8047545190 | C85: Calibrator β2‑Microglobulin | D85: 2 | E85: 84 | G85: =(F21*(0.014*(500/2000))) -> 0 | H85: =30*BC!$B$47/E85 -> 0 | I85: =IF(G85>H85,G85,H85) -> 0 | J85: =ROUNDUP(I85,0) -> 0 | K85: 1 | L85: 25.5 | M85: =L85*K85 -> 25.5 | N85: =((L85*$L$139)+L85) -> #DIV/0! | P85: =K85/D85 -> 0.5 | Q85: =ROUNDUP(P85,0) -> 1
B86: 4528417190 | C86: Cfas HbA1c | D86: 3 | E86: 84 | G86: =(F44*(0.014*(500/2000))) -> 0 | H86: =30*BC!$B$47/E86 -> 0 | I86: =IF(G86>H86,G86,H86) -> 0 | J86: =ROUNDUP(I86,0) -> 0 | K86: 1 | L86: 150.34 | M86: =L86*K86 -> 150.34 | N86: =((L86*$L$139)+L86) -> #DIV/0! | P86: =K86/D86 -> 0.33333333 | Q86: =ROUNDUP(P86,0) -> 1
B87: 3121305122 | C87: Cfas Proteins U | D87: 5 | E87: 28 | G87: =(A16*(0.008*(350/1000))) -> 0 | H87: =30*BC!$B$47/E87 -> 0 | I87: =IF(G87>H87,G87,H87) -> 0 | J87: =ROUNDUP(I87,0) -> 0 | K87: 1 | L87: 75.2 | M87: =L87*K87 -> 75.2 | N87: =((L87*$L$139)+L87) -> #DIV/0! | P87: =K87/D87 -> 0.2 | Q87: =ROUNDUP(P87,0) -> 1
B88: 5050901190 | C88: D-Dimer Gen.2 Calibrator Set | D88: 1 | E88: 84 | G88: =(F38*(0.04*(350/1000))) -> 0 | H88: =30*BC!$B$47/E88 -> 0 | I88: =IF(G88>H88,G88,H88) -> 0 | J88: =ROUNDUP(I88,0) -> 0 | K88: 1 | L88: 282 | M88: =L88*K88 -> 282 | N88: =((L88*$L$139)+L88) -> #DIV/0! | P88: =K88/D88 -> 1 | Q88: =ROUNDUP(P88,0) -> 1
B89: 12146401216 | C89: Fe Standard | D89: 1 | E89: 360 | G89: =(F72*(0.02*(200/1000))) -> 0 | H89: =30*BC!$B$47/E89 -> 0 | I89: =IF(G89>H89,G89,H89) -> 0 | J89: =ROUNDUP(I89,0) -> 0 | K89: 1 | L89: 183 | M89: =L89*K89 -> 183 | N89: =((L89*$L$139)+L89) -> #DIV/0! | P89: =K89/D89 -> 1 | Q89: =ROUNDUP(P89,0) -> 1
B90: 5385504190 | C90: HCYS Calibrator Kit | D90: 2 | E90: 28 | G90: =(F46*(0.02*(200/1000))) -> 0 | H90: =30*BC!$B$47/E90 -> 0 | I90: =IF(G90>H90,G90,H90) -> 0 | J90: =ROUNDUP(I90,0) -> 0 | K90: 1 | L90: 40 | M90: =L90*K90 -> 40 | N90: =((L90*$L$139)+L90) -> #DIV/0! | P90: =K90/D90 -> 0.5 | Q90: =ROUNDUP(P90,0) -> 1
B91: 11098993122 | C91: Precimat Fructosamina | D91: 3 | E91: 28 | G91: =(F40*(0.02*(200/1000))) -> 0 | H91: =30*BC!$B$47/E91 -> 0 | I91: =IF(G91>H91,G91,H91) -> 0 | J91: =ROUNDUP(I91,0) -> 0 | K91: 1 | L91: 26.67 | M91: =L91*K91 -> 26.67 | N91: =((L91*$L$139)+L91) -> #DIV/0! | P91: =K91/D91 -> 0.33333333 | Q91: =ROUNDUP(P91,0) -> 1
B92: 3304671190 | C92: PRECISET DAT PLUS I | D92: 1 | E92: 60 | G92: =(A31*(0.02*(200/1000))) -> 0 | H92: =30*BC!$B$47/E92 -> 0 | I92: =IF(G92>H92,G92,H92) -> 0 | J92: =ROUNDUP(I92,0) -> 0 | K92: 1 | L92: 231 | M92: =L92*K92 -> 231 | N92: =((L92*$L$139)+L92) -> #DIV/0! | P92: =K92/D92 -> 1 | Q92: =ROUNDUP(P92,0) -> 1
B93: 5852641190 | C93: Preciset Lp(a) Gen.2 | D93: 1 | E93: 14 | G93: =(F59*(0.02*(200/1000))) -> 0 | H93: =30*BC!$B$47/E93 -> 0 | I93: =IF(G93>H93,G93,H93) -> 0 | J93: =ROUNDUP(I93,0) -> 0 | K93: 1 | L93: 384 | M93: =L93*K93 -> 384 | N93: =((L93*$L$139)+L93) -> #DIV/0! | P93: =K93/D93 -> 1 | Q93: =ROUNDUP(P93,0) -> 1
B94: 12172828322 | C94: Preciset RF | D94: 1 | E94: 30 | G94: =(F64*(0.04*(350/1000))) -> 0 | H94: =30*BC!$B$47/E94 -> 0 | I94: =IF(G94>H94,G94,H94) -> 0 | J94: =ROUNDUP(I94,0) -> 0 | K94: 1 | L94: 197 | M94: =L94*K94 -> 197 | N94: =((L94*$L$139)+L94) -> #DIV/0! | P94: =K94/D94 -> 1 | Q94: =ROUNDUP(P94,0) -> 1
C95: CONTROLES | G95: PRODUCTO CALCULADO | H95: MINIMOS POR ESTABILIDAD
B96: 20752401190 | C96: Ammonia/Ethanol/CO2 Control Normal | D96: 5 | E96: 56 | G96: =(A19*(0.025*(500/2000))) -> 0 | H96: =30*BC!$B$47/E96 -> 0 | I96: =IF(G96>H96,G96,H96) -> 0 | J96: =ROUNDUP(I96,0) -> 0 | K96: 1 | L96: 41.4 | M96: =L96*K96 -> 41.4 | N96: =((L96*$L$139)+L96) -> #DIV/0! | P96: =K96/D96 -> 0.2 | Q96: =ROUNDUP(P96,0) -> 1
B97: 20753009190 | C97: Ammonia/Ethanol/CO2 Control Abnormal | D97: 5 | E97: 56 | G97: =(A19*(0.025*(500/2000))) -> 0 | H97: =30*BC!$B$47/E97 -> 0 | I97: =IF(G97>H97,G97,H97) -> 0 | J97: =ROUNDUP(I97,0) -> 0 | K97: 1 | L97: 45.4 | M97: =L97*K97 -> 45.4 | N97: =((L97*$L$139)+L97) -> #DIV/0! | P97: =K97/D97 -> 0.2 | Q97: =ROUNDUP(P97,0) -> 1
B98: 8362785190 | C98: Control Set β2‑Microglobulin (Nivel 1-2) | D98: 2 | E98: 84 | G98: =(F21*(0.025*(500/2000))) -> 0 | H98: =30*BC!$B$47/E98 -> 0 | I98: =IF(G98>H98,G98,H98) -> 0 | J98: =ROUNDUP(I98,0) -> 0 | K98: 1 | L98: 122 | M98: =L98*K98 -> 122 | N98: =((L98*$L$139)+L98) -> #DIV/0! | P98: =K98/D98 -> 0.5 | Q98: =ROUNDUP(P98,0) -> 1
B99: 8278202190 | C99: CONTROL-SET STFR | D99: 3 | E99: 28 | G99: =(F65*(0.025*(500/2000))) -> 0 | H99: =30*BC!$B$47/E99 -> 0 | I99: =IF(G99>H99,G99,H99) -> 0 | J99: =ROUNDUP(I99,0) -> 0 | K99: 1 | L99: 103 | M99: =L99*K99 -> 103 | N99: =((L99*$L$139)+L99) -> #DIV/0! | P99: =K99/D99 -> 0.33333333 | Q99: =ROUNDUP(P99,0) -> 1
B100: 6729371190 | C100: Cystatin C Control Set Gen.2 (1,2,3) | D100: 3 | E100: 30 | H100: =30*BC!$B$47/E100 -> 0 | I100: =IF(G100>H100,G100,H100) -> 0 | J100: =ROUNDUP(I100,0) -> 0 | K100: 1 | L100: 527 | M100: =L100*K100 -> 527 | N100: =((L100*$L$139)+L100) -> #DIV/0! | P100: =K100/D100 -> 0.33333333 | Q100: =ROUNDUP(P100,0) -> 1
B101: 5050936190 | C101: D-Dimer Gen.2 Control I/II | D101: 2 | E101: 84 | G101: =(F38*(0.08*(350/1000))) -> 0 | H101: =30*BC!$B$47/E101 -> 0 | I101: =IF(G101>H101,G101,H101) -> 0 | J101: =ROUNDUP(I101,0) -> 0 | K101: 1 | L101: 244 | M101: =L101*K101 -> 244 | N101: =((L101*$L$139)+L101) -> #DIV/0! | P101: =K101/D101 -> 0.5 | Q101: =ROUNDUP(P101,0) -> 1
B102: 5142423190 | C102: HCYS Control Kit Control 1 y 2 | D102: 2 | E102: 28 | G102: =(F46*(0.04*(200/1000))) -> 0 | H102: =30*BC!$B$47/E102 -> 0 | I102: =IF(G102>H102,G102,H102) -> 0 | J102: =ROUNDUP(I102,0) -> 0 | K102: 1 | L102: 37 | M102: =L102*K102 -> 37 | N102: =((L102*$L$139)+L102) -> #DIV/0! | P102: =K102/D102 -> 0.5 | Q102: =ROUNDUP(P102,0) -> 1
B103: 5947626190 | C103: PreciControl ClinChem Multi 1, 4x5 ml | D103: 4 | E103: 14 | G103: =(A13/(0.003*400)/3000) -> 0 | H103: =30*BC!$B$47/E103 -> 0 | I103: =IF(G103>H103,G103,H103) -> 0 | J103: =ROUNDUP(I103,0) -> 0 | K103: 1 | L103: 14.25 | M103: =L103*K103 -> 14.25 | N103: =((L103*$L$139)+L103) -> #DIV/0! | P103: =K103/D103 -> 0.25 | Q103: =ROUNDUP(P103,0) -> 1
B104: 5947774190 | C104: PreciControl ClinChem Multi 2, 4x5 ml | D104: 4 | E104: 14 | G104: =(A13/(0.003*400)/3000) -> 0 | H104: =30*BC!$B$47/E104 -> 0 | I104: =IF(G104>H104,G104,H104) -> 0 | J104: =ROUNDUP(I104,0) -> 0 | K104: 1 | L104: 22.75 | M104: =L104*K104 -> 22.75 | N104: =((L104*$L$139)+L104) -> #DIV/0! | P104: =K104/D104 -> 0.25 | Q104: =ROUNDUP(P104,0) -> 1
B105: 5479207190 | C105: PreciControl HbA1c norm | D105: 4 | E105: 28 | G105: =(F44*(0.025*(500/2000))) -> 0 | H105: =30*BC!$B$47/E105 -> 0 | I105: =IF(G105>H105,G105,H105) -> 0 | J105: =ROUNDUP(I105,0) -> 0 | K105: 1 | L105: 77.25 | M105: =L105*K105 -> 77.25 | N105: =((L105*$L$139)+L105) -> #DIV/0! | P105: =K105/D105 -> 0.25 | Q105: =ROUNDUP(P105,0) -> 1
B106: 5912504190 | C106: PreciControl HbA1c path | D106: 4 | E106: 28 | G106: =(F44*(0.025*(500/2000))) -> 0 | H106: =30*BC!$B$47/E106 -> 0 | I106: =IF(G106>H106,G106,H106) -> 0 | J106: =ROUNDUP(I106,0) -> 0 | K106: 1 | L106: 154.5 | M106: =L106*K106 -> 154.5 | N106: =((L106*$L$139)+L106) -> #DIV/0! | P106: =K106/D106 -> 0.25 | Q106: =ROUNDUP(P106,0) -> 1
B107: 5852650190 | C107: PreciControl Lp(a) Gen.2 | D107: 2 | E107: 14 | G107: =(F59*(0.04*(200/1000))) -> 0 | H107: =30*BC!$B$47/E107 -> 0 | I107: =IF(G107>H107,G107,H107) -> 0 | J107: =ROUNDUP(I107,0) -> 0 | K107: 1 | L107: 286 | M107: =L107*K107 -> 286 | N107: =((L107*$L$139)+L107) -> #DIV/0! | P107: =K107/D107 -> 0.5 | Q107: =ROUNDUP(P107,0) -> 1
B108: 11098985122 | C108: PRECINORM FRUC | D108: 3 | E108: 28 | G108: =(F40*(0.04*(200/1000))) -> 0 | H108: =30*BC!$B$47/E108 -> 0 | I108: =IF(G108>H108,G108,H108) -> 0 | J108: =ROUNDUP(I108,0) -> 0 | K108: 1 | L108: 21 | M108: =L108*K108 -> 21 | N108: =((L108*$L$139)+L108) -> #DIV/0! | P108: =K108/D108 -> 0.33333333 | Q108: =ROUNDUP(P108,0) -> 1
B109: 3121313122 | C109: PRECINORM PUC | D109: 4 | E109: 28 | G109: =(A16*(0.0025*(250/100))) -> 0 | H109: =30*BC!$B$47/E109 -> 0 | I109: =IF(G109>H109,G109,H109) -> 0 | J109: =ROUNDUP(I109,0) -> 0 | K109: 1 | L109: 115 | M109: =L109*K109 -> 115 | N109: =((L109*$L$139)+L109) -> #DIV/0! | P109: =K109/D109 -> 0.25 | Q109: =ROUNDUP(P109,0) -> 1
B110: 11174118122 | C110: PRECIPATH FRUC | D110: 3 | E110: 28 | G110: =(F40*(0.04*(200/1000))) -> 0 | H110: =30*BC!$B$47/E110 -> 0 | I110: =IF(G110>H110,G110,H110) -> 0 | J110: =ROUNDUP(I110,0) -> 0 | K110: 1 | L110: 23.67 | M110: =L110*K110 -> 23.67 | N110: =((L110*$L$139)+L110) -> #DIV/0! | P110: =K110/D110 -> 0.33333333 | Q110: =ROUNDUP(P110,0) -> 1
B111: 3121291122 | C111: PRECIPATH PUC | D111: 4 | E111: 28 | G111: =(A16*(0.0025*(250/100))) -> 0 | H111: =30*BC!$B$47/E111 -> 0 | I111: =IF(G111>H111,G111,H111) -> 0 | J111: =ROUNDUP(I111,0) -> 0 | K111: 1 | L111: 98 | M111: =L111*K111 -> 98 | N111: =((L111*$L$139)+L111) -> #DIV/0! | P111: =K111/D111 -> 0.25 | Q111: =ROUNDUP(P111,0) -> 1
B112: 3005496122 | C112: RF Control Set | D112: 4 | E112: 30 | G112: =(F64*(0.08*(350/1000))) -> 0 | H112: =30*BC!$B$47/E112 -> 0 | I112: =IF(G112>H112,G112,H112) -> 0 | J112: =ROUNDUP(I112,0) -> 0 | K112: 1 | L112: 52.75 | M112: =L112*K112 -> 52.75 | N112: =((L112*$L$139)+L112) -> #DIV/0! | P112: =K112/D112 -> 0.25 | Q112: =ROUNDUP(P112,0) -> 1
C113: CONSUMIBLES | G113: PRODUCTO CALCULADO | H113: MINIMOS POR ESTABILIDAD
B114: 4880285190 | C114: Cell Wash Solution I / NaOH-D | D114: 2 | E114: 70 | G114: =(F74/(0.00025*800)/12000) -> 0 | H114: =30*BC!$B$47/E114 -> 0 | I114: =IF(G114>H114,G114,H114) -> 0 | J114: =ROUNDUP(I114,0) -> 0 | K114: 1 | L114: 32.5 | M114: =L114*K114 -> 32.5 | N114: =((L114*$L$139)+L114) -> #DIV/0! | P114: =K114/D114 -> 0.5 | Q114: =ROUNDUP(P114,0) -> 1
B115: 4880307190 | C115: Cell Wash Solution II / Acid Wash | D115: 2 | E115: 84 | G115: =(F74/(0.025*800)/12000) -> 0 | H115: =30*BC!$B$47/E115 -> 0 | I115: =IF(G115>H115,G115,H115) -> 0 | J115: =ROUNDUP(I115,0) -> 0 | K115: 1 | L115: 35.5 | M115: =L115*K115 -> 35.5 | N115: =((L115*$L$139)+L115) -> #DIV/0! | P115: =K115/D115 -> 0.5 | Q115: =ROUNDUP(P115,0) -> 1
B116: 4444191001 | C116: cobas sample cups | D116: 1 | E116: 365 | G116: =((F74-(F74*0.9))/E116) -> 0 | H116: =30*BC!$B$47/E116 -> 0 | I116: =IF(G116>H116,G116,H116) -> 0 | J116: =ROUNDUP(I116,0) -> 0 | K116: 1 | L116: 9 | M116: =L116*K116 -> 9 | N116: =((L116*$L$139)+L116) -> #DIV/0! | P116: =K116/D116 -> 1 | Q116: =ROUNDUP(P116,0) -> 1
B117: 4555040001 | C117: Cuvettes – reaction cell sets | D117: 3 | E117: 84 | G117: =(F74/(0.07*30)/6300) -> 0 | H117: =30*BC!$B$47/E117 -> 0 | I117: =IF(G117>H117,G117,H117) -> 0 | J117: =ROUNDUP(I117,0) -> 0 | K117: 1 | L117: 936 | M117: =L117*K117 -> 936 | N117: =((L117*$L$139)+L117) -> #DIV/0! | P117: =K117/D117 -> 0.33333333 | Q117: =ROUNDUP(P117,0) -> 1
B118: 5422485190 | C118: Ecotergent | D118: 1 | E118: 28 | G118: =(F74/(0.7*11)/120) -> 0 | H118: =30*BC!$B$47/E118 -> 0 | I118: =IF(G118>H118,G118,H118) -> 0 | J118: =ROUNDUP(I118,0) -> 0 | K118: 1 | L118: 32 | M118: =L118*K118 -> 32 | N118: =((L118*$L$139)+L118) -> #DIV/0! | P118: =K118/D118 -> 1 | Q118: =ROUNDUP(P118,0) -> 1
B119: 4554124001 | C119: FILTRO DE RESINA IONICA REGENERADA 20" | D119: 1 | E119: 30 | G119: =(F74/(0.05*30)/6300) -> 0 | H119: =30*BC!$B$47/E119 -> 0 | I119: =IF(G119>H119,G119,H119) -> 0 | J119: =ROUNDUP(I119,0) -> 0 | K119: 1 | L119: 178 | M119: =L119*K119 -> 178 | N119: =((L119*$L$139)+L119) -> #DIV/0! | P119: =K119/D119 -> 1 | Q119: =ROUNDUP(P119,0) -> 1
B120: 4516273001 | C120: FILTRO NOM. P/SEDIMENTS GX05-20XX (BLANCO) | D120: 1 | E120: 30 | G120: =(F74/(0.05*30)/6300) -> 0 | H120: =30*BC!$B$47/E120 -> 0 | I120: =IF(G120>H120,G120,H120) -> 0 | J120: =ROUNDUP(I120,0) -> 0 | K120: 1 | L120: 26 | M120: =L120*K120 -> 26 | N120: =((L120*$L$139)+L120) -> #DIV/0! | P120: =K120/D120 -> 1 | Q120: =ROUNDUP(P120,0) -> 1
B121: 4516265001 | C121: FILTRO NOM. P/SEDIMENTS PX5-20 PURTR (AZUL) | D121: 1 | E121: 30 | G121: =(F74/(0.05*30)/6300) -> 0 | H121: =30*BC!$B$47/E121 -> 0 | I121: =IF(G121>H121,G121,H121) -> 0 | J121: =ROUNDUP(I121,0) -> 0 | K121: 1 | L121: 61 | M121: =L121*K121 -> 61 | N121: =((L121*$L$139)+L121) -> #DIV/0! | P121: =K121/D121 -> 1 | Q121: =ROUNDUP(P121,0) -> 1
B122: 4528182190 | C122: HBA1C TQ HAEMOLYZING RGT, COBAS C | D122: 1 | E122: 28 | G122: =(F44/(0.025*500)/100) -> 0 | H122: =30*BC!$B$47/E122 -> 0 | I122: =IF(G122>H122,G122,H122) -> 0 | J122: =ROUNDUP(I122,0) -> 0 | K122: 1 | L122: 26 | M122: =L122*K122 -> 26 | N122: =((L122*$L$139)+L122) -> #DIV/0! | P122: =K122/D122 -> 1 | Q122: =ROUNDUP(P122,0) -> 1
B123: 4813707001 | C123: Lamp, Halogen | D123: 1 | E123: 45 | G123: =(F74/(0.07*30)/6300) -> 0 | H123: =30*BC!$B$47/E123 -> 0 | I123: =IF(G123>H123,G123,H123) -> 0 | J123: =ROUNDUP(I123,0) -> 0 | K123: 1 | L123: 402 | M123: =L123*K123 -> 402 | N123: =((L123*$L$139)+L123) -> #DIV/0! | P123: =K123/D123 -> 1 | Q123: =ROUNDUP(P123,0) -> 1
B124: 4516303001 | C124: MEMBRANE EQ.OSMOSIS, AG2521TF 2.5 diam | D124: 1 | E124: 360 | G124: =(F74/(0.025*500)/12000) -> 0 | H124: =30*BC!$B$47/E124 -> 0 | I124: =IF(G124>H124,G124,H124) -> 0 | J124: =ROUNDUP(I124,0) -> 0 | K124: 1 | L124: 859 | M124: =L124*K124 -> 859 | N124: =((L124*$L$139)+L124) -> #DIV/0! | P124: =K124/D124 -> 1 | Q124: =ROUNDUP(P124,0) -> 1
B125: 4708725190 | C125: Multiclean, Sample Cleaner 1 | D125: 12 | E125: 28 | G125: =(F74/(0.00025*250)/56000) -> 0 | H125: =30*BC!$B$47/E125 -> 0 | I125: =IF(G125>H125,G125,H125) -> 0 | J125: =ROUNDUP(I125,0) -> 0 | K125: 1 | L125: 4.09 | M125: =L125*K125 -> 4.09 | N125: =((L125*$L$139)+L125) -> #DIV/0! | P125: =K125/D125 -> 0.083333333 | Q125: =ROUNDUP(P125,0) -> 1
B126: 4489357190 | C126: NaCl 9% Diluent | D126: 1 | E126: 84 | G126: =(F74/(0.03*200)/12000) -> 0 | H126: =30*BC!$B$47/E126 -> 0 | I126: =IF(G126>H126,G126,H126) -> 0 | J126: =ROUNDUP(I126,0) -> 0 | K126: 1 | L126: 14 | M126: =L126*K126 -> 14 | N126: =((L126*$L$139)+L126) -> #DIV/0! | P126: =K126/D126 -> 1 | Q126: =ROUNDUP(P126,0) -> 1
B127: 4489241190 | C127: NaOH-D c pack | D127: 1 | E127: 84 | G127: =(F74/(0.0003*800)/12000) -> 0 | H127: =30*BC!$B$47/E127 -> 0 | I127: =IF(G127>H127,G127,H127) -> 0 | J127: =ROUNDUP(I127,0) -> 0 | K127: 1 | L127: 5 | M127: =L127*K127 -> 5 | N127: =((L127*$L$139)+L127) -> #DIV/0! | P127: =K127/D127 -> 1 | Q127: =ROUNDUP(P127,0) -> 1
B128: 4489225190 | C128: SMS | D128: 1 | E128: 84 | G128: =(F74/(0.04*300)/12000) -> 0 | H128: =30*BC!$B$47/E128 -> 0 | I128: =IF(G128>H128,G128,H128) -> 0 | J128: =ROUNDUP(I128,0) -> 0 | K128: 1 | L128: 7 | M128: =L128*K128 -> 7 | N128: =((L128*$L$139)+L128) -> #DIV/0! | P128: =K128/D128 -> 1 | Q128: =ROUNDUP(P128,0) -> 1
B129: 4516303001 | C129: MEMBRANE EQ.OSMOSIS, AG2521TF 2.5 DIAM | D129: 1 | E129: 365 | G129: =(F75/(0.04*300)/12000) -> 0 | H129: =30*BC!$B$47/E129 -> 0 | I129: =IF(G129>H129,G129,H129) -> 0 | J129: =ROUNDUP(I129,0) -> 0 | K129: 1 | L129: 7 | M129: 859 | N129: =((L129*$L$139)+L129) -> #DIV/0! | P129: =K129/D129 -> 1 | Q129: =ROUNDUP(P129,0) -> 1
B130: FAM154 | C130: RESINA MIXTA GRANEL X KG | D130: 1 | E130: 365 | G130: =(F76/(0.04*300)/12000) -> 0 | H130: =30*BC!$B$47/E130 -> 0 | I130: =IF(G130>H130,G130,H130) -> 0 | J130: =ROUNDUP(I130,0) -> 0 | K130: 1 | L130: 7 | M130: 50 | N130: =((L130*$L$139)+L130) -> #DIV/0! | P130: =K130/D130 -> 1 | Q130: =ROUNDUP(P130,0) -> 1
B131: 4516265001 | C131: FILTRO NOM. P/SEDIMENTS PX5-20 PURTR (AZUL) | D131: 1 | E131: 365 | G131: =(F77/(0.04*300)/12000) -> 0 | H131: =30*BC!$B$47/E131 -> 0 | I131: =IF(G131>H131,G131,H131) -> 0 | J131: =ROUNDUP(I131,0) -> 0 | K131: 1 | L131: 7 | M131: 61 | N131: =((L131*$L$139)+L131) -> #DIV/0! | P131: =K131/D131 -> 1 | Q131: =ROUNDUP(P131,0) -> 1
...

Sheet e411
A1: CLIENTE
A2: FECHA
A3: MODALIDAD
A4: PLAZO | C4: MESES
A5: PROYECCIÓN | C5: MESES
A6: EQUIPO | B6: E411 DISK
A8: I.D | B8: DESCRIPCION | C8: NOMBRE | D8: DET/KIT | E8: DIAS ESTABILIDAD | F8: DET/AÑO/PROCESO | G8: PRODUCTO CALCULADO | H8: MINIMOS POR ESTABILIDAD | I8: PRODUCTO A ENTREGAR
A9: 8946710190 | B9: ACTH ELECSYS COBAS E 100 V2 | C9: Hormona Adrenocorticotrópica | D9: 100 | E9: 84 | G9: =F9/D9 -> 0 | H9: =(360/E9) -> 4.2857143
A10: 9015060190 | B10: AFP ELECSYS COBAS E 100 V2 | C10: Alfa1 - Fetoproteína | D10: 100 | E10: 56 | G10: =F10/D10 -> 0 | H10: =(360/E10) -> 6.4285714
A11: 10059516190 | B11: AMH plus Elecsys cobas e 100 V3 | C11: Hormona Antimülleriana | D11: 100 | G11: =F11/D11 -> 0 | H11: =(360/E11) -> #DIV/0!
A12: 6368590190 | B12: ANTI TPO | C12: Anti-Peroxidasa Tiroidea | D12: 100 | E12: 15 | G12: =F12/D12 -> 0 | H12: =(360/E12) -> 24
A13: 5031656190 | B13: ANTI-CCP ELECSYS COBAS E 100 | C13: Anticuerpos Antipéptido Cíclico Citrulinado | D13: 100 | E13: 28 | G13: =F13/D13 -> 0 | H13: =(360/E13) -> 12.857143
A14: 8086630190 | B14: ANTI-HAV G2 ELECSYS,COBAS E100 (COI) | C14: Anticuerpos Hepatitis A | D14: 100 | E14: 56 | G14: =F14/D14 -> 0 | H14: =(360/E14) -> 6.4285714
A15: 11820591122 | B15: ANTI-HAV IGM ELECSYS COBAS E 100 | C15: Anticuerpos IGM Hepatitis A | D15: 100 | E15: 56 | G15: =F15/D15 -> 0 | H15: =(360/E15) -> 6.4285714
A16: 11820567122 | B16: ANTI-HBC IGM ELECSYS COBAS E 100 | C16: Anticuerpos IGM Hepatitis B | D16: 100 | E16: 28 | G16: =F16/D16 -> 0 | H16: =(360/E16) -> 12.857143
A17: 9014918190 | B17: Anti-HBc II ELECSYS COBAS E100 | C17: Anticuerpos IgG e IgM Hepatitis B | D17: 100 | E17: 56 | G17: =F17/D17 -> 0 | H17: =(360/E17) -> 6.4285714
A18: 11820613122 | B18: ANTI-HBE ELECSYS COBAS E 100 | C18: Anticuerpo contra antigeno de HBE | D18: 100 | E18: 56 | G18: =F18/D18 -> 0 | H18: =(360/E18) -> 6.4285714
A19: 8498598190 | B19: Anti-HBs G2 Elecsys cobas e 100 V2 | C19: Anticuerpo contra antigeno de HBs | D19: 100 | E19: 56 | G19: =F19/D19 -> 0 | H19: =(360/E19) -> 6.4285714
A20: 8836981190 | B20: ANTI-HCV G2 ELECSYS COBAS E 100 V2 | C20: Anticuerpos contra el virus de la hepatitis C | D20: 100 | E20: 49 | G20: =F20/D20 -> 0 | H20: =(360/E20) -> 7.3469388
A21: 9203095190 | B21: ANTI-SARS-COV-2 ELECSYS COBAS E 200 | C21: Antígeno de la nucleocápside del coronavirus 2 | D21: 200 | E21: 28 | G21: =F21/D21 -> 0 | H21: =(360/E21) -> 12.857143
A22: 9289267190 | B22: ANTI-SARS-COV-2 S ELECSYS COBAS E 200 | C22: Anticuerpos de proteina espícula S contra el corona virus 2 | D22: 200 | E22: 28 | G22: =F22/D22 -> 0 | H22: =(360/E22) -> 12.857143
A23: 9004998190 | B23: ANTI-TG ELECSYS COBAS E 100 V5 | C23: Anticuerpos anti-tiroglobulina | D23: 100 | E23: 42 | G23: =F23/D23 -> 0 | H23: =(360/E23) -> 8.5714286
... A75: 9315268190 | B75: PROBNP G2 ELECSYS COBAS E 100 V2 | C75: Péptidos natriuréticos | D75: 100 | E75: 56 | G75: =F75/D75 -> 0 | H75: =(360/E75) -> 6.4285714
A76: 8836744190 | B76: PROBNP G2 STAT ELECSYS COBAS E 100 V2 | C76: Péptidos natriuréticos STAT | D76: 100 | G76: =F76/D76 -> 0 | H76: =(360/E76) -> #DIV/0!
A77: 7092539190 | B77: PROGESTERONE G3 ELECSYS COBAS E 100 | C77: Progesterona | D77: 100 | E77: 56 | G77: =F77/D77 -> 0 | H77: =(360/E77) -> 6.4285714
A78: 9007636190 | B78: PROGRP ELECSYS COBAS E 100 V2 | C78: Péptido liberador de gastrina | D78: 100 | E78: 42 | G78: =F78/D78 -> 0 | H78: =(360/E78) -> 8.5714286
A79: 3203093190 | B79: PROLACTIN G2 ELECSYS COBAS E 100 V2.1 | C79: Prolactina | D79: 100 | E79: 56 | G79: =F79/D79 -> 0 | H79: =(360/E79) -> 6.4285714
A80: 9005757190 | B80: PTH (1-84) ELECSYS COBAS E 100 V2 | C80: Parathormona 1-84 | D80: 100 | E80: 56 | G80: =F80/D80 -> 0 | H80: =(360/E80) -> 6.4285714
A81: 8928380190 | B81: PTH ELECSYS COBAS E 100 | C81: Parathormona | D81: 100 | E81: 56 | G81: =F81/D81 -> 0 | H81: =(360/E81) -> 6.4285714
A82: 4618793190 | B82: RUBELLA IGG ELECSYS COBAS E 100 | C82: Rubéola Inmunoglobina G | D82: 100 | E82: 84 | G82: =F82/D82 -> 0 | H82: =(360/E82) -> 4.2857143
A83: 4618831190 | B83: RUBELLA IGM ELECSYS COBAS E100 | C83: Rubéola Inmunoglobina M | D83: 100 | E83: 84 | G83: =F83/D83 -> 0 | H83: =(360/E83) -> 4.2857143
A84: 9345272190 | B84: SARS-COV-2 AG ELECSYS COBAS E 200 | C84: Antigeno corona virus 2 | D84: 200 | E84: 56 | G84: =F84/D84 -> 0 | H84: =(360/E84) -> 6.4285714
A85: 7126972190 | B85: SCC ELECSYS COBAS E 100 | C85: Antígeno del Carcinoma de Células Escamosas | D85: 100 | E85: 49 | G85: =F85/D85 -> 0 | H85: =(360/E85) -> 7.3469388
A86: 5109523190 | B86: SFLT1 ELECSYS COBAS E 100 | C86: Tirosina quinasa -1 | D86: 100 | E86: 84 | G86: =F86/D86 -> 0 | H86: =(360/E86) -> 4.2857143
A87: 3052001190 | B87: SHBG ELECSYS COBAS E 100 | C87: Globulina Fijadora de Hormonas Sexuales | D87: 100 | E87: 49 | G87: =F87/D87 -> 0 | H87: =(360/E87) -> 7.3469388
A88: 9014977190 | B88: SYPHILIS ELECSYS COBAS E 100 V2 | C88: Anticuerpos Treponema Pallidum | D88: 100 | E88: 28 | G88: =F88/D88 -> 0 | H88: =(360/E88) -> 12.857143
... A102: 9038078190 | B102: VITAMIN D TOTAL G3 ELECSYS COBAS E 100 | C102: Vitamina D | D102: 100 | E102: 28 | G102: =F102/D102 -> 0 | H102: =(360/E102) -> 12.857143
A103: TOTAL DET | F103: =SUM(F9:F102) -> 0
A104: CALIBRADORES | D104: PRESENTACION | E104: DIAS ESTABILDAD | G104: PRODUCTO CALCULADO | H104: MINIMOS POR ESTABILIDAD | I104: PRODUCTO A ENTREGAR
A105: 8959820190 | B105: ACTH CS ELECSYS V2 | C105: - | D105: 2 | E105: 28 | H105: =(360/E105)/D105 -> 6.4285714
A106: 9227261190 | B106: AFP G2 CS ELECSYS V3 | C106: - | D106: 2 | E106: 84 | H106: =(360/E106)/D106 -> 2.1428571
A107: 7957203190 | B107: AMH PLUS CS ELECSYS | C107: - | D107: 2 | E107: 28 | H107: =(360/E107)/D107 -> 6.4285714
A108: 9289291190 | B108: Anti SARS-COV-2-S CS | C108: - | D108: 2 | E108: 42 | H108: =(360/E108)/D108 -> 4.2857143
A109: 9005030190 | B109: ANTI-TG CS ELECSYS | C109: - | D109: 2 | E109: 42 | H109: =(360/E109)/D109 -> 4.2857143
A110: 6472931190 | B110: ANTI-TPO CS ELECSYS | C110: - | D110: 2 | E110: 56 | H110: =(360/E110)/D110 -> 3.2142857
A111: 8496641190 | B111: ANTI-TSHR CS | C111: - | D111: 2 | E111: 84 | H111: =(360/E111)/D111 -> 2.1428571
A112: 11972316122 | B112: B-CrossLaps CS | C112: - | D112: 2 | E112: 84 | H112: =(360/E112)/D112 -> 2.1428571
A113: 7030207190 | B113: CA 125 CS | C113: - | D113: 2 | E113: 140 | H113: =(360/E113)/D113 -> 1.2857143
A114: 3045846122 | B114: CA 15-3 G2 CS ELECSYS | C114: - | D114: 2 | E114: 84 | H114: =(360/E114)/D114 -> 2.1428571
A115: 11776215122 | B115: CA 19-9 CS | C115: - | D115: 2 | E115: 56 | H115: =(360/E115)/D115 -> 3.2142857
A116: 9175130190 | B116: CA 72-4 CS ELECSYS V2 | C116: - | D116: 2 | E116: 42 | H116: =(360/E116)/D116 -> 4.2857143
A117: 11731645322 | B117: CEA CS | C117: - | D117: 2 | E117: 84 | H117: =(360/E117)/D117 -> 2.1428571
A118: 5957656190 | B118: CK-MB STAT CS | C118: - | D118: 2 | E118: 84 | H118: =(360/E118)/D118 -> 2.1428571
A119: 6687750190 | B119: Cortisol CS | C119: - | D119: 2 | E119: 84 | H119: =(360/E119)/D119 -> 2.1428571
A120: 3184919190 | B120: C-PEPTIDE CS ELECSYS | C120: - | D120: 2 | E120: 28 | H120: =(360/E120)/D120 -> 6.4285714
A121: 11820974322 | B121: CYFRA 21-1 CS | C121: - | D121: 2 | E121: 56 | H121: =(360/E121)/D121 -> 3.2142857
A122: 3000095122 | B122: DHEA-S CS ELECSYS | C122: - | D122: 2 | E122: 84 | H122: =(360/E122)/D122 -> 2.1428571
A123: 11820907322 | B123: DIGOXIN CS | C123: - | D123: 2 | E123: 56 | H123: =(360/E123)/D123 -> 3.2142857
A124: 6656048190 | B124: ESTRADIOL G3 CS ELECYSS | C124: - | D124: 2 | E124: 31 | H124: =(360/E124)/D124 -> 5.8064516
A125: 3737586190 | B125: Ferritina CS | C125: - | D125: 2 | E125: 84 | H125: =(360/E125)/D125 -> 2.1428571
A126: 7560001190 | B126: Folate G3 CS | C126: - | D126: 2 | E126: 84 | H126: =(360/E126)/D126 -> 2.1428571
A127: 4854080200 | B127: FREE B HCG CS | C127: - | D127: 2 | E127: 84 | H127: =(360/E127)/D127 -> 2.1428571
A128: 8851964190 | B128: Free PSA Calset | C128: - | D128: 2 | E128: 84 | H128: =(360/E128)/D128 -> 2.1428571
A129: 9557440190 | B129: FSH CS Elecsys V3.1 | C129: - | D129: 2 | E129: 84 | H129: =(360/E129)/D129 -> 2.1428571
A130: 9077871190 | B130: FT3 Calset | C130: - | D130: 2 | E130: 56 | H130: =(360/E130)/D130 -> 3.2142857
A131: 9043292190 | B131: FT4 Calset | C131: - | D131: 2 | E131: 84 | H131: =(360/E131)/D131 -> 2.1428571
A132: 7125941190 | B132: GDF-15 CS | C132: - | D132: 2 | E132: 56 | H132: =(360/E132)/D132 -> 3.2142857
A133: 9013296190 | B133: HCG STAT CS | C133: - | D133: 2 | E133: 84 | H133: =(360/E133)/D133 -> 2.1428571
A134: 3302652190 | B134: HCG+B CalSet | C134: - | D134: 2 | E134: 84 | H134: =(360/E134)/D134 -> 2.1428571
A135: 5950945190 | B135: HE4 CS | C135: - | D135: 2 | E135: 56 | H135: =(360/E135)/D135 -> 3.2142857
A136: 5390133190 | B136: HGH CS | C136: - | D136: 2 | E136: 28 | H136: =(360/E136)/D136 -> 6.4285714
A137: 11930427122 | B137: IgE CS | C137: - | D137: 2 | E137: 84 | H137: =(360/E137)/D137 -> 2.1428571
A138: 7475969190 | B138: IGF-1 CS | C138: - | D138: 2 | E138: 31 | H138: =(360/E138)/D138 -> 5.8064516
A139: 7574762190 | B139: IGFBP-3 CS | C139: - | D139: 2 | E139: 84 | H139: =(360/E139)/D139 -> 2.1428571
A140: 5109469190 | B140: IL 6 CS ELECSYS | C140: - | D140: 2 | E140: 84 | H140: =(360/E140)/D140 -> 2.1428571
A141: 12017504122 | B141: Insulina CS | C141: - | D141: 2 | E141: 84 | H141: =(360/E141)/D141 -> 2.1428571
A142: 9557423190 | B142: LH Calset | C142: - | D142: 2 | E142: 84 | H142: =(360/E142)/D142 -> 2.1428571
A143: 11820893122 | B143: MYOGLOBIN STAT CS | C143: - | D143: 2 | E143: 84 | H143: =(360/E143)/D143 -> 2.1428571
A144: 11972111122 | B144: N-MID OSTEOCALCIN CS | C144: - | D144: 2 | E144: 84 | H144: =(360/E144)/D144 -> 2.1428571
A145: 12133121122 | B145: NSE CS | C145: - | D145: 2 | E145: 42 | H145: =(360/E145)/D145 -> 4.2857143
A146: 4854101200 | B146: PAPP-A CS | C146: - | D146: 2 | E146: 84 | H146: =(360/E146)/D146 -> 2.1428571
A147: 5144701190 | B147: PIGF CS | C147: - | D147: 2 | E147: 28 | H147: =(360/E147)/D147 -> 6.4285714
A148: 9315292190 | B148: proBNP CS | C148: - | D148: 2 | E148: 84 | H148: =(360/E148)/D148 -> 2.1428571
A149: 9315276190 | B149: proBNP STAT CS | C149: - | D149: 2 | H149: =(360/E149)/D149 -> #DIV/0!
A150: 7092547190 | B150: Progesterona Calset | C150: - | D150: 2 | E150: 31 | H150: =(360/E150)/D150 -> 5.8064516
A151: 6505970190 | B151: ProGRP CS | C151: - | D151: 2 | E151: 56 | H151: =(360/E151)/D151 -> 3.2142857
A152: 3277356190 | B152: Prolactin CalSet | C152: - | D152: 2 | E152: 84 | H152: =(360/E152)/D152 -> 2.1428571
A153: 5608554190 | B153: PTH (1-84) CS | C153: - | D153: 2 | E153: 90 | H153: =(360/E153)/D153 -> 2
A154: 8928452190 | B154: PTH CS ELECSYS V2 | C154: - | D154: 2 | E154: 84 | H154: =(360/E154)/D154 -> 2.1428571
A155: 7126999190 | B155: SCC CS | C155: - | D155: 2 | E155: 28 | H155: =(360/E155)/D155 -> 6.4285714
