Workbook

Sheet BC
A1: INFORMACIÓN GENERAL PARA CASO DE NEGOCIO (BC)
A2: Actualización: 06 noviembre 2024. 13:11
A3: TIPO DE CLIENTE
A4: ENTIDAD CONTRATANTE
A5: CLIENTE
A6: Código del Proceso
A7: Objeto de contratación
A8: Provincia /Ciudad
A9: * Ambiente de Laboratorio :
A10: Número de días por semana que trabaja el laboratorio
A11: Turnos por dia
A12: Horas por turno
... A52: Observaciones
A54: *Inversiones adicionales | B54: Características | C54: Estado | D54: Cantidad | E54: Precio | F54: Total
A55: Control externo de tercera opinión | D55: 0 | E55: 0 | F55: =D55*E55 -> 0
A56: Control interno interlaboratorial | D56: 0 | E56: 0 | F56: =D56*E56 -> 0
A57: Póliza $ 66.593,64 | D57: 0 | E57: 0 | F57: =D57*E57 -> 0
A58: Póliza de seguro de equipos | D58: 0 | E58: 0 | F58: =D58*E58 -> 0
A59: Ups equipo | B59: Equipo | D59: 0 | E59: 0 | F59: =D59*E59 -> 0
A60: Ups servidor | B60: Powest on line 1kva 1000VA | D60: 0 | E60: 200 | F60: =D60*E60 -> 0
A61: LIS | D61: 1 | E61: 1920 | F61: =D61*E61 -> 1920
A62: Interfaz | D62: 1 | E62: 0 | F62: =D62*E62 -> 0
A63: Lantronix | D63: 0 | E63: 820 | F63: =D63*E63 -> 0
A64: IP publica | D64: 0 | E64: 0 | F64: =D64*E64 -> 0
A65: Punto de consulta web | D65: 0 | E65: 0 | F65: =D65*E65 -> 0
A66: Internet | D66: 0 | E66: 0 | F66: =D66*E66 -> 0
A67: Servidor | D67: 0 | E67: 0 | F67: =D67*E67 -> 0
A68: Computadores Desktop HP P20AV 19.5 | B68: Monitor + Teclado y mouse | D68: 0 | E68: 900 | F68: =D68*E68 -> 0
A69: Impresora Epson L4260 Laser multifuncion | D69: 0 | E69: 300 | F69: =D69*E69 -> 0
A70: Tinta | B70: Juego de 4 colores | D70: 0 | E70: 65 | F70: =D70*E70 -> 0
A71: Impresora Epson Toner | D71: 0 | E71: 980 | F71: =D71*E71 -> 0
A72: Toner | B72: Juego de 4 colores | D72: 0 | E72: 568 | F72: =D72*E72 -> 0
A73: Impresora Zebra Termica ZD230 ETHERNET Y USB | D73: 0 | E73: 400 | F73: =D73*E73 -> 0
A74: Sistema de destilación de agua pequeño | D74: 0 | F74: =D74*E74 -> 0
A75: Sistema de osmosis | D75: 0 | E75: 0 | F75: =D75*E75 -> 0
A76: Sitema de prefiltracion | D76: 0 | E76: 0 | F76: =D76*E76 -> 0
A77: Tanque para resina mixta (muerta) | D77: 0 | E77: 0 | F77: =D77*E77 -> 0
A78: Tubo contenedor de resina | D78: 0 | F78: =D78*E78 -> 0
A79: Estructura de proteccion para sistema de agua | D79: 0 | E79: 400 | F79: =D79*E79 -> 0
A80: MEMBRANE EQ.OSMOSIS, AG2521TF 2.5 diam | D80: 0 | E80: 600 | F80: =D80*E80 -> 0
A81: FILTER NOM. P/SEDIMENTS PX10-20XX PURTR (CARBON) | D81: 0 | F81: =D81*E81 -> 0
A82: FILTER NOM.P/SEDIMENTS GX05-20XX HYTREX (FIBRA) | D82: 0 | F82: =D82*E82 -> 0
A83: RESINA IONICA REGENERADA 20 " | D83: 0 | F83: =D83*E83 -> 0
A84: RESINA MUERTA 16kilos | D84: 0 | F84: =D84*E84 -> 0
A85: Sal en grano x quintal | D85: 0 | F85: =D85*E85 -> 0
A86: Climatizacion del area | B86: 36000 btus por gravedad | D86: 0 | E86: 1600 | F86: =D86*E86 -> 0
A87: Rollo de cable UTP CAT5e x 100m | D87: 0 | E87: 31 | F87: =D87*E87 -> 0
A88: Conector RJ45 Delta CAT5E x 50 unds | D88: 0 | E88: 10 | F88: =D88*E88 -> 0
A89: Rack Cerrado POWEST 5UR | B89: Soporte para servidor | D89: 0 | E89: 150 | F89: =D89*E89 -> 0
A90: Switch HP Aruba Ion 5 puertos | D90: 0 | E90: 60 | F90: =D90*E90 -> 0
A91: Switch HP Aruba Ion 1430 24 puertos | D91: 0 | E91: 200 | F91: =D91*E91 -> 0
A92: Extensiones y cortapicos | D92: 0 | E92: 0 | F92: =D92*E92 -> 0
A93: Extras (tairas, canaletas, espiral plastico) | D93: 0 | E93: 100 | F93: =D93*E93 -> 0
A94: Etiquetas | B94: Rollo x | D94: 0 | E94: 6.29 | F94: =D94*E94 -> 0
A95: A4 printer paper | B95: Paquete x 500 uds | D95: 0 | E95: 3.85 | F95: =D95*E95 -> 0
A96: Refrigerador panorámico | D96: 0 | E96: 600 | F96: =D96*E96 -> 0
A97: Refrigerador médico | B97: Refrigerador/congeldor | D97: 0 | E97: 3500 | F97: =D97*E97 -> 0
A98: Termometro para refrigerador | D98: 0 | E98: 400 | F98: =D98*E98 -> 0
A99: Termohigrometros | D99: 0 | E99: 70 | F99: =D99*E99 -> 0
A100: Cronometros digitales | D100: 0 | E100: 60 | F100: =D100*E100 -> 0
A101: Centrifuga | B101: 24 Tubos | D101: 0 | E101: 3800 | F101: =D101*E101 -> 0
A102: Servicio Logisticos Proveedores | D102: 0 | E102: 0 | F102: =D102*E102 -> 0
A103: Servicio Logisticos Clientes | D103: 0 | E103: 0 | F103: =D103*E103 -> 0
A104: Ampolla de agua bidestilada | D104: 0 | E104: 0.35 | F104: =D104*E104 -> 0
A105: Agua destilada por galón | D105: 0 | E105: 2.8 | F105: =D105*E105 -> 0
A106: Hisopos x 100 uds | B106: Mantenimiento | D106: 0 | E106: 0.62 | F106: =D106*E106 -> 0
A107: Gasas x 100 uds | B107: Mantenimiento | D107: 0 | E107: 5.9 | F107: =D107*E107 -> 0
A108: Alcohol prepad 10 x 100 uds | B108: Mantenimiento | D108: 0 | E108: 5 | F108: =D108*E108 -> 0
E109: Sub total | F109: =SUM(F55:F108) -> 1920
E110: 0.15 | F110: =+F109*0.15 -> 288
E111: Total | F111: =F109+F110 -> 2208
A113: ¿Porque es importante ganar este proceso ?

Sheet BIOMETRIA HEMATICA
A1: Parámetro | B1: DET/AÑO PROCESO
A2: BIOMETRIA HEMATICA | B2: 12200 | C2: RETICULOCITOS | E2: PLAQUETAS FLUORESCENTES | G2: FLUIDOS CORPORALES
A6: TIEMPO CONTRATO EN MESES | B6: 12
A10: NUMERO DE EQUIPOS | B10: 1

Sheet DETERMINACION XP-300
A2: Parámetro | B2: ID | C2: PRODUCTO | D2: DET/KIT | E2: DIAS ESTABILIDAD | F2: DET/AÑO PROCESO | G2: PRODUCTO CALCULADO | H2: MINIMOS POR ESTABILIDAD | I2: PRODUCTO A ENTREGAR | J2: REDONDEADO A ENTREGAR | K2: PVP | L2: TOTAL | M2: PVP BIOMETRIA | N2: PARA PROCESO | O2: VALOR INICIAL DEL PROCESO | P2: VALOR FINAL DEL PROCESO
A3: Biometria básica | B3: 3145611001 | C3: CELLPACK 20L | D3: 450 | E3: 60 | F3: ='BIOMETRIA HEMATICA'!$B$2 -> 12200 | G3: =F3/D3 -> 27.111111 | H3: =(360/E3)*'BIOMETRIA HEMATICA'!$B$10 -> 6 | I3: =IF(G3>H3,G3,H3) -> 27.111111 | J3: =ROUNDUP(I3,0) -> 28 | K3: 253 | L3: =K3*J3 -> 7084 | M3: =(SUM(L3:L8)/'BIOMETRIA HEMATICA'!B2)+L10 -> 2.2294262 | N3: =((M3*0.15)+M3) -> 2.5638402 | O3: =N3*'BIOMETRIA HEMATICA'!B2 -> 31278.85 | P3: =M3*'BIOMETRIA HEMATICA'!B2 -> 27199
B4: 12216540001 | C4: STROMA WH KX21 x 500ML | D4: 450 | E4: 60 | F4: ='BIOMETRIA HEMATICA'!$B$2 -> 12200 | G4: =F4/D4 -> 27.111111 | H4: =(360/E4)*'BIOMETRIA HEMATICA'!$B$10 -> 6 | I4: =IF(G4>H4,G4,H4) -> 27.111111 | J4: =ROUNDUP(I4,0) -> 28 | K4: 264 | L4: =K4*J4 -> 7392
B5: 3134466001 | C5: EIGHT CHECK-3WP XTRA ( 4 X 2 ML) | D5: =(((F3/30)/12)*E5) -> 2880.5556 | E5: 85 | F5: ='BIOMETRIA HEMATICA'!$B$2 -> 12200 | G5: =F5/D5 -> 4.2352941 | H5: =(360/E5)*'BIOMETRIA HEMATICA'!$B$10 -> 4.2352941 | I5: =IF(G5>H5,G5,H5) -> 4.2352941 | J5: =ROUNDUP(I5,0) -> 5 | K5: 269 | L5: =K5*J5 -> 1345
B6: 3113353180 | C6: PAPER ROLL F.PRINTER STP211-144 (10PCS.) | D6: 900 | E6: 365 | F6: ='BIOMETRIA HEMATICA'!$B$2 -> 12200 | G6: =F6/D6 -> 13.555556 | H6: =(360/E6)*'BIOMETRIA HEMATICA'!$B$10 -> 0.98630137 | I6: =IF(G6>H6,G6,H6) -> 13.555556 | J6: =ROUNDUP(I6,0) -> 14 | K6: 80 | L6: =K6*J6 -> 1120
C8: ADICIONALES | J8: ='BIOMETRIA HEMATICA'!B6 -> 12 | K8: =BC!F109 -> 1920 | L8: =(K8/J8)*J8 -> 1920
C9: ALQUILER | K9: 210 | L9: =(K9*J8)/(12) -> 210
C10: EQUIPO | K10: 8338 | L10: =((((K10)/(J8)*12))/'BIOMETRIA HEMATICA'!B2)*(J8/12) -> 0.68344262

Sheet PRUEBA EFECTIVA XP-300
A2: Parámetro | B2: ID | C2: PRODUCTO | D2: DET/KIT | E2: DIAS ESTABILIDAD | F2: DET/AÑO PROCESO | G2: PRODUCTO CALCULADO | H2: MINIMOS POR ESTABILIDAD | I2: PRODUCTO A ENTREGAR | J2: REDONDEADO A ENTREGAR | K2: PVP | L2: TOTAL | M2: PVP BIOMETRIA | N2: PARA PROCESO | O2: VALOR INICIAL DEL PROCESO | P2: VALOR FINAL DEL PROCESO
A3: Biometria básica | B3: 3145611001 | C3: CELLPACK 20L | D3: 450 | E3: 60 | F3: =('BIOMETRIA HEMATICA'!$B$2*0.2)+'BIOMETRIA HEMATICA'!$B$2 -> 14640 | G3: =F3/D3 -> 32.533333 | H3: =(360/E3)*'BIOMETRIA HEMATICA'!$B$10 -> 6 | I3: =IF(G3>H3,G3,H3) -> 32.533333 | J3: =ROUNDUP(I3,0) -> 33 | K3: 253 | L3: =K3*J3 -> 8349 | M3: =(SUM(L3:L8)/'BIOMETRIA HEMATICA'!B2)+L10 -> 2.4609836 | N3: =((M3*0.15)+M3) -> 2.8301311 | O3: =N3*'BIOMETRIA HEMATICA'!B2 -> 34527.6 | P3: =M3*'BIOMETRIA HEMATICA'!B2 -> 30024
B4: 12216540001 | C4: STROMA WH KX21 x 500ML | D4: 450 | E4: 60 | F4: =('BIOMETRIA HEMATICA'!$B$2*0.2)+'BIOMETRIA HEMATICA'!$B$2 -> 14640 | G4: =F4/D4 -> 32.533333 | H4: =(360/E4)*'BIOMETRIA HEMATICA'!$B$10 -> 6 | I4: =IF(G4>H4,G4,H4) -> 32.533333 | J4: =ROUNDUP(I4,0) -> 33 | K4: 264 | L4: =K4*J4 -> 8712
B5: 3134466001 | C5: EIGHT CHECK-3WP XTRA ( 4 X 2 ML) | D5: =(((F3/30)/12)*E5) -> 3456.6667 | E5: 85 | F5: =('BIOMETRIA HEMATICA'!$B$2*0.2)+'BIOMETRIA HEMATICA'!$B$2 -> 14640 | G5: =F5/D5 -> 4.2352941 | H5: =(360/E5)*'BIOMETRIA HEMATICA'!$B$10 -> 4.2352941 | I5: =IF(G5>H5,G5,H5) -> 4.2352941 | J5: =ROUNDUP(I5,0) -> 5 | K5: 269 | L5: =K5*J5 -> 1345
B6: 3113353180 | C6: PAPER ROLL F.PRINTER STP211-144 (10PCS.) | D6: 900 | E6: 365 | F6: =('BIOMETRIA HEMATICA'!$B$2*0.2)+'BIOMETRIA HEMATICA'!$B$2 -> 14640 | G6: =F6/D6 -> 16.266667 | H6: =(360/E6)*'BIOMETRIA HEMATICA'!$B$10 -> 0.98630137 | I6: =IF(G6>H6,G6,H6) -> 16.266667 | J6: =ROUNDUP(I6,0) -> 17 | K6: 80 | L6: =K6*J6 -> 1360
C8: ADICIONALES | J8: ='BIOMETRIA HEMATICA'!B6 -> 12 | K8: =BC!F109 -> 1920 | L8: =(K8/J8)*J8 -> 1920
C9: ALQUILER | K9: 210 | L9: =(K9*J8)/(12) -> 210
C10: EQUIPO | K10: 8338 | L10: =((((K10)/(J8)*12))/'BIOMETRIA HEMATICA'!B2)*(J8/12) -> 0.68344262

Sheet COMODATO TODO COMPRADO XP-300
A2: Parámetro | B2: ID | C2: PRODUCTO | D2: DET/KIT | E2: DIAS ESTABILIDAD | F2: DET/AÑO PROCESO | G2: PRODUCTO CALCULADO | H2: MINIMOS POR ESTABILIDAD | I2: PRODUCTO A ENTREGAR | J2: REDONDEADO A ENTREGAR | K2: PVP | L2: TOTAL | M2: PVP TODO COMPRADO | N2: TOTAL TODO COMPRADO | O2: PVP BIOMETRIA
A3: Biometria básica | B3: 3145611001 | C3: CELLPACK 20L | D3: 450 | E3: 60 | F3: ='BIOMETRIA HEMATICA'!$B$2 -> 12200 | G3: =F3/D3 -> 27.111111 | H3: =(360/E3)*'BIOMETRIA HEMATICA'!$B$10 -> 6 | I3: =IF(G3>H3,G3,H3) -> 27.111111 | J3: =ROUNDDOWN(I3,0) -> 27 | K3: 253 | L3: =K3*J3 -> 6831 | M3: =(K3*$L$13)+K3 -> 286.52348 | N3: =M3*J3 -> 7736.1341 | O3: =(SUM(N3:N6)/'BIOMETRIA HEMATICA'!B2)+L10 -> 2.1756557
B4: 12216540001 | C4: STROMA WH KX21 x 500ML | D4: 450 | E4: 60 | F4: ='BIOMETRIA HEMATICA'!$B$2 -> 12200 | G4: =F4/D4 -> 27.111111 | H4: =(360/E4)*'BIOMETRIA HEMATICA'!$B$10 -> 6 | I4: =IF(G4>H4,G4,H4) -> 27.111111 | J4: =ROUNDDOWN(I4,0) -> 27 | K4: 264 | L4: =K4*J4 -> 7128 | M4: =(K4*$L$13)+K4 -> 298.98103 | N4: =M4*J4 -> 8072.4877
B5: 3134466001 | C5: EIGHT CHECK-3WP XTRA ( 4 X 2 ML) | D5: =(((F3/30)/12)*E5) -> 2880.5556 | E5: 85 | F5: ='BIOMETRIA HEMATICA'!$B$2 -> 12200 | G5: =F5/D5 -> 4.2352941 | H5: =(360/E5)*'BIOMETRIA HEMATICA'!$B$10 -> 4.2352941 | I5: =IF(G5>H5,G5,H5) -> 4.2352941 | J5: =ROUNDDOWN(I5,0) -> 4 | K5: 269 | L5: =K5*J5 -> 1076 | M5: =(K5*$L$13)+K5 -> 304.64355 | N5: =M5*J5 -> 1218.5742
B6: 3113353180 | C6: PAPER ROLL F.PRINTER STP211-144 (10PCS.) | D6: 900 | E6: 365 | F6: ='BIOMETRIA HEMATICA'!$B$2 -> 12200 | G6: =F6/D6 -> 13.555556 | H6: =(360/E6)*'BIOMETRIA HEMATICA'!$B$10 -> 0.98630137 | I6: =IF(G6>H6,G6,H6) -> 13.555556 | J6: =ROUNDDOWN(I6,0) -> 13 | K6: 80 | L6: =K6*J6 -> 1040 | M6: =(K6*$L$13)+K6 -> 90.600311 | N6: =M6*J6 -> 1177.804
C8: ADICIONALES | J8: ='BIOMETRIA HEMATICA'!B6 -> 12 | K8: =BC!F109 -> 1920 | L8: =(K8/J8)*J8 -> 1920
C9: REPUESTOS | K9: 210 | L9: =(K9*J8)/(12) -> 210
C10: EQUIPO | K10: 8338 | L10: =((((K10)/(J8)*12))/'BIOMETRIA HEMATICA'!B2)*(J8/12) -> 0.68344262
L11: =SUM(L8:L9) -> 2130
L12: =SUM(L3:L6) -> 16075
L13: =L11/L12 -> 0.13250389
L14: =SUM(L3:L10) -> 18205.683

Sheet DETERMINACION XN
A1: XNL-350 SIN LICENCIAS
A2: Parámetro | B2: ID | C2: PRODUCTO | D2: DET/KIT | E2: DIAS ESTABILIDAD | F2: DET/AÑO PROCESO | G2: PRODUCTO CALCULADO | H2: MINIMOS POR ESTABILIDAD | I2: PRODUCTO A ENTREGAR | K2: REDONDEADO A ENTREGAR | L2: PVP | M2: TOTAL | O2: PVP BIOMETRIA COMPLETA | P2: PARA PROCESO | Q2: VALOR INICIAL DEL PROCESO | R2: VALOR FINAL DEL PROCESO
A3: Biometria básica | B3: 6510167001 | C3: CELLPACK DCL | D3: 450 | E3: 60 | F3: ='BIOMETRIA HEMATICA'!$B$2 -> 12200 | G3: =F3/D3 -> 27.111111 | H3: =(360/E3)*'BIOMETRIA HEMATICA'!$B$10 -> 6 | I3: =IF(G3>H3,G3,H3) -> 27.111111 | K3: =ROUNDUP(I3,0) -> 28 | L3: 121 | M3: =L3*K3 -> 3388 | O3: =(SUM(M3:N12)/F3)+M16+(BC!F109/'DETERMINACION XN'!F3) -> 1.8263852 | P3: =((O3*0.15)+O3) -> 2.100343 | Q3: =P3*'BIOMETRIA HEMATICA'!B2 -> 25624.185 | R3: =O3*'BIOMETRIA HEMATICA'!B2 -> 22281.9
B4: 3337006001 | C4: SULFOLYSER REAGENT X 5L | D4: 9450 | E4: 60 | F4: ='BIOMETRIA HEMATICA'!$B$2 -> 12200 | G4: =F4/D4 -> 1.2910053 | H4: =(360/E4)*'BIOMETRIA HEMATICA'!$B$10 -> 6 | I4: =IF(G4>H4,G4,H4) -> 6 | J4: =IF(N4>N5,0,I4) -> 6 | L4: 1107 | M4: =L4*K4 -> 0 | N4: =L4*K4 -> 0 | O4: PVP BIOMETRIA | P4: PARA PROCESO | Q4: VALOR INICIAL DEL PROCESO | R4: VALOR FINAL DEL PROCESO
B5: 12215616001 | C5: SULFOLYSER REAGENT 500 ml | D5: 850 | E5: 60 | F5: ='BIOMETRIA HEMATICA'!$B$2 -> 12200 | G5: =F5/D5 -> 14.352941 | H5: =(360/E5)*'BIOMETRIA HEMATICA'!$B$10 -> 6 | I5: =IF(G5>H5,G5,H5) -> 14.352941 | J5: =IF(N5>N4,0,I5) -> 0 | K5: =ROUNDUP(I5,0) -> 15 | L5: 228.33 | M5: =L5*K5 -> 3424.95 | N5: =L5*K5 -> 3424.95 | O5: =(SUM(M3:N9)/'BIOMETRIA HEMATICA'!B2)+M16 -> 1.6690082 | P5: =((O5*0.15)+O5) -> 1.9193594 | Q5: =P5*'BIOMETRIA HEMATICA'!B2 -> 23416.185 | R5: =O5*'BIOMETRIA HEMATICA'!B2 -> 20361.9
B6: 7837984001 | C6: WDF Lysercell WDF | D6: 2450 | E6: 90 | F6: ='BIOMETRIA HEMATICA'!$B$2 -> 12200 | G6: =F6/D6 -> 4.9795918 | H6: =(360/E6)*'BIOMETRIA HEMATICA'!$B$10 -> 4 | I6: =IF(G6>H6,G6,H6) -> 4.9795918 | K6: =ROUNDUP(I6,0) -> 5 | L6: 176 | M6: =L6*K6 -> 880
B7: 6510256001 | C7: WDF Fluorocell WDF 2X42 ML | D7: 3400 | E7: 180 | F7: ='BIOMETRIA HEMATICA'!$B$2 -> 12200 | G7: =F7/D7 -> 3.5882353 | H7: =(360/E7)*'BIOMETRIA HEMATICA'!$B$10 -> 2 | I7: =IF(G7>H7,G7,H7) -> 3.5882353 | K7: =ROUNDUP(I7,0) -> 4 | L7: 862 | M7: =L7*K7 -> 3448
B8: 6952291001 | C8: CELLCLEAN AUTO 4 ML X 20 | D8: =(((F3/30)/12)*E8) -> 5083.3333 | E8: 150 | F8: ='BIOMETRIA HEMATICA'!$B$2 -> 12200 | G8: =F8/D8 -> 2.4 | H8: =(360/E8)*'BIOMETRIA HEMATICA'!$B$10 -> 2.4 | I8: =IF(G8>H8,G8,H8) -> 2.4 | K8: =ROUNDUP(I8,0) -> 3 | L8: 52 | M8: =L8*K8 -> 156
B9: 7051506001 | C9: XN Check 12x3.0ml Level 1,2,3 | D9: =(((F3/30)/12)*E9) -> 1897.7778 | E9: 56 | F9: ='BIOMETRIA HEMATICA'!$B$2 -> 12200 | G9: =F9/D9 -> 6.4285714 | H9: =(360/E9)*'BIOMETRIA HEMATICA'!$B$10 -> 6.4285714 | I9: =IF(G9>H9,G9,H9) -> 6.4285714 | L9: 544 | M9: =L9*K9 -> 0
A10: Reticulocitos | B10: 6510272001 | C10: FLUOROCELL RET 2 X 12ML | D10: 650 | E10: 180 | F10: ='BIOMETRIA HEMATICA'!$D$2 -> 0 | G10: =F10/D10 -> 0 | H10: =(360/E10)*'BIOMETRIA HEMATICA'!$B$10 -> 2 | I10: =IF(G10>H10,G10,H10) -> 2 | J10: =IF(G10=0,0,G10) -> 0 | L10: 1705 | M10: =L10*K10 -> 0
B11: 9426752001 | C11: CELLPACK DFL 1 L | D11: 450 | E11: 60 | F11: ='BIOMETRIA HEMATICA'!$D$2 -> 0 | G11: =F11/D11 -> 0 | H11: =(360/E11)*'BIOMETRIA HEMATICA'!$B$10 -> 6 | I11: =IF(G11>H11,G11,H11) -> 6 | J11: =IF(G11=0,0,G11) -> 0 | L11: 34 | M11: =L11*K11 -> 0
A12: Líquidos | B12: 7051409001 | C12: XN-Check BF 6x3.0ml Level 1,2 | D12: =(((F3/30)/12)*E12) -> 1897.7778 | E12: 56 | F12: ='BIOMETRIA HEMATICA'!$H$2 -> 0 | G12: =F12/D12 -> 0 | H12: =(360/E12)*'BIOMETRIA HEMATICA'!$B$10 -> 6.4285714 | I12: =IF(G12>H12,G12,H12) -> 6.4285714 | J12: =IF(G12=0,0,G12) -> 0 | L12: 661 | M12: =L12*K12 -> 0
C14: ADICIONALES | K14: ='BIOMETRIA HEMATICA'!B6 -> 12 | L14: =BC!F109 -> 1920 | M14: =(L14/K14)*K14 -> 1920
C15: MANTENIMIENTO/REPUESTOS | L15: 470 | M15: =(L15*K14)/(12) -> 470
C16: EQUIPO | L16: 21362 | M16: =((((L15)*(K14))/'BIOMETRIA HEMATICA'!B2)) -> 0.46229508
A20: XNL-350 CON LICENCIAS
A21: Parámetro | B21: ID | C21: PRODUCTO | D21: DET/KIT | E21: DIAS ESTABILIDAD | F21: DET/AÑO PROCESO | G21: PRODUCTO CALCULADO | H21: MINIMOS POR ESTABILIDAD | I21: PRODUCTO A ENTREGAR | K21: REDONDEADO A ENTREGAR | L21: PVP | M21: TOTAL | O21: PVP BIOMETRIA COMPLETA | P21: PARA PROCESO | Q21: VALOR INICIAL DEL PROCESO | R21: VALOR FINAL DEL PROCESO
A22: Biometria básica | B22: 6510167001 | C22: CELLPACK DCL | D22: 450 | E22: 60 | F22: ='BIOMETRIA HEMATICA'!$B$2 -> 12200 | G22: =F22/D22 -> 27.111111 | H22: =(360/E22)*'BIOMETRIA HEMATICA'!$B$10 -> 6 | I22: =IF(G22>H22,G22,H22) -> 27.111111 | K22: =ROUNDUP(I22,0) -> 28 | L22: 121 | M22: =L22*K22 -> 3388 | O22: =(SUM(M22:M31)/'BIOMETRIA HEMATICA'!B2)+M35 -> 3.0186844 | P22: =((O22*0.15)+O22) -> 3.4714871 | Q22: =P22*'BIOMETRIA HEMATICA'!B21 -> 0 | R22: =O22*'BIOMETRIA HEMATICA'!B21 -> 0
B23: 3337006001 | C23: SULFOLYSER REAGENT X 5L | D23: 9450 | E23: 60 | F23: ='BIOMETRIA HEMATICA'!$B$2 -> 12200 | G23: =F23/D23 -> 1.2910053 | H23: =(360/E23)*'BIOMETRIA HEMATICA'!$B$10 -> 6 | I23: =IF(G23>H23,G23,H23) -> 6 | J23: =IF(N23>N24,0,I23) -> 0 | K23: =ROUNDUP(I23,0) -> 6 | L23: 1107 | M23: =L23*K23 -> 6642 | N23: =L23*K23 -> 6642 | O23: PVP BIOMETRIA | P23: PARA PROCESO | Q23: VALOR INICIAL DEL PROCESO | R23: VALOR FINAL DEL PROCESO
B24: 12215616001 | C24: SULFOLYSER REAGENT 500 ml | D24: 850 | E24: 60 | F24: ='BIOMETRIA HEMATICA'!$B$2 -> 12200 | G24: =F24/D24 -> 14.352941 | H24: =(360/E24)*'BIOMETRIA HEMATICA'!$B$10 -> 6 | I24: =IF(G24>H24,G24,H24) -> 14.352941 | J24: =IF(N24>N23,0,I24) -> 14.352941 | K24: =ROUNDUP(I24,0) -> 15 | L24: 228.33 | M24: =L24*K24 -> 3424.95 | N24: =L24*K24 -> 3424.95 | O24: =(SUM(M22:M28)/'BIOMETRIA HEMATICA'!B2)+M35 -> 2.3431926 | P24: =((O24*0.15)+O24) -> 2.6946715 | Q24: =P24*'BIOMETRIA HEMATICA'!B21 -> 0 | R24: =O24*'BIOMETRIA HEMATICA'!B21 -> 0
B25: 7837984001 | C25: WDF Lysercell WDF | D25: 2450 | E25: 90 | F25: ='BIOMETRIA HEMATICA'!$B$2 -> 12200 | G25: =F25/D25 -> 4.9795918 | H25: =(360/E25)*'BIOMETRIA HEMATICA'!$B$10 -> 4 | I25: =IF(G25>H25,G25,H25) -> 4.9795918 | K25: =ROUNDUP(I25,0) -> 5 | L25: 176 | M25: =L25*K25 -> 880
B26: 6510256001 | C26: WDF Fluorocell WDF 2X42 ML | D26: 3400 | E26: 180 | F26: ='BIOMETRIA HEMATICA'!$B$2 -> 12200 | G26: =F26/D26 -> 3.5882353 | H26: =(360/E26)*'BIOMETRIA HEMATICA'!$B$10 -> 2 | I26: =IF(G26>H26,G26,H26) -> 3.5882353 | K26: =ROUNDUP(I26,0) -> 4 | L26: 862 | M26: =L26*K26 -> 3448
B27: 6952291001 | C27: CELLCLEAN AUTO 4 ML X 20 | D27: =(((F22/30)/12)*E27) -> 5083.3333 | E27: 150 | F27: ='BIOMETRIA HEMATICA'!$B$2 -> 12200 | G27: =F27/D27 -> 2.4 | H27: =(360/E27)*'BIOMETRIA HEMATICA'!$B$10 -> 2.4 | I27: =IF(G27>H27,G27,H27) -> 2.4 | K27: =ROUNDUP(I27,0) -> 3 | L27: 52 | M27: =L27*K27 -> 156
B28: 7051506001 | C28: XN Check 12x3.0ml Level 1,2,3 | D28: =(((F22/30)/12)*E28) -> 1897.7778 | E28: 56 | F28: ='BIOMETRIA HEMATICA'!$B$2 -> 12200 | G28: =F28/D28 -> 6.4285714 | H28: =(360/E28)*'BIOMETRIA HEMATICA'!$B$10 -> 6.4285714 | I28: =IF(G28>H28,G28,H28) -> 6.4285714 | K28: =ROUNDUP(I28,0) -> 7 | L28: 544 | M28: =L28*K28 -> 3808
A29: Reticulocitos | B29: 6510272001 | C29: FLUOROCELL RET 2 X 12ML | D29: 650 | E29: 180 | F29: ='BIOMETRIA HEMATICA'!$D$2 -> 0 | G29: =F29/D29 -> 0 | H29: =(360/E29)*'BIOMETRIA HEMATICA'!$B$10 -> 2 | I29: =IF(G29>H29,G29,H29) -> 2 | J29: =IF(G29=0,0,G29) -> 0 | K29: =ROUNDUP(I29,0) -> 2 | L29: 1705 | M29: =L29*K29 -> 3410
B30: 9426752001 | C30: CELLPACK DFL 1 L | D30: 450 | E30: 60 | F30: ='BIOMETRIA HEMATICA'!$D$2 -> 0 | G30: =F30/D30 -> 0 | H30: =(360/E30)*'BIOMETRIA HEMATICA'!$B$10 -> 6 | I30: =IF(G30>H30,G30,H30) -> 6 | J30: =IF(G30=0,0,G30) -> 0 | K30: =ROUNDUP(I30,0) -> 6 | L30: 34 | M30: =L30*K30 -> 204
A31: Líquidos | B31: 7051409001 | C31: XN-Check BF 6x3.0ml Level 1,2 | D31: =(((F22/30)/12)*E31) -> 1897.7778 | E31: 56 | F31: ='BIOMETRIA HEMATICA'!$H$2 -> 0 | G31: =F31/D31 -> 0 | H31: =(360/E31)*'BIOMETRIA HEMATICA'!$B$10 -> 6.4285714 | I31: =IF(G31>H31,G31,H31) -> 6.4285714 | J31: =IF(G10=0,0,G31) -> 0 | K31: =ROUNDUP(I31,0) -> 7 | L31: 661 | M31: =L31*K31 -> 4627
C33: ADICIONALES | K33: ='BIOMETRIA HEMATICA'!B6 -> 12 | L33: =BC!F109 -> 1920 | M33: =(L33/K33)*K33 -> 1920
C34: ALQUILER | L34: 570 | M34: =(L34*K33)/(12) -> 570
C35: EQUIPO | L35: 29260 | M35: =((((L34)*(K33))/'BIOMETRIA HEMATICA'!B2)) -> 0.56065574
A39: XNL-450 SIN LICENCIAS
A40: Parámetro | B40: ID | C40: PRODUCTO | D40: DET/KIT | E40: DIAS ESTABILIDAD | F40: DET/AÑO PROCESO | G40: PRODUCTO CALCULADO | H40: MINIMOS POR ESTABILIDAD | I40: PRODUCTO A ENTREGAR | K40: REDONDEADO A ENTREGAR | L40: PVP | M40: TOTAL | O40: PVP BIOMETRIA COMPLETA | P40: PARA PROCESO | Q40: VALOR INICIAL DEL PROCESO | R40: VALOR FINAL DEL PROCESO
A41: Biometria básica | B41: 6510167001 | C41: CELLPACK DCL | D41: 450 | E41: 60 | F41: ='BIOMETRIA HEMATICA'!$B$2 -> 12200 | G41: =F41/D41 -> 27.111111 | H41: =(360/E41)*'BIOMETRIA HEMATICA'!$B$10 -> 6 | I41: =IF(G41>H41,G41,H41) -> 27.111111 | K41: =ROUNDUP(I41,0) -> 28 | L41: 121 | M41: =L41*K41 -> 3388 | O41: =(SUM(M41:M50)/'BIOMETRIA HEMATICA'!B2)+M54 -> 1.4866352 | P41: =((O41*0.15)+O41) -> 1.7096305 | Q41: =P41*'BIOMETRIA HEMATICA'!B40 -> 0 | R41: =O41*'BIOMETRIA HEMATICA'!B40 -> 0
B42: 3337006001 | C42: SULFOLYSER REAGENT X 5L | D42: 9450 | E42: 60 | F42: ='BIOMETRIA HEMATICA'!$B$2 -> 12200 | G42: =F42/D42 -> 1.2910053 | H42: =(360/E42)*'BIOMETRIA HEMATICA'!$B$10 -> 6 | I42: =IF(G42>H42,G42,H42) -> 6 | J42: =IF(N42>N43,0,I42) -> 6 | L42: 1107 | M42: =L42*K42 -> 0 | N42: =L42*K42 -> 0 | O42: PVP BIOMETRIA | P42: PARA PROCESO | Q42: VALOR INICIAL DEL PROCESO | R42: VALOR FINAL DEL PROCESO
B43: 12215616001 | C43: SULFOLYSER REAGENT 500 ml | D43: 850 | E43: 60 | F43: ='BIOMETRIA HEMATICA'!$B$2 -> 12200 | G43: =F43/D43 -> 14.352941 | H43: =(360/E43)*'BIOMETRIA HEMATICA'!$B$10 -> 6 | I43: =IF(G43>H43,G43,H43) -> 14.352941 | J43: =IF(N43>N42,0,I43) -> 0 | K43: =ROUNDUP(I43,0) -> 15 | L43: 228.33 | M43: =L43*K43 -> 3424.95 | N43: =L43*K43 -> 3424.95 | O43: =(SUM(M41:M47)/'BIOMETRIA HEMATICA'!B2)+M54 -> 1.4866352 | P43: =((O43*0.15)+O43) -> 1.7096305 | Q43: =P43*'BIOMETRIA HEMATICA'!B40 -> 0 | R43: =O43*'BIOMETRIA HEMATICA'!B40 -> 0
B44: 7837984001 | C44: WDF Lysercell WDF | D44: 2450 | E44: 90 | F44: ='BIOMETRIA HEMATICA'!$B$2 -> 12200 | G44: =F44/D44 -> 4.9795918 | H44: =(360/E44)*'BIOMETRIA HEMATICA'!$B$10 -> 4 | I44: =IF(G44>H44,G44,H44) -> 4.9795918 | K44: =ROUNDUP(I44,0) -> 5 | L44: 176 | M44: =L44*K44 -> 880
B45: 6510256001 | C45: WDF Fluorocell WDF 2X42 ML | D45: 3400 | E45: 180 | F45: ='BIOMETRIA HEMATICA'!$B$2 -> 12200 | G45: =F45/D45 -> 3.5882353 | H45: =(360/E45)*'BIOMETRIA HEMATICA'!$B$10 -> 2 | I45: =IF(G45>H45,G45,H45) -> 3.5882353 | K45: =ROUNDUP(I45,0) -> 4 | L45: 862 | M45: =L45*K45 -> 3448
B46: 6952291001 | C46: CELLCLEAN AUTO 4 ML X 20 | D46: =(((F41/30)/12)*E46) -> 5083.3333 | E46: 150 | F46: ='BIOMETRIA HEMATICA'!$B$2 -> 12200 | G46: =F46/D46 -> 2.4 | H46: =(360/E46)*'BIOMETRIA HEMATICA'!$B$10 -> 2.4 | I46: =IF(G46>H46,G46,H46) -> 2.4 | K46: =ROUNDUP(I46,0) -> 3 | L46: 52 | M46: =L46*K46 -> 156
B47: 7051506001 | C47: XN Check 12x3.0ml Level 1,2,3 | D47: =(((F41/30)/12)*E47) -> 1897.7778 | E47: 56 | F47: ='BIOMETRIA HEMATICA'!$B$2 -> 12200 | G47: =F47/D47 -> 6.4285714 | H47: =(360/E47)*'BIOMETRIA HEMATICA'!$B$10 -> 6.4285714 | I47: =IF(G47>H47,G47,H47) -> 6.4285714 | L47: 544 | M47: =L47*K47 -> 0
A48: Reticulocitos | B48: 6510272001 | C48: FLUOROCELL RET 2 X 12ML | D48: 650 | E48: 180 | F48: ='BIOMETRIA HEMATICA'!$D$2 -> 0 | G48: =F48/D48 -> 0 | H48: =(360/E48)*'BIOMETRIA HEMATICA'!$B$10 -> 2 | I48: =IF(G48>H48,G48,H48) -> 2 | J48: =IF(G48=0,0,G48) -> 0 | L48: 1705 | M48: =L48*K48 -> 0
B49: 9426752001 | C49: CELLPACK DFL 1 L | D49: 450 | E49: 60 | F49: ='BIOMETRIA HEMATICA'!$D$2 -> 0 | G49: =F49/D49 -> 0 | H49: =(360/E49)*'BIOMETRIA HEMATICA'!$B$10 -> 6 | I49: =IF(G49>H49,G49,H49) -> 6 | J49: =IF(G49=0,0,G49) -> 0 | L49: 34 | M49: =L49*K49 -> 0
A50: Líquidos | B50: 7051409001 | C50: XN-Check BF 6x3.0ml Level 1,2 | D50: =(((F41/30)/12)*E50) -> 1897.7778 | E50: 56 | F50: ='BIOMETRIA HEMATICA'!$H$2 -> 0 | G50: =F50/D50 -> 0 | H50: =(360/E50)*'BIOMETRIA HEMATICA'!$B$10 -> 6.4285714 | I50: =IF(G50>H50,G50,H50) -> 6.4285714 | J50: =IF(G29=0,0,G50) -> 0 | L50: 661 | M50: =L50*K50 -> 0
C52: ADICIONALES | K52: ='BIOMETRIA HEMATICA'!B6 -> 12 | L52: =BC!F109 -> 1920 | M52: =(L52/K52)*K52 -> 1920
C53: ALQUILER | L53: 570 | M53: =(L53*K52)/(12) -> 570
C54: EQUIPO | L54: 26389 | M54: =((((L53)*(K52))/'BIOMETRIA HEMATICA'!B2)) -> 0.56065574
A58: XNL-450 CON LICENCIAS
A59: Parámetro | B59: ID | C59: PRODUCTO | D59: DET/KIT | E59: DIAS ESTABILIDAD | F59: DET/AÑO PROCESO | G59: PRODUCTO CALCULADO | H59: MINIMOS POR ESTABILIDAD | I59: PRODUCTO A ENTREGAR | K59: REDONDEADO A ENTREGAR | L59: PVP | M59: TOTAL | O59: PVP BIOMETRIA COMPLETA | P59: PARA PROCESO | Q59: VALOR INICIAL DEL PROCESO | R59: VALOR FINAL DEL PROCESO
A60: Biometria básica | B60: 6510167001 | C60: CELLPACK DCL | D60: 450 | E60: 60 | F60: ='BIOMETRIA HEMATICA'!$B$2 -> 12200 | G60: =F60/D60 -> 27.111111 | H60: =(360/E60)*'BIOMETRIA HEMATICA'!$B$10 -> 6 | I60: =IF(G60>H60,G60,H60) -> 27.111111 | K60: =ROUNDUP(I60,0) -> 28 | L60: 121 | M60: =L60*K60 -> 3388 | O60: =(SUM(M60:M69)/'BIOMETRIA HEMATICA'!B2)+M73 -> 3.1170451 | P60: =((O60*0.15)+O60) -> 3.5846018 | Q60: =P60*'BIOMETRIA HEMATICA'!B59 -> 0 | R60: =O60*'BIOMETRIA HEMATICA'!B59 -> 0
B61: 3337006001 | C61: SULFOLYSER REAGENT X 5L | D61: 9450 | E61: 60 | F61: ='BIOMETRIA HEMATICA'!$B$2 -> 12200 | G61: =F61/D61 -> 1.2910053 | H61: =(360/E61)*'BIOMETRIA HEMATICA'!$B$10 -> 6 | I61: =IF(G61>H61,G61,H61) -> 6 | J61: =IF(N61>N62,0,I61) -> 0 | K61: =ROUNDUP(I61,0) -> 6 | L61: 1107 | M61: =L61*K61 -> 6642 | N61: =L61*K61 -> 6642 | O61: PVP BIOMETRIA | P61: PARA PROCESO | Q61: VALOR INICIAL DEL PROCESO | R61: VALOR FINAL DEL PROCESO
B62: 12215616001 | C62: SULFOLYSER REAGENT 500 ml | D62: 850 | E62: 60 | F62: ='BIOMETRIA HEMATICA'!$B$2 -> 12200 | G62: =F62/D62 -> 14.352941 | H62: =(360/E62)*'BIOMETRIA HEMATICA'!$B$10 -> 6 | I62: =IF(G62>H62,G62,H62) -> 14.352941 | J62: =IF(N62>N61,0,I62) -> 14.352941 | K62: =ROUNDUP(I62,0) -> 15 | L62: 228.33 | M62: =L62*K62 -> 3424.95 | N62: =L62*K62 -> 3424.95 | O62: =(SUM(M60:M66)/'BIOMETRIA HEMATICA'!B2)+M73 -> 2.4415533 | P62: =((O62*0.15)+O62) -> 2.8077863 | Q62: =P62*'BIOMETRIA HEMATICA'!B59 -> 0 | R62: =O62*'BIOMETRIA HEMATICA'!B59 -> 0
B63: 7837984001 | C63: WDF Lysercell WDF | D63: 2450 | E63: 90 | F63: ='BIOMETRIA HEMATICA'!$B$2 -> 12200 | G63: =F63/D63 -> 4.9795918 | H63: =(360/E63)*'BIOMETRIA HEMATICA'!$B$10 -> 4 | I63: =IF(G63>H63,G63,H63) -> 4.9795918 | K63: =ROUNDUP(I63,0) -> 5 | L63: 176 | M63: =L63*K63 -> 880
B64: 6510256001 | C64: WDF Fluorocell WDF 2X42 ML | D64: 3400 | E64: 180 | F64: ='BIOMETRIA HEMATICA'!$B$2 -> 12200 | G64: =F64/D64 -> 3.5882353 | H64: =(360/E64)*'BIOMETRIA HEMATICA'!$B$10 -> 2 | I64: =IF(G64>H64,G64,H64) -> 3.5882353 | K64: =ROUNDUP(I64,0) -> 4 | L64: 862 | M64: =L64*K64 -> 3448
B65: 6952291001 | C65: CELLCLEAN AUTO 4 ML X 20 | D65: =(((F60/30)/12)*E65) -> 5083.3333 | E65: 150 | F65: ='BIOMETRIA HEMATICA'!$B$2 -> 12200 | G65: =F65/D65 -> 2.4 | H65: =(360/E65)*'BIOMETRIA HEMATICA'!$B$10 -> 2.4 | I65: =IF(G65>H65,G65,H65) -> 2.4 | K65: =ROUNDUP(I65,0) -> 3 | L65: 52 | M65: =L65*K65 -> 156
B66: 7051506001 | C66: XN Check 12x3.0ml Level 1,2,3 | D66: =(((F60/30)/12)*E66) -> 1897.7778 | E66: 56 | F66: ='BIOMETRIA HEMATICA'!$B$2 -> 12200 | G66: =F66/D66 -> 6.4285714 | H66: =(360/E66)*'BIOMETRIA HEMATICA'!$B$10 -> 6.4285714 | I66: =IF(G66>H66,G66,H66) -> 6.4285714 | K66: =ROUNDUP(I66,0) -> 7 | L66: 544 | M66: =L66*K66 -> 3808
A67: Reticulocitos | B67: 6510272001 | C67: FLUOROCELL RET 2 X 12ML | D67: 650 | E67: 180 | F67: ='BIOMETRIA HEMATICA'!$D$2 -> 0 | G67: =F67/D67 -> 0 | H67: =(360/E67)*'BIOMETRIA HEMATICA'!$B$10 -> 2 | I67: =IF(G67>H67,G67,H67) -> 2 | J67: =IF(G67=0,0,G67) -> 0 | K67: =ROUNDUP(I67,0) -> 2 | L67: 1705 | M67: =L67*K67 -> 3410
B68: 9426752001 | C68: CELLPACK DFL 1 L | D68: 450 | E68: 60 | F68: ='BIOMETRIA HEMATICA'!$D$2 -> 0 | G68: =F68/D68 -> 0 | H68: =(360/E68)*'BIOMETRIA HEMATICA'!$B$10 -> 6 | I68: =IF(G68>H68,G68,H68) -> 6 | J68: =IF(G68=0,0,G68) -> 0 | K68: =ROUNDUP(I68,0) -> 6 | L68: 34 | M68: =L68*K68 -> 204
A69: Líquidos | B69: 7051409001 | C69: XN-Check BF 6x3.0ml Level 1,2 | D69: =(((F60/30)/12)*E69) -> 1897.7778 | E69: 56 | F69: ='BIOMETRIA HEMATICA'!$H$2 -> 0 | G69: =F69/D69 -> 0 | H69: =(360/E69)*'BIOMETRIA HEMATICA'!$B$10 -> 6.4285714 | I69: =IF(G69>H69,G69,H69) -> 6.4285714 | J69: =IF(G48=0,0,G69) -> 0 | K69: =ROUNDUP(I69,0) -> 7 | L69: 661 | M69: =L69*K69 -> 4627
C71: ADICIONALES | K71: ='BIOMETRIA HEMATICA'!B6 -> 12 | L71: =BC!F109 -> 1920 | M71: =(L71/K71)*K71 -> 1920
C72: ALQUILER | L72: 670 | M72: =(L72*K71)/(12) -> 670
C73: EQUIPO | L73: 34287 | M73: =((((L72)*(K71))/'BIOMETRIA HEMATICA'!B2)) -> 0.65901639
A77: XNL-550 SIN LICENCIAS
A78: Parámetro | B78: ID | C78: PRODUCTO | D78: DET/KIT | E78: DIAS ESTABILIDAD | F78: DET/AÑO PROCESO | G78: PRODUCTO CALCULADO | H78: MINIMOS POR ESTABILIDAD | I78: PRODUCTO A ENTREGAR | K78: REDONDEADO A ENTREGAR | L78: PVP | M78: TOTAL | O78: PVP BIOMETRIA COMPLETA | P78: PARA PROCESO | Q78: VALOR INICIAL DEL PROCESO | R78: VALOR FINAL DEL PROCESO
A79: Biometria básica | B79: 6510167001 | C79: CELLPACK DCL | D79: 450 | E79: 60 | F79: ='BIOMETRIA HEMATICA'!$B$2 -> 12200 | G79: =F79/D79 -> 27.111111 | H79: =(360/E79)*'BIOMETRIA HEMATICA'!$B$10 -> 6 | I79: =IF(G79>H79,G79,H79) -> 27.111111 | K79: =ROUNDUP(I79,0) -> 28 | L79: 121 | M79: =L79*K79 -> 3388 | O79: =(SUM(M79:M88)/'BIOMETRIA HEMATICA'!B2)+M92+(BC!F109/'DETERMINACION XN'!F3) -> 1.6882746 | P79: =((O79*0.15)+O79) -> 1.9415158 | Q79: =P79*'BIOMETRIA HEMATICA'!B78 -> 0 | R79: =O79*'BIOMETRIA HEMATICA'!B78 -> 0
B80: 3337006001 | C80: SULFOLYSER REAGENT X 5L | D80: 9450 | E80: 60 | F80: ='BIOMETRIA HEMATICA'!$B$2 -> 12200 | G80: =F80/D80 -> 1.2910053 | H80: =(360/E80)*'BIOMETRIA HEMATICA'!$B$10 -> 6 | I80: =IF(G80>H80,G80,H80) -> 6 | J80: =IF(N80>N81,0,I80) -> 6 | K80: 0 | L80: 1107 | M80: =L80*K80 -> 0 | N80: =L80*K80 -> 0 | O80: PVP BIOMETRIA | P80: PARA PROCESO | Q80: VALOR INICIAL DEL PROCESO | R80: VALOR FINAL DEL PROCESO
B81: 12215616001 | C81: SULFOLYSER REAGENT 500 ml | D81: 850 | E81: 60 | F81: ='BIOMETRIA HEMATICA'!$B$2 -> 12200 | G81: =F81/D81 -> 14.352941 | H81: =(360/E81)*'BIOMETRIA HEMATICA'!$B$10 -> 6 | I81: =IF(G81>H81,G81,H81) -> 14.352941 | J81: =IF(N81>N80,0,I81) -> 0 | K81: =ROUNDUP(I81,0) -> 15 | L81: 228.33 | M81: =L81*K81 -> 3424.95 | N81: =L81*K81 -> 3424.95 | O81: =(SUM(M79:M85)/'BIOMETRIA HEMATICA'!B2)+M92 -> 1.5308975 | P81: =((O81*0.15)+O81) -> 1.7605322 | Q81: =P81*'BIOMETRIA HEMATICA'!B78 -> 0 | R81: =O81*'BIOMETRIA HEMATICA'!B78 -> 0
B82: 7837984001 | C82: WDF Lysercell WDF | D82: 2450 | E82: 90 | F82: ='BIOMETRIA HEMATICA'!$B$2 -> 12200 | G82: =F82/D82 -> 4.9795918 | H82: =(360/E82)*'BIOMETRIA HEMATICA'!$B$10 -> 4 | I82: =IF(G82>H82,G82,H82) -> 4.9795918 | K82: =ROUNDUP(I82,0) -> 5 | L82: 176 | M82: =L82*K82 -> 880
B83: 6510256001 | C83: WDF Fluorocell WDF 2X42 ML | D83: 3400 | E83: 180 | F83: ='BIOMETRIA HEMATICA'!$B$2 -> 12200 | G83: =F83/D83 -> 3.5882353 | H83: =(360/E83)*'BIOMETRIA HEMATICA'!$B$10 -> 2 | I83: =IF(G83>H83,G83,H83) -> 3.5882353 | K83: =ROUNDUP(I83,0) -> 4 | L83: 862 | M83: =L83*K83 -> 3448
B84: 6952291001 | C84: CELLCLEAN AUTO 4 ML X 20 | D84: =(((F79/30)/12)*E84) -> 5083.3333 | E84: 150 | F84: ='BIOMETRIA HEMATICA'!$B$2 -> 12200 | G84: =F84/D84 -> 2.4 | H84: =(360/E84)*'BIOMETRIA HEMATICA'!$B$10 -> 2.4 | I84: =IF(G84>H84,G84,H84) -> 2.4 | K84: =ROUNDUP(I84,0) -> 3 | L84: 52 | M84: =L84*K84 -> 156
B85: 7051506001 | C85: XN Check 12x3.0ml Level 1,2,3 | D85: =(((F79/30)/12)*E85) -> 1897.7778 | E85: 56 | F85: ='BIOMETRIA HEMATICA'!$B$2 -> 12200 | G85: =F85/D85 -> 6.4285714 | H85: =(360/E85)*'BIOMETRIA HEMATICA'!$B$10 -> 6.4285714 | I85: =IF(G85>H85,G85,H85) -> 6.4285714 | L85: 544 | M85: =L85*K85 -> 0
A86: Reticulocitos | B86: 6510272001 | C86: FLUOROCELL RET 2 X 12ML | D86: 650 | E86: 180 | F86: ='BIOMETRIA HEMATICA'!$D$2 -> 0 | G86: =F86/D86 -> 0 | H86: =(360/E86)*'BIOMETRIA HEMATICA'!$B$10 -> 2 | I86: =IF(G86>H86,G86,H86) -> 2 | J86: =IF(G86=0,0,G86) -> 0 | L86: 1705 | M86: =L86*K86 -> 0
B87: 9426752001 | C87: CELLPACK DFL 1 L | D87: 450 | E87: 60 | F87: ='BIOMETRIA HEMATICA'!$D$2 -> 0 | G87: =F87/D87 -> 0 | H87: =(360/E87)*'BIOMETRIA HEMATICA'!$B$10 -> 6 | I87: =IF(G87>H87,G87,H87) -> 6 | J87: =IF(G87=0,0,G87) -> 0 | L87: 34 | M87: =L87*K87 -> 0
A88: Líquidos | B88: 7051409001 | C88: XN-Check BF 6x3.0ml Level 1,2 | D88: =(((F79/30)/12)*E88) -> 1897.7778 | E88: 56 | F88: ='BIOMETRIA HEMATICA'!$H$2 -> 0 | G88: =F88/D88 -> 0 | H88: =(360/E88)*'BIOMETRIA HEMATICA'!$B$10 -> 6.4285714 | I88: =IF(G88>H88,G88,H88) -> 6.4285714 | J88: =IF(G67=0,0,G88) -> 0 | L88: 661 | M88: =L88*K88 -> 0
C90: ADICIONALES | K90: ='BIOMETRIA HEMATICA'!B6 -> 12 | L90: =BC!F109 -> 1920 | M90: =(L90/K90)*K90 -> 1920
C91: ALQUILER | L91: 615 | M91: =(L91*K90)/(12) -> 615
C92: EQUIPO | L92: 28941 | M92: =((((L91)*(K90))/'BIOMETRIA HEMATICA'!B2)) -> 0.60491803
A96: XNL-550 CON LICENCIAS
A97: Parámetro | B97: ID | C97: PRODUCTO | D97: DET/KIT | E97: DIAS ESTABILIDAD | F97: DET/AÑO PROCESO | G97: PRODUCTO CALCULADO | H97: MINIMOS POR ESTABILIDAD | I97: PRODUCTO A ENTREGAR | K97: REDONDEADO A ENTREGAR | L97: PVP | M97: TOTAL | O97: PVP BIOMETRIA COMPLETA | P97: PARA PROCESO | Q97: VALOR INICIAL DEL PROCESO | R97: VALOR FINAL DEL PROCESO
A98: Biometria básica | B98: 6510167001 | C98: CELLPACK DCL | D98: 450 | E98: 60 | F98: ='BIOMETRIA HEMATICA'!$B$2-'BIOMETRIA HEMATICA'!$D$2 -> 12200 | G98: =F98/D98 -> 27.111111 | H98: =(360/E98)*'BIOMETRIA HEMATICA'!$B$10 -> 6 | I98: =IF(G98>H98,G98,H98) -> 27.111111 | K98: =ROUNDUP(I98,0) -> 28 | L98: 121 | M98: =L98*K98 -> 3388 | O98: =(SUM(M98:M107)/'BIOMETRIA HEMATICA'!B2)+M111 -> 3.1563893 | P98: =((O98*0.15)+O98) -> 3.6298477 | Q98: =P98*'BIOMETRIA HEMATICA'!B97 -> 0 | R98: =O98*'BIOMETRIA HEMATICA'!B97 -> 0
B99: 3337006001 | C99: SULFOLYSER REAGENT X 5L | D99: 9450 | E99: 60 | F99: ='BIOMETRIA HEMATICA'!$B$2-'BIOMETRIA HEMATICA'!$D$2 -> 12200 | G99: =F99/D99 -> 1.2910053 | H99: =(360/E99)*'BIOMETRIA HEMATICA'!$B$10 -> 6 | I99: =IF(G99>H99,G99,H99) -> 6 | J99: =IF(N99>N100,0,I99) -> 0 | K99: =ROUNDUP(I99,0) -> 6 | L99: 1107 | M99: =L99*K99 -> 6642 | N99: =L99*K99 -> 6642 | O99: PVP BIOMETRIA | P99: PARA PROCESO | Q99: VALOR INICIAL DEL PROCESO | R99: VALOR FINAL DEL PROCESO
B100: 12215616001 | C100: SULFOLYSER REAGENT 500 ml | D100: 850 | E100: 60 | F100: ='BIOMETRIA HEMATICA'!$B$2-'BIOMETRIA HEMATICA'!$D$2 -> 12200 | G100: =F100/D100 -> 14.352941 | H100: =(360/E100)*'BIOMETRIA HEMATICA'!$B$10 -> 6 | I100: =IF(G100>H100,G100,H100) -> 14.352941 | J100: =IF(N100>N99,0,I100) -> 14.352941 | K100: =ROUNDUP(I100,0) -> 15 | L100: 228.33 | M100: =L100*K100 -> 3424.95 | N100: =L100*K100 -> 3424.95 | O100: =(SUM(M98:M104)/'BIOMETRIA HEMATICA'!B2)+M111 -> 2.4808975 | P100: =((O100*0.15)+O100) -> 2.8530322 | Q100: =P100*'BIOMETRIA HEMATICA'!B97 -> 0 | R100: =O100*'BIOMETRIA HEMATICA'!B97 -> 0
B101: 7837984001 | C101: WDF Lysercell WDF | D101: 2450 | E101: 90 | F101: ='BIOMETRIA HEMATICA'!$B$2-'BIOMETRIA HEMATICA'!$D$2 -> 12200 | G101: =F101/D101 -> 4.9795918 | H101: =(360/E101)*'BIOMETRIA HEMATICA'!$B$10 -> 4 | I101: =IF(G101>H101,G101,H101) -> 4.9795918 | K101: =ROUNDUP(I101,0) -> 5 | L101: 176 | M101: =L101*K101 -> 880
B102: 6510256001 | C102: WDF Fluorocell WDF 2X42 ML | D102: 3400 | E102: 180 | F102: ='BIOMETRIA HEMATICA'!$B$2-'BIOMETRIA HEMATICA'!$D$2 -> 12200 | G102: =F102/D102 -> 3.5882353 | H102: =(360/E102)*'BIOMETRIA HEMATICA'!$B$10 -> 2 | I102: =IF(G102>H102,G102,H102) -> 3.5882353 | K102: =ROUNDUP(I102,0) -> 4 | L102: 862 | M102: =L102*K102 -> 3448
B103: 6952291001 | C103: CELLCLEAN AUTO 4 ML X 20 | D103: =(((F98/30)/12)*E103) -> 5083.3333 | E103: 150 | F103: ='BIOMETRIA HEMATICA'!$B$2-'BIOMETRIA HEMATICA'!$D$2 -> 12200 | G103: =F103/D103 -> 2.4 | H103: =(360/E103)*'BIOMETRIA HEMATICA'!$B$10 -> 2.4 | I103: =IF(G103>H103,G103,H103) -> 2.4 | K103: =ROUNDUP(I103,0) -> 3 | L103: 52 | M103: =L103*K103 -> 156
B104: 7051506001 | C104: XN Check 12x3.0ml Level 1,2,3 | D104: =(((F98/30)/12)*E104) -> 1897.7778 | E104: 56 | F104: ='BIOMETRIA HEMATICA'!$B$2-'BIOMETRIA HEMATICA'!$D$2 -> 12200 | G104: =F104/D104 -> 6.4285714 | H104: =(360/E104)*'BIOMETRIA HEMATICA'!$B$10 -> 6.4285714 | I104: =IF(G104>H104,G104,H104) -> 6.4285714 | K104: =ROUNDUP(I104,0) -> 7 | L104: 544 | M104: =L104*K104 -> 3808
A105: Reticulocitos | B105: 6510272001 | C105: FLUOROCELL RET 2 X 12ML | D105: 650 | E105: 180 | F105: ='BIOMETRIA HEMATICA'!$D$2 -> 0 | G105: =F105/D105 -> 0 | H105: =(360/E105)*'BIOMETRIA HEMATICA'!$B$10 -> 2 | I105: =IF(G105>H105,G105,H105) -> 2 | J105: =IF(G105=0,0,G105) -> 0 | K105: =ROUNDUP(I105,0) -> 2 | L105: 1705 | M105: =L105*K105 -> 3410
B106: 9426752001 | C106: CELLPACK DFL 1 L | D106: 450 | E106: 60 | F106: ='BIOMETRIA HEMATICA'!$D$2 -> 0 | G106: =F106/D106 -> 0 | H106: =(360/E106)*'BIOMETRIA HEMATICA'!$B$10 -> 6 | I106: =IF(G106>H106,G106,H106) -> 6 | J106: =IF(G106=0,0,G106) -> 0 | K106: =ROUNDUP(I106,0) -> 6 | L106: 34 | M106: =L106*K106 -> 204
A107: Líquidos | B107: 7051409001 | C107: XN-Check BF 6x3.0ml Level 1,2 | D107: =(((F98/30)/12)*E107) -> 1897.7778 | E107: 56 | F107: ='BIOMETRIA HEMATICA'!$H$2 -> 0 | G107: =F107/D107 -> 0 | H107: =(360/E107)*'BIOMETRIA HEMATICA'!$B$10 -> 6.4285714 | I107: =IF(G107>H107,G107,H107) -> 6.4285714 | J107: =IF(G86=0,0,G107) -> 0 | K107: =ROUNDUP(I107,0) -> 7 | L107: 661 | M107: =L107*K107 -> 4627
C109: ADICIONALES | K109: ='BIOMETRIA HEMATICA'!B6 -> 12 | L109: =BC!F109 -> 1920 | M109: =(L109/K109)*K109 -> 1920
C110: ALQUILER | L110: 710 | M110: =(L110*K109)/(12) -> 710
C111: EQUIPO | L111: 36850 | M111: =((((L110)*(K109))/'BIOMETRIA HEMATICA'!B2)) -> 0.69836066
A115: XN-1000 SIN LICENCIAS
A116: Parámetro | B116: ID | C116: PRODUCTO | D116: DET/KIT | E116: DIAS ESTABILIDAD | F116: DET/AÑO PROCESO | G116: PRODUCTO CALCULADO | H116: MINIMOS POR ESTABILIDAD | I116: PRODUCTO A ENTREGAR | K116: REDONDEADO A ENTREGAR | L116: PVP | M116: TOTAL | O116: PVP BIOMETRIA COMPLETA | P116: PARA PROCESO | Q116: VALOR INICIAL DEL PROCESO | R116: VALOR FINAL DEL PROCESO
A117: Biometria básica | B117: 6510167001 | C117: CELLPACK DCL | D117: 450 | E117: 60 | F117: ='BIOMETRIA HEMATICA'!$B$2 -> 12200 | G117: =F117/D117 -> 27.111111 | H117: =(360/E117)*'BIOMETRIA HEMATICA'!$B$10 -> 6 | I117: =IF(G117>H117,G117,H117) -> 27.111111 | K117: =ROUNDUP(I117,0) -> 28 | L117: 121 | M117: =L117*K117 -> 3388 | O117: =(SUM(M117:M130)/'BIOMETRIA HEMATICA'!B2)+M134 -> 5.3624549 | P117: =((O117*0.15)+O117) -> 6.1668232 | Q117: =P117*'BIOMETRIA HEMATICA'!B116 -> 0 | R117: =O117*'BIOMETRIA HEMATICA'!B116 -> 0
B118: 3337006001 | C118: SULFOLYSER REAGENT X 5L | D118: 9450 | E118: 60 | F118: ='BIOMETRIA HEMATICA'!$B$2 -> 12200 | G118: =F118/D118 -> 1.2910053 | H118: =(360/E118)*'BIOMETRIA HEMATICA'!$B$10 -> 6 | I118: =IF(G118>H118,G118,H118) -> 6 | J118: =IF(N118>N119,0,I118) -> 0 | K118: =ROUNDUP(I118,0) -> 6 | L118: 1107 | M118: =L118*K118 -> 6642 | N118: =L118*K118 -> 6642 | O118: PVP BIOMETRIA | P118: PARA PROCESO | Q118: VALOR INICIAL DEL PROCESO | R118: VALOR FINAL DEL PROCESO
B119: 12215616001 | C119: SULFOLYSER REAGENT 500 ml | D119: 850 | E119: 60 | F119: ='BIOMETRIA HEMATICA'!$B$2 -> 12200 | G119: =F119/D119 -> 14.352941 | H119: =(360/E119)*'BIOMETRIA HEMATICA'!$B$10 -> 6 | I119: =IF(G119>H119,G119,H119) -> 14.352941 | J119: =IF(N119>N118,0,I119) -> 14.352941 | K119: =ROUNDUP(I119,0) -> 15 | L119: 228.33 | M119: =L119*K119 -> 3424.95 | N119: =L119*K119 -> 3424.95 | O119: =(SUM(M117:M125)/'BIOMETRIA HEMATICA'!B2)+M134 -> 4.5808975 | P119: =((O119*0.15)+O119) -> 5.2680322 | Q119: =P119*'BIOMETRIA HEMATICA'!B116 -> 0 | R119: =O119*'BIOMETRIA HEMATICA'!B116 -> 0
B120: 7837984001 | C120: WDF Lysercell WDF | D120: 2450 | E120: 90 | F120: ='BIOMETRIA HEMATICA'!$B$2 -> 12200 | G120: =F120/D120 -> 4.9795918 | H120: =(360/E120)*'BIOMETRIA HEMATICA'!$B$10 -> 4 | I120: =IF(G120>H120,G120,H120) -> 4.9795918 | K120: =ROUNDUP(I120,0) -> 5 | L120: 176 | M120: =L120*K120 -> 880
B121: 6510256001 | C121: WDF Fluorocell WDF 2X42 ML | D121: 3400 | E121: 180 | F121: ='BIOMETRIA HEMATICA'!$B$2 -> 12200 | G121: =F121/D121 -> 3.5882353 | H121: =(360/E121)*'BIOMETRIA HEMATICA'!$B$10 -> 2 | I121: =IF(G121>H121,G121,H121) -> 3.5882353 | K121: =ROUNDUP(I121,0) -> 4 | L121: 862 | M121: =L121*K121 -> 3448
B122: 6510248001 | C122: FLUOROCELL WNR 2 X 82ML | D122: 6945 | E122: 180 | F122: ='BIOMETRIA HEMATICA'!$B$2 -> 12200 | G122: =F122/D122 -> 1.7566595 | H122: =(360/E122)*'BIOMETRIA HEMATICA'!$B$10 -> 2 | I122: =IF(G122>H122,G122,H122) -> 2 | K122: =ROUNDUP(I122,0) -> 2 | L122: 634 | M122: =L122*K122 -> 1268
B123: 7838000001 | C123: LYSERCELL-WNR WNR-210A | D123: 2950 | E123: 90 | F123: ='BIOMETRIA HEMATICA'!$B$2 -> 12200 | G123: =F123/D123 -> 4.1355932 | H123: =(360/E123)*'BIOMETRIA HEMATICA'!$B$10 -> 4 | I123: =IF(G123>H123,G123,H123) -> 4.1355932 | K123: =ROUNDUP(I123,0) -> 5 | L123: 128 | M123: =L123*K123 -> 640
B124: 6952291001 | C124: CELLCLEAN AUTO 4 ML X 20 | D124: =(((F117/30)/12)*E124) -> 5083.3333 | E124: 150 | F124: ='BIOMETRIA HEMATICA'!$B$2 -> 12200 | G124: =F124/D124 -> 2.4 | H124: =(360/E124)*'BIOMETRIA HEMATICA'!$B$10 -> 2.4 | I124: =IF(G124>H124,G124,H124) -> 2.4 | K124: =ROUNDUP(I124,0) -> 3 | L124: 52 | M124: =L124*K124 -> 156
...

Sheet PRUEBA EFECTIVA XN
A1: XNL-350 SIN LICENCIAS
A2: Parámetro | B2: ID | C2: PRODUCTO | D2: DET/KIT | E2: DIAS ESTABILIDAD | F2: DET/AÑO PROCESO | G2: PRODUCTO CALCULADO | H2: MINIMOS POR ESTABILIDAD | I2: PRODUCTO A ENTREGAR | K2: REDONDEADO A ENTREGAR | L2: PVP | M2: TOTAL | O2: PVP BIOMETRIA COMPLETA | P2: PARA PROCESO | Q2: VALOR INICIAL DEL PROCESO | R2: VALOR FINAL DEL PROCESO
A3: Biometria básica | B3: 6510167001 | C3: CELLPACK DCL | D3: 450 | E3: 60 | F3: =(('BIOMETRIA HEMATICA'!$B$2)*0.2)+('BIOMETRIA HEMATICA'!$B$2) -> 14640 | G3: =F3/D3 -> 32.533333 | H3: =(360/E3)*'BIOMETRIA HEMATICA'!$B$10 -> 6 | I3: =IF(G3>H3,G3,H3) -> 32.533333 | K3: =ROUNDUP(I3,0) -> 33 | L3: 121 | M3: =L3*K3 -> 3993 | O3: =(SUM(M3:N12)/'BIOMETRIA HEMATICA'!B2)+M16 -> 3.9924492 | P3: =((O3*0.15)+O3) -> 4.5913166 | Q3: =P3*'BIOMETRIA HEMATICA'!B2 -> 56014.062 | R3: =O3*'BIOMETRIA HEMATICA'!B2 -> 48707.88
B4: 3337006001 | C4: SULFOLYSER REAGENT X 5L | D4: 9450 | E4: 60 | F4: =(('BIOMETRIA HEMATICA'!$B$2)*0.2)+('BIOMETRIA HEMATICA'!$B$2) -> 14640 | G4: =F4/D4 -> 1.5492063 | H4: =(360/E4)*'BIOMETRIA HEMATICA'!$B$10 -> 6 | I4: =IF(G4>H4,G4,H4) -> 6 | J4: =IF(N4>N5,0,I4) -> 0 | K4: =ROUNDUP(I4,0) -> 6 | L4: 1107 | M4: =L4*K4 -> 6642 | N4: =L4*K4 -> 6642 | O4: PVP BIOMETRIA | P4: PARA PROCESO | Q4: VALOR INICIAL DEL PROCESO | R4: VALOR FINAL DEL PROCESO
B5: 12215616001 | C5: SULFOLYSER REAGENT 500 ml | D5: 850 | E5: 60 | F5: =(('BIOMETRIA HEMATICA'!$B$2)*0.2)+('BIOMETRIA HEMATICA'!$B$2) -> 14640 | G5: =F5/D5 -> 17.223529 | H5: =(360/E5)*'BIOMETRIA HEMATICA'!$B$10 -> 6 | I5: =IF(G5>H5,G5,H5) -> 17.223529 | J5: =IF(N5>N4,0,I5) -> 17.223529 | K5: =ROUNDUP(I5,0) -> 18 | L5: 228.33 | M5: =L5*K5 -> 4109.94 | N5: =L5*K5 -> 4109.94 | O5: =(SUM(M3:N9)/'BIOMETRIA HEMATICA'!B2)+M16 -> 3.3169574 | P5: =((O5*0.15)+O5) -> 3.814501 | Q5: =P5*'BIOMETRIA HEMATICA'!B2 -> 46536.912 | R5: =O5*'BIOMETRIA HEMATICA'!B2 -> 40466.88
B6: 7837984001 | C6: WDF Lysercell WDF | D6: 2450 | E6: 90 | F6: =(('BIOMETRIA HEMATICA'!$B$2)*0.2)+('BIOMETRIA HEMATICA'!$B$2) -> 14640 | G6: =F6/D6 -> 5.9755102 | H6: =(360/E6)*'BIOMETRIA HEMATICA'!$B$10 -> 4 | I6: =IF(G6>H6,G6,H6) -> 5.9755102 | K6: =ROUNDUP(I6,0) -> 6 | L6: 176 | M6: =L6*K6 -> 1056
B7: 6510256001 | C7: WDF Fluorocell WDF 2X42 ML | D7: 3400 | E7: 180 | F7: =(('BIOMETRIA HEMATICA'!$B$2)*0.2)+('BIOMETRIA HEMATICA'!$B$2) -> 14640 | G7: =F7/D7 -> 4.3058824 | H7: =(360/E7)*'BIOMETRIA HEMATICA'!$B$10 -> 2 | I7: =IF(G7>H7,G7,H7) -> 4.3058824 | K7: =ROUNDUP(I7,0) -> 5 | L7: 862 | M7: =L7*K7 -> 4310
B8: 6952291001 | C8: CELLCLEAN AUTO 4 ML X 20 | D8: =(((F3/30)/12)*E8) -> 6100 | E8: 150 | F8: =(('BIOMETRIA HEMATICA'!$B$2)*0.2)+('BIOMETRIA HEMATICA'!$B$2) -> 14640 | G8: =F8/D8 -> 2.4 | H8: =(360/E8)*'BIOMETRIA HEMATICA'!$B$10 -> 2.4 | I8: =IF(G8>H8,G8,H8) -> 2.4 | K8: =ROUNDUP(I8,0) -> 3 | L8: 52 | M8: =L8*K8 -> 156
B9: 7051506001 | C9: XN Check 12x3.0ml Level 1,2,3 | D9: =(((F3/30)/12)*E9) -> 2277.3333 | E9: 56 | F9: =(('BIOMETRIA HEMATICA'!$B$2)*0.2)+('BIOMETRIA HEMATICA'!$B$2) -> 14640 | G9: =F9/D9 -> 6.4285714 | H9: =(360/E9)*'BIOMETRIA HEMATICA'!$B$10 -> 6.4285714 | I9: =IF(G9>H9,G9,H9) -> 6.4285714 | K9: =ROUNDUP(I9,0) -> 7 | L9: 544 | M9: =L9*K9 -> 3808
A10: Reticulocitos | B10: 6510272001 | C10: FLUOROCELL RET 2 X 12ML | D10: 650 | E10: 180 | F10: =(('BIOMETRIA HEMATICA'!$D$2)*0.2)+('BIOMETRIA HEMATICA'!$D$2) -> 0 | G10: =F10/D10 -> 0 | H10: =(360/E10)*'BIOMETRIA HEMATICA'!$B$10 -> 2 | I10: =IF(G10>H10,G10,H10) -> 2 | J10: =IF(G10=0,0,G10) -> 0 | K10: =ROUNDUP(I10,0) -> 2 | L10: 1705 | M10: =L10*K10 -> 3410
B11: 9426752001 | C11: CELLPACK DFL 1 L | D11: 450 | E11: 60 | F11: =(('BIOMETRIA HEMATICA'!$D$2)*0.2)+('BIOMETRIA HEMATICA'!$D$2) -> 0 | G11: =F11/D11 -> 0 | H11: =(360/E11)*'BIOMETRIA HEMATICA'!$B$10 -> 6 | I11: =IF(G11>H11,G11,H11) -> 6 | J11: =IF(G11=0,0,G11) -> 0 | K11: =ROUNDUP(I11,0) -> 6 | L11: 34 | M11: =L11*K11 -> 204
A12: Líquidos | B12: 7051409001 | C12: XN-Check BF 6x3.0ml Level 1,2 | D12: =(((F3/30)/12)*E12) -> 2277.3333 | E12: 56 | F12: =(('BIOMETRIA HEMATICA'!$H$2)*0.2)+('BIOMETRIA HEMATICA'!$H$2) -> 0 | G12: =F12/D12 -> 0 | H12: =(360/E12)*'BIOMETRIA HEMATICA'!$B$10 -> 6.4285714 | I12: =IF(G12>H12,G12,H12) -> 6.4285714 | J12: =IF(G12=0,0,G12) -> 0 | K12: =ROUNDUP(I12,0) -> 7 | L12: 661 | M12: =L12*K12 -> 4627
C14: ADICIONALES | K14: ='BIOMETRIA HEMATICA'!B6 -> 12 | L14: =BC!F109 -> 1920 | M14: =(L14/K14)*K14 -> 1920
C15: ALQUILER | L15: 470 | M15: =(L15*K14)/(12) -> 470
C16: EQUIPO | L16: 21362 | M16: =((((L15)*(K14))/'BIOMETRIA HEMATICA'!B2)) -> 0.46229508
A20: XNL-350 CON LICENCIAS
A21: Parámetro | B21: ID | C21: PRODUCTO | D21: DET/KIT | E21: DIAS ESTABILIDAD | F21: DET/AÑO PROCESO | G21: PRODUCTO CALCULADO | H21: MINIMOS POR ESTABILIDAD | I21: PRODUCTO A ENTREGAR | K21: REDONDEADO A ENTREGAR | L21: PVP | M21: TOTAL | O21: PVP BIOMETRIA | P21: PARA PROCESO | Q21: VALOR INICIAL DEL PROCESO | R21: VALOR FINAL DEL PROCESO
A22: Biometria básica | B22: 6510167001 | C22: CELLPACK DCL | D22: 450 | E22: 60 | F22: =(('BIOMETRIA HEMATICA'!$B$2)*0.2)+('BIOMETRIA HEMATICA'!$B$2) -> 14640 | G22: =F22/D22 -> 32.533333 | H22: =(360/E22)*'BIOMETRIA HEMATICA'!$B$10 -> 6 | I22: =IF(G22>H22,G22,H22) -> 32.533333 | K22: =ROUNDUP(I22,0) -> 33 | L22: 121 | M22: =L22*K22 -> 3993 | O22: =(SUM(M22:M34)/'BIOMETRIA HEMATICA'!B2)+M35 -> 3.4136016 | P22: =((O22*0.15)+O22) -> 3.9256419 | Q22: =P22*'BIOMETRIA HEMATICA'!B2 -> 47892.831 | R22: =O22*'BIOMETRIA HEMATICA'!B2 -> 41645.94
B23: 3337006001 | C23: SULFOLYSER REAGENT X 5L | D23: 9450 | E23: 60 | F23: =(('BIOMETRIA HEMATICA'!$B$2)*0.2)+('BIOMETRIA HEMATICA'!$B$2) -> 14640 | G23: =F23/D23 -> 1.5492063 | H23: =(360/E23)*'BIOMETRIA HEMATICA'!$B$10 -> 6 | I23: =IF(G23>H23,G23,H23) -> 6 | J23: =IF(N23>N24,0,I23) -> 0 | K23: =ROUNDUP(I23,0) -> 6 | L23: 1107 | M23: =L23*K23 -> 6642 | N23: =L23*K23 -> 6642
B24: 12215616001 | C24: SULFOLYSER REAGENT 500 ml | D24: 850 | E24: 60 | F24: =(('BIOMETRIA HEMATICA'!$B$2)*0.2)+('BIOMETRIA HEMATICA'!$B$2) -> 14640 | G24: =F24/D24 -> 17.223529 | H24: =(360/E24)*'BIOMETRIA HEMATICA'!$B$10 -> 6 | I24: =IF(G24>H24,G24,H24) -> 17.223529 | J24: =IF(N24>N23,0,I24) -> 17.223529 | K24: =ROUNDUP(I24,0) -> 18 | L24: 228.33 | M24: =L24*K24 -> 4109.94 | N24: =L24*K24 -> 4109.94
B25: 7837984001 | C25: WDF Lysercell WDF | D25: 2450 | E25: 90 | F25: =(('BIOMETRIA HEMATICA'!$B$2)*0.2)+('BIOMETRIA HEMATICA'!$B$2) -> 14640 | G25: =F25/D25 -> 5.9755102 | H25: =(360/E25)*'BIOMETRIA HEMATICA'!$B$10 -> 4 | I25: =IF(G25>H25,G25,H25) -> 5.9755102 | K25: =ROUNDUP(I25,0) -> 6 | L25: 176 | M25: =L25*K25 -> 1056
B26: 6510256001 | C26: WDF Fluorocell WDF 2X42 ML | D26: 3400 | E26: 180 | F26: =(('BIOMETRIA HEMATICA'!$B$2)*0.2)+('BIOMETRIA HEMATICA'!$B$2) -> 14640 | G26: =F26/D26 -> 4.3058824 | H26: =(360/E26)*'BIOMETRIA HEMATICA'!$B$10 -> 2 | I26: =IF(G26>H26,G26,H26) -> 4.3058824 | K26: =ROUNDUP(I26,0) -> 5 | L26: 862 | M26: =L26*K26 -> 4310
B27: 6952291001 | C27: CELLCLEAN AUTO 4 ML X 20 | D27: =(((F22/30)/12)*E27) -> 6100 | E27: 150 | F27: =(('BIOMETRIA HEMATICA'!$B$2)*0.2)+('BIOMETRIA HEMATICA'!$B$2) -> 14640 | G27: =F27/D27 -> 2.4 | H27: =(360/E27)*'BIOMETRIA HEMATICA'!$B$10 -> 2.4 | I27: =IF(G27>H27,G27,H27) -> 2.4 | K27: =ROUNDUP(I27,0) -> 3 | L27: 52 | M27: =L27*K27 -> 156
B28: 7051506001 | C28: XN Check 12x3.0ml Level 1,2,3 | D28: =(((F22/30)/12)*E28) -> 2277.3333 | E28: 56 | F28: =(('BIOMETRIA HEMATICA'!$B$2)*0.2)+('BIOMETRIA HEMATICA'!$B$2) -> 14640 | G28: =F28/D28 -> 6.4285714 | H28: =(360/E28)*'BIOMETRIA HEMATICA'!$B$10 -> 6.4285714 | I28: =IF(G28>H28,G28,H28) -> 6.4285714 | K28: =ROUNDUP(I28,0) -> 7 | L28: 544 | M28: =L28*K28 -> 3808
A29: Reticulocitos | B29: 6510272001 | C29: FLUOROCELL RET 2 X 12ML | D29: 650 | E29: 180 | F29: =(('BIOMETRIA HEMATICA'!$D$2)*0.2)+('BIOMETRIA HEMATICA'!$D$2) -> 0 | G29: =F29/D29 -> 0 | H29: =(360/E29)*'BIOMETRIA HEMATICA'!$B$10 -> 2 | I29: =IF(G29>H29,G29,H29) -> 2 | J29: =IF(G29=0,0,G29) -> 0 | K29: =ROUNDUP(I29,0) -> 2 | L29: 1705 | M29: =L29*K29 -> 3410
B30: 9426752001 | C30: CELLPACK DFL 1 L | D30: 450 | E30: 60 | F30: =(('BIOMETRIA HEMATICA'!$D$2)*0.2)+('BIOMETRIA HEMATICA'!$D$2) -> 0 | G30: =F30/D30 -> 0 | H30: =(360/E30)*'BIOMETRIA HEMATICA'!$B$10 -> 6 | I30: =IF(G30>H30,G30,H30) -> 6 | J30: =IF(G30=0,0,G30) -> 0 | K30: =ROUNDUP(I30,0) -> 6 | L30: 34 | M30: =L30*K30 -> 204
A31: Líquidos | B31: 7051409001 | C31: XN-Check BF 6x3.0ml Level 1,2 | D31: =(((F22/30)/12)*E31) -> 2277.3333 | E31: 56 | F31: =(('BIOMETRIA HEMATICA'!$H$2)*0.2)+('BIOMETRIA HEMATICA'!$H$2) -> 0 | G31: =F31/D31 -> 0 | H31: =(360/E31)*'BIOMETRIA HEMATICA'!$B$10 -> 6.4285714 | I31: =IF(G31>H31,G31,H31) -> 6.4285714 | J31: =IF(G10=0,0,G31) -> 0 | K31: =ROUNDUP(I31,0) -> 7 | L31: 661 | M31: =L31*K31 -> 4627
C33: ADICIONALES | K33: ='BIOMETRIA HEMATICA'!B6 -> 12 | L33: =BC!F109 -> 1920 | M33: =(L33/K33)*K33 -> 1920
C34: MANTENIMIENTO/REPUESTOS | L34: 570 | M34: =(L34*K33)/(12) -> 570
C35: EQUIPO | L35: 29260 | M35: =((((L34)*(K33))/'BIOMETRIA HEMATICA'!B2)) -> 0.56065574
A39: XNL-450 SIN LICENCIAS
A40: Parámetro | B40: ID | C40: PRODUCTO | D40: DET/KIT | E40: DIAS ESTABILIDAD | F40: DET/AÑO PROCESO | G40: PRODUCTO CALCULADO | H40: MINIMOS POR ESTABILIDAD | I40: PRODUCTO A ENTREGAR | K40: REDONDEADO A ENTREGAR | L40: PVP | M40: TOTAL | O40: PVP BIOMETRIA COMPLETA | P40: PARA PROCESO | Q40: VALOR INICIAL DEL PROCESO | R40: VALOR FINAL DEL PROCESO
A41: Biometria básica | B41: 6510167001 | C41: CELLPACK DCL | D41: 450 | E41: 60 | F41: =(('BIOMETRIA HEMATICA'!$B$2)*0.2)+('BIOMETRIA HEMATICA'!$B$2) -> 14640 | G41: =F41/D41 -> 32.533333 | H41: =(360/E41)*'BIOMETRIA HEMATICA'!$B$10 -> 6 | I41: =IF(G41>H41,G41,H41) -> 32.533333 | K41: =ROUNDUP(I41,0) -> 33 | L41: 121 | M41: =L41*K41 -> 3993 | O41: =(SUM(M41:M50)/'BIOMETRIA HEMATICA'!B2)+M54 -> 3.2095033 | P41: =((O41*0.15)+O41) -> 3.6909288 | Q41: =P41*'BIOMETRIA HEMATICA'!B40 -> 0 | R41: =O41*'BIOMETRIA HEMATICA'!B40 -> 0
B42: 3337006001 | C42: SULFOLYSER REAGENT X 5L | D42: 9450 | E42: 60 | F42: =(('BIOMETRIA HEMATICA'!$B$2)*0.2)+('BIOMETRIA HEMATICA'!$B$2) -> 14640 | G42: =F42/D42 -> 1.5492063 | H42: =(360/E42)*'BIOMETRIA HEMATICA'!$B$10 -> 6 | I42: =IF(G42>H42,G42,H42) -> 6 | J42: =IF(N42>N43,0,I42) -> 0 | K42: =ROUNDUP(I42,0) -> 6 | L42: 1107 | M42: =L42*K42 -> 6642 | N42: =L42*K42 -> 6642 | O42: PVP BIOMETRIA | P42: PARA PROCESO | Q42: VALOR INICIAL DEL PROCESO | R42: VALOR FINAL DEL PROCESO
B43: 12215616001 | C43: SULFOLYSER REAGENT 500 ml | D43: 850 | E43: 60 | F43: =(('BIOMETRIA HEMATICA'!$B$2)*0.2)+('BIOMETRIA HEMATICA'!$B$2) -> 14640 | G43: =F43/D43 -> 17.223529 | H43: =(360/E43)*'BIOMETRIA HEMATICA'!$B$10 -> 6 | I43: =IF(G43>H43,G43,H43) -> 17.223529 | J43: =IF(N43>N42,0,I43) -> 17.223529 | K43: =ROUNDUP(I43,0) -> 18 | L43: 228.33 | M43: =L43*K43 -> 4109.94 | N43: =L43*K43 -> 4109.94 | O43: =(SUM(M41:M47)/'BIOMETRIA HEMATICA'!B2)+M54 -> 2.5340115 | P43: =((O43*0.15)+O43) -> 2.9141132 | Q43: =P43*'BIOMETRIA HEMATICA'!B40 -> 0 | R43: =O43*'BIOMETRIA HEMATICA'!B40 -> 0
B44: 7837984001 | C44: WDF Lysercell WDF | D44: 2450 | E44: 90 | F44: =(('BIOMETRIA HEMATICA'!$B$2)*0.2)+('BIOMETRIA HEMATICA'!$B$2) -> 14640 | G44: =F44/D44 -> 5.9755102 | H44: =(360/E44)*'BIOMETRIA HEMATICA'!$B$10 -> 4 | I44: =IF(G44>H44,G44,H44) -> 5.9755102 | K44: =ROUNDUP(I44,0) -> 6 | L44: 176 | M44: =L44*K44 -> 1056
B45: 6510256001 | C45: WDF Fluorocell WDF 2X42 ML | D45: 3400 | E45: 180 | F45: =(('BIOMETRIA HEMATICA'!$B$2)*0.2)+('BIOMETRIA HEMATICA'!$B$2) -> 14640 | G45: =F45/D45 -> 4.3058824 | H45: =(360/E45)*'BIOMETRIA HEMATICA'!$B$10 -> 2 | I45: =IF(G45>H45,G45,H45) -> 4.3058824 | K45: =ROUNDUP(I45,0) -> 5 | L45: 862 | M45: =L45*K45 -> 4310
B46: 6952291001 | C46: CELLCLEAN AUTO 4 ML X 20 | D46: =(((F41/30)/12)*E46) -> 6100 | E46: 150 | F46: =(('BIOMETRIA HEMATICA'!$B$2)*0.2)+('BIOMETRIA HEMATICA'!$B$2) -> 14640 | G46: =F46/D46 -> 2.4 | H46: =(360/E46)*'BIOMETRIA HEMATICA'!$B$10 -> 2.4 | I46: =IF(G46>H46,G46,H46) -> 2.4 | K46: =ROUNDUP(I46,0) -> 3 | L46: 52 | M46: =L46*K46 -> 156
B47: 7051506001 | C47: XN Check 12x3.0ml Level 1,2,3 | D47: =(((F41/30)/12)*E47) -> 2277.3333 | E47: 56 | F47: =(('BIOMETRIA HEMATICA'!$B$2)*0.2)+('BIOMETRIA HEMATICA'!$B$2) -> 14640 | G47: =F47/D47 -> 6.4285714 | H47: =(360/E47)*'BIOMETRIA HEMATICA'!$B$10 -> 6.4285714 | I47: =IF(G47>H47,G47,H47) -> 6.4285714 | K47: =ROUNDUP(I47,0) -> 7 | L47: 544 | M47: =L47*K47 -> 3808
A48: Reticulocitos | B48: 6510272001 | C48: FLUOROCELL RET 2 X 12ML | D48: 650 | E48: 180 | F48: =(('BIOMETRIA HEMATICA'!$D$2)*0.2)+('BIOMETRIA HEMATICA'!$D$2) -> 0 | G48: =F48/D48 -> 0 | H48: =(360/E48)*'BIOMETRIA HEMATICA'!$B$10 -> 2 | I48: =IF(G48>H48,G48,H48) -> 2 | J48: =IF(G48=0,0,G48) -> 0 | K48: =ROUNDUP(I48,0) -> 2 | L48: 1705 | M48: =L48*K48 -> 3410
B49: 9426752001 | C49: CELLPACK DFL 1 L | D49: 450 | E49: 60 | F49: =(('BIOMETRIA HEMATICA'!$D$2)*0.2)+('BIOMETRIA HEMATICA'!$D$2) -> 0 | G49: =F49/D49 -> 0 | H49: =(360/E49)*'BIOMETRIA HEMATICA'!$B$10 -> 6 | I49: =IF(G49>H49,G49,H49) -> 6 | J49: =IF(G49=0,0,G49) -> 0 | K49: =ROUNDUP(I49,0) -> 6 | L49: 34 | M49: =L49*K49 -> 204
A50: Líquidos | B50: 7051409001 | C50: XN-Check BF 6x3.0ml Level 1,2 | D50: =(((F41/30)/12)*E50) -> 2277.3333 | E50: 56 | F50: =(('BIOMETRIA HEMATICA'!$H$2)*0.2)+('BIOMETRIA HEMATICA'!$H$2) -> 0 | G50: =F50/D50 -> 0 | H50: =(360/E50)*'BIOMETRIA HEMATICA'!$B$10 -> 6.4285714 | I50: =IF(G50>H50,G50,H50) -> 6.4285714 | J50: =IF(G29=0,0,G50) -> 0 | K50: =ROUNDUP(I50,0) -> 7 | L50: 661 | M50: =L50*K50 -> 4627
C52: ADICIONALES | K52: ='BIOMETRIA HEMATICA'!B6 -> 12 | L52: =BC!F109 -> 1920 | M52: =(L52/K52)*K52 -> 1920
C53: MANTENIMIENTO/REPUESTOS | L53: 570 | M53: =(L53*K52)/(12) -> 570
C54: EQUIPO | L54: 26389 | M54: =((((L53)*(K52))/'BIOMETRIA HEMATICA'!B2)) -> 0.56065574
A58: XNL-450 CON LICENCIAS
A59: Parámetro | B59: ID | C59: PRODUCTO | D59: DET/KIT | E59: DIAS ESTABILIDAD | F59: DET/AÑO PROCESO | G59: PRODUCTO CALCULADO | H59: MINIMOS POR ESTABILIDAD | I59: PRODUCTO A ENTREGAR | K59: REDONDEADO A ENTREGAR | L59: PVP | M59: TOTAL | O59: PVP BIOMETRIA COMPLETA | P59: PARA PROCESO | Q59: VALOR INICIAL DEL PROCESO | R59: VALOR FINAL DEL PROCESO
A60: Biometria básica | B60: 6510167001 | C60: CELLPACK DCL | D60: 450 | E60: 60 | F60: =(('BIOMETRIA HEMATICA'!$B$2)*0.2)+('BIOMETRIA HEMATICA'!$B$2) -> 14640 | G60: =F60/D60 -> 32.533333 | H60: =(360/E60)*'BIOMETRIA HEMATICA'!$B$10 -> 6 | I60: =IF(G60>H60,G60,H60) -> 32.533333 | K60: =ROUNDUP(I60,0) -> 33 | L60: 121 | M60: =L60*K60 -> 3993 | O60: =(SUM(M60:M69)/'BIOMETRIA HEMATICA'!B2)+M73 -> 3.3078639 | P60: =((O60*0.15)+O60) -> 3.8040435 | Q60: =P60*'BIOMETRIA HEMATICA'!B59 -> 0 | R60: =O60*'BIOMETRIA HEMATICA'!B59 -> 0
B61: 3337006001 | C61: SULFOLYSER REAGENT X 5L | D61: 9450 | E61: 60 | F61: =(('BIOMETRIA HEMATICA'!$B$2)*0.2)+('BIOMETRIA HEMATICA'!$B$2) -> 14640 | G61: =F61/D61 -> 1.5492063 | H61: =(360/E61)*'BIOMETRIA HEMATICA'!$B$10 -> 6 | I61: =IF(G61>H61,G61,H61) -> 6 | J61: =IF(N61>N62,0,I61) -> 0 | K61: =ROUNDUP(I61,0) -> 6 | L61: 1107 | M61: =L61*K61 -> 6642 | N61: =L61*K61 -> 6642 | O61: PVP BIOMETRIA | P61: PARA PROCESO | Q61: VALOR INICIAL DEL PROCESO | R61: VALOR FINAL DEL PROCESO
B62: 12215616001 | C62: SULFOLYSER REAGENT 500 ml | D62: 850 | E62: 60 | F62: =(('BIOMETRIA HEMATICA'!$B$2)*0.2)+('BIOMETRIA HEMATICA'!$B$2) -> 14640 | G62: =F62/D62 -> 17.223529 | H62: =(360/E62)*'BIOMETRIA HEMATICA'!$B$10 -> 6 | I62: =IF(G62>H62,G62,H62) -> 17.223529 | J62: =IF(N62>N61,0,I62) -> 17.223529 | K62: =ROUNDUP(I62,0) -> 18 | L62: 228.33 | M62: =L62*K62 -> 4109.94 | N62: =L62*K62 -> 4109.94 | O62: =(SUM(M60:M66)/'BIOMETRIA HEMATICA'!B2)+M73 -> 2.6323721 | P62: =((O62*0.15)+O62) -> 3.027228 | Q62: =P62*'BIOMETRIA HEMATICA'!B59 -> 0 | R62: =O62*'BIOMETRIA HEMATICA'!B59 -> 0
B63: 7837984001 | C63: WDF Lysercell WDF | D63: 2450 | E63: 90 | F63: =(('BIOMETRIA HEMATICA'!$B$2)*0.2)+('BIOMETRIA HEMATICA'!$B$2) -> 14640 | G63: =F63/D63 -> 5.9755102 | H63: =(360/E63)*'BIOMETRIA HEMATICA'!$B$10 -> 4 | I63: =IF(G63>H63,G63,H63) -> 5.9755102 | K63: =ROUNDUP(I63,0) -> 6 | L63: 176 | M63: =L63*K63 -> 1056
B64: 6510256001 | C64: WDF Fluorocell WDF 2X42 ML | D64: 3400 | E64: 180 | F64: =(('BIOMETRIA HEMATICA'!$B$2)*0.2)+('BIOMETRIA HEMATICA'!$B$2) -> 14640 | G64: =F64/D64 -> 4.3058824 | H64: =(360/E64)*'BIOMETRIA HEMATICA'!$B$10 -> 2 | I64: =IF(G64>H64,G64,H64) -> 4.3058824 | K64: =ROUNDUP(I64,0) -> 5 | L64: 862 | M64: =L64*K64 -> 4310
B65: 6952291001 | C65: CELLCLEAN AUTO 4 ML X 20 | D65: =(((F60/30)/12)*E65) -> 6100 | E65: 150 | F65: =(('BIOMETRIA HEMATICA'!$B$2)*0.2)+('BIOMETRIA HEMATICA'!$B$2) -> 14640 | G65: =F65/D65 -> 2.4 | H65: =(360/E65)*'BIOMETRIA HEMATICA'!$B$10 -> 2.4 | I65: =IF(G65>H65,G65,H65) -> 2.4 | K65: =ROUNDUP(I65,0) -> 3 | L65: 52 | M65: =L65*K65 -> 156
B66: 7051506001 | C66: XN Check 12x3.0ml Level 1,2,3 | D66: =(((F60/30)/12)*E66) -> 2277.3333 | E66: 56 | F66: =(('BIOMETRIA HEMATICA'!$B$2)*0.2)+('BIOMETRIA HEMATICA'!$B$2) -> 14640 | G66: =F66/D66 -> 6.4285714 | H66: =(360/E66)*'BIOMETRIA HEMATICA'!$B$10 -> 6.4285714 | I66: =IF(G66>H66,G66,H66) -> 6.4285714 | K66: =ROUNDUP(I66,0) -> 7 | L66: 544 | M66: =L66*K66 -> 3808
A67: Reticulocitos | B67: 6510272001 | C67: FLUOROCELL RET 2 X 12ML | D67: 650 | E67: 180 | F67: =(('BIOMETRIA HEMATICA'!$D$2)*0.2)+('BIOMETRIA HEMATICA'!$D$2) -> 0 | G67: =F67/D67 -> 0 | H67: =(360/E67)*'BIOMETRIA HEMATICA'!$B$10 -> 2 | I67: =IF(G67>H67,G67,H67) -> 2 | J67: =IF(G67=0,0,G67) -> 0 | K67: =ROUNDUP(I67,0) -> 2 | L67: 1705 | M67: =L67*K67 -> 3410
B68: 9426752001 | C68: CELLPACK DFL 1 L | D68: 450 | E68: 60 | F68: =(('BIOMETRIA HEMATICA'!$D$2)*0.2)+('BIOMETRIA HEMATICA'!$D$2) -> 0 | G68: =F68/D68 -> 0 | H68: =(360/E68)*'BIOMETRIA HEMATICA'!$B$10 -> 6 | I68: =IF(G68>H68,G68,H68) -> 6 | J68: =IF(G68=0,0,G68) -> 0 | K68: =ROUNDUP(I68,0) -> 6 | L68: 34 | M68: =L68*K68 -> 204
A69: Líquidos | B69: 7051409001 | C69: XN-Check BF 6x3.0ml Level 1,2 | D69: =(((F60/30)/12)*E69) -> 2277.3333 | E69: 56 | F69: =(('BIOMETRIA HEMATICA'!$H$2)*0.2+('BIOMETRIA HEMATICA'!$H$2)) -> 0 | G69: =F69/D69 -> 0 | H69: =(360/E69)*'BIOMETRIA HEMATICA'!$B$10 -> 6.4285714 | I69: =IF(G69>H69,G69,H69) -> 6.4285714 | J69: =IF(G48=0,0,G69) -> 0 | K69: =ROUNDUP(I69,0) -> 7 | L69: 661 | M69: =L69*K69 -> 4627
C71: ADICIONALES | K71: ='BIOMETRIA HEMATICA'!B6 -> 12 | L71: =BC!F109 -> 1920 | M71: =(L71/K71)*K71 -> 1920
C72: MANTENIMIENTO/REPUESTOS | L72: 670 | M72: =(L72*K71)/(12) -> 670
C73: EQUIPO | L73: 34287 | M73: =((((L72)*(K71))/'BIOMETRIA HEMATICA'!B2)) -> 0.65901639
A77: XNL-550 SIN LICENCIAS
A78: Parámetro | B78: ID | C78: PRODUCTO | D78: DET/KIT | E78: DIAS ESTABILIDAD | F78: DET/AÑO PROCESO | G78: PRODUCTO CALCULADO | H78: MINIMOS POR ESTABILIDAD | I78: PRODUCTO A ENTREGAR | K78: REDONDEADO A ENTREGAR | L78: PVP | M78: TOTAL | O78: PVP BIOMETRIA COMPLETA | P78: PARA PROCESO | Q78: VALOR INICIAL DEL PROCESO | R78: VALOR FINAL DEL PROCESO
A79: Biometria básica | B79: 6510167001 | C79: CELLPACK DCL | D79: 450 | E79: 60 | F79: =(('BIOMETRIA HEMATICA'!$B$2)*0.2)+('BIOMETRIA HEMATICA'!$B$2) -> 14640 | G79: =F79/D79 -> 32.533333 | H79: =(360/E79)*'BIOMETRIA HEMATICA'!$B$10 -> 6 | I79: =IF(G79>H79,G79,H79) -> 32.533333 | K79: =ROUNDUP(I79,0) -> 33 | L79: 121 | M79: =L79*K79 -> 3993 | O79: =(SUM(M79:M88)/'BIOMETRIA HEMATICA'!B2)+M92 -> 3.2537656 | P79: =((O79*0.15)+O79) -> 3.7418304 | Q79: =P79*'BIOMETRIA HEMATICA'!B78 -> 0 | R79: =O79*'BIOMETRIA HEMATICA'!B78 -> 0
B80: 3337006001 | C80: SULFOLYSER REAGENT X 5L | D80: 9450 | E80: 60 | F80: =(('BIOMETRIA HEMATICA'!$B$2)*0.2)+('BIOMETRIA HEMATICA'!$B$2) -> 14640 | G80: =F80/D80 -> 1.5492063 | H80: =(360/E80)*'BIOMETRIA HEMATICA'!$B$10 -> 6 | I80: =IF(G80>H80,G80,H80) -> 6 | J80: =IF(N80>N81,0,I80) -> 0 | K80: =ROUNDUP(I80,0) -> 6 | L80: 1107 | M80: =L80*K80 -> 6642 | N80: =L80*K80 -> 6642 | O80: PVP BIOMETRIA | P80: PARA PROCESO | Q80: VALOR INICIAL DEL PROCESO | R80: VALOR FINAL DEL PROCESO
B81: 12215616001 | C81: SULFOLYSER REAGENT 500 ml | D81: 850 | E81: 60 | F81: =(('BIOMETRIA HEMATICA'!$B$2)*0.2)+('BIOMETRIA HEMATICA'!$B$2) -> 14640 | G81: =F81/D81 -> 17.223529 | H81: =(360/E81)*'BIOMETRIA HEMATICA'!$B$10 -> 6 | I81: =IF(G81>H81,G81,H81) -> 17.223529 | J81: =IF(N81>N80,0,I81) -> 17.223529 | K81: =ROUNDUP(I81,0) -> 18 | L81: 228.33 | M81: =L81*K81 -> 4109.94 | N81: =L81*K81 -> 4109.94 | O81: =(SUM(M79:M85)/'BIOMETRIA HEMATICA'!B2)+M92 -> 2.5782738 | P81: =((O81*0.15)+O81) -> 2.9650148 | Q81: =P81*'BIOMETRIA HEMATICA'!B78 -> 0 | R81: =O81*'BIOMETRIA HEMATICA'!B78 -> 0
B82: 7837984001 | C82: WDF Lysercell WDF | D82: 2450 | E82: 90 | F82: =(('BIOMETRIA HEMATICA'!$B$2)*0.2)+('BIOMETRIA HEMATICA'!$B$2) -> 14640 | G82: =F82/D82 -> 5.9755102 | H82: =(360/E82)*'BIOMETRIA HEMATICA'!$B$10 -> 4 | I82: =IF(G82>H82,G82,H82) -> 5.9755102 | K82: =ROUNDUP(I82,0) -> 6 | L82: 176 | M82: =L82*K82 -> 1056
B83: 6510256001 | C83: WDF Fluorocell WDF 2X42 ML | D83: 3400 | E83: 180 | F83: =(('BIOMETRIA HEMATICA'!$B$2)*0.2)+('BIOMETRIA HEMATICA'!$B$2) -> 14640 | G83: =F83/D83 -> 4.3058824 | H83: =(360/E83)*'BIOMETRIA HEMATICA'!$B$10 -> 2 | I83: =IF(G83>H83,G83,H83) -> 4.3058824 | K83: =ROUNDUP(I83,0) -> 5 | L83: 862 | M83: =L83*K83 -> 4310
B84: 6952291001 | C84: CELLCLEAN AUTO 4 ML X 20 | D84: =(((F79/30)/12)*E84) -> 6100 | E84: 150 | F84: =(('BIOMETRIA HEMATICA'!$B$2)*0.2)+('BIOMETRIA HEMATICA'!$B$2) -> 14640 | G84: =F84/D84 -> 2.4 | H84: =(360/E84)*'BIOMETRIA HEMATICA'!$B$10 -> 2.4 | I84: =IF(G84>H84,G84,H84) -> 2.4 | K84: =ROUNDUP(I84,0) -> 3 | L84: 52 | M84: =L84*K84 -> 156
B85: 7051506001 | C85: XN Check 12x3.0ml Level 1,2,3 | D85: =(((F79/30)/12)*E85) -> 2277.3333 | E85: 56 | F85: =(('BIOMETRIA HEMATICA'!$B$2)*0.2)+('BIOMETRIA HEMATICA'!$B$2) -> 14640 | G85: =F85/D85 -> 6.4285714 | H85: =(360/E85)*'BIOMETRIA HEMATICA'!$B$10 -> 6.4285714 | I85: =IF(G85>H85,G85,H85) -> 6.4285714 | K85: =ROUNDUP(I85,0) -> 7 | L85: 544 | M85: =L85*K85 -> 3808
A86: Reticulocitos | B86: 6510272001 | C86: FLUOROCELL RET 2 X 12ML | D86: 650 | E86: 180 | F86: =(('BIOMETRIA HEMATICA'!$D$2)*0.2)+('BIOMETRIA HEMATICA'!$D$2) -> 0 | G86: =F86/D86 -> 0 | H86: =(360/E86)*'BIOMETRIA HEMATICA'!$B$10 -> 2 | I86: =IF(G86>H86,G86,H86) -> 2 | J86: =IF(G86=0,0,G86) -> 0 | K86: =ROUNDUP(I86,0) -> 2 | L86: 1705 | M86: =L86*K86 -> 3410
B87: 9426752001 | C87: CELLPACK DFL 1 L | D87: 450 | E87: 60 | F87: =(('BIOMETRIA HEMATICA'!$D$2)*0.2)+('BIOMETRIA HEMATICA'!$D$2) -> 0 | G87: =F87/D87 -> 0 | H87: =(360/E87)*'BIOMETRIA HEMATICA'!$B$10 -> 6 | I87: =IF(G87>H87,G87,H87) -> 6 | J87: =IF(G87=0,0,G87) -> 0 | K87: =ROUNDUP(I87,0) -> 6 | L87: 34 | M87: =L87*K87 -> 204
A88: Líquidos | B88: 7051409001 | C88: XN-Check BF 6x3.0ml Level 1,2 | D88: =(((F79/30)/12)*E88) -> 2277.3333 | E88: 56 | F88: =(('BIOMETRIA HEMATICA'!$H$2)*0.2)+('BIOMETRIA HEMATICA'!$H$2) -> 0 | G88: =F88/D88 -> 0 | H88: =(360/E88)*'BIOMETRIA HEMATICA'!$B$10 -> 6.4285714 | I88: =IF(G88>H88,G88,H88) -> 6.4285714 | J88: =IF(G67=0,0,G88) -> 0 | K88: =ROUNDUP(I88,0) -> 7 | L88: 661 | M88: =L88*K88 -> 4627
C90: ADICIONALES | K90: ='BIOMETRIA HEMATICA'!B6 -> 12 | L90: =BC!F109 -> 1920 | M90: =(L90/K90)*K90 -> 1920
C91: MANTENIMIENTO/REPUESTOS | L91: 615 | M91: =(L91*K90)/(12) -> 615
C92: EQUIPO | L92: 28941 | M92: =((((L91)*(K90))/'BIOMETRIA HEMATICA'!B2)) -> 0.60491803
A96: XNL-550 CON LICENCIAS
A97: Parámetro | B97: ID | C97: PRODUCTO | D97: DET/KIT | E97: DIAS ESTABILIDAD | F97: DET/AÑO PROCESO | G97: PRODUCTO CALCULADO | H97: MINIMOS POR ESTABILIDAD | I97: PRODUCTO A ENTREGAR | K97: REDONDEADO A ENTREGAR | L97: PVP | M97: TOTAL | O97: PVP BIOMETRIA COMPLETA | P97: PARA PROCESO | Q97: VALOR INICIAL DEL PROCESO | R97: VALOR FINAL DEL PROCESO
A98: Biometria básica | B98: 6510167001 | C98: CELLPACK DCL | D98: 450 | E98: 60 | F98: =(('BIOMETRIA HEMATICA'!$B$2)*0.2)+('BIOMETRIA HEMATICA'!$B$2) -> 14640 | G98: =F98/D98 -> 32.533333 | H98: =(360/E98)*'BIOMETRIA HEMATICA'!$B$10 -> 6 | I98: =IF(G98>H98,G98,H98) -> 32.533333 | K98: =ROUNDUP(I98,0) -> 33 | L98: 121 | M98: =L98*K98 -> 3993 | O98: =(SUM(M98:M107)/'BIOMETRIA HEMATICA'!B2)+M111 -> 3.3472082 | P98: =((O98*0.15)+O98) -> 3.8492894 | Q98: =P98*'BIOMETRIA HEMATICA'!B97 -> 0 | R98: =O98*'BIOMETRIA HEMATICA'!B97 -> 0
B99: 3337006001 | C99: SULFOLYSER REAGENT X 5L | D99: 9450 | E99: 60 | F99: =(('BIOMETRIA HEMATICA'!$B$2)*0.2)+('BIOMETRIA HEMATICA'!$B$2) -> 14640 | G99: =F99/D99 -> 1.5492063 | H99: =(360/E99)*'BIOMETRIA HEMATICA'!$B$10 -> 6 | I99: =IF(G99>H99,G99,H99) -> 6 | J99: =IF(N99>N100,0,I99) -> 0 | K99: =ROUNDUP(I99,0) -> 6 | L99: 1107 | M99: =L99*K99 -> 6642 | N99: =L99*K99 -> 6642 | O99: PVP BIOMETRIA | P99: PARA PROCESO | Q99: VALOR INICIAL DEL PROCESO | R99: VALOR FINAL DEL PROCESO
B100: 12215616001 | C100: SULFOLYSER REAGENT 500 ml | D100: 850 | E100: 60 | F100: =(('BIOMETRIA HEMATICA'!$B$2)*0.2)+('BIOMETRIA HEMATICA'!$B$2) -> 14640 | G100: =F100/D100 -> 17.223529 | H100: =(360/E100)*'BIOMETRIA HEMATICA'!$B$10 -> 6 | I100: =IF(G100>H100,G100,H100) -> 17.223529 | J100: =IF(N100>N99,0,I100) -> 17.223529 | K100: =ROUNDUP(I100,0) -> 18 | L100: 228.33 | M100: =L100*K100 -> 4109.94 | N100: =L100*K100 -> 4109.94 | O100: =(SUM(M98:M104)/'BIOMETRIA HEMATICA'!B2)+M111 -> 2.6717164 | P100: =((O100*0.15)+O100) -> 3.0724739 | Q100: =P100*'BIOMETRIA HEMATICA'!B97 -> 0 | R100: =O100*'BIOMETRIA HEMATICA'!B97 -> 0
B101: 7837984001 | C101: WDF Lysercell WDF | D101: 2450 | E101: 90 | F101: =(('BIOMETRIA HEMATICA'!$B$2)*0.2)+('BIOMETRIA HEMATICA'!$B$2) -> 14640 | G101: =F101/D101 -> 5.9755102 | H101: =(360/E101)*'BIOMETRIA HEMATICA'!$B$10 -> 4 | I101: =IF(G101>H101,G101,H101) -> 5.9755102 | K101: =ROUNDUP(I101,0) -> 6 | L101: 176 | M101: =L101*K101 -> 1056
B102: 6510256001 | C102: WDF Fluorocell WDF 2X42 ML | D102: 3400 | E102: 180 | F102: =(('BIOMETRIA HEMATICA'!$B$2)*0.2)+('BIOMETRIA HEMATICA'!$B$2) -> 14640 | G102: =F102/D102 -> 4.3058824 | H102: =(360/E102)*'BIOMETRIA HEMATICA'!$B$10 -> 2 | I102: =IF(G102>H102,G102,H102) -> 4.3058824 | K102: =ROUNDUP(I102,0) -> 5 | L102: 862 | M102: =L102*K102 -> 4310
B103: 6952291001 | C103: CELLCLEAN AUTO 4 ML X 20 | D103: =(((F98/30)/12)*E103) -> 6100 | E103: 150 | F103: =(('BIOMETRIA HEMATICA'!$B$2)*0.2)+('BIOMETRIA HEMATICA'!$B$2) -> 14640 | G103: =F103/D103 -> 2.4 | H103: =(360/E103)*'BIOMETRIA HEMATICA'!$B$10 -> 2.4 | I103: =IF(G103>H103,G103,H103) -> 2.4 | K103: =ROUNDUP(I103,0) -> 3 | L103: 52 | M103: =L103*K103 -> 156
B104: 7051506001 | C104: XN Check 12x3.0ml Level 1,2,3 | D104: =(((F98/30)/12)*E104) -> 2277.3333 | E104: 56 | F104: =(('BIOMETRIA HEMATICA'!$B$2)*0.2)+('BIOMETRIA HEMATICA'!$B$2) -> 14640 | G104: =F104/D104 -> 6.4285714 | H104: =(360/E104)*'BIOMETRIA HEMATICA'!$B$10 -> 6.4285714 | I104: =IF(G104>H104,G104,H104) -> 6.4285714 | K104: =ROUNDUP(I104,0) -> 7 | L104: 544 | M104: =L104*K104 -> 3808
A105: Reticulocitos | B105: 6510272001 | C105: FLUOROCELL RET 2 X 12ML | D105: 650 | E105: 180 | F105: =(('BIOMETRIA HEMATICA'!$D$2)*0.2)+('BIOMETRIA HEMATICA'!$D$2) -> 0 | G105: =F105/D105 -> 0 | H105: =(360/E105)*'BIOMETRIA HEMATICA'!$B$10 -> 2 | I105: =IF(G105>H105,G105,H105) -> 2 | J105: =IF(G105=0,0,G105) -> 0 | K105: =ROUNDUP(I105,0) -> 2 | L105: 1705 | M105: =L105*K105 -> 3410
B106: 9426752001 | C106: CELLPACK DFL 1 L | D106: 450 | E106: 60 | F106: =(('BIOMETRIA HEMATICA'!$D$2)*0.2)+('BIOMETRIA HEMATICA'!$D$2) -> 0 | G106: =F106/D106 -> 0 | H106: =(360/E106)*'BIOMETRIA HEMATICA'!$B$10 -> 6 | I106: =IF(G106>H106,G106,H106) -> 6 | J106: =IF(G106=0,0,G106) -> 0 | K106: =ROUNDUP(I106,0) -> 6 | L106: 34 | M106: =L106*K106 -> 204
A107: Líquidos | B107: 7051409001 | C107: XN-Check BF 6x3.0ml Level 1,2 | D107: =(((F98/30)/12)*E107) -> 2277.3333 | E107: 56 | F107: =(('BIOMETRIA HEMATICA'!$H$2)*0.2)+('BIOMETRIA HEMATICA'!$H$2) -> 0 | G107: =F107/D107 -> 0 | H107: =(360/E107)*'BIOMETRIA HEMATICA'!$B$10 -> 6.4285714 | I107: =IF(G107>H107,G107,H107) -> 6.4285714 | J107: =IF(G86=0,0,G107) -> 0 | K107: =ROUNDUP(I107,0) -> 7 | L107: 661 | M107: =L107*K107 -> 4627
C109: ADICIONALES | K109: ='BIOMETRIA HEMATICA'!B6 -> 12 | L109: =BC!F109 -> 1920 | M109: =(L109/K109)*K109 -> 1920
C110: MANTENIMIENTO/REPUESTOS | L110: 710 | M110: =(L110*K109)/(12) -> 710
C111: EQUIPO | L111: 36850 | M111: =((((L110)*(K109))/'BIOMETRIA HEMATICA'!B2)) -> 0.69836066
A115: XN-1000 SIN LICENCIAS
A116: Parámetro | B116: ID | C116: PRODUCTO | D116: DET/KIT | E116: DIAS ESTABILIDAD | F116: DET/AÑO PROCESO | G116: PRODUCTO CALCULADO | H116: MINIMOS POR ESTABILIDAD | I116: PRODUCTO A ENTREGAR | K116: REDONDEADO A ENTREGAR | L116: PVP | M116: TOTAL | O116: PVP BIOMETRIA COMPLETA | P116: PARA PROCESO | Q116: VALOR INICIAL DEL PROCESO | R116: VALOR FINAL DEL PROCESO
A117: Biometria básica | B117: 6510167001 | C117: CELLPACK DCL | D117: 450 | E117: 60 | F117: =(('BIOMETRIA HEMATICA'!$B$2)*0.2)+('BIOMETRIA HEMATICA'!$B$2) -> 14640 | G117: =F117/D117 -> 32.533333 | H117: =(360/E117)*'BIOMETRIA HEMATICA'!$B$10 -> 6 | I117: =IF(G117>H117,G117,H117) -> 32.533333 | K117: =ROUNDUP(I117,0) -> 33 | L117: 121 | M117: =L117*K117 -> 3993 | O117: =(SUM(M117:M130)/'BIOMETRIA HEMATICA'!B2)+M134 -> 5.605241 | P117: =((O117*0.15)+O117) -> 6.4460271 | Q117: =P117*'BIOMETRIA HEMATICA'!B116 -> 0 | R117: =O117*'BIOMETRIA HEMATICA'!B116 -> 0
B118: 3337006001 | C118: SULFOLYSER REAGENT X 5L | D118: 9450 | E118: 60 | F118: =(('BIOMETRIA HEMATICA'!$B$2)*0.2)+('BIOMETRIA HEMATICA'!$B$2) -> 14640 | G118: =F118/D118 -> 1.5492063 | H118: =(360/E118)*'BIOMETRIA HEMATICA'!$B$10 -> 6 | I118: =IF(G118>H118,G118,H118) -> 6 | J118: =IF(N118>N119,0,I118) -> 0 | K118: =ROUNDUP(I118,0) -> 6 | L118: 1107 | M118: =L118*K118 -> 6642 | N118: =L118*K118 -> 6642 | O118: PVP BIOMETRIA | P118: PARA PROCESO | Q118: VALOR INICIAL DEL PROCESO | R118: VALOR FINAL DEL PROCESO
B119: 12215616001 | C119: SULFOLYSER REAGENT 500 ml | D119: 850 | E119: 60 | F119: =(('BIOMETRIA HEMATICA'!$B$2)*0.2)+('BIOMETRIA HEMATICA'!$B$2) -> 14640 | G119: =F119/D119 -> 17.223529 | H119: =(360/E119)*'BIOMETRIA HEMATICA'!$B$10 -> 6 | I119: =IF(G119>H119,G119,H119) -> 17.223529 | J119: =IF(N119>N118,0,I119) -> 17.223529 | K119: =ROUNDUP(I119,0) -> 18 | L119: 228.33 | M119: =L119*K119 -> 4109.94 | N119: =L119*K119 -> 4109.94 | O119: =(SUM(M117:M125)/'BIOMETRIA HEMATICA'!B2)+M134 -> 4.8236836 | P119: =((O119*0.15)+O119) -> 5.5472361 | Q119: =P119*'BIOMETRIA HEMATICA'!B116 -> 0 | R119: =O119*'BIOMETRIA HEMATICA'!B116 -> 0
B120: 7837984001 | C120: WDF Lysercell WDF | D120: 2450 | E120: 90 | F120: =(('BIOMETRIA HEMATICA'!$B$2)*0.2)+('BIOMETRIA HEMATICA'!$B$2) -> 14640 | G120: =F120/D120 -> 5.9755102 | H120: =(360/E120)*'BIOMETRIA HEMATICA'!$B$10 -> 4 | I120: =IF(G120>H120,G120,H120) -> 5.9755102 | K120: =ROUNDUP(I120,0) -> 6 | L120: 176 | M120: =L120*K120 -> 1056
B121: 6510256001 | C121: WDF Fluorocell WDF 2X42 ML | D121: 3400 | E121: 180 | F121: =(('BIOMETRIA HEMATICA'!$B$2)*0.2)+('BIOMETRIA HEMATICA'!$B$2) -> 14640 | G121: =F121/D121 -> 4.3058824 | H121: =(360/E121)*'BIOMETRIA HEMATICA'!$B$10 -> 2 | I121: =IF(G121>H121,G121,H121) -> 4.3058824 | K121: =ROUNDUP(I121,0) -> 5 | L121: 862 | M121: =L121*K121 -> 4310
B122: 6510248001 | C122: FLUOROCELL WNR 2 X 82ML | D122: 6945 | E122: 180 | F122: =(('BIOMETRIA HEMATICA'!$B$2)*0.2)+('BIOMETRIA HEMATICA'!$B$2) -> 14640 | G122: =F122/D122 -> 2.1079914 | H122: =(360/E122)*'BIOMETRIA HEMATICA'!$B$10 -> 2 | I122: =IF(G122>H122,G122,H122) -> 2.1079914 | K122: =ROUNDUP(I122,0) -> 3 | L122: 634 | M122: =L122*K122 -> 1902
B123: 7838000001 | C123: LYSERCELL-WNR WNR-210A | D123: 2950 | E123: 90 | F123: =(('BIOMETRIA HEMATICA'!$B$2)*0.2)+('BIOMETRIA HEMATICA'!$B$2) -> 14640 | G123: =F123/D123 -> 4.9627119 | H123: =(360/E123)*'BIOMETRIA HEMATICA'!$B$10 -> 4 | I123: =IF(G123>H123,G123,H123) -> 4.9627119 | K123: =ROUNDUP(I123,0) -> 5 | L123: 128 | M123: =L123*K123 -> 640
B124: 6952291001 | C124: CELLCLEAN AUTO 4 ML X 20 | D124: =(((F117/30)/12)*E124) -> 6100 | E124: 150 | F124: =(('BIOMETRIA HEMATICA'!$B$2)*0.2)+('BIOMETRIA HEMATICA'!$B$2) -> 14640 | G124: =F124/D124 -> 2.4 | H124: =(360/E124)*'BIOMETRIA HEMATICA'!$B$10 -> 2.4 | I124: =IF(G124>H124,G124,H124) -> 2.4 | K124: =ROUNDUP(I124,0) -> 3 | L124: 52 | M124: =L124*K124 -> 156
...

Sheet COMODATO TODO COMPRADO XN
A1: XNL-350 SIN LICENCIAS
A2: Parámetro | B2: ID | C2: PRODUCTO | D2: DET/KIT | E2: DIAS ESTABILIDAD | F2: DET/AÑO PROCESO | G2: PRODUCTO CALCULADO | H2: MINIMOS POR ESTABILIDAD | I2: PRODUCTO A ENTREGAR | K2: REDONDEADO A ENTREGAR | L2: PVP | M2: TOTAL | O2: PVP TODO COMPRADO | P2: TOTAL TODO COMPRADO | Q2: PVP BIOMETRIA COMPLETA
A3: Biometria básica | B3: 6510167001 | C3: CELLPACK DCL | D3: 450 | E3: 60 | F3: =(('BIOMETRIA HEMATICA'!$B$2)) -> 12200 | G3: =F3/D3 -> 27.111111 | H3: =(360/E3)*'BIOMETRIA HEMATICA'!$B$10 -> 6 | I3: =IF(G3>H3,G3,H3) -> 27.111111 | K3: =ROUNDDOWN(I3,0) -> 27 | L3: 121 | M3: =L3*K3 -> 3267 | O3: =(L3*$L$19)+L3 -> 522.45087 | P3: =O3*K3 -> 14106.173 | Q3: =(SUM(P3:P12)/'BIOMETRIA HEMATICA'!B2)+M16 -> 10.139641
B4: 3337006001 | C4: SULFOLYSER REAGENT X 5L | D4: 9450 | E4: 60 | F4: =(('BIOMETRIA HEMATICA'!$B$2)) -> 12200 | G4: =F4/D4 -> 1.2910053 | H4: =(360/E4)*'BIOMETRIA HEMATICA'!$B$10 -> 6 | I4: =IF(G4>H4,G4,H4) -> 6 | J4: =IF(N4>N5,0,I4) -> 0 | K4: =ROUNDDOWN(I4,0) -> 6 | L4: 1107 | M4: =L4*K4 -> 6642 | N4: =L4*K4 -> 6642 | O4: =(L4*$L$19)+L4 -> 4779.7778 | P4: =O4*K4 -> 28678.667 | Q4: PVP BIOMETRIA
B5: 12215616001 | C5: SULFOLYSER REAGENT 500 ml | D5: 850 | E5: 60 | F5: =(('BIOMETRIA HEMATICA'!$B$2)) -> 12200 | G5: =F5/D5 -> 14.352941 | H5: =(360/E5)*'BIOMETRIA HEMATICA'!$B$10 -> 6 | I5: =IF(G5>H5,G5,H5) -> 14.352941 | J5: =IF(N5>N4,0,I5) -> 14.352941 | K5: =ROUNDDOWN(I5,0) -> 14 | L5: 228.33 | M5: =L5*K5 -> 3196.62 | N5: =L5*K5 -> 3196.62 | O5: =(L5*$L$19)+L5 -> 985.87774 | P5: =O5*K5 -> 13802.288 | Q5: =(SUM(P3:P9)/'BIOMETRIA HEMATICA'!B2)+M16 -> 7.4569573
B6: 7837984001 | C6: WDF Lysercell WDF | D6: 2450 | E6: 90 | F6: =(('BIOMETRIA HEMATICA'!$B$2)) -> 12200 | G6: =F6/D6 -> 4.9795918 | H6: =(360/E6)*'BIOMETRIA HEMATICA'!$B$10 -> 4 | I6: =IF(G6>H6,G6,H6) -> 4.9795918 | K6: =ROUNDDOWN(I6,0) -> 4 | L6: 176 | M6: =L6*K6 -> 704 | O6: =(L6*$L$19)+L6 -> 759.92854 | P6: =O6*K6 -> 3039.7141
B7: 6510256001 | C7: WDF Fluorocell WDF 2X42 ML | D7: 3400 | E7: 180 | F7: =(('BIOMETRIA HEMATICA'!$B$2)) -> 12200 | G7: =F7/D7 -> 3.5882353 | H7: =(360/E7)*'BIOMETRIA HEMATICA'!$B$10 -> 2 | I7: =IF(G7>H7,G7,H7) -> 3.5882353 | K7: =ROUNDDOWN(I7,0) -> 3 | L7: 862 | M7: =L7*K7 -> 2586 | O7: =(L7*$L$19)+L7 -> 3721.9227 | P7: =O7*K7 -> 11165.768
B8: 6952291001 | C8: CELLCLEAN AUTO 4 ML X 20 | D8: =(((F3/30)/12)*E8) -> 5083.3333 | E8: 150 | F8: =(('BIOMETRIA HEMATICA'!$B$2)) -> 12200 | G8: =F8/D8 -> 2.4 | H8: =(360/E8)*'BIOMETRIA HEMATICA'!$B$10 -> 2.4 | I8: =IF(G8>H8,G8,H8) -> 2.4 | K8: =ROUNDDOWN(I8,0) -> 2 | L8: 52 | M8: =L8*K8 -> 104 | O8: =(L8*$L$19)+L8 -> 224.52434 | P8: =O8*K8 -> 449.04868
B9: 7051506001 | C9: XN Check 12x3.0ml Level 1,2,3 | D9: =(((F3/30)/12)*E9) -> 1897.7778 | E9: 56 | F9: =(('BIOMETRIA HEMATICA'!$B$2)) -> 12200 | G9: =F9/D9 -> 6.4285714 | H9: =(360/E9)*'BIOMETRIA HEMATICA'!$B$10 -> 6.4285714 | I9: =IF(G9>H9,G9,H9) -> 6.4285714 | K9: =ROUNDDOWN(I9,0) -> 6 | L9: 544 | M9: =L9*K9 -> 3264 | O9: =(L9*$L$19)+L9 -> 2348.87 | P9: =O9*K9 -> 14093.22
A10: Reticulocitos | B10: 6510272001 | C10: FLUOROCELL RET 2 X 12ML | D10: 650 | E10: 180 | F10: =(('BIOMETRIA HEMATICA'!$D$2)) -> 0 | G10: =F10/D10 -> 0 | H10: =(360/E10)*'BIOMETRIA HEMATICA'!$B$10 -> 2 | I10: =IF(G10>H10,G10,H10) -> 2 | J10: =IF(G10=0,0,G10) -> 0 | K10: =ROUNDDOWN(I10,0) -> 2 | L10: 1705 | M10: =L10*K10 -> 3410 | O10: =(L10*$L$19)+L10 -> 7361.8077 | P10: =O10*K10 -> 14723.615
B11: 9426752001 | C11: CELLPACK DFL 1 L | D11: 450 | E11: 60 | F11: =(('BIOMETRIA HEMATICA'!$D$2)) -> 0 | G11: =F11/D11 -> 0 | H11: =(360/E11)*'BIOMETRIA HEMATICA'!$B$10 -> 6 | I11: =IF(G11>H11,G11,H11) -> 6 | J11: =IF(G11=0,0,G11) -> 0 | K11: =ROUNDDOWN(I11,0) -> 6 | L11: 34 | M11: =L11*K11 -> 204 | O11: =(L11*$L$19)+L11 -> 146.80438 | P11: =O11*K11 -> 880.82626
A12: Líquidos | B12: 7051409001 | C12: XN-Check BF 6x3.0ml Level 1,2 | D12: =(((F3/30)/12)*E12) -> 1897.7778 | E12: 56 | F12: =(('BIOMETRIA HEMATICA'!$H$2)) -> 0 | G12: =F12/D12 -> 0 | H12: =(360/E12)*'BIOMETRIA HEMATICA'!$B$10 -> 6.4285714 | I12: =IF(G12>H12,G12,H12) -> 6.4285714 | J12: =IF(G12=0,0,G12) -> 0 | K12: =ROUNDDOWN(I12,0) -> 6 | L12: 661 | M12: =L12*K12 -> 3966 | O12: =(L12*$L$19)+L12 -> 2854.0498 | P12: =O12*K12 -> 17124.299
P13: =SUM(P3:P12) -> 118063.62
C14: ADICIONALES | K14: ='BIOMETRIA HEMATICA'!B6 -> 12 | L14: =BC!F109 -> 1920 | M14: =(L14/K14)*K14 -> 1920
C15: MANTENIMIENTO/REPUESTOS | L15: 470 | M15: =(L15*K14) -> 5640
C16: EQUIPO | L16: 21362 | M16: =((((L15)*(K14))/'BIOMETRIA HEMATICA'!B2)) -> 0.46229508
L17: =SUM(M14:M15) -> 7560 | P17: =P13-L18 -> 90720
L18: =SUM(M3:M12) -> 27343.62 | P18: =L15*K14 -> 5640
L19: =(L17/L18)*K14 -> 3.3177758
A24: XNL-350 CON LICENCIAS
A25: Parámetro | B25: ID | C25: PRODUCTO | D25: DET/KIT | E25: DIAS ESTABILIDAD | F25: DET/AÑO PROCESO | G25: PRODUCTO CALCULADO | H25: MINIMOS POR ESTABILIDAD | I25: PRODUCTO A ENTREGAR | K25: REDONDEADO A ENTREGAR | L25: PVP | M25: TOTAL | O25: PVP TODO COMPRADO | P25: TOTAL TODO COMPRADO | Q25: PVP BIOMETRIA COMPLETA
A26: Biometria básica | B26: 6510167001 | C26: CELLPACK DCL | D26: 450 | E26: 60 | F26: =(('BIOMETRIA HEMATICA'!$B$2)) -> 12200 | G26: =F26/D26 -> 27.111111 | H26: =(360/E26)*'BIOMETRIA HEMATICA'!$B$10 -> 6 | I26: =IF(G26>H26,G26,H26) -> 27.111111 | K26: =ROUNDDOWN(I26,0) -> 27 | L26: 121 | M26: =L26*K26 -> 3267 | O26: =(L26*$L$42)+L26 -> 586.17323 | P26: =O26*K26 -> 15826.677 | Q26: =(SUM(P26:P35)/'BIOMETRIA HEMATICA'!B2)+M39 -> 11.41833
B27: 3337006001 | C27: SULFOLYSER REAGENT X 5L | D27: 9450 | E27: 60 | F27: =(('BIOMETRIA HEMATICA'!$B$2)) -> 12200 | G27: =F27/D27 -> 1.2910053 | H27: =(360/E27)*'BIOMETRIA HEMATICA'!$B$10 -> 6 | I27: =IF(G27>H27,G27,H27) -> 6 | J27: =IF(N27>N28,0,I27) -> 0 | K27: =ROUNDDOWN(I27,0) -> 6 | L27: 1107 | M27: =L27*K27 -> 6642 | N27: =L27*K27 -> 6642 | O27: =(L27*$L$42)+L27 -> 5362.7584 | P27: =O27*K27 -> 32176.55 | Q27: PVP BIOMETRIA
B28: 12215616001 | C28: SULFOLYSER REAGENT 500 ml | D28: 850 | E28: 60 | F28: =(('BIOMETRIA HEMATICA'!$B$2)) -> 12200 | G28: =F28/D28 -> 14.352941 | H28: =(360/E28)*'BIOMETRIA HEMATICA'!$B$10 -> 6 | I28: =IF(G28>H28,G28,H28) -> 14.352941 | J28: =IF(N28>N27,0,I28) -> 14.352941 | K28: =ROUNDDOWN(I28,0) -> 14 | L28: 228.33 | M28: =L28*K28 -> 3196.62 | N28: =L28*K28 -> 3196.62 | O28: =(L28*$L$42)+L28 -> 1106.1234 | P28: =O28*K28 -> 15485.728 | Q28: =(SUM(P26:P32)/'BIOMETRIA HEMATICA'!B2)+M39 -> 8.4084439
B29: 7837984001 | C29: WDF Lysercell WDF | D29: 2450 | E29: 90 | F29: =(('BIOMETRIA HEMATICA'!$B$2)) -> 12200 | G29: =F29/D29 -> 4.9795918 | H29: =(360/E29)*'BIOMETRIA HEMATICA'!$B$10 -> 4 | I29: =IF(G29>H29,G29,H29) -> 4.9795918 | K29: =ROUNDDOWN(I29,0) -> 4 | L29: 176 | M29: =L29*K29 -> 704 | O29: =(L29*$L$42)+L29 -> 852.61561 | P29: =O29*K29 -> 3410.4624
B30: 6510256001 | C30: WDF Fluorocell WDF 2X42 ML | D30: 3400 | E30: 180 | F30: =(('BIOMETRIA HEMATICA'!$B$2)) -> 12200 | G30: =F30/D30 -> 3.5882353 | H30: =(360/E30)*'BIOMETRIA HEMATICA'!$B$10 -> 2 | I30: =IF(G30>H30,G30,H30) -> 3.5882353 | K30: =ROUNDDOWN(I30,0) -> 3 | L30: 862 | M30: =L30*K30 -> 2586 | O30: =(L30*$L$42)+L30 -> 4175.8787 | P30: =O30*K30 -> 12527.636
B31: 6952291001 | C31: CELLCLEAN AUTO 4 ML X 20 | D31: =(((F26/30)/12)*E31) -> 5083.3333 | E31: 150 | F31: =(('BIOMETRIA HEMATICA'!$B$2)) -> 12200 | G31: =F31/D31 -> 2.4 | H31: =(360/E31)*'BIOMETRIA HEMATICA'!$B$10 -> 2.4 | I31: =IF(G31>H31,G31,H31) -> 2.4 | K31: =ROUNDDOWN(I31,0) -> 2 | L31: 52 | M31: =L31*K31 -> 104 | O31: =(L31*$L$42)+L31 -> 251.90916 | P31: =O31*K31 -> 503.81831
B32: 7051506001 | C32: XN Check 12x3.0ml Level 1,2,3 | D32: =(((F26/30)/12)*E32) -> 1897.7778 | E32: 56 | F32: =(('BIOMETRIA HEMATICA'!$B$2)) -> 12200 | G32: =F32/D32 -> 6.4285714 | H32: =(360/E32)*'BIOMETRIA HEMATICA'!$B$10 -> 6.4285714 | I32: =IF(G32>H32,G32,H32) -> 6.4285714 | K32: =ROUNDDOWN(I32,0) -> 6 | L32: 544 | M32: =L32*K32 -> 3264 | O32: =(L32*$L$42)+L32 -> 2635.3573 | P32: =O32*K32 -> 15812.144
A33: Reticulocitos | B33: 6510272001 | C33: FLUOROCELL RET 2 X 12ML | D33: 650 | E33: 180 | F33: =(('BIOMETRIA HEMATICA'!$D$2)) -> 0 | G33: =F33/D33 -> 0 | H33: =(360/E33)*'BIOMETRIA HEMATICA'!$B$10 -> 2 | I33: =IF(G33>H33,G33,H33) -> 2 | J33: =IF(G33=0,0,G33) -> 0 | K33: =ROUNDDOWN(I33,0) -> 2 | L33: 1705 | M33: =L33*K33 -> 3410 | O33: =(L33*$L$42)+L33 -> 8259.7137 | P33: =O33*K33 -> 16519.427
B34: 9426752001 | C34: CELLPACK DFL 1 L | D34: 450 | E34: 60 | F34: =(('BIOMETRIA HEMATICA'!$D$2)) -> 0 | G34: =F34/D34 -> 0 | H34: =(360/E34)*'BIOMETRIA HEMATICA'!$B$10 -> 6 | I34: =IF(G34>H34,G34,H34) -> 6 | J34: =IF(G34=0,0,G34) -> 0 | K34: =ROUNDDOWN(I34,0) -> 6 | L34: 34 | M34: =L34*K34 -> 204 | O34: =(L34*$L$42)+L34 -> 164.70983 | P34: =O34*K34 -> 988.259
A35: Líquidos | B35: 7051409001 | C35: XN-Check BF 6x3.0ml Level 1,2 | D35: =(((F26/30)/12)*E35) -> 1897.7778 | E35: 56 | F35: =(('BIOMETRIA HEMATICA'!$H$2)) -> 0 | G35: =F35/D35 -> 0 | H35: =(360/E35)*'BIOMETRIA HEMATICA'!$B$10 -> 6.4285714 | I35: =IF(G35>H35,G35,H35) -> 6.4285714 | J35: =IF(G10=0,0,G35) -> 0 | K35: =ROUNDDOWN(I35,0) -> 6 | L35: 661 | M35: =L35*K35 -> 3966 | O35: =(L35*$L$42)+L35 -> 3202.1529 | P35: =O35*K35 -> 19212.918
P36: =SUM(P26:P35) -> 132463.62
C37: ADICIONALES | K37: ='BIOMETRIA HEMATICA'!B6 -> 12 | L37: =BC!F109 -> 1920 | M37: =(L37/K37)*K37 -> 1920
C38: MANTENIMIENTO/REPUESTOS | L38: 570 | M38: =(L38*K37) -> 6840
C39: EQUIPO | L39: 29260 | M39: =((((L38)*(K37))/'BIOMETRIA HEMATICA'!B2)) -> 0.56065574
L40: =SUM(M37:M38) -> 8760 | P40: =P36-L41 -> 105120
L41: =SUM(M26:M35) -> 27343.62 | P41: =L38*K37 -> 6840
L42: =(L40/L41)*K37 -> 3.8444068
A46: XNL-450 SIN LICENCIAS
A47: Parámetro | B47: ID | C47: PRODUCTO | D47: DET/KIT | E47: DIAS ESTABILIDAD | F47: DET/AÑO PROCESO | G47: PRODUCTO CALCULADO | H47: MINIMOS POR ESTABILIDAD | I47: PRODUCTO A ENTREGAR | K47: REDONDEADO A ENTREGAR | L47: PVP | M47: TOTAL | O47: PVP TODO COMPRADO | P47: TOTAL TODO COMPRADO | Q47: PVP BIOMETRIA COMPLETA
A48: Biometria básica | B48: 6510167001 | C48: CELLPACK DCL | D48: 450 | E48: 60 | F48: =(('BIOMETRIA HEMATICA'!$B$2)) -> 12200 | G48: =F48/D48 -> 27.111111 | H48: =(360/E48)*'BIOMETRIA HEMATICA'!$B$10 -> 6 | I48: =IF(G48>H48,G48,H48) -> 27.111111 | K48: =ROUNDDOWN(I48,0) -> 27 | L48: 121 | M48: =L48*K48 -> 3267 | O48: =(L48*$L$64)+L48 -> 586.17323 | P48: =O48*K48 -> 15826.677 | Q48: =(SUM(P48:P57)/'BIOMETRIA HEMATICA'!B2)+M61 -> 11.41833
B49: 3337006001 | C49: SULFOLYSER REAGENT X 5L | D49: 9450 | E49: 60 | F49: =(('BIOMETRIA HEMATICA'!$B$2)) -> 12200 | G49: =F49/D49 -> 1.2910053 | H49: =(360/E49)*'BIOMETRIA HEMATICA'!$B$10 -> 6 | I49: =IF(G49>H49,G49,H49) -> 6 | J49: =IF(N49>N50,0,I49) -> 0 | K49: =ROUNDDOWN(I49,0) -> 6 | L49: 1107 | M49: =L49*K49 -> 6642 | N49: =L49*K49 -> 6642 | O49: =(L49*$L$64)+L49 -> 5362.7584 | P49: =O49*K49 -> 32176.55 | Q49: PVP BIOMETRIA
B50: 12215616001 | C50: SULFOLYSER REAGENT 500 ml | D50: 850 | E50: 60 | F50: =(('BIOMETRIA HEMATICA'!$B$2)) -> 12200 | G50: =F50/D50 -> 14.352941 | H50: =(360/E50)*'BIOMETRIA HEMATICA'!$B$10 -> 6 | I50: =IF(G50>H50,G50,H50) -> 14.352941 | J50: =IF(N50>N49,0,I50) -> 14.352941 | K50: =ROUNDDOWN(I50,0) -> 14 | L50: 228.33 | M50: =L50*K50 -> 3196.62 | N50: =L50*K50 -> 3196.62 | O50: =(L50*$L$64)+L50 -> 1106.1234 | P50: =O50*K50 -> 15485.728 | Q50: =(SUM(P48:P54)/'BIOMETRIA HEMATICA'!B2)+M61 -> 8.4084439
B51: 7837984001 | C51: WDF Lysercell WDF | D51: 2450 | E51: 90 | F51: =(('BIOMETRIA HEMATICA'!$B$2)) -> 12200 | G51: =F51/D51 -> 4.9795918 | H51: =(360/E51)*'BIOMETRIA HEMATICA'!$B$10 -> 4 | I51: =IF(G51>H51,G51,H51) -> 4.9795918 | K51: =ROUNDDOWN(I51,0) -> 4 | L51: 176 | M51: =L51*K51 -> 704 | O51: =(L51*$L$64)+L51 -> 852.61561 | P51: =O51*K51 -> 3410.4624
B52: 6510256001 | C52: WDF Fluorocell WDF 2X42 ML | D52: 3400 | E52: 180 | F52: =(('BIOMETRIA HEMATICA'!$B$2)) -> 12200 | G52: =F52/D52 -> 3.5882353 | H52: =(360/E52)*'BIOMETRIA HEMATICA'!$B$10 -> 2 | I52: =IF(G52>H52,G52,H52) -> 3.5882353 | K52: =ROUNDDOWN(I52,0) -> 3 | L52: 862 | M52: =L52*K52 -> 2586 | O52: =(L52*$L$64)+L52 -> 4175.8787 | P52: =O52*K52 -> 12527.636
B53: 6952291001 | C53: CELLCLEAN AUTO 4 ML X 20 | D53: =(((F48/30)/12)*E53) -> 5083.3333 | E53: 150 | F53: =(('BIOMETRIA HEMATICA'!$B$2)) -> 12200 | G53: =F53/D53 -> 2.4 | H53: =(360/E53)*'BIOMETRIA HEMATICA'!$B$10 -> 2.4 | I53: =IF(G53>H53,G53,H53) -> 2.4 | K53: =ROUNDDOWN(I53,0) -> 2 | L53: 52 | M53: =L53*K53 -> 104 | O53: =(L53*$L$64)+L53 -> 251.90916 | P53: =O53*K53 -> 503.81831
B54: 7051506001 | C54: XN Check 12x3.0ml Level 1,2,3 | D54: =(((F48/30)/12)*E54) -> 1897.7778 | E54: 56 | F54: =(('BIOMETRIA HEMATICA'!$B$2)) -> 12200 | G54: =F54/D54 -> 6.4285714 | H54: =(360/E54)*'BIOMETRIA HEMATICA'!$B$10 -> 6.4285714 | I54: =IF(G54>H54,G54,H54) -> 6.4285714 | K54: =ROUNDDOWN(I54,0) -> 6 | L54: 544 | M54: =L54*K54 -> 3264 | O54: =(L54*$L$64)+L54 -> 2635.3573 | P54: =O54*K54 -> 15812.144
A55: Reticulocitos | B55: 6510272001 | C55: FLUOROCELL RET 2 X 12ML | D55: 650 | E55: 180 | F55: =(('BIOMETRIA HEMATICA'!$D$2)) -> 0 | G55: =F55/D55 -> 0 | H55: =(360/E55)*'BIOMETRIA HEMATICA'!$B$10 -> 2 | I55: =IF(G55>H55,G55,H55) -> 2 | J55: =IF(G55=0,0,G55) -> 0 | K55: =ROUNDDOWN(I55,0) -> 2 | L55: 1705 | M55: =L55*K55 -> 3410 | O55: =(L55*$L$64)+L55 -> 8259.7137 | P55: =O55*K55 -> 16519.427
B56: 9426752001 | C56: CELLPACK DFL 1 L | D56: 450 | E56: 60 | F56: =(('BIOMETRIA HEMATICA'!$D$2)) -> 0 | G56: =F56/D56 -> 0 | H56: =(360/E56)*'BIOMETRIA HEMATICA'!$B$10 -> 6 | I56: =IF(G56>H56,G56,H56) -> 6 | J56: =IF(G56=0,0,G56) -> 0 | K56: =ROUNDDOWN(I56,0) -> 6 | L56: 34 | M56: =L56*K56 -> 204 | O56: =(L56*$L$64)+L56 -> 164.70983 | P56: =O56*K56 -> 988.259
A57: Líquidos | B57: 7051409001 | C57: XN-Check BF 6x3.0ml Level 1,2 | D57: =(((F48/30)/12)*E57) -> 1897.7778 | E57: 56 | F57: =(('BIOMETRIA HEMATICA'!$H$2)) -> 0 | G57: =F57/D57 -> 0 | H57: =(360/E57)*'BIOMETRIA HEMATICA'!$B$10 -> 6.4285714 | I57: =IF(G57>H57,G57,H57) -> 6.4285714 | J57: =IF(G33=0,0,G57) -> 0 | K57: =ROUNDDOWN(I57,0) -> 6 | L57: 661 | M57: =L57*K57 -> 3966 | O57: =(L57*$L$64)+L57 -> 3202.1529 | P57: =O57*K57 -> 19212.918
P58: =SUM(P48:P57) -> 132463.62
C59: ADICIONALES | K59: ='BIOMETRIA HEMATICA'!B6 -> 12 | L59: =BC!F109 -> 1920 | M59: =(L59/K59)*K59 -> 1920
C60: MANTENIMIENTO/REPUESTOS | L60: 570 | M60: =(L60*K59) -> 6840
C61: EQUIPO | L61: 26389 | M61: =((((L60)*(K59))/'BIOMETRIA HEMATICA'!B2)) -> 0.56065574
L62: =SUM(M59:M60) -> 8760 | P62: =P58-L63 -> 105120
L63: =SUM(M48:M57) -> 27343.62 | P63: =L60*K59 -> 6840
L64: =(L62/L63)*K59 -> 3.8444068
A68: XNL-450 CON LICENCIAS
A69: Parámetro | B69: ID | C69: PRODUCTO | D69: DET/KIT | E69: DIAS ESTABILIDAD | F69: DET/AÑO PROCESO | G69: PRODUCTO CALCULADO | H69: MINIMOS POR ESTABILIDAD | I69: PRODUCTO A ENTREGAR | K69: REDONDEADO A ENTREGAR | L69: PVP | M69: TOTAL | O69: PVP TODO COMPRADO | P69: TOTAL TODO COMPRADO | Q69: PVP BIOMETRIA COMPLETA
A70: Biometria básica | B70: 6510167001 | C70: CELLPACK DCL | D70: 450 | E70: 60 | F70: =(('BIOMETRIA HEMATICA'!$B$2)) -> 12200 | G70: =F70/D70 -> 27.111111 | H70: =(360/E70)*'BIOMETRIA HEMATICA'!$B$10 -> 6 | I70: =IF(G70>H70,G70,H70) -> 27.111111 | K70: =ROUNDDOWN(I70,0) -> 27 | L70: 121 | M70: =L70*K70 -> 3267 | O70: =(L70*$L$86)+L70 -> 649.89559 | P70: =O70*K70 -> 17547.181 | Q70: =(SUM(P70:P79)/'BIOMETRIA HEMATICA'!B2)+M83 -> 12.697018
B71: 3337006001 | C71: SULFOLYSER REAGENT X 5L | D71: 9450 | E71: 60 | F71: =(('BIOMETRIA HEMATICA'!$B$2)) -> 12200 | G71: =F71/D71 -> 1.2910053 | H71: =(360/E71)*'BIOMETRIA HEMATICA'!$B$10 -> 6 | I71: =IF(G71>H71,G71,H71) -> 6 | J71: =IF(N71>N72,0,I71) -> 0 | K71: =ROUNDDOWN(I71,0) -> 6 | L71: 1107 | M71: =L71*K71 -> 6642 | N71: =L71*K71 -> 6642 | O71: =(L71*$L$86)+L71 -> 5945.739 | P71: =O71*K71 -> 35674.434 | Q71: PVP BIOMETRIA
B72: 12215616001 | C72: SULFOLYSER REAGENT 500 ml | D72: 850 | E72: 60 | F72: =(('BIOMETRIA HEMATICA'!$B$2)) -> 12200 | G72: =F72/D72 -> 14.352941 | H72: =(360/E72)*'BIOMETRIA HEMATICA'!$B$10 -> 6 | I72: =IF(G72>H72,G72,H72) -> 14.352941 | J72: =IF(N72>N71,0,I72) -> 14.352941 | K72: =ROUNDDOWN(I72,0) -> 14 | L72: 228.33 | M72: =L72*K72 -> 3196.62 | N72: =L72*K72 -> 3196.62 | O72: =(L72*$L$86)+L72 -> 1226.3691 | P72: =O72*K72 -> 17169.167 | Q72: =(SUM(P70:P76)/'BIOMETRIA HEMATICA'!B2)+M83 -> 9.3599305
B73: 7837984001 | C73: WDF Lysercell WDF | D73: 2450 | E73: 90 | F73: =(('BIOMETRIA HEMATICA'!$B$2)) -> 12200 | G73: =F73/D73 -> 4.9795918 | H73: =(360/E73)*'BIOMETRIA HEMATICA'!$B$10 -> 4 | I73: =IF(G73>H73,G73,H73) -> 4.9795918 | K73: =ROUNDDOWN(I73,0) -> 4 | L73: 176 | M73: =L73*K73 -> 704 | O73: =(L73*$L$86)+L73 -> 945.30267 | P73: =O73*K73 -> 3781.2107
B74: 6510256001 | C74: WDF Fluorocell WDF 2X42 ML | D74: 3400 | E74: 180 | F74: =(('BIOMETRIA HEMATICA'!$B$2)) -> 12200 | G74: =F74/D74 -> 3.5882353 | H74: =(360/E74)*'BIOMETRIA HEMATICA'!$B$10 -> 2 | I74: =IF(G74>H74,G74,H74) -> 3.5882353 | K74: =ROUNDDOWN(I74,0) -> 3 | L74: 862 | M74: =L74*K74 -> 2586 | O74: =(L74*$L$86)+L74 -> 4629.8347 | P74: =O74*K74 -> 13889.504
B75: 6952291001 | C75: CELLCLEAN AUTO 4 ML X 20 | D75: =(((F70/30)/12)*E75) -> 5083.3333 | E75: 150 | F75: =(('BIOMETRIA HEMATICA'!$B$2)) -> 12200 | G75: =F75/D75 -> 2.4 | H75: =(360/E75)*'BIOMETRIA HEMATICA'!$B$10 -> 2.4 | I75: =IF(G75>H75,G75,H75) -> 2.4 | K75: =ROUNDDOWN(I75,0) -> 2 | L75: 52 | M75: =L75*K75 -> 104 | O75: =(L75*$L$86)+L75 -> 279.29397 | P75: =O75*K75 -> 558.58794
B76: 7051506001 | C76: XN Check 12x3.0ml Level 1,2,3 | D76: =(((F70/30)/12)*E76) -> 1897.7778 | E76: 56 | F76: =(('BIOMETRIA HEMATICA'!$B$2)) -> 12200 | G76: =F76/D76 -> 6.4285714 | H76: =(360/E76)*'BIOMETRIA HEMATICA'!$B$10 -> 6.4285714 | I76: =IF(G76>H76,G76,H76) -> 6.4285714 | K76: =ROUNDDOWN(I76,0) -> 6 | L76: 544 | M76: =L76*K76 -> 3264 | O76: =(L76*$L$86)+L76 -> 2921.8446 | P76: =O76*K76 -> 17531.068
A77: Reticulocitos | B77: 6510272001 | C77: FLUOROCELL RET 2 X 12ML | D77: 650 | E77: 180 | F77: =(('BIOMETRIA HEMATICA'!$D$2)) -> 0 | G77: =F77/D77 -> 0 | H77: =(360/E77)*'BIOMETRIA HEMATICA'!$B$10 -> 2 | I77: =IF(G77>H77,G77,H77) -> 2 | J77: =IF(G77=0,0,G77) -> 0 | K77: =ROUNDDOWN(I77,0) -> 2 | L77: 1705 | M77: =L77*K77 -> 3410 | O77: =(L77*$L$86)+L77 -> 9157.6197 | P77: =O77*K77 -> 18315.239
B78: 9426752001 | C78: CELLPACK DFL 1 L | D78: 450 | E78: 60 | F78: =(('BIOMETRIA HEMATICA'!$D$2)) -> 0 | G78: =F78/D78 -> 0 | H78: =(360/E78)*'BIOMETRIA HEMATICA'!$B$10 -> 6 | I78: =IF(G78>H78,G78,H78) -> 6 | J78: =IF(G78=0,0,G78) -> 0 | K78: =ROUNDDOWN(I78,0) -> 6 | L78: 34 | M78: =L78*K78 -> 204 | O78: =(L78*$L$86)+L78 -> 182.61529 | P78: =O78*K78 -> 1095.6917
A79: Líquidos | B79: 7051409001 | C79: XN-Check BF 6x3.0ml Level 1,2 | D79: =(((F70/30)/12)*E79) -> 1897.7778 | E79: 56 | F79: =(('BIOMETRIA HEMATICA'!$H$2)) -> 0 | G79: =F79/D79 -> 0 | H79: =(360/E79)*'BIOMETRIA HEMATICA'!$B$10 -> 6.4285714 | I79: =IF(G79>H79,G79,H79) -> 6.4285714 | J79: =IF(G55=0,0,G79) -> 0 | K79: =ROUNDDOWN(I79,0) -> 6 | L79: 661 | M79: =L79*K79 -> 3966 | O79: =(L79*$L$86)+L79 -> 3550.2561 | P79: =O79*K79 -> 21301.536
P80: =SUM(P70:P79) -> 146863.62
C81: ADICIONALES | K81: ='BIOMETRIA HEMATICA'!B6 -> 12 | L81: =BC!F109 -> 1920 | M81: =(L81/K81)*K81 -> 1920
C82: MANTENIMIENTO/REPUESTOS | L82: 670 | M82: =(L82*K81) -> 8040
C83: EQUIPO | L83: 34287 | M83: =((((L82)*(K81))/'BIOMETRIA HEMATICA'!B2)) -> 0.65901639
L84: =SUM(M81:M82) -> 9960 | P84: =P80-L85 -> 119520
L85: =SUM(M70:M79) -> 27343.62 | P85: =L82*K81 -> 8040
L86: =(L84/L85)*K81 -> 4.3710379
A90: XNL-550 SIN LICENCIAS
A91: Parámetro | B91: ID | C91: PRODUCTO | D91: DET/KIT | E91: DIAS ESTABILIDAD | F91: DET/AÑO PROCESO | G91: PRODUCTO CALCULADO | H91: MINIMOS POR ESTABILIDAD | I91: PRODUCTO A ENTREGAR | K91: REDONDEADO A ENTREGAR | L91: PVP | M91: TOTAL | O91: PVP TODO COMPRADO | P91: TOTAL TODO COMPRADO | Q91: PVP BIOMETRIA COMPLETA
A92: Biometria básica | B92: 6510167001 | C92: CELLPACK DCL | D92: 450 | E92: 60 | F92: =(('BIOMETRIA HEMATICA'!$B$2)) -> 12200 | G92: =F92/D92 -> 27.111111 | H92: =(360/E92)*'BIOMETRIA HEMATICA'!$B$10 -> 6 | I92: =IF(G92>H92,G92,H92) -> 27.111111 | K92: =ROUNDDOWN(I92,0) -> 27 | L92: 121 | M92: =L92*K92 -> 3267 | O92: =(L92*$L$108)+L92 -> 211.58779 | P92: =O92*K92 -> 5712.8703 | Q92: =(SUM(P92:P101)/F92)+M105 -> 2.0178377
B93: 3337006001 | C93: SULFOLYSER REAGENT X 5L | D93: 9450 | E93: 60 | F93: =(('BIOMETRIA HEMATICA'!$B$2)) -> 12200 | G93: =F93/D93 -> 1.2910053 | H93: =(360/E93)*'BIOMETRIA HEMATICA'!$B$10 -> 6 | I93: =IF(G93>H93,G93,H93) -> 6 | J93: =IF(N93>N94,0,I93) -> 6 | K93: 0 | L93: 1107 | M93: =L93*K93 -> 0 | N93: =L93*K93 -> 0 | O93: =(L93*$L$108)+L93 -> 1935.766 | P93: =O93*K93 -> 0 | Q93: PVP BIOMETRIA
B94: 12215616001 | C94: SULFOLYSER REAGENT 500 ml | D94: 850 | E94: 60 | F94: =(('BIOMETRIA HEMATICA'!$B$2)) -> 12200 | G94: =F94/D94 -> 14.352941 | H94: =(360/E94)*'BIOMETRIA HEMATICA'!$B$10 -> 6 | I94: =IF(G94>H94,G94,H94) -> 14.352941 | J94: =IF(N94>N93,0,I94) -> 0 | K94: =ROUNDDOWN(I94,0) -> 14 | L94: 228.33 | M94: =L94*K94 -> 3196.62 | N94: =L94*K94 -> 3196.62 | O94: =(L94*$L$108)+L94 -> 399.2714 | P94: =O94*K94 -> 5589.7997 | Q94: =(SUM(P92:P98)/'BIOMETRIA HEMATICA'!B2)+M105 -> 2.0178377
B95: 7837984001 | C95: WDF Lysercell WDF | D95: 2450 | E95: 90 | F95: =(('BIOMETRIA HEMATICA'!$B$2)) -> 12200 | G95: =F95/D95 -> 4.9795918 | H95: =(360/E95)*'BIOMETRIA HEMATICA'!$B$10 -> 4 | I95: =IF(G95>H95,G95,H95) -> 4.9795918 | K95: =ROUNDDOWN(I95,0) -> 4 | L95: 176 | M95: =L95*K95 -> 704 | O95: =(L95*$L$108)+L95 -> 307.76406 | P95: =O95*K95 -> 1231.0562
B96: 6510256001 | C96: WDF Fluorocell WDF 2X42 ML | D96: 3400 | E96: 180 | F96: =(('BIOMETRIA HEMATICA'!$B$2)) -> 12200 | G96: =F96/D96 -> 3.5882353 | H96: =(360/E96)*'BIOMETRIA HEMATICA'!$B$10 -> 2 | I96: =IF(G96>H96,G96,H96) -> 3.5882353 | K96: =ROUNDDOWN(I96,0) -> 3 | L96: 862 | M96: =L96*K96 -> 2586 | O96: =(L96*$L$108)+L96 -> 1507.3444 | P96: =O96*K96 -> 4522.0332
B97: 6952291001 | C97: CELLCLEAN AUTO 4 ML X 20 | D97: =(((F92/30)/12)*E97) -> 5083.3333 | E97: 150 | F97: =(('BIOMETRIA HEMATICA'!$B$2)) -> 12200 | G97: =F97/D97 -> 2.4 | H97: =(360/E97)*'BIOMETRIA HEMATICA'!$B$10 -> 2.4 | I97: =IF(G97>H97,G97,H97) -> 2.4 | K97: =ROUNDDOWN(I97,0) -> 2 | L97: 52 | M97: =L97*K97 -> 104 | O97: =(L97*$L$108)+L97 -> 90.930289 | P97: =O97*K97 -> 181.86058
B98: 7051506001 | C98: XN Check 12x3.0ml Level 1,2,3 | D98: =(((F92/30)/12)*E98) -> 1897.7778 | E98: 56 | F98: =(('BIOMETRIA HEMATICA'!$B$2)) -> 12200 | G98: =F98/D98 -> 6.4285714 | H98: =(360/E98)*'BIOMETRIA HEMATICA'!$B$10 -> 6.4285714 | I98: =IF(G98>H98,G98,H98) -> 6.4285714 | K98: 0 | L98: 544 | M98: =L98*K98 -> 0 | O98: =(L98*$L$108)+L98 -> 951.27072 | P98: =O98*K98 -> 0
A99: Reticulocitos | B99: 6510272001 | C99: FLUOROCELL RET 2 X 12ML | D99: 650 | E99: 180 | F99: =(('BIOMETRIA HEMATICA'!$D$2)) -> 0 | G99: =F99/D99 -> 0 | H99: =(360/E99)*'BIOMETRIA HEMATICA'!$B$10 -> 2 | I99: =IF(G99>H99,G99,H99) -> 2 | J99: =IF(G99=0,0,G99) -> 0 | L99: 1705 | M99: =L99*K99 -> 0 | O99: =(L99*$L$108)+L99 -> 2981.4643 | P99: =O99*K99 -> 0
B100: 9426752001 | C100: CELLPACK DFL 1 L | D100: 450 | E100: 60 | F100: =(('BIOMETRIA HEMATICA'!$D$2)) -> 0 | G100: =F100/D100 -> 0 | H100: =(360/E100)*'BIOMETRIA HEMATICA'!$B$10 -> 6 | I100: =IF(G100>H100,G100,H100) -> 6 | J100: =IF(G100=0,0,G100) -> 0 | L100: 34 | M100: =L100*K100 -> 0 | O100: =(L100*$L$108)+L100 -> 59.45442 | P100: =O100*K100 -> 0
A101: Líquidos | B101: 7051409001 | C101: XN-Check BF 6x3.0ml Level 1,2 | D101: =(((F92/30)/12)*E101) -> 1897.7778 | E101: 56 | F101: =(('BIOMETRIA HEMATICA'!$H$2)) -> 0 | G101: =F101/D101 -> 0 | H101: =(360/E101)*'BIOMETRIA HEMATICA'!$B$10 -> 6.4285714 | I101: =IF(G101>H101,G101,H101) -> 6.4285714 | J101: =IF(G77=0,0,G101) -> 0 | L101: 661 | M101: =L101*K101 -> 0 | O101: =(L101*$L$108)+L101 -> 1155.8639 | P101: =O101*K101 -> 0
P102: =SUM(P92:P101) -> 17237.62
C103: ADICIONALES | K103: ='BIOMETRIA HEMATICA'!B6 -> 12 | L103: =BC!F109 -> 1920 | M103: =(L103/K103)*K103 -> 1920
C104: MANTENIMIENTO/REPUESTOS | L104: 615 | M104: =(L104*K103) -> 7380
C105: EQUIPO | L105: 28941 | M105: =((((L104)*(K103))/F92)) -> 0.60491803
L106: =SUM(M103:N104) -> 9300 | P106: =P102-L107 -> 7380
L107: =SUM(M92:M101) -> 9857.62 | P107: =L104*K103 -> 7380
L108: =(L104/L107)*K103 -> 0.74865941
A112: XNL-550 CON LICENCIAS
A113: Parámetro | B113: ID | C113: PRODUCTO | D113: DET/KIT | E113: DIAS ESTABILIDAD | F113: DET/AÑO PROCESO | G113: PRODUCTO CALCULADO | H113: MINIMOS POR ESTABILIDAD | I113: PRODUCTO A ENTREGAR | K113: REDONDEADO A ENTREGAR | L113: PVP | M113: TOTAL | O113: PVP TODO COMPRADO | P113: TOTAL TODO COMPRADO | Q113: PVP BIOMETRIA COMPLETA
A114: Biometria básica | B114: 6510167001 | C114: CELLPACK DCL | D114: 450 | E114: 60 | F114: =(('BIOMETRIA HEMATICA'!$B$2)) -> 12200 | G114: =F114/D114 -> 27.111111 | H114: =(360/E114)*'BIOMETRIA HEMATICA'!$B$10 -> 6 | I114: =IF(G114>H114,G114,H114) -> 27.111111 | K114: =ROUNDDOWN(I114,0) -> 27 | L114: 121 | M114: =L114*K114 -> 3267 | O114: =(L114*$L$130)+L114 -> 675.38453 | P114: =O114*K114 -> 18235.382 | Q114: =(SUM(P114:P123)/'BIOMETRIA HEMATICA'!B2)+M127 -> 13.208493
B115: 3337006001 | C115: SULFOLYSER REAGENT X 5L | D115: 9450 | E115: 60 | F115: =(('BIOMETRIA HEMATICA'!$B$2)) -> 12200 | G115: =F115/D115 -> 1.2910053 | H115: =(360/E115)*'BIOMETRIA HEMATICA'!$B$10 -> 6 | I115: =IF(G115>H115,G115,H115) -> 6 | J115: =IF(N115>N116,0,I115) -> 0 | K115: =ROUNDDOWN(I115,0) -> 6 | L115: 1107 | M115: =L115*K115 -> 6642 | N115: =L115*K115 -> 6642 | O115: =(L115*$L$130)+L115 -> 6178.9312 | P115: =O115*K115 -> 37073.587 | Q115: PVP BIOMETRIA
B116: 12215616001 | C116: SULFOLYSER REAGENT 500 ml | D116: 850 | E116: 60 | F116: =(('BIOMETRIA HEMATICA'!$B$2)) -> 12200 | G116: =F116/D116 -> 14.352941 | H116: =(360/E116)*'BIOMETRIA HEMATICA'!$B$10 -> 6 | I116: =IF(G116>H116,G116,H116) -> 14.352941 | J116: =IF(N116>N115,0,I116) -> 14.352941 | K116: =ROUNDDOWN(I116,0) -> 14 | L116: 228.33 | M116: =L116*K116 -> 3196.62 | N116: =L116*K116 -> 3196.62 | O116: =(L116*$L$130)+L116 -> 1274.4674 | P116: =O116*K116 -> 17842.543 | Q116: =(SUM(P114:P120)/'BIOMETRIA HEMATICA'!B2)+M127 -> 9.7405252
...
